Workbook

Sheet Menu
A1: USINA PETRIBÚ — PLANEJAMENTO INTEGRADO DE MANUTENÇÃO · AgroVector v1.1
A2: Clique no módulo para navegar (⌂ MENU em cada aba retorna aqui). Status: DADO REAL = fonte cliente/histórico · ESTIMATIVA = validar (células amarelas) · PENDENTE = falta dado do cliente.
B4: ENTRADAS
B5: 📐 Premissas | C5: Índices por oficina (calibrados por 97.307 OS), disponibilidade MO, calendário, sazonalidade, gatilhos S/A/B/C e uso semanal por classe. | D5: REAL + ESTIMATIVA
B6: 🚛 Frota | C6: 384 ativos "Em Uso" no escopo garagem, com classe, setor e unidade de medição. | D6: DADO REAL
B7: 👷 Pessoas | C7: Equipe por oficina com custo mensal e custo/hora automáticos. | D7: PENDENTE (Evandro)
B8: ✅ Checklist | C8: HH incremental por classe × tipo, derivado dos gatilhos do cliente. | D8: REAL + ESTIMATIVA
B9: MOTOR / PROGRAMAÇÃO
B10: 📅 Cronograma por Classe | C10: Padrão de disparo S/A/B/C por classe × 52 semanas. | D10: CALCULADO
B11: 🗓 Cronograma por Ativo | C11: Grade completa: 384 ativos × 52 semanas, com filtro por classe. | D11: CALCULADO
B12: 📆 Agenda | C12: 2.101 preventivas em datas reais por ativo, com responsável automático. Veja também Mapa_Preventivas (classe × mês). Todos os 384 ativos têm agenda — pico dez–mar (1.026 eventos, igual ao app). | D12: CALCULADO
B13: RESULTADOS
B14: 📊 Plano de Preventivas | C14: HH preventiva por oficina × mês. | D14: CALCULADO
B15: 🔧 Plano de Corretivas | C15: HH corretiva esperada (mix real × deflator × sazonalidade calibrada). | D15: CALCULADO
B16: ⚖️ Disponibilidade | C16: Capacidade vs. demanda e saldo com semáforo. | D16: ZERADO até Pessoas
B17: 👥 Recursos | C17: Headcount necessário vs. atual (gap) por oficina × mês. | D17: ZERADO até Pessoas
B18: 🛢 Insumos & Peças | C18: Execuções/ano por classe × tipo — base para vincular os 5.171 itens. | D18: PENDENTE vínculo
B19: 💰 Saving | C19: Corretiva evitada (Δ HH) e R$ quando houver custo/hora. | D19: PARCIAL
B20: 📋 Resumo | C20: KPIs executivos: preventivas por tipo, HH por classe, custo MO, saving. | D20: CALCULADO
B21: APOIO
B22: 📈 Calibração OS | C22: Mix prev/corr por oficina e sazonalidade extraídos do histórico. | D22: DADO REAL
B23: ℹ️ Leia-me | C23: Instruções, modelagem por classe, o que validar e pendências. | D23: —

Sheet Leia-me
A1: PLANEJAMENTO DE MANUTENÇÃO — USINA PETRIBÚ v1.0 · VALIDAÇÃO DOS CONSULTORES | E1: ⌂ MENU
A3: 1 | B3: Objetivo | C3: Versão Petribú da planilha funcional (mesmo motor do app agrovector_manutencao_Petribu_v1.0). Consultores devem VALIDAR premissas, gatilhos, HH e uso semanal por classe — os resultados recalculam em tempo real.
A4: 2 | B4: O que já é dado real | C4: Frota: 384 ativos "Em Uso" no escopo garagem (aba Frota, fonte template_frota_Dados) · Sazonalidade e mix prev/corr por oficina: calibrados com 97.307 OS de ago/23 a mai/26 (aba Calibração_OS) · Gatilhos S/A/B/C: template preenchido pelo cliente · Safra: set–mar (calendário PE).
A5: 3 | B5: Modelagem por classe | C5: Como os horímetros atuais não foram informados (3 de 625) e o uso semanal é estimado por classe, o cronograma é calculado POR CLASSE e multiplicado pela quantidade de ativos — matematicamente idêntico ao cálculo ativo a ativo nessas condições. Quando os horímetros chegarem, migra-se para o modelo por ativo.
A6: 4 | B6: O que validar (células amarelas = estimativa) | C6: Uso semanal safra/entressafra por classe · HH incremental dos checklists (Carregadeira e Veículo Leve foram assumidos) · Deflator e % terceiros por oficina · Disponibilidade de MO · Distribuição das preventivas entre oficinas (hoje 100% em Central-Taisa).
A7: 5 | B7: Pendências que zeram resultados | C7: PESSOAS: não recebido — Disponibilidade, Recursos, custo/HH e Saving ficam zerados/vermelhos até preencher a aba Pessoas. Insumos: 5.171 itens sem vínculo com atividades — aba não incluída nesta versão.
A8: 6 | B8: Referência de conferência | C8: O app Petribú v1.0 com os mesmos dados calcula: 2.102 preventivas/ano · 7.988 HH preventiva/ano · 22.783 HH corretiva/ano. O Resumo desta planilha deve bater com esses números.
A9: 7 | B9: Cores Fabio | C9: VERDE OK · AMARELO atenção/estimativa · VERMELHO crítico (fonte branca). Cronograma: S verde · A amarelo · B/C vermelho.

Sheet Calibração_OS
A1: CALIBRAÇÃO PELO HISTÓRICO DE OS — 97.307 OS · ago/2023 a mai/2026 (template_OS_Dados.xlsx) | H1: ⌂ MENU
A3: MIX PREVENTIVA × CORRETIVA POR OFICINA (por contagem de OS)
A4: Oficina | B4: % Prev | C4: % Corr | D4: Nº OS
A5: Oficina Volante-Socorro | B5: 9 | C5: 91 | D5: 56813
A6: Oficina Mecânica Central-Taisa | B6: 28 | C6: 72 | D6: 26024
A7: Oficina Implementos Rodoviários | B7: 67 | C7: 33 | D7: 8682
A8: Oficina Mecânica Externa | B8: 5 | C8: 95 | D8: 3128
A9: Oficina Mecânica Central - Pátio Externo | B9: 37 | C9: 63 | D9: 1311
A10: PitStop | B10: 14 | C10: 86 | D10: 759
A12: SAZONALIDADE DE CORRETIVAS (fator normalizado, média = 1,0)
A13: Mês | B13: Jan | C13: Fev | D13: Mar | E13: Abr | F13: Mai | G13: Jun | H13: Jul | I13: Ago | J13: Set | K13: Out | L13: Nov | M13: Dez
A14: Fator | B14: 1.24 | C14: 1.2 | D14: 1.09 | E14: 0.69 | F14: 0.5 | G14: 0.36 | H14: 0.46 | I14: 1.06 | J14: 1.25 | K14: 1.42 | L14: 1.4 | M14: 1.33
A16: Leitura: setembro–março (safra) concentra corretivas (pico 1,42 em outubro); abril–julho é a janela de folga (vale 0,36 em junho) — ideal para preventivas pesadas e reformas. Campo hh_executadas está 0% preenchido nas OS: HH corretiva será calibrada por custo ÷ custo/HH quando Pessoas chegar.

Sheet Premissas
A1: PREMISSAS — USINA PETRIBÚ (índices calibrados pelo histórico; amarelo = estimativa a validar) | M1: ⌂ MENU
A3: ÍNDICES POR OFICINA
A4: Oficina | B4: % Preventiva | C4: % Corretiva | D4: Check % | E4: Deflator (% a.a.) | F4: % Terceiros
A5: Oficina Mecânica Central-Taisa | B5: 28 | C5: 72 | D5: =IF(B5+C5=100,"OK","≠100") -> OK | E5: 5 | F5: 10
A6: Oficina Volante-Socorro | B6: 9 | C6: 91 | D6: =IF(B6+C6=100,"OK","≠100") -> OK | E6: 8 | F6: 5
A7: Oficina Implementos Rodoviários | B7: 67 | C7: 33 | D7: =IF(B7+C7=100,"OK","≠100") -> OK | E7: 3 | F7: 10
A8: Oficina Mecânica Externa | B8: 5 | C8: 95 | D8: =IF(B8+C8=100,"OK","≠100") -> OK | E8: 8 | F8: 20
A9: Oficina Implementos Agrícolas | B9: 50 | C9: 50 | D9: =IF(B9+C9=100,"OK","≠100") -> OK | E9: 5 | F9: 10
A10: PitStop | B10: 14 | C10: 86 | D10: =IF(B10+C10=100,"OK","≠100") -> OK | E10: 5 | F10: 0
A12: DISPONIBILIDADE DE MÃO DE OBRA (default Vector — validar com turnos reais)
A13: Oficina | B13: H.Brutas/dia | C13: Almoço (h) | D13: Café (h) | E13: Abertura OS (h) | F13: Produtividade % | G13: Absenteísmo % | H13: Férias % | I13: Trein. (h/ano) | J13: H.Efetivas/dia | K13: H.Líquidas/dia
A14: Oficina Mecânica Central-Taisa | B14: 8.8 | C14: 1.2 | D14: 0.17 | E14: 0.25 | F14: 80 | G14: 5 | H14: 8.33 | I14: 16 | J14: =MAX(0,B14-C14-D14-E14) -> 7.18 | K14: =ROUND(J14*(1-MIN(G14/100+H14/100/12+I14/MAX(1,252*J14),0.99))*(F14/100),2) -> 5.37
A15: Oficina Volante-Socorro | B15: 8.8 | C15: 1.2 | D15: 0.17 | E15: 0.25 | F15: 80 | G15: 5 | H15: 8.33 | I15: 16 | J15: =MAX(0,B15-C15-D15-E15) -> 7.18 | K15: =ROUND(J15*(1-MIN(G15/100+H15/100/12+I15/MAX(1,252*J15),0.99))*(F15/100),2) -> 5.37
A16: Oficina Implementos Rodoviários | B16: 8.8 | C16: 1.2 | D16: 0.17 | E16: 0.25 | F16: 80 | G16: 5 | H16: 8.33 | I16: 16 | J16: =MAX(0,B16-C16-D16-E16) -> 7.18 | K16: =ROUND(J16*(1-MIN(G16/100+H16/100/12+I16/MAX(1,252*J16),0.99))*(F16/100),2) -> 5.37
A17: Oficina Mecânica Externa | B17: 8.8 | C17: 1.2 | D17: 0.17 | E17: 0.25 | F17: 80 | G17: 5 | H17: 8.33 | I17: 16 | J17: =MAX(0,B17-C17-D17-E17) -> 7.18 | K17: =ROUND(J17*(1-MIN(G17/100+H17/100/12+I17/MAX(1,252*J17),0.99))*(F17/100),2) -> 5.37
A18: Oficina Implementos Agrícolas | B18: 8.8 | C18: 1.2 | D18: 0.17 | E18: 0.25 | F18: 80 | G18: 5 | H18: 8.33 | I18: 16 | J18: =MAX(0,B18-C18-D18-E18) -> 7.18 | K18: =ROUND(J18*(1-MIN(G18/100+H18/100/12+I18/MAX(1,252*J18),0.99))*(F18/100),2) -> 5.37
A19: PitStop | B19: 8.8 | C19: 1.2 | D19: 0.17 | E19: 0.25 | F19: 80 | G19: 5 | H19: 8.33 | I19: 16 | J19: =MAX(0,B19-C19-D19-E19) -> 7.18 | K19: =ROUND(J19*(1-MIN(G19/100+H19/100/12+I19/MAX(1,252*J19),0.99))*(F19/100),2) -> 5.37
A21: CALENDÁRIO E SAZONALIDADE (sazonal = calibrada pelo histórico) | F21: Início da safra | G21: 2026-09-01
A22: Mês | B22: Dias úteis | C22: Fator sazonal corretivas | D22: Safra (informativo) | F22: Fim da safra | G22: 2027-03-31
A23: Jan | B23: 22 | C23: 1.24 | D23: Sim
A24: Fev | B24: 20 | C24: 1.2 | D24: Sim
A25: Mar | B25: 22 | C25: 1.09 | D25: Sim
A26: Abr | B26: 20 | C26: 0.69 | D26: Não
A27: Mai | B27: 20 | C27: 0.5 | D27: Não
A28: Jun | B28: 22 | C28: 0.36 | D28: Não
A29: Jul | B29: 21 | C29: 0.46 | D29: Não
A30: Ago | B30: 20 | C30: 1.06 | D30: Não
A31: Set | B31: 23 | C31: 1.25 | D31: Sim
A32: Out | B32: 22 | C32: 1.42 | D32: Sim
A33: Nov | B33: 21 | C33: 1.4 | D33: Sim
A34: Dez | B34: 23 | C34: 1.33 | D34: Sim
A35: TOTAL/MÉDIA | B35: =SUM(B23:B34) -> 256 | C35: =ROUND(AVERAGE(C23:C34),2) -> 1
A37: CLASSES — GATILHOS (do template do cliente) · USO SEMANAL ESTIMADO (amarelo = validar) · QTD DA FROTA
A38: Classe | B38: Unidade | C38: Int. S | D38: Int. A | E38: Int. B | F38: Int. C | G38: Uso sem. SAFRA | H38: Uso sem. ENTRESSAFRA | I38: Qtd ativos | J38: Uso inicial
A39: Colhedora | B39: Horas | C39: 150 | D39: 300 | E39: 600 | F39: 1200 | G39: 60 | H39: 5 | I39: =COUNTIF(Frota!$C$5:$C$388,$A39) -> 8 | J39: 0
A40: Trator | B40: Horas | C40: 250 | D40: 500 | E40: 1000 | F40: 2000 | G40: 40 | H40: 15 | I40: =COUNTIF(Frota!$C$5:$C$388,$A40) -> 102 | J40: 0
A41: Caminhão | B41: KM | C41: 10000 | D41: 20000 | E41: 40000 | F41: 80000 | G41: 1500 | H41: 400 | I41: =COUNTIF(Frota!$C$5:$C$388,$A41) -> 121 | J41: 0
A42: Carregadeira/Pesada | B42: Horas | C42: 250 | D42: 500 | E42: 1000 | F42: 2000 | G42: 45 | H42: 10 | I42: =COUNTIF(Frota!$C$5:$C$388,$A42) -> 73 | J42: 0
A43: Veículo Leve | B43: KM | C43: 10000 | D43: 20000 | E43: 40000 | G43: 700 | H43: 500 | I43: =COUNTIF(Frota!$C$5:$C$388,$A43) -> 50 | J43: 0
A44: Pulverizador | B44: Horas | C44: 100 | D44: 200 | G44: 20 | H44: 20 | I44: =COUNTIF(Frota!$C$5:$C$388,$A44) -> 12 | J44: 0
A45: Implemento | B45: Horas | C45: 200 | D45: 400 | G45: 25 | H45: 5 | I45: =COUNTIF(Frota!$C$5:$C$388,$A45) -> 18 | J45: 0

Sheet Frota
A1: FROTA PETRIBÚ — 384 ativos "Em Uso" no escopo garagem (fonte: template_frota_Dados.xlsx · 240 ativos fora do escopo: irrigação, motos, motores) | J1: ⌂ MENU
A4: id_ativo | B4: Descrição | C4: Classe (app) | D4: Classe Operacional | E4: Setor | F4: Unidade | G4: Ano | H4: Placa/Série
A5: 101005 | B5: MB 1725 Atego | C5: Caminhão | D5: Cam. Comboio Abs. | E5: Transporte | F5: km | G5: 2007 | H5: KKA-8897
A6: 101006 | B6: MB 710 4X2 | C6: Caminhão | D6: Cam. Oficina | E6: Transporte | F6: km | G6: 2001 | H6: KKM-6051
A7: 101011 | B7: MB 1720 6x6 | C7: Caminhão | D7: Cam. Oficina | E7: Transporte | F7: km | G7: 2002 | H7: KKU-6541
A8: 101014 | B8: MB 1113 4x2 | C8: Caminhão | D8: Carga Seca | E8: Transporte | F8: km | G8: 1977 | H8: KJE-0688
A9: 101016 | B9: MB 2423 6x4 | C9: Caminhão | D9: Cam. Oficina | E9: Transporte | F9: km | G9: 2005 | H9: KJM-0447
A10: 101028 | B10: MB 2423 6x4 | C10: Caminhão | D10: Cam. Oficina | E10: Transporte | F10: km | G10: 2007 | H10: KKN-9637
A11: 101047 | B11: VW 31-320 | C11: Caminhão | D11: Cam. Basculante | E11: Transporte | F11: km | G11: 2011 | H11: PFL-3208
A12: 101048 | B12: MB 3344 6x4 | C12: Caminhão | D12: Cam. Canavieiro | E12: Colheita | F12: km | G12: 2011 | H12: PFL-3638
A13: 101050 | B13: MB 2729 6x4 | C13: Caminhão | D13: Cam. Prancha | E13: Transporte | F13: km | G13: 2014 | H13: OYZ-1570
A14: 101051 | B14: MB 2729 6x4 | C14: Caminhão | D14: Cam. Pipa | E14: Transporte | F14: km | G14: 2014 | H14: OYZ-4380
A15: 101052 | B15: MB 2729 6x4 | C15: Caminhão | D15: Cam. Pipa | E15: Transporte | F15: km | G15: 2014 | H15: OYZ-4F10
A16: 101053 | B16: MB 2729 6x4 | C16: Caminhão | D16: Cam. Pipa | E16: Transporte | F16: km | G16: 2014 | H16: OYZ-4420
... A388: 580002 | B388: Chinesa | C388: Implemento | D388: Cortadeira Cana | E388: Agrícola | F388: h | G388: 2026 | H388: 0

Sheet Pessoas
A1: PESSOAS — PENDENTE: solicitar ao cliente (Evandro). Sem esta aba, Disponibilidade, Recursos e Saving ficam zerados. | K1: ⌂ MENU
A4: Nome | B4: Cargo | C4: Oficina | D4: Turno | E4: Salário | F4: Encargos % | G4: Status | H4: Custo Mensal (R$) | I4: Custo/Hora (R$)
H5: =IF($A5="","",ROUND(E5*(1+F5/100),2)) | I5: =IF($A5="","",ROUND(H5/MAX(1,(Premissas!$B$35/12)*VLOOKUP(C5,Premissas!$A$14:$K$19,11,0)),2))
H6: =IF($A6="","",ROUND(E6*(1+F6/100),2)) | I6: =IF($A6="","",ROUND(H6/MAX(1,(Premissas!$B$35/12)*VLOOKUP(C6,Premissas!$A$14:$K$19,11,0)),2))
H7: =IF($A7="","",ROUND(E7*(1+F7/100),2)) | I7: =IF($A7="","",ROUND(H7/MAX(1,(Premissas!$B$35/12)*VLOOKUP(C7,Premissas!$A$14:$K$19,11,0)),2))
H8: =IF($A8="","",ROUND(E8*(1+F8/100),2)) | I8: =IF($A8="","",ROUND(H8/MAX(1,(Premissas!$B$35/12)*VLOOKUP(C8,Premissas!$A$14:$K$19,11,0)),2))
H9: =IF($A9="","",ROUND(E9*(1+F9/100),2)) | I9: =IF($A9="","",ROUND(H9/MAX(1,(Premissas!$B$35/12)*VLOOKUP(C9,Premissas!$A$14:$K$19,11,0)),2))
H10: =IF($A10="","",ROUND(E10*(1+F10/100),2)) | I10: =IF($A10="","",ROUND(H10/MAX(1,(Premissas!$B$35/12)*VLOOKUP(C10,Premissas!$A$14:$K$19,11,0)),2))
H11: =IF($A11="","",ROUND(E11*(1+F11/100),2)) | I11: =IF($A11="","",ROUND(H11/MAX(1,(Premissas!$B$35/12)*VLOOKUP(C11,Premissas!$A$14:$K$19,11,0)),2))
H12: =IF($A12="","",ROUND(E12*(1+F12/100),2)) | I12: =IF($A12="","",ROUND(H12/MAX(1,(Premissas!$B$35/12)*VLOOKUP(C12,Premissas!$A$14:$K$19,11,0)),2))
H13: =IF($A13="","",ROUND(E13*(1+F13/100),2)) | I13: =IF($A13="","",ROUND(H13/MAX(1,(Premissas!$B$35/12)*VLOOKUP(C13,Premissas!$A$14:$K$19,11,0)),2))
H14: =IF($A14="","",ROUND(E14*(1+F14/100),2)) | I14: =IF($A14="","",ROUND(H14/MAX(1,(Premissas!$B$35/12)*VLOOKUP(C14,Premissas!$A$14:$K$19,11,0)),2))
H15: =IF($A15="","",ROUND(E15*(1+F15/100),2)) | I15: =IF($A15="","",ROUND(H15/MAX(1,(Premissas!$B$35/12)*VLOOKUP(C15,Premissas!$A$14:$K$19,11,0)),2))
H16: =IF($A16="","",ROUND(E16*(1+F16/100),2)) | I16: =IF($A16="","",ROUND(H16/MAX(1,(Premissas!$B$35/12)*VLOOKUP(C16,Premissas!$A$14:$K$19,11,0)),2))
... H44: =IF($A44="","",ROUND(E44*(1+F44/100),2)) | I44: =IF($A44="","",ROUND(H44/MAX(1,(Premissas!$B$35/12)*VLOOKUP(C44,Premissas!$A$14:$K$19,11,0)),2))

Sheet Checklist
A1: CHECKLIST — HH INCREMENTAL por classe × tipo (dos gatilhos do cliente; herança reconstrói o total). Amarelo = HH assumido, validar. | O1: ⌂ MENU
A4: Checklist | B4: Tipo Prev | C4: Classe | D4: Oficina | E4: Atividade | F4: Cargo | G4: Tipo Ativ | H4: HH | I4: Insumo | J4: Qtd | K4: Un | L4: Peça | M4: Qtd
A5: Rev. S — Trator | B5: S | C5: Trator | D5: Oficina Mecânica Central-Taisa | E5: Revisão S — itens incrementais (Trator) | F5: Mecânico | G5: Troca | H5: 2.5 | J5: 0 | M5: 0
A6: Rev. A — Trator | B6: A | C6: Trator | D6: Oficina Mecânica Central-Taisa | E6: Revisão A — itens incrementais (Trator) | F6: Mecânico | G6: Troca | H6: 2 | J6: 0 | M6: 0
A7: Rev. B — Trator | B7: B | C7: Trator | D7: Oficina Mecânica Central-Taisa | E7: Revisão B — itens incrementais (Trator) | F7: Mecânico | G7: Troca | H7: 3.5 | J7: 0 | M7: 0
A8: Rev. C — Trator | B8: C | C8: Trator | D8: Oficina Mecânica Central-Taisa | E8: Revisão C — itens incrementais (Trator) | F8: Mecânico | G8: Troca | H8: 8 | J8: 0 | M8: 0
A9: Rev. S — Colhedora | B9: S | C9: Colhedora | D9: Oficina Mecânica Central-Taisa | E9: Revisão S — itens incrementais (Colhedora) | F9: Mecânico | G9: Troca | H9: 3 | J9: 0 | M9: 0
A10: Rev. A — Colhedora | B10: A | C10: Colhedora | D10: Oficina Mecânica Central-Taisa | E10: Revisão A — itens incrementais (Colhedora) | F10: Mecânico | G10: Troca | H10: 3 | J10: 0 | M10: 0
A11: Rev. B — Colhedora | B11: B | C11: Colhedora | D11: Oficina Mecânica Central-Taisa | E11: Revisão B — itens incrementais (Colhedora) | F11: Mecânico | G11: Troca | H11: 6 | J11: 0 | M11: 0
A12: Rev. C — Colhedora | B12: C | C12: Colhedora | D12: Oficina Mecânica Central-Taisa | E12: Revisão C — itens incrementais (Colhedora) | F12: Mecânico | G12: Troca | H12: 12 | J12: 0 | M12: 0
A13: Rev. S — Caminhão | B13: S | C13: Caminhão | D13: Oficina Mecânica Central-Taisa | E13: Revisão S — itens incrementais (Caminhão) | F13: Mecânico | G13: Troca | H13: 2 | J13: 0 | M13: 0
A14: Rev. A — Caminhão | B14: A | C14: Caminhão | D14: Oficina Mecânica Central-Taisa | E14: Revisão A — itens incrementais (Caminhão) | F14: Mecânico | G14: Troca | H14: 2 | J14: 0 | M14: 0
A15: Rev. B — Caminhão | B15: B | C15: Caminhão | D15: Oficina Mecânica Central-Taisa | E15: Revisão B — itens incrementais (Caminhão) | F15: Mecânico | G15: Troca | H15: 4 | J15: 0 | M15: 0
A16: Rev. C — Caminhão | B16: C | C16: Caminhão | D16: Oficina Mecânica Central-Taisa | E16: Revisão C — itens incrementais (Caminhão) | F16: Mecânico | G16: Troca | H16: 8 | J16: 0 | M16: 0
... A27: Rev. A — Implemento | B27: A | C27: Implemento | D27: Oficina Mecânica Central-Taisa | E27: Revisão A — itens incrementais (Implemento) | F27: Mecânico | G27: Troca | H27: 1.5 | J27: 0 | M27: 0

Sheet Cronograma
A1: CRONOGRAMA — CLASSE × 52 semanas (todos os ativos da classe seguem este padrão; × Qtd no plano) | BD1: ⌂ MENU
A2: S verde · A amarelo · B/C vermelho (cores Fabio). Uso inicial = 0 até receber horímetros do cliente.
A4: Classe (× qtd ativos) | B4: S01 | C4: S02 | D4: S03 | E4: S04 | F4: S05 | G4: S06 | H4: S07 | I4: S08 | J4: S09 | K4: S10 | L4: S11 | M4: S12 | N4: S13 | O4: S14 | P4: S15 | Q4: S16 | R4: S17 | S4: S18 | T4: S19 | U4: S20 | V4: S21 | W4: S22 | X4: S23 | Y4: S24 | Z4: S25 | AA4: S26 | AB4: S27 | AC4: S28 | AD4: S29 | AE4: S30 | AF4: S31 | AG4: S32 | AH4: S33 | AI4: S34 | AJ4: S35 | AK4: S36 | AL4: S37 | AM4: S38 | AN4: S39 | AO4: S40 | AP4: S41 | AQ4: S42 | AR4: S43 | AS4: S44 | AT4: S45 | AU4: S46 | AV4: S47 | AW4: S48 | AX4: S49 | AY4: S50 | AZ4: S51 | BA4: S52
A5: =Premissas!$A$39&" (×"&Premissas!$I$39&")" -> Colhedora (×8) | B5: =IF(INT(Cron_Uso!B5/Premissas!$C$39)>INT(Premissas!$J$39/Premissas!$C$39),IF(N(Premissas!$F$39)>0,IF(MOD(INT(Cron_Uso!B5/Premissas!$C$39)*Premissas!$C$39,N(Premissas!$F$39))=0,"C",IF(N(Premissas!$E$39)>0,IF(MOD(INT(Cron_Uso!B5/Premissas!$C$39)*Premissas!$C$39,N(Premissas!$E$39))=0,"B",IF(N(Premissas!$D$39)>0,IF(MOD(INT(Cron_Uso!B5/Premissas!$C$39)*Premissas!$C$39,N(Premissas!$D$39))=0,"A","S"),"S")),IF(N(Premissas!$D$39)>0,IF(MOD(INT(Cron_Uso!B5/Premissas!$C$39)*Premissas!$C$39,N(Premissas!$D$39))=0,"A","S"),"S"))),IF(N(Premissas!$E$39)>0,IF(MOD(INT(Cron_Uso!B5/Premissas!$C$39)*Premissas!$C$39,N(Premissas!$E$39))=0,"B",IF(N(Premissas!$D$39)>0,IF(MOD(INT(Cron_Uso!B5/Premissas!$C$39)*Premissas!$C$39,N(Premissas!$D$39))=0,"A","S"),"S")),IF(N(Premissas!$D$39)>0,IF(MOD(INT(Cron_Uso!B5/Premissas!$C$39)*Premissas!$C$39,N(Premissas!$D$39))=0,"A","S"),"S"))),"") | C5: =IF(INT(Cron_Uso!C5/Premissas!$C$39)>INT(Cron_Uso!B5/Premissas!$C$39),IF(N(Premissas!$F$39)>0,IF(MOD(INT(Cron_Uso!C5/Premissas!$C$39)*Premissas!$C$39,N(Premissas!$F$39))=0,"C",IF(N(Premissas!$E$39)>0,IF(MOD(INT(Cron_Uso!C5/Premissas!$C$39)*Premissas!$C$39,N(Premissas!$E$39))=0,"B",IF(N(Premissas!$D$39)>0,IF(MOD(INT(Cron_Uso!C5/Premissas!$C$39)*Premissas!$C$39,N(Premissas!$D$39))=0,"A","S"),"S")),IF(N(Premissas!$D$39)>0,IF(MOD(INT(Cron_Uso!C5/Premissas!$C$39)*Premissas!$C$39,N(Premissas!$D$39))=0,"A","S"),"S"))),IF(N(Premissas!$E$39)>0,IF(MOD(INT(Cron_Uso!C5/Premissas!$C$39)*Premissas!$C$39,N(Premissas!$E$39))=0,"B",IF(N(Premissas!$D$39)>0,IF(MOD(INT(Cron_Uso!C5/Premissas!$C$39)*Premissas!$C$39,N(Premissas!$D$39))=0,"A","S"),"S")),IF(N(Premissas!$D$39)>0,IF(MOD(INT(Cron_Uso!C5/Premissas!$C$39)*Premissas!$C$39,N(Premissas!$D$39))=0,"A","S"),"S"))),"") | D5: =IF(INT(Cron_Uso!D5/Premissas!$C$39)>INT(Cron_Uso!C5/Premissas!$C$39),IF(N(Premissas!$F$39)>0,IF(MOD(INT(Cron_Uso!D5/Premissas!$C$39)*Premissas!$C$39,N(Premissas!$F$39))=0,"C",IF(N(Premissas!$E$39)>0,IF(MOD(INT(Cron_Uso!D5/Premissas!$C$39)*Premissas!$C$39,N(Premissas!$E$39))=0,"B",IF(N(Premissas!$D$39)>0,IF(MOD(INT(Cron_Uso!D5/Premissas!$C$39)*Premissas!$C$39,N(Premissas!$D$39))=0,"A","S"),"S")),IF(N(Premissas!$D$39)>0,IF(MOD(INT(Cron_Uso!D5/Premissas!$C$39)*Premissas!$C$39,N(Premissas!$D$39))=0,"A","S"),"S"))),IF(N(Premissas!$E$39)>0,IF(MOD(INT(Cron_Uso!D5/Premissas!$C$39)*Premissas!$C$39,N(Premissas!$E$39))=0,"B",IF(N(Premissas!$D$39)>0,IF(MOD(INT(Cron_Uso!D5/Premissas!$C$39)*Premissas!$C$39,N(Premissas!$D$39))=0,"A","S"),"S")),IF(N(Premissas!$D$39)>0,IF(MOD(INT(Cron_Uso!D5/Premissas!$C$39)*Premissas!$C$39,N(Premissas!$D$39))=0,"A","S"),"S"))),"") -> S | E5: =IF(INT(Cron_Uso!E5/Premissas!$C$39)>INT(Cron_Uso!D5/Premissas!$C$39),IF(N(Premissas!$F$39)>0,IF(MOD(INT(Cron_Uso!E5/Premissas!$C$39)*Premissas!$C$39,N(Premissas!$F$39))=0,"C",IF(N(Premissas!$E$39)>0,IF(MOD(INT(Cron_Uso!E5/Premissas!$C$39)*Premissas!$C$39,N(Premissas!$E$39))=0,"B",IF(N(Premissas!$D$39)>0,IF(MOD(INT(Cron_Uso!E5/Premissas!$C$39)*Premissas!$C$39,N(Premissas!$D$39))=0,"A","S"),"S")),IF(N(Premissas!$D$39)>0,IF(MOD(INT(Cron_Uso!E5/Premissas!$C$39)*Premissas!$C$39,N(Premissas!$D$39))=0,"A","S"),"S"))),IF(N(Premissas!$E$39)>0,IF(MOD(INT(Cron_Uso!E5/Premissas!$C$39)*Premissas!$C$39,N(Premissas!$E$39))=0,"B",IF(N(Premissas!$D$39)>0,IF(MOD(INT(Cron_Uso!E5/Premissas!$C$39)*Premissas!$C$39,N(Premissas!$D$39))=0,"A","S"),"S")),IF(N(Premissas!$D$39)>0,IF(MOD(INT(Cron_Uso!E5/Premissas!$C$39)*Premissas!$C$39,N(Premissas!$D$39))=0,"A","S"),"S"))),"") | F5: =IF(INT(Cron_Uso!F5/Premissas!$C$39)>INT(Cron_Uso!E5/Premissas!$C$39),IF(N(Premissas!$F$39)>0,IF(MOD(INT(Cron_Uso!F5/Premissas!$C$39)*Premissas!$C$39,N(Premissas!$F$39))=0,"C",IF(N(Premissas!$E$39)>0,IF(MOD(INT(Cron_Uso!F5/Premissas!$C$39)*Premissas!$C$39,N(Premissas!$E$39))=0,"B",IF(N(Premissas!$D$39)>0,IF(MOD(INT(Cron_Uso!F5/Premissas!$C$39)*Premissas!$C$39,N(Premissas!$D$39))=0,"A","S"),"S")),IF(N(Premissas!$D$39)>0,IF(MOD(INT(Cron_Uso!F5/Premissas!$C$39)*Premissas!$C$39,N(Premissas!$D$39))=0,"A","S"),"S"))),IF(N(Premissas!$E$39)>0,IF(MOD(INT(Cron_Uso!F5/Premissas!$C$39)*Premissas!$C$39,N(Premissas!$E$39))=0,"B",IF(N(Premissas!$D$39)>0,IF(MOD(INT(Cron_Uso!F5/Premissas!$C$39)*Premissas!$C$39,N(Premissas!$D$39))=0,"A","S"),"S")),IF(N(Premissas!$D$39)>0,IF(MOD(INT(Cron_Uso!F5/Premissas!$C$39)*Premissas!$C$39,N(Premissas!$D$39))=0,"A","S"),"S"))),"") -> A | G5: =IF(INT(Cron_Uso!G5/Premissas!$C$39)>INT(Cron_Uso!F5/Premissas!$C$39),IF(N(Premissas!$F$39)>0,IF(MOD(INT(Cron_Uso!G5/Premissas!$C$39)*Premissas!$C$39,N(Premissas!$F$39))=0,"C",IF(N(Premissas!$E$39)>0,IF(MOD(INT(Cron_Uso!G5/Premissas!$C$39)*Premissas!$C$39,N(Premissas!$E$39))=0,"B",IF(N(Premissas!$D$39)>0,IF(MOD(INT(Cron_Uso!G5/Premissas!$C$39)*Premissas!$C$39,N(Premissas!$D$39))=0,"A","S"),"S")),IF(N(Premissas!$D$39)>0,IF(MOD(INT(Cron_Uso!G5/Premissas!$C$39)*Premissas!$C$39,N(Premissas!$D$39))=0,"A","S"),"S"))),IF(N(Premissas!$E$39)>0,IF(MOD(INT(Cron_Uso!G5/Premissas!$C$39)*Premissas!$C$39,N(Premissas!$E$39))=0,"B",IF(N(Premissas!$D$39)>0,IF(MOD(INT(Cron_Uso!G5/Premissas!$C$39)*Premissas!$C$39,N(Premissas!$D$39))=0,"A","S"),"S")),IF(N(Premissas!$D$39)>0,IF(MOD(INT(Cron_Uso!G5/Premissas!$C$39)*Premissas!$C$39,N(Premissas!$D$39))=0,"A","S"),"S"))),"") | H5: =IF(INT(Cron_Uso!H5/Premissas!$C$39)>INT(Cron_Uso!G5/Premissas!$C$39),IF(N(Premissas!$F$39)>0,IF(MOD(INT(Cron_Uso!H5/Premissas!$C$39)*Premissas!$C$39,N(Premissas!$F$39))=0,"C",IF(N(Premissas!$E$39)>0,IF(MOD(INT(Cron_Uso!H5/Premissas!$C$39)*Premissas!$C$39,N(Premissas!$E$39))=0,"B",IF(N(Premissas!$D$39)>0,IF(MOD(INT(Cron_Uso!H5/Premissas!$C$39)*Premissas!$C$39,N(Premissas!$D$39))=0,"A","S"),"S")),IF(N(Premissas!$D$39)>0,IF(MOD(INT(Cron_Uso!H5/Premissas!$C$39)*Premissas!$C$39,N(Premissas!$D$39))=0,"A","S"),"S"))),IF(N(Premissas!$E$39)>0,IF(MOD(INT(Cron_Uso!H5/Premissas!$C$39)*Premissas!$C$39,N(Premissas!$E$39))=0,"B",IF(N(Premissas!$D$39)>0,IF(MOD(INT(Cron_Uso!H5/Premissas!$C$39)*Premissas!$C$39,N(Premissas!$D$39))=0,"A","S"),"S")),IF(N(Premissas!$D$39)>0,IF(MOD(INT(Cron_Uso!H5/Premissas!$C$39)*Premissas!$C$39,N(Premissas!$D$39))=0,"A","S"),"S"))),"") | I5: =IF(INT(Cron_Uso!I5/Premissas!$C$39)>INT(Cron_Uso!H5/Premissas!$C$39),IF(N(Premissas!$F$39)>0,IF(MOD(INT(Cron_Uso!I5/Premissas!$C$39)*Premissas!$C$39,N(Premissas!$F$39))=0,"C",IF(N(Premissas!$E$39)>0,IF(MOD(INT(Cron_Uso!I5/Premissas!$C$39)*Premissas!$C$39,N(Premissas!$E$39))=0,"B",IF(N(Premissas!$D$39)>0,IF(MOD(INT(Cron_Uso!I5/Premissas!$C$39)*Premissas!$C$39,N(Premissas!$D$39))=0,"A","S"),"S")),IF(N(Premissas!$D$39)>0,IF(MOD(INT(Cron_Uso!I5/Premissas!$C$39)*Premissas!$C$39,N(Premissas!$D$39))=0,"A","S"),"S"))),IF(N(Premissas!$E$39)>0,IF(MOD(INT(Cron_Uso!I5/Premissas!$C$39)*Premissas!$C$39,N(Premissas!$E$39))=0,"B",IF(N(Premissas!$D$39)>0,IF(MOD(INT(Cron_Uso!I5/Premissas!$C$39)*Premissas!$C$39,N(Premissas!$D$39))=0,"A","S"),"S")),IF(N(Premissas!$D$39)>0,IF(MOD(INT(Cron_Uso!I5/Premissas!$C$39)*Premissas!$C$39,N(Premissas!$D$39))=0,"A","S"),"S"))),"") -> S | J5: =IF(INT(Cron_Uso!J5/Premissas!$C$39)>INT(Cron_Uso!I5/Premissas!$C$39),IF(N(Premissas!$F$39)>0,IF(MOD(INT(Cron_Uso!J5/Premissas!$C$39)*Premissas!$C$39,N(Premissas!$F$39))=0,"C",IF(N(Premissas!$E$39)>0,IF(MOD(INT(Cron_Uso!J5/Premissas!$C$39)*Premissas!$C$39,N(Premissas!$E$39))=0,"B",IF(N(Premissas!$D$39)>0,IF(MOD(INT(Cron_Uso!J5/Premissas!$C$39)*Premissas!$C$39,N(Premissas!$D$39))=0,"A","S"),"S")),IF(N(Premissas!$D$39)>0,IF(MOD(INT(Cron_Uso!J5/Premissas!$C$39)*Premissas!$C$39,N(Premissas!$D$39))=0,"A","S"),"S"))),IF(N(Premissas!$E$39)>0,IF(MOD(INT(Cron_Uso!J5/Premissas!$C$39)*Premissas!$C$39,N(Premissas!$E$39))=0,"B",IF(N(Premissas!$D$39)>0,IF(MOD(INT(Cron_Uso!J5/Premissas!$C$39)*Premissas!$C$39,N(Premissas!$D$39))=0,"A","S"),"S")),IF(N(Premissas!$D$39)>0,IF(MOD(INT(Cron_Uso!J5/Premissas!$C$39)*Premissas!$C$39,N(Premissas!$D$39))=0,"A","S"),"S"))),"") | ... BA5: =IF(INT(Cron_Uso!BA5/Premissas!$C$39)>INT(Cron_Uso!AZ5/Premissas!$C$39),IF(N(Premissas!$F$39)>0,IF(MOD(INT(Cron_Uso!BA5/Premissas!$C$39)*Premissas!$C$39,N(Premissas!$F$39))=0,"C",IF(N(Premissas!$E$39)>0,IF(MOD(INT(Cron_Uso!BA5/Premissas!$C$39)*Premissas!$C$39,N(Premissas!$E$39))=0,"B",IF(N(Premissas!$D$39)>0,IF(MOD(INT(Cron_Uso!BA5/Premissas!$C$39)*Premissas!$C$39,N(Premissas!$D$39))=0,"A","S"),"S")),IF(N(Premissas!$D$39)>0,IF(MOD(INT(Cron_Uso!BA5/Premissas!$C$39)*Premissas!$C$39,N(Premissas!$D$39))=0,"A","S"),"S"))),IF(N(Premissas!$E$39)>0,IF(MOD(INT(Cron_Uso!BA5/Premissas!$C$39)*Premissas!$C$39,N(Premissas!$E$39))=0,"B",IF(N(Premissas!$D$39)>0,IF(MOD(INT(Cron_Uso!BA5/Premissas!$C$39)*Premissas!$C$39,N(Premissas!$D$39))=0,"A","S"),"S")),IF(N(Premissas!$D$39)>0,IF(MOD(INT(Cron_Uso!BA5/Premissas!$C$39)*Premissas!$C$39,N(Premissas!$D$39))=0,"A","S"),"S"))),"")
A6: =Premissas!$A$40&" (×"&Premissas!$I$40&")" -> Trator (×102) | B6: =IF(INT(Cron_Uso!B6/Premissas!$C$40)>INT(Premissas!$J$40/Premissas!$C$40),IF(N(Premissas!$F$40)>0,IF(MOD(INT(Cron_Uso!B6/Premissas!$C$40)*Premissas!$C$40,N(Premissas!$F$40))=0,"C",IF(N(Premissas!$E$40)>0,IF(MOD(INT(Cron_Uso!B6/Premissas!$C$40)*Premissas!$C$40,N(Premissas!$E$40))=0,"B",IF(N(Premissas!$D$40)>0,IF(MOD(INT(Cron_Uso!B6/Premissas!$C$40)*Premissas!$C$40,N(Premissas!$D$40))=0,"A","S"),"S")),IF(N(Premissas!$D$40)>0,IF(MOD(INT(Cron_Uso!B6/Premissas!$C$40)*Premissas!$C$40,N(Premissas!$D$40))=0,"A","S"),"S"))),IF(N(Premissas!$E$40)>0,IF(MOD(INT(Cron_Uso!B6/Premissas!$C$40)*Premissas!$C$40,N(Premissas!$E$40))=0,"B",IF(N(Premissas!$D$40)>0,IF(MOD(INT(Cron_Uso!B6/Premissas!$C$40)*Premissas!$C$40,N(Premissas!$D$40))=0,"A","S"),"S")),IF(N(Premissas!$D$40)>0,IF(MOD(INT(Cron_Uso!B6/Premissas!$C$40)*Premissas!$C$40,N(Premissas!$D$40))=0,"A","S"),"S"))),"") | C6: =IF(INT(Cron_Uso!C6/Premissas!$C$40)>INT(Cron_Uso!B6/Premissas!$C$40),IF(N(Premissas!$F$40)>0,IF(MOD(INT(Cron_Uso!C6/Premissas!$C$40)*Premissas!$C$40,N(Premissas!$F$40))=0,"C",IF(N(Premissas!$E$40)>0,IF(MOD(INT(Cron_Uso!C6/Premissas!$C$40)*Premissas!$C$40,N(Premissas!$E$40))=0,"B",IF(N(Premissas!$D$40)>0,IF(MOD(INT(Cron_Uso!C6/Premissas!$C$40)*Premissas!$C$40,N(Premissas!$D$40))=0,"A","S"),"S")),IF(N(Premissas!$D$40)>0,IF(MOD(INT(Cron_Uso!C6/Premissas!$C$40)*Premissas!$C$40,N(Premissas!$D$40))=0,"A","S"),"S"))),IF(N(Premissas!$E$40)>0,IF(MOD(INT(Cron_Uso!C6/Premissas!$C$40)*Premissas!$C$40,N(Premissas!$E$40))=0,"B",IF(N(Premissas!$D$40)>0,IF(MOD(INT(Cron_Uso!C6/Premissas!$C$40)*Premissas!$C$40,N(Premissas!$D$40))=0,"A","S"),"S")),IF(N(Premissas!$D$40)>0,IF(MOD(INT(Cron_Uso!C6/Premissas!$C$40)*Premissas!$C$40,N(Premissas!$D$40))=0,"A","S"),"S"))),"") | D6: =IF(INT(Cron_Uso!D6/Premissas!$C$40)>INT(Cron_Uso!C6/Premissas!$C$40),IF(N(Premissas!$F$40)>0,IF(MOD(INT(Cron_Uso!D6/Premissas!$C$40)*Premissas!$C$40,N(Premissas!$F$40))=0,"C",IF(N(Premissas!$E$40)>0,IF(MOD(INT(Cron_Uso!D6/Premissas!$C$40)*Premissas!$C$40,N(Premissas!$E$40))=0,"B",IF(N(Premissas!$D$40)>0,IF(MOD(INT(Cron_Uso!D6/Premissas!$C$40)*Premissas!$C$40,N(Premissas!$D$40))=0,"A","S"),"S")),IF(N(Premissas!$D$40)>0,IF(MOD(INT(Cron_Uso!D6/Premissas!$C$40)*Premissas!$C$40,N(Premissas!$D$40))=0,"A","S"),"S"))),IF(N(Premissas!$E$40)>0,IF(MOD(INT(Cron_Uso!D6/Premissas!$C$40)*Premissas!$C$40,N(Premissas!$E$40))=0,"B",IF(N(Premissas!$D$40)>0,IF(MOD(INT(Cron_Uso!D6/Premissas!$C$40)*Premissas!$C$40,N(Premissas!$D$40))=0,"A","S"),"S")),IF(N(Premissas!$D$40)>0,IF(MOD(INT(Cron_Uso!D6/Premissas!$C$40)*Premissas!$C$40,N(Premissas!$D$40))=0,"A","S"),"S"))),"") | E6: =IF(INT(Cron_Uso!E6/Premissas!$C$40)>INT(Cron_Uso!D6/Premissas!$C$40),IF(N(Premissas!$F$40)>0,IF(MOD(INT(Cron_Uso!E6/Premissas!$C$40)*Premissas!$C$40,N(Premissas!$F$40))=0,"C",IF(N(Premissas!$E$40)>0,IF(MOD(INT(Cron_Uso!E6/Premissas!$C$40)*Premissas!$C$40,N(Premissas!$E$40))=0,"B",IF(N(Premissas!$D$40)>0,IF(MOD(INT(Cron_Uso!E6/Premissas!$C$40)*Premissas!$C$40,N(Premissas!$D$40))=0,"A","S"),"S")),IF(N(Premissas!$D$40)>0,IF(MOD(INT(Cron_Uso!E6/Premissas!$C$40)*Premissas!$C$40,N(Premissas!$D$40))=0,"A","S"),"S"))),IF(N(Premissas!$E$40)>0,IF(MOD(INT(Cron_Uso!E6/Premissas!$C$40)*Premissas!$C$40,N(Premissas!$E$40))=0,"B",IF(N(Premissas!$D$40)>0,IF(MOD(INT(Cron_Uso!E6/Premissas!$C$40)*Premissas!$C$40,N(Premissas!$D$40))=0,"A","S"),"S")),IF(N(Premissas!$D$40)>0,IF(MOD(INT(Cron_Uso!E6/Premissas!$C$40)*Premissas!$C$40,N(Premissas!$D$40))=0,"A","S"),"S"))),"") | F6: =IF(INT(Cron_Uso!F6/Premissas!$C$40)>INT(Cron_Uso!E6/Premissas!$C$40),IF(N(Premissas!$F$40)>0,IF(MOD(INT(Cron_Uso!F6/Premissas!$C$40)*Premissas!$C$40,N(Premissas!$F$40))=0,"C",IF(N(Premissas!$E$40)>0,IF(MOD(INT(Cron_Uso!F6/Premissas!$C$40)*Premissas!$C$40,N(Premissas!$E$40))=0,"B",IF(N(Premissas!$D$40)>0,IF(MOD(INT(Cron_Uso!F6/Premissas!$C$40)*Premissas!$C$40,N(Premissas!$D$40))=0,"A","S"),"S")),IF(N(Premissas!$D$40)>0,IF(MOD(INT(Cron_Uso!F6/Premissas!$C$40)*Premissas!$C$40,N(Premissas!$D$40))=0,"A","S"),"S"))),IF(N(Premissas!$E$40)>0,IF(MOD(INT(Cron_Uso!F6/Premissas!$C$40)*Premissas!$C$40,N(Premissas!$E$40))=0,"B",IF(N(Premissas!$D$40)>0,IF(MOD(INT(Cron_Uso!F6/Premissas!$C$40)*Premissas!$C$40,N(Premissas!$D$40))=0,"A","S"),"S")),IF(N(Premissas!$D$40)>0,IF(MOD(INT(Cron_Uso!F6/Premissas!$C$40)*Premissas!$C$40,N(Premissas!$D$40))=0,"A","S"),"S"))),"") | G6: =IF(INT(Cron_Uso!G6/Premissas!$C$40)>INT(Cron_Uso!F6/Premissas!$C$40),IF(N(Premissas!$F$40)>0,IF(MOD(INT(Cron_Uso!G6/Premissas!$C$40)*Premissas!$C$40,N(Premissas!$F$40))=0,"C",IF(N(Premissas!$E$40)>0,IF(MOD(INT(Cron_Uso!G6/Premissas!$C$40)*Premissas!$C$40,N(Premissas!$E$40))=0,"B",IF(N(Premissas!$D$40)>0,IF(MOD(INT(Cron_Uso!G6/Premissas!$C$40)*Premissas!$C$40,N(Premissas!$D$40))=0,"A","S"),"S")),IF(N(Premissas!$D$40)>0,IF(MOD(INT(Cron_Uso!G6/Premissas!$C$40)*Premissas!$C$40,N(Premissas!$D$40))=0,"A","S"),"S"))),IF(N(Premissas!$E$40)>0,IF(MOD(INT(Cron_Uso!G6/Premissas!$C$40)*Premissas!$C$40,N(Premissas!$E$40))=0,"B",IF(N(Premissas!$D$40)>0,IF(MOD(INT(Cron_Uso!G6/Premissas!$C$40)*Premissas!$C$40,N(Premissas!$D$40))=0,"A","S"),"S")),IF(N(Premissas!$D$40)>0,IF(MOD(INT(Cron_Uso!G6/Premissas!$C$40)*Premissas!$C$40,N(Premissas!$D$40))=0,"A","S"),"S"))),"") | H6: =IF(INT(Cron_Uso!H6/Premissas!$C$40)>INT(Cron_Uso!G6/Premissas!$C$40),IF(N(Premissas!$F$40)>0,IF(MOD(INT(Cron_Uso!H6/Premissas!$C$40)*Premissas!$C$40,N(Premissas!$F$40))=0,"C",IF(N(Premissas!$E$40)>0,IF(MOD(INT(Cron_Uso!H6/Premissas!$C$40)*Premissas!$C$40,N(Premissas!$E$40))=0,"B",IF(N(Premissas!$D$40)>0,IF(MOD(INT(Cron_Uso!H6/Premissas!$C$40)*Premissas!$C$40,N(Premissas!$D$40))=0,"A","S"),"S")),IF(N(Premissas!$D$40)>0,IF(MOD(INT(Cron_Uso!H6/Premissas!$C$40)*Premissas!$C$40,N(Premissas!$D$40))=0,"A","S"),"S"))),IF(N(Premissas!$E$40)>0,IF(MOD(INT(Cron_Uso!H6/Premissas!$C$40)*Premissas!$C$40,N(Premissas!$E$40))=0,"B",IF(N(Premissas!$D$40)>0,IF(MOD(INT(Cron_Uso!H6/Premissas!$C$40)*Premissas!$C$40,N(Premissas!$D$40))=0,"A","S"),"S")),IF(N(Premissas!$D$40)>0,IF(MOD(INT(Cron_Uso!H6/Premissas!$C$40)*Premissas!$C$40,N(Premissas!$D$40))=0,"A","S"),"S"))),"") -> S | I6: =IF(INT(Cron_Uso!I6/Premissas!$C$40)>INT(Cron_Uso!H6/Premissas!$C$40),IF(N(Premissas!$F$40)>0,IF(MOD(INT(Cron_Uso!I6/Premissas!$C$40)*Premissas!$C$40,N(Premissas!$F$40))=0,"C",IF(N(Premissas!$E$40)>0,IF(MOD(INT(Cron_Uso!I6/Premissas!$C$40)*Premissas!$C$40,N(Premissas!$E$40))=0,"B",IF(N(Premissas!$D$40)>0,IF(MOD(INT(Cron_Uso!I6/Premissas!$C$40)*Premissas!$C$40,N(Premissas!$D$40))=0,"A","S"),"S")),IF(N(Premissas!$D$40)>0,IF(MOD(INT(Cron_Uso!I6/Premissas!$C$40)*Premissas!$C$40,N(Premissas!$D$40))=0,"A","S"),"S"))),IF(N(Premissas!$E$40)>0,IF(MOD(INT(Cron_Uso!I6/Premissas!$C$40)*Premissas!$C$40,N(Premissas!$E$40))=0,"B",IF(N(Premissas!$D$40)>0,IF(MOD(INT(Cron_Uso!I6/Premissas!$C$40)*Premissas!$C$40,N(Premissas!$D$40))=0,"A","S"),"S")),IF(N(Premissas!$D$40)>0,IF(MOD(INT(Cron_Uso!I6/Premissas!$C$40)*Premissas!$C$40,N(Premissas!$D$40))=0,"A","S"),"S"))),"") | J6: =IF(INT(Cron_Uso!J6/Premissas!$C$40)>INT(Cron_Uso!I6/Premissas!$C$40),IF(N(Premissas!$F$40)>0,IF(MOD(INT(Cron_Uso!J6/Premissas!$C$40)*Premissas!$C$40,N(Premissas!$F$40))=0,"C",IF(N(Premissas!$E$40)>0,IF(MOD(INT(Cron_Uso!J6/Premissas!$C$40)*Premissas!$C$40,N(Premissas!$E$40))=0,"B",IF(N(Premissas!$D$40)>0,IF(MOD(INT(Cron_Uso!J6/Premissas!$C$40)*Premissas!$C$40,N(Premissas!$D$40))=0,"A","S"),"S")),IF(N(Premissas!$D$40)>0,IF(MOD(INT(Cron_Uso!J6/Premissas!$C$40)*Premissas!$C$40,N(Premissas!$D$40))=0,"A","S"),"S"))),IF(N(Premissas!$E$40)>0,IF(MOD(INT(Cron_Uso!J6/Premissas!$C$40)*Premissas!$C$40,N(Premissas!$E$40))=0,"B",IF(N(Premissas!$D$40)>0,IF(MOD(INT(Cron_Uso!J6/Premissas!$C$40)*Premissas!$C$40,N(Premissas!$D$40))=0,"A","S"),"S")),IF(N(Premissas!$D$40)>0,IF(MOD(INT(Cron_Uso!J6/Premissas!$C$40)*Premissas!$C$40,N(Premissas!$D$40))=0,"A","S"),"S"))),"") | ... BA6: =IF(INT(Cron_Uso!BA6/Premissas!$C$40)>INT(Cron_Uso!AZ6/Premissas!$C$40),IF(N(Premissas!$F$40)>0,IF(MOD(INT(Cron_Uso!BA6/Premissas!$C$40)*Premissas!$C$40,N(Premissas!$F$40))=0,"C",IF(N(Premissas!$E$40)>0,IF(MOD(INT(Cron_Uso!BA6/Premissas!$C$40)*Premissas!$C$40,N(Premissas!$E$40))=0,"B",IF(N(Premissas!$D$40)>0,IF(MOD(INT(Cron_Uso!BA6/Premissas!$C$40)*Premissas!$C$40,N(Premissas!$D$40))=0,"A","S"),"S")),IF(N(Premissas!$D$40)>0,IF(MOD(INT(Cron_Uso!BA6/Premissas!$C$40)*Premissas!$C$40,N(Premissas!$D$40))=0,"A","S"),"S"))),IF(N(Premissas!$E$40)>0,IF(MOD(INT(Cron_Uso!BA6/Premissas!$C$40)*Premissas!$C$40,N(Premissas!$E$40))=0,"B",IF(N(Premissas!$D$40)>0,IF(MOD(INT(Cron_Uso!BA6/Premissas!$C$40)*Premissas!$C$40,N(Premissas!$D$40))=0,"A","S"),"S")),IF(N(Premissas!$D$40)>0,IF(MOD(INT(Cron_Uso!BA6/Premissas!$C$40)*Premissas!$C$40,N(Premissas!$D$40))=0,"A","S"),"S"))),"")
A7: =Premissas!$A$41&" (×"&Premissas!$I$41&")" -> Caminhão (×121) | B7: =IF(INT(Cron_Uso!B7/Premissas!$C$41)>INT(Premissas!$J$41/Premissas!$C$41),IF(N(Premissas!$F$41)>0,IF(MOD(INT(Cron_Uso!B7/Premissas!$C$41)*Premissas!$C$41,N(Premissas!$F$41))=0,"C",IF(N(Premissas!$E$41)>0,IF(MOD(INT(Cron_Uso!B7/Premissas!$C$41)*Premissas!$C$41,N(Premissas!$E$41))=0,"B",IF(N(Premissas!$D$41)>0,IF(MOD(INT(Cron_Uso!B7/Premissas!$C$41)*Premissas!$C$41,N(Premissas!$D$41))=0,"A","S"),"S")),IF(N(Premissas!$D$41)>0,IF(MOD(INT(Cron_Uso!B7/Premissas!$C$41)*Premissas!$C$41,N(Premissas!$D$41))=0,"A","S"),"S"))),IF(N(Premissas!$E$41)>0,IF(MOD(INT(Cron_Uso!B7/Premissas!$C$41)*Premissas!$C$41,N(Premissas!$E$41))=0,"B",IF(N(Premissas!$D$41)>0,IF(MOD(INT(Cron_Uso!B7/Premissas!$C$41)*Premissas!$C$41,N(Premissas!$D$41))=0,"A","S"),"S")),IF(N(Premissas!$D$41)>0,IF(MOD(INT(Cron_Uso!B7/Premissas!$C$41)*Premissas!$C$41,N(Premissas!$D$41))=0,"A","S"),"S"))),"") | C7: =IF(INT(Cron_Uso!C7/Premissas!$C$41)>INT(Cron_Uso!B7/Premissas!$C$41),IF(N(Premissas!$F$41)>0,IF(MOD(INT(Cron_Uso!C7/Premissas!$C$41)*Premissas!$C$41,N(Premissas!$F$41))=0,"C",IF(N(Premissas!$E$41)>0,IF(MOD(INT(Cron_Uso!C7/Premissas!$C$41)*Premissas!$C$41,N(Premissas!$E$41))=0,"B",IF(N(Premissas!$D$41)>0,IF(MOD(INT(Cron_Uso!C7/Premissas!$C$41)*Premissas!$C$41,N(Premissas!$D$41))=0,"A","S"),"S")),IF(N(Premissas!$D$41)>0,IF(MOD(INT(Cron_Uso!C7/Premissas!$C$41)*Premissas!$C$41,N(Premissas!$D$41))=0,"A","S"),"S"))),IF(N(Premissas!$E$41)>0,IF(MOD(INT(Cron_Uso!C7/Premissas!$C$41)*Premissas!$C$41,N(Premissas!$E$41))=0,"B",IF(N(Premissas!$D$41)>0,IF(MOD(INT(Cron_Uso!C7/Premissas!$C$41)*Premissas!$C$41,N(Premissas!$D$41))=0,"A","S"),"S")),IF(N(Premissas!$D$41)>0,IF(MOD(INT(Cron_Uso!C7/Premissas!$C$41)*Premissas!$C$41,N(Premissas!$D$41))=0,"A","S"),"S"))),"") | D7: =IF(INT(Cron_Uso!D7/Premissas!$C$41)>INT(Cron_Uso!C7/Premissas!$C$41),IF(N(Premissas!$F$41)>0,IF(MOD(INT(Cron_Uso!D7/Premissas!$C$41)*Premissas!$C$41,N(Premissas!$F$41))=0,"C",IF(N(Premissas!$E$41)>0,IF(MOD(INT(Cron_Uso!D7/Premissas!$C$41)*Premissas!$C$41,N(Premissas!$E$41))=0,"B",IF(N(Premissas!$D$41)>0,IF(MOD(INT(Cron_Uso!D7/Premissas!$C$41)*Premissas!$C$41,N(Premissas!$D$41))=0,"A","S"),"S")),IF(N(Premissas!$D$41)>0,IF(MOD(INT(Cron_Uso!D7/Premissas!$C$41)*Premissas!$C$41,N(Premissas!$D$41))=0,"A","S"),"S"))),IF(N(Premissas!$E$41)>0,IF(MOD(INT(Cron_Uso!D7/Premissas!$C$41)*Premissas!$C$41,N(Premissas!$E$41))=0,"B",IF(N(Premissas!$D$41)>0,IF(MOD(INT(Cron_Uso!D7/Premissas!$C$41)*Premissas!$C$41,N(Premissas!$D$41))=0,"A","S"),"S")),IF(N(Premissas!$D$41)>0,IF(MOD(INT(Cron_Uso!D7/Premissas!$C$41)*Premissas!$C$41,N(Premissas!$D$41))=0,"A","S"),"S"))),"") | E7: =IF(INT(Cron_Uso!E7/Premissas!$C$41)>INT(Cron_Uso!D7/Premissas!$C$41),IF(N(Premissas!$F$41)>0,IF(MOD(INT(Cron_Uso!E7/Premissas!$C$41)*Premissas!$C$41,N(Premissas!$F$41))=0,"C",IF(N(Premissas!$E$41)>0,IF(MOD(INT(Cron_Uso!E7/Premissas!$C$41)*Premissas!$C$41,N(Premissas!$E$41))=0,"B",IF(N(Premissas!$D$41)>0,IF(MOD(INT(Cron_Uso!E7/Premissas!$C$41)*Premissas!$C$41,N(Premissas!$D$41))=0,"A","S"),"S")),IF(N(Premissas!$D$41)>0,IF(MOD(INT(Cron_Uso!E7/Premissas!$C$41)*Premissas!$C$41,N(Premissas!$D$41))=0,"A","S"),"S"))),IF(N(Premissas!$E$41)>0,IF(MOD(INT(Cron_Uso!E7/Premissas!$C$41)*Premissas!$C$41,N(Premissas!$E$41))=0,"B",IF(N(Premissas!$D$41)>0,IF(MOD(INT(Cron_Uso!E7/Premissas!$C$41)*Premissas!$C$41,N(Premissas!$D$41))=0,"A","S"),"S")),IF(N(Premissas!$D$41)>0,IF(MOD(INT(Cron_Uso!E7/Premissas!$C$41)*Premissas!$C$41,N(Premissas!$D$41))=0,"A","S"),"S"))),"") | F7: =IF(INT(Cron_Uso!F7/Premissas!$C$41)>INT(Cron_Uso!E7/Premissas!$C$41),IF(N(Premissas!$F$41)>0,IF(MOD(INT(Cron_Uso!F7/Premissas!$C$41)*Premissas!$C$41,N(Premissas!$F$41))=0,"C",IF(N(Premissas!$E$41)>0,IF(MOD(INT(Cron_Uso!F7/Premissas!$C$41)*Premissas!$C$41,N(Premissas!$E$41))=0,"B",IF(N(Premissas!$D$41)>0,IF(MOD(INT(Cron_Uso!F7/Premissas!$C$41)*Premissas!$C$41,N(Premissas!$D$41))=0,"A","S"),"S")),IF(N(Premissas!$D$41)>0,IF(MOD(INT(Cron_Uso!F7/Premissas!$C$41)*Premissas!$C$41,N(Premissas!$D$41))=0,"A","S"),"S"))),IF(N(Premissas!$E$41)>0,IF(MOD(INT(Cron_Uso!F7/Premissas!$C$41)*Premissas!$C$41,N(Premissas!$E$41))=0,"B",IF(N(Premissas!$D$41)>0,IF(MOD(INT(Cron_Uso!F7/Premissas!$C$41)*Premissas!$C$41,N(Premissas!$D$41))=0,"A","S"),"S")),IF(N(Premissas!$D$41)>0,IF(MOD(INT(Cron_Uso!F7/Premissas!$C$41)*Premissas!$C$41,N(Premissas!$D$41))=0,"A","S"),"S"))),"") | G7: =IF(INT(Cron_Uso!G7/Premissas!$C$41)>INT(Cron_Uso!F7/Premissas!$C$41),IF(N(Premissas!$F$41)>0,IF(MOD(INT(Cron_Uso!G7/Premissas!$C$41)*Premissas!$C$41,N(Premissas!$F$41))=0,"C",IF(N(Premissas!$E$41)>0,IF(MOD(INT(Cron_Uso!G7/Premissas!$C$41)*Premissas!$C$41,N(Premissas!$E$41))=0,"B",IF(N(Premissas!$D$41)>0,IF(MOD(INT(Cron_Uso!G7/Premissas!$C$41)*Premissas!$C$41,N(Premissas!$D$41))=0,"A","S"),"S")),IF(N(Premissas!$D$41)>0,IF(MOD(INT(Cron_Uso!G7/Premissas!$C$41)*Premissas!$C$41,N(Premissas!$D$41))=0,"A","S"),"S"))),IF(N(Premissas!$E$41)>0,IF(MOD(INT(Cron_Uso!G7/Premissas!$C$41)*Premissas!$C$41,N(Premissas!$E$41))=0,"B",IF(N(Premissas!$D$41)>0,IF(MOD(INT(Cron_Uso!G7/Premissas!$C$41)*Premissas!$C$41,N(Premissas!$D$41))=0,"A","S"),"S")),IF(N(Premissas!$D$41)>0,IF(MOD(INT(Cron_Uso!G7/Premissas!$C$41)*Premissas!$C$41,N(Premissas!$D$41))=0,"A","S"),"S"))),"") | H7: =IF(INT(Cron_Uso!H7/Premissas!$C$41)>INT(Cron_Uso!G7/Premissas!$C$41),IF(N(Premissas!$F$41)>0,IF(MOD(INT(Cron_Uso!H7/Premissas!$C$41)*Premissas!$C$41,N(Premissas!$F$41))=0,"C",IF(N(Premissas!$E$41)>0,IF(MOD(INT(Cron_Uso!H7/Premissas!$C$41)*Premissas!$C$41,N(Premissas!$E$41))=0,"B",IF(N(Premissas!$D$41)>0,IF(MOD(INT(Cron_Uso!H7/Premissas!$C$41)*Premissas!$C$41,N(Premissas!$D$41))=0,"A","S"),"S")),IF(N(Premissas!$D$41)>0,IF(MOD(INT(Cron_Uso!H7/Premissas!$C$41)*Premissas!$C$41,N(Premissas!$D$41))=0,"A","S"),"S"))),IF(N(Premissas!$E$41)>0,IF(MOD(INT(Cron_Uso!H7/Premissas!$C$41)*Premissas!$C$41,N(Premissas!$E$41))=0,"B",IF(N(Premissas!$D$41)>0,IF(MOD(INT(Cron_Uso!H7/Premissas!$C$41)*Premissas!$C$41,N(Premissas!$D$41))=0,"A","S"),"S")),IF(N(Premissas!$D$41)>0,IF(MOD(INT(Cron_Uso!H7/Premissas!$C$41)*Premissas!$C$41,N(Premissas!$D$41))=0,"A","S"),"S"))),"") -> S | I7: =IF(INT(Cron_Uso!I7/Premissas!$C$41)>INT(Cron_Uso!H7/Premissas!$C$41),IF(N(Premissas!$F$41)>0,IF(MOD(INT(Cron_Uso!I7/Premissas!$C$41)*Premissas!$C$41,N(Premissas!$F$41))=0,"C",IF(N(Premissas!$E$41)>0,IF(MOD(INT(Cron_Uso!I7/Premissas!$C$41)*Premissas!$C$41,N(Premissas!$E$41))=0,"B",IF(N(Premissas!$D$41)>0,IF(MOD(INT(Cron_Uso!I7/Premissas!$C$41)*Premissas!$C$41,N(Premissas!$D$41))=0,"A","S"),"S")),IF(N(Premissas!$D$41)>0,IF(MOD(INT(Cron_Uso!I7/Premissas!$C$41)*Premissas!$C$41,N(Premissas!$D$41))=0,"A","S"),"S"))),IF(N(Premissas!$E$41)>0,IF(MOD(INT(Cron_Uso!I7/Premissas!$C$41)*Premissas!$C$41,N(Premissas!$E$41))=0,"B",IF(N(Premissas!$D$41)>0,IF(MOD(INT(Cron_Uso!I7/Premissas!$C$41)*Premissas!$C$41,N(Premissas!$D$41))=0,"A","S"),"S")),IF(N(Premissas!$D$41)>0,IF(MOD(INT(Cron_Uso!I7/Premissas!$C$41)*Premissas!$C$41,N(Premissas!$D$41))=0,"A","S"),"S"))),"") | J7: =IF(INT(Cron_Uso!J7/Premissas!$C$41)>INT(Cron_Uso!I7/Premissas!$C$41),IF(N(Premissas!$F$41)>0,IF(MOD(INT(Cron_Uso!J7/Premissas!$C$41)*Premissas!$C$41,N(Premissas!$F$41))=0,"C",IF(N(Premissas!$E$41)>0,IF(MOD(INT(Cron_Uso!J7/Premissas!$C$41)*Premissas!$C$41,N(Premissas!$E$41))=0,"B",IF(N(Premissas!$D$41)>0,IF(MOD(INT(Cron_Uso!J7/Premissas!$C$41)*Premissas!$C$41,N(Premissas!$D$41))=0,"A","S"),"S")),IF(N(Premissas!$D$41)>0,IF(MOD(INT(Cron_Uso!J7/Premissas!$C$41)*Premissas!$C$41,N(Premissas!$D$41))=0,"A","S"),"S"))),IF(N(Premissas!$E$41)>0,IF(MOD(INT(Cron_Uso!J7/Premissas!$C$41)*Premissas!$C$41,N(Premissas!$E$41))=0,"B",IF(N(Premissas!$D$41)>0,IF(MOD(INT(Cron_Uso!J7/Premissas!$C$41)*Premissas!$C$41,N(Premissas!$D$41))=0,"A","S"),"S")),IF(N(Premissas!$D$41)>0,IF(MOD(INT(Cron_Uso!J7/Premissas!$C$41)*Premissas!$C$41,N(Premissas!$D$41))=0,"A","S"),"S"))),"") | ... BA7: =IF(INT(Cron_Uso!BA7/Premissas!$C$41)>INT(Cron_Uso!AZ7/Premissas!$C$41),IF(N(Premissas!$F$41)>0,IF(MOD(INT(Cron_Uso!BA7/Premissas!$C$41)*Premissas!$C$41,N(Premissas!$F$41))=0,"C",IF(N(Premissas!$E$41)>0,IF(MOD(INT(Cron_Uso!BA7/Premissas!$C$41)*Premissas!$C$41,N(Premissas!$E$41))=0,"B",IF(N(Premissas!$D$41)>0,IF(MOD(INT(Cron_Uso!BA7/Premissas!$C$41)*Premissas!$C$41,N(Premissas!$D$41))=0,"A","S"),"S")),IF(N(Premissas!$D$41)>0,IF(MOD(INT(Cron_Uso!BA7/Premissas!$C$41)*Premissas!$C$41,N(Premissas!$D$41))=0,"A","S"),"S"))),IF(N(Premissas!$E$41)>0,IF(MOD(INT(Cron_Uso!BA7/Premissas!$C$41)*Premissas!$C$41,N(Premissas!$E$41))=0,"B",IF(N(Premissas!$D$41)>0,IF(MOD(INT(Cron_Uso!BA7/Premissas!$C$41)*Premissas!$C$41,N(Premissas!$D$41))=0,"A","S"),"S")),IF(N(Premissas!$D$41)>0,IF(MOD(INT(Cron_Uso!BA7/Premissas!$C$41)*Premissas!$C$41,N(Premissas!$D$41))=0,"A","S"),"S"))),"")
A8: =Premissas!$A$42&" (×"&Premissas!$I$42&")" -> Carregadeira/Pesada (×73) | B8: =IF(INT(Cron_Uso!B8/Premissas!$C$42)>INT(Premissas!$J$42/Premissas!$C$42),IF(N(Premissas!$F$42)>0,IF(MOD(INT(Cron_Uso!B8/Premissas!$C$42)*Premissas!$C$42,N(Premissas!$F$42))=0,"C",IF(N(Premissas!$E$42)>0,IF(MOD(INT(Cron_Uso!B8/Premissas!$C$42)*Premissas!$C$42,N(Premissas!$E$42))=0,"B",IF(N(Premissas!$D$42)>0,IF(MOD(INT(Cron_Uso!B8/Premissas!$C$42)*Premissas!$C$42,N(Premissas!$D$42))=0,"A","S"),"S")),IF(N(Premissas!$D$42)>0,IF(MOD(INT(Cron_Uso!B8/Premissas!$C$42)*Premissas!$C$42,N(Premissas!$D$42))=0,"A","S"),"S"))),IF(N(Premissas!$E$42)>0,IF(MOD(INT(Cron_Uso!B8/Premissas!$C$42)*Premissas!$C$42,N(Premissas!$E$42))=0,"B",IF(N(Premissas!$D$42)>0,IF(MOD(INT(Cron_Uso!B8/Premissas!$C$42)*Premissas!$C$42,N(Premissas!$D$42))=0,"A","S"),"S")),IF(N(Premissas!$D$42)>0,IF(MOD(INT(Cron_Uso!B8/Premissas!$C$42)*Premissas!$C$42,N(Premissas!$D$42))=0,"A","S"),"S"))),"") | C8: =IF(INT(Cron_Uso!C8/Premissas!$C$42)>INT(Cron_Uso!B8/Premissas!$C$42),IF(N(Premissas!$F$42)>0,IF(MOD(INT(Cron_Uso!C8/Premissas!$C$42)*Premissas!$C$42,N(Premissas!$F$42))=0,"C",IF(N(Premissas!$E$42)>0,IF(MOD(INT(Cron_Uso!C8/Premissas!$C$42)*Premissas!$C$42,N(Premissas!$E$42))=0,"B",IF(N(Premissas!$D$42)>0,IF(MOD(INT(Cron_Uso!C8/Premissas!$C$42)*Premissas!$C$42,N(Premissas!$D$42))=0,"A","S"),"S")),IF(N(Premissas!$D$42)>0,IF(MOD(INT(Cron_Uso!C8/Premissas!$C$42)*Premissas!$C$42,N(Premissas!$D$42))=0,"A","S"),"S"))),IF(N(Premissas!$E$42)>0,IF(MOD(INT(Cron_Uso!C8/Premissas!$C$42)*Premissas!$C$42,N(Premissas!$E$42))=0,"B",IF(N(Premissas!$D$42)>0,IF(MOD(INT(Cron_Uso!C8/Premissas!$C$42)*Premissas!$C$42,N(Premissas!$D$42))=0,"A","S"),"S")),IF(N(Premissas!$D$42)>0,IF(MOD(INT(Cron_Uso!C8/Premissas!$C$42)*Premissas!$C$42,N(Premissas!$D$42))=0,"A","S"),"S"))),"") | D8: =IF(INT(Cron_Uso!D8/Premissas!$C$42)>INT(Cron_Uso!C8/Premissas!$C$42),IF(N(Premissas!$F$42)>0,IF(MOD(INT(Cron_Uso!D8/Premissas!$C$42)*Premissas!$C$42,N(Premissas!$F$42))=0,"C",IF(N(Premissas!$E$42)>0,IF(MOD(INT(Cron_Uso!D8/Premissas!$C$42)*Premissas!$C$42,N(Premissas!$E$42))=0,"B",IF(N(Premissas!$D$42)>0,IF(MOD(INT(Cron_Uso!D8/Premissas!$C$42)*Premissas!$C$42,N(Premissas!$D$42))=0,"A","S"),"S")),IF(N(Premissas!$D$42)>0,IF(MOD(INT(Cron_Uso!D8/Premissas!$C$42)*Premissas!$C$42,N(Premissas!$D$42))=0,"A","S"),"S"))),IF(N(Premissas!$E$42)>0,IF(MOD(INT(Cron_Uso!D8/Premissas!$C$42)*Premissas!$C$42,N(Premissas!$E$42))=0,"B",IF(N(Premissas!$D$42)>0,IF(MOD(INT(Cron_Uso!D8/Premissas!$C$42)*Premissas!$C$42,N(Premissas!$D$42))=0,"A","S"),"S")),IF(N(Premissas!$D$42)>0,IF(MOD(INT(Cron_Uso!D8/Premissas!$C$42)*Premissas!$C$42,N(Premissas!$D$42))=0,"A","S"),"S"))),"") | E8: =IF(INT(Cron_Uso!E8/Premissas!$C$42)>INT(Cron_Uso!D8/Premissas!$C$42),IF(N(Premissas!$F$42)>0,IF(MOD(INT(Cron_Uso!E8/Premissas!$C$42)*Premissas!$C$42,N(Premissas!$F$42))=0,"C",IF(N(Premissas!$E$42)>0,IF(MOD(INT(Cron_Uso!E8/Premissas!$C$42)*Premissas!$C$42,N(Premissas!$E$42))=0,"B",IF(N(Premissas!$D$42)>0,IF(MOD(INT(Cron_Uso!E8/Premissas!$C$42)*Premissas!$C$42,N(Premissas!$D$42))=0,"A","S"),"S")),IF(N(Premissas!$D$42)>0,IF(MOD(INT(Cron_Uso!E8/Premissas!$C$42)*Premissas!$C$42,N(Premissas!$D$42))=0,"A","S"),"S"))),IF(N(Premissas!$E$42)>0,IF(MOD(INT(Cron_Uso!E8/Premissas!$C$42)*Premissas!$C$42,N(Premissas!$E$42))=0,"B",IF(N(Premissas!$D$42)>0,IF(MOD(INT(Cron_Uso!E8/Premissas!$C$42)*Premissas!$C$42,N(Premissas!$D$42))=0,"A","S"),"S")),IF(N(Premissas!$D$42)>0,IF(MOD(INT(Cron_Uso!E8/Premissas!$C$42)*Premissas!$C$42,N(Premissas!$D$42))=0,"A","S"),"S"))),"") | F8: =IF(INT(Cron_Uso!F8/Premissas!$C$42)>INT(Cron_Uso!E8/Premissas!$C$42),IF(N(Premissas!$F$42)>0,IF(MOD(INT(Cron_Uso!F8/Premissas!$C$42)*Premissas!$C$42,N(Premissas!$F$42))=0,"C",IF(N(Premissas!$E$42)>0,IF(MOD(INT(Cron_Uso!F8/Premissas!$C$42)*Premissas!$C$42,N(Premissas!$E$42))=0,"B",IF(N(Premissas!$D$42)>0,IF(MOD(INT(Cron_Uso!F8/Premissas!$C$42)*Premissas!$C$42,N(Premissas!$D$42))=0,"A","S"),"S")),IF(N(Premissas!$D$42)>0,IF(MOD(INT(Cron_Uso!F8/Premissas!$C$42)*Premissas!$C$42,N(Premissas!$D$42))=0,"A","S"),"S"))),IF(N(Premissas!$E$42)>0,IF(MOD(INT(Cron_Uso!F8/Premissas!$C$42)*Premissas!$C$42,N(Premissas!$E$42))=0,"B",IF(N(Premissas!$D$42)>0,IF(MOD(INT(Cron_Uso!F8/Premissas!$C$42)*Premissas!$C$42,N(Premissas!$D$42))=0,"A","S"),"S")),IF(N(Premissas!$D$42)>0,IF(MOD(INT(Cron_Uso!F8/Premissas!$C$42)*Premissas!$C$42,N(Premissas!$D$42))=0,"A","S"),"S"))),"") | G8: =IF(INT(Cron_Uso!G8/Premissas!$C$42)>INT(Cron_Uso!F8/Premissas!$C$42),IF(N(Premissas!$F$42)>0,IF(MOD(INT(Cron_Uso!G8/Premissas!$C$42)*Premissas!$C$42,N(Premissas!$F$42))=0,"C",IF(N(Premissas!$E$42)>0,IF(MOD(INT(Cron_Uso!G8/Premissas!$C$42)*Premissas!$C$42,N(Premissas!$E$42))=0,"B",IF(N(Premissas!$D$42)>0,IF(MOD(INT(Cron_Uso!G8/Premissas!$C$42)*Premissas!$C$42,N(Premissas!$D$42))=0,"A","S"),"S")),IF(N(Premissas!$D$42)>0,IF(MOD(INT(Cron_Uso!G8/Premissas!$C$42)*Premissas!$C$42,N(Premissas!$D$42))=0,"A","S"),"S"))),IF(N(Premissas!$E$42)>0,IF(MOD(INT(Cron_Uso!G8/Premissas!$C$42)*Premissas!$C$42,N(Premissas!$E$42))=0,"B",IF(N(Premissas!$D$42)>0,IF(MOD(INT(Cron_Uso!G8/Premissas!$C$42)*Premissas!$C$42,N(Premissas!$D$42))=0,"A","S"),"S")),IF(N(Premissas!$D$42)>0,IF(MOD(INT(Cron_Uso!G8/Premissas!$C$42)*Premissas!$C$42,N(Premissas!$D$42))=0,"A","S"),"S"))),"") -> S | H8: =IF(INT(Cron_Uso!H8/Premissas!$C$42)>INT(Cron_Uso!G8/Premissas!$C$42),IF(N(Premissas!$F$42)>0,IF(MOD(INT(Cron_Uso!H8/Premissas!$C$42)*Premissas!$C$42,N(Premissas!$F$42))=0,"C",IF(N(Premissas!$E$42)>0,IF(MOD(INT(Cron_Uso!H8/Premissas!$C$42)*Premissas!$C$42,N(Premissas!$E$42))=0,"B",IF(N(Premissas!$D$42)>0,IF(MOD(INT(Cron_Uso!H8/Premissas!$C$42)*Premissas!$C$42,N(Premissas!$D$42))=0,"A","S"),"S")),IF(N(Premissas!$D$42)>0,IF(MOD(INT(Cron_Uso!H8/Premissas!$C$42)*Premissas!$C$42,N(Premissas!$D$42))=0,"A","S"),"S"))),IF(N(Premissas!$E$42)>0,IF(MOD(INT(Cron_Uso!H8/Premissas!$C$42)*Premissas!$C$42,N(Premissas!$E$42))=0,"B",IF(N(Premissas!$D$42)>0,IF(MOD(INT(Cron_Uso!H8/Premissas!$C$42)*Premissas!$C$42,N(Premissas!$D$42))=0,"A","S"),"S")),IF(N(Premissas!$D$42)>0,IF(MOD(INT(Cron_Uso!H8/Premissas!$C$42)*Premissas!$C$42,N(Premissas!$D$42))=0,"A","S"),"S"))),"") | I8: =IF(INT(Cron_Uso!I8/Premissas!$C$42)>INT(Cron_Uso!H8/Premissas!$C$42),IF(N(Premissas!$F$42)>0,IF(MOD(INT(Cron_Uso!I8/Premissas!$C$42)*Premissas!$C$42,N(Premissas!$F$42))=0,"C",IF(N(Premissas!$E$42)>0,IF(MOD(INT(Cron_Uso!I8/Premissas!$C$42)*Premissas!$C$42,N(Premissas!$E$42))=0,"B",IF(N(Premissas!$D$42)>0,IF(MOD(INT(Cron_Uso!I8/Premissas!$C$42)*Premissas!$C$42,N(Premissas!$D$42))=0,"A","S"),"S")),IF(N(Premissas!$D$42)>0,IF(MOD(INT(Cron_Uso!I8/Premissas!$C$42)*Premissas!$C$42,N(Premissas!$D$42))=0,"A","S"),"S"))),IF(N(Premissas!$E$42)>0,IF(MOD(INT(Cron_Uso!I8/Premissas!$C$42)*Premissas!$C$42,N(Premissas!$E$42))=0,"B",IF(N(Premissas!$D$42)>0,IF(MOD(INT(Cron_Uso!I8/Premissas!$C$42)*Premissas!$C$42,N(Premissas!$D$42))=0,"A","S"),"S")),IF(N(Premissas!$D$42)>0,IF(MOD(INT(Cron_Uso!I8/Premissas!$C$42)*Premissas!$C$42,N(Premissas!$D$42))=0,"A","S"),"S"))),"") | J8: =IF(INT(Cron_Uso!J8/Premissas!$C$42)>INT(Cron_Uso!I8/Premissas!$C$42),IF(N(Premissas!$F$42)>0,IF(MOD(INT(Cron_Uso!J8/Premissas!$C$42)*Premissas!$C$42,N(Premissas!$F$42))=0,"C",IF(N(Premissas!$E$42)>0,IF(MOD(INT(Cron_Uso!J8/Premissas!$C$42)*Premissas!$C$42,N(Premissas!$E$42))=0,"B",IF(N(Premissas!$D$42)>0,IF(MOD(INT(Cron_Uso!J8/Premissas!$C$42)*Premissas!$C$42,N(Premissas!$D$42))=0,"A","S"),"S")),IF(N(Premissas!$D$42)>0,IF(MOD(INT(Cron_Uso!J8/Premissas!$C$42)*Premissas!$C$42,N(Premissas!$D$42))=0,"A","S"),"S"))),IF(N(Premissas!$E$42)>0,IF(MOD(INT(Cron_Uso!J8/Premissas!$C$42)*Premissas!$C$42,N(Premissas!$E$42))=0,"B",IF(N(Premissas!$D$42)>0,IF(MOD(INT(Cron_Uso!J8/Premissas!$C$42)*Premissas!$C$42,N(Premissas!$D$42))=0,"A","S"),"S")),IF(N(Premissas!$D$42)>0,IF(MOD(INT(Cron_Uso!J8/Premissas!$C$42)*Premissas!$C$42,N(Premissas!$D$42))=0,"A","S"),"S"))),"") | ... BA8: =IF(INT(Cron_Uso!BA8/Premissas!$C$42)>INT(Cron_Uso!AZ8/Premissas!$C$42),IF(N(Premissas!$F$42)>0,IF(MOD(INT(Cron_Uso!BA8/Premissas!$C$42)*Premissas!$C$42,N(Premissas!$F$42))=0,"C",IF(N(Premissas!$E$42)>0,IF(MOD(INT(Cron_Uso!BA8/Premissas!$C$42)*Premissas!$C$42,N(Premissas!$E$42))=0,"B",IF(N(Premissas!$D$42)>0,IF(MOD(INT(Cron_Uso!BA8/Premissas!$C$42)*Premissas!$C$42,N(Premissas!$D$42))=0,"A","S"),"S")),IF(N(Premissas!$D$42)>0,IF(MOD(INT(Cron_Uso!BA8/Premissas!$C$42)*Premissas!$C$42,N(Premissas!$D$42))=0,"A","S"),"S"))),IF(N(Premissas!$E$42)>0,IF(MOD(INT(Cron_Uso!BA8/Premissas!$C$42)*Premissas!$C$42,N(Premissas!$E$42))=0,"B",IF(N(Premissas!$D$42)>0,IF(MOD(INT(Cron_Uso!BA8/Premissas!$C$42)*Premissas!$C$42,N(Premissas!$D$42))=0,"A","S"),"S")),IF(N(Premissas!$D$42)>0,IF(MOD(INT(Cron_Uso!BA8/Premissas!$C$42)*Premissas!$C$42,N(Premissas!$D$42))=0,"A","S"),"S"))),"")
A9: =Premissas!$A$43&" (×"&Premissas!$I$43&")" -> Veículo Leve (×50) | B9: =IF(INT(Cron_Uso!B9/Premissas!$C$43)>INT(Premissas!$J$43/Premissas!$C$43),IF(N(Premissas!$F$43)>0,IF(MOD(INT(Cron_Uso!B9/Premissas!$C$43)*Premissas!$C$43,N(Premissas!$F$43))=0,"C",IF(N(Premissas!$E$43)>0,IF(MOD(INT(Cron_Uso!B9/Premissas!$C$43)*Premissas!$C$43,N(Premissas!$E$43))=0,"B",IF(N(Premissas!$D$43)>0,IF(MOD(INT(Cron_Uso!B9/Premissas!$C$43)*Premissas!$C$43,N(Premissas!$D$43))=0,"A","S"),"S")),IF(N(Premissas!$D$43)>0,IF(MOD(INT(Cron_Uso!B9/Premissas!$C$43)*Premissas!$C$43,N(Premissas!$D$43))=0,"A","S"),"S"))),IF(N(Premissas!$E$43)>0,IF(MOD(INT(Cron_Uso!B9/Premissas!$C$43)*Premissas!$C$43,N(Premissas!$E$43))=0,"B",IF(N(Premissas!$D$43)>0,IF(MOD(INT(Cron_Uso!B9/Premissas!$C$43)*Premissas!$C$43,N(Premissas!$D$43))=0,"A","S"),"S")),IF(N(Premissas!$D$43)>0,IF(MOD(INT(Cron_Uso!B9/Premissas!$C$43)*Premissas!$C$43,N(Premissas!$D$43))=0,"A","S"),"S"))),"") | C9: =IF(INT(Cron_Uso!C9/Premissas!$C$43)>INT(Cron_Uso!B9/Premissas!$C$43),IF(N(Premissas!$F$43)>0,IF(MOD(INT(Cron_Uso!C9/Premissas!$C$43)*Premissas!$C$43,N(Premissas!$F$43))=0,"C",IF(N(Premissas!$E$43)>0,IF(MOD(INT(Cron_Uso!C9/Premissas!$C$43)*Premissas!$C$43,N(Premissas!$E$43))=0,"B",IF(N(Premissas!$D$43)>0,IF(MOD(INT(Cron_Uso!C9/Premissas!$C$43)*Premissas!$C$43,N(Premissas!$D$43))=0,"A","S"),"S")),IF(N(Premissas!$D$43)>0,IF(MOD(INT(Cron_Uso!C9/Premissas!$C$43)*Premissas!$C$43,N(Premissas!$D$43))=0,"A","S"),"S"))),IF(N(Premissas!$E$43)>0,IF(MOD(INT(Cron_Uso!C9/Premissas!$C$43)*Premissas!$C$43,N(Premissas!$E$43))=0,"B",IF(N(Premissas!$D$43)>0,IF(MOD(INT(Cron_Uso!C9/Premissas!$C$43)*Premissas!$C$43,N(Premissas!$D$43))=0,"A","S"),"S")),IF(N(Premissas!$D$43)>0,IF(MOD(INT(Cron_Uso!C9/Premissas!$C$43)*Premissas!$C$43,N(Premissas!$D$43))=0,"A","S"),"S"))),"") | D9: =IF(INT(Cron_Uso!D9/Premissas!$C$43)>INT(Cron_Uso!C9/Premissas!$C$43),IF(N(Premissas!$F$43)>0,IF(MOD(INT(Cron_Uso!D9/Premissas!$C$43)*Premissas!$C$43,N(Premissas!$F$43))=0,"C",IF(N(Premissas!$E$43)>0,IF(MOD(INT(Cron_Uso!D9/Premissas!$C$43)*Premissas!$C$43,N(Premissas!$E$43))=0,"B",IF(N(Premissas!$D$43)>0,IF(MOD(INT(Cron_Uso!D9/Premissas!$C$43)*Premissas!$C$43,N(Premissas!$D$43))=0,"A","S"),"S")),IF(N(Premissas!$D$43)>0,IF(MOD(INT(Cron_Uso!D9/Premissas!$C$43)*Premissas!$C$43,N(Premissas!$D$43))=0,"A","S"),"S"))),IF(N(Premissas!$E$43)>0,IF(MOD(INT(Cron_Uso!D9/Premissas!$C$43)*Premissas!$C$43,N(Premissas!$E$43))=0,"B",IF(N(Premissas!$D$43)>0,IF(MOD(INT(Cron_Uso!D9/Premissas!$C$43)*Premissas!$C$43,N(Premissas!$D$43))=0,"A","S"),"S")),IF(N(Premissas!$D$43)>0,IF(MOD(INT(Cron_Uso!D9/Premissas!$C$43)*Premissas!$C$43,N(Premissas!$D$43))=0,"A","S"),"S"))),"") | E9: =IF(INT(Cron_Uso!E9/Premissas!$C$43)>INT(Cron_Uso!D9/Premissas!$C$43),IF(N(Premissas!$F$43)>0,IF(MOD(INT(Cron_Uso!E9/Premissas!$C$43)*Premissas!$C$43,N(Premissas!$F$43))=0,"C",IF(N(Premissas!$E$43)>0,IF(MOD(INT(Cron_Uso!E9/Premissas!$C$43)*Premissas!$C$43,N(Premissas!$E$43))=0,"B",IF(N(Premissas!$D$43)>0,IF(MOD(INT(Cron_Uso!E9/Premissas!$C$43)*Premissas!$C$43,N(Premissas!$D$43))=0,"A","S"),"S")),IF(N(Premissas!$D$43)>0,IF(MOD(INT(Cron_Uso!E9/Premissas!$C$43)*Premissas!$C$43,N(Premissas!$D$43))=0,"A","S"),"S"))),IF(N(Premissas!$E$43)>0,IF(MOD(INT(Cron_Uso!E9/Premissas!$C$43)*Premissas!$C$43,N(Premissas!$E$43))=0,"B",IF(N(Premissas!$D$43)>0,IF(MOD(INT(Cron_Uso!E9/Premissas!$C$43)*Premissas!$C$43,N(Premissas!$D$43))=0,"A","S"),"S")),IF(N(Premissas!$D$43)>0,IF(MOD(INT(Cron_Uso!E9/Premissas!$C$43)*Premissas!$C$43,N(Premissas!$D$43))=0,"A","S"),"S"))),"") | F9: =IF(INT(Cron_Uso!F9/Premissas!$C$43)>INT(Cron_Uso!E9/Premissas!$C$43),IF(N(Premissas!$F$43)>0,IF(MOD(INT(Cron_Uso!F9/Premissas!$C$43)*Premissas!$C$43,N(Premissas!$F$43))=0,"C",IF(N(Premissas!$E$43)>0,IF(MOD(INT(Cron_Uso!F9/Premissas!$C$43)*Premissas!$C$43,N(Premissas!$E$43))=0,"B",IF(N(Premissas!$D$43)>0,IF(MOD(INT(Cron_Uso!F9/Premissas!$C$43)*Premissas!$C$43,N(Premissas!$D$43))=0,"A","S"),"S")),IF(N(Premissas!$D$43)>0,IF(MOD(INT(Cron_Uso!F9/Premissas!$C$43)*Premissas!$C$43,N(Premissas!$D$43))=0,"A","S"),"S"))),IF(N(Premissas!$E$43)>0,IF(MOD(INT(Cron_Uso!F9/Premissas!$C$43)*Premissas!$C$43,N(Premissas!$E$43))=0,"B",IF(N(Premissas!$D$43)>0,IF(MOD(INT(Cron_Uso!F9/Premissas!$C$43)*Premissas!$C$43,N(Premissas!$D$43))=0,"A","S"),"S")),IF(N(Premissas!$D$43)>0,IF(MOD(INT(Cron_Uso!F9/Premissas!$C$43)*Premissas!$C$43,N(Premissas!$D$43))=0,"A","S"),"S"))),"") | G9: =IF(INT(Cron_Uso!G9/Premissas!$C$43)>INT(Cron_Uso!F9/Premissas!$C$43),IF(N(Premissas!$F$43)>0,IF(MOD(INT(Cron_Uso!G9/Premissas!$C$43)*Premissas!$C$43,N(Premissas!$F$43))=0,"C",IF(N(Premissas!$E$43)>0,IF(MOD(INT(Cron_Uso!G9/Premissas!$C$43)*Premissas!$C$43,N(Premissas!$E$43))=0,"B",IF(N(Premissas!$D$43)>0,IF(MOD(INT(Cron_Uso!G9/Premissas!$C$43)*Premissas!$C$43,N(Premissas!$D$43))=0,"A","S"),"S")),IF(N(Premissas!$D$43)>0,IF(MOD(INT(Cron_Uso!G9/Premissas!$C$43)*Premissas!$C$43,N(Premissas!$D$43))=0,"A","S"),"S"))),IF(N(Premissas!$E$43)>0,IF(MOD(INT(Cron_Uso!G9/Premissas!$C$43)*Premissas!$C$43,N(Premissas!$E$43))=0,"B",IF(N(Premissas!$D$43)>0,IF(MOD(INT(Cron_Uso!G9/Premissas!$C$43)*Premissas!$C$43,N(Premissas!$D$43))=0,"A","S"),"S")),IF(N(Premissas!$D$43)>0,IF(MOD(INT(Cron_Uso!G9/Premissas!$C$43)*Premissas!$C$43,N(Premissas!$D$43))=0,"A","S"),"S"))),"") | H9: =IF(INT(Cron_Uso!H9/Premissas!$C$43)>INT(Cron_Uso!G9/Premissas!$C$43),IF(N(Premissas!$F$43)>0,IF(MOD(INT(Cron_Uso!H9/Premissas!$C$43)*Premissas!$C$43,N(Premissas!$F$43))=0,"C",IF(N(Premissas!$E$43)>0,IF(MOD(INT(Cron_Uso!H9/Premissas!$C$43)*Premissas!$C$43,N(Premissas!$E$43))=0,"B",IF(N(Premissas!$D$43)>0,IF(MOD(INT(Cron_Uso!H9/Premissas!$C$43)*Premissas!$C$43,N(Premissas!$D$43))=0,"A","S"),"S")),IF(N(Premissas!$D$43)>0,IF(MOD(INT(Cron_Uso!H9/Premissas!$C$43)*Premissas!$C$43,N(Premissas!$D$43))=0,"A","S"),"S"))),IF(N(Premissas!$E$43)>0,IF(MOD(INT(Cron_Uso!H9/Premissas!$C$43)*Premissas!$C$43,N(Premissas!$E$43))=0,"B",IF(N(Premissas!$D$43)>0,IF(MOD(INT(Cron_Uso!H9/Premissas!$C$43)*Premissas!$C$43,N(Premissas!$D$43))=0,"A","S"),"S")),IF(N(Premissas!$D$43)>0,IF(MOD(INT(Cron_Uso!H9/Premissas!$C$43)*Premissas!$C$43,N(Premissas!$D$43))=0,"A","S"),"S"))),"") | I9: =IF(INT(Cron_Uso!I9/Premissas!$C$43)>INT(Cron_Uso!H9/Premissas!$C$43),IF(N(Premissas!$F$43)>0,IF(MOD(INT(Cron_Uso!I9/Premissas!$C$43)*Premissas!$C$43,N(Premissas!$F$43))=0,"C",IF(N(Premissas!$E$43)>0,IF(MOD(INT(Cron_Uso!I9/Premissas!$C$43)*Premissas!$C$43,N(Premissas!$E$43))=0,"B",IF(N(Premissas!$D$43)>0,IF(MOD(INT(Cron_Uso!I9/Premissas!$C$43)*Premissas!$C$43,N(Premissas!$D$43))=0,"A","S"),"S")),IF(N(Premissas!$D$43)>0,IF(MOD(INT(Cron_Uso!I9/Premissas!$C$43)*Premissas!$C$43,N(Premissas!$D$43))=0,"A","S"),"S"))),IF(N(Premissas!$E$43)>0,IF(MOD(INT(Cron_Uso!I9/Premissas!$C$43)*Premissas!$C$43,N(Premissas!$E$43))=0,"B",IF(N(Premissas!$D$43)>0,IF(MOD(INT(Cron_Uso!I9/Premissas!$C$43)*Premissas!$C$43,N(Premissas!$D$43))=0,"A","S"),"S")),IF(N(Premissas!$D$43)>0,IF(MOD(INT(Cron_Uso!I9/Premissas!$C$43)*Premissas!$C$43,N(Premissas!$D$43))=0,"A","S"),"S"))),"") | J9: =IF(INT(Cron_Uso!J9/Premissas!$C$43)>INT(Cron_Uso!I9/Premissas!$C$43),IF(N(Premissas!$F$43)>0,IF(MOD(INT(Cron_Uso!J9/Premissas!$C$43)*Premissas!$C$43,N(Premissas!$F$43))=0,"C",IF(N(Premissas!$E$43)>0,IF(MOD(INT(Cron_Uso!J9/Premissas!$C$43)*Premissas!$C$43,N(Premissas!$E$43))=0,"B",IF(N(Premissas!$D$43)>0,IF(MOD(INT(Cron_Uso!J9/Premissas!$C$43)*Premissas!$C$43,N(Premissas!$D$43))=0,"A","S"),"S")),IF(N(Premissas!$D$43)>0,IF(MOD(INT(Cron_Uso!J9/Premissas!$C$43)*Premissas!$C$43,N(Premissas!$D$43))=0,"A","S"),"S"))),IF(N(Premissas!$E$43)>0,IF(MOD(INT(Cron_Uso!J9/Premissas!$C$43)*Premissas!$C$43,N(Premissas!$E$43))=0,"B",IF(N(Premissas!$D$43)>0,IF(MOD(INT(Cron_Uso!J9/Premissas!$C$43)*Premissas!$C$43,N(Premissas!$D$43))=0,"A","S"),"S")),IF(N(Premissas!$D$43)>0,IF(MOD(INT(Cron_Uso!J9/Premissas!$C$43)*Premissas!$C$43,N(Premissas!$D$43))=0,"A","S"),"S"))),"") | ... BA9: =IF(INT(Cron_Uso!BA9/Premissas!$C$43)>INT(Cron_Uso!AZ9/Premissas!$C$43),IF(N(Premissas!$F$43)>0,IF(MOD(INT(Cron_Uso!BA9/Premissas!$C$43)*Premissas!$C$43,N(Premissas!$F$43))=0,"C",IF(N(Premissas!$E$43)>0,IF(MOD(INT(Cron_Uso!BA9/Premissas!$C$43)*Premissas!$C$43,N(Premissas!$E$43))=0,"B",IF(N(Premissas!$D$43)>0,IF(MOD(INT(Cron_Uso!BA9/Premissas!$C$43)*Premissas!$C$43,N(Premissas!$D$43))=0,"A","S"),"S")),IF(N(Premissas!$D$43)>0,IF(MOD(INT(Cron_Uso!BA9/Premissas!$C$43)*Premissas!$C$43,N(Premissas!$D$43))=0,"A","S"),"S"))),IF(N(Premissas!$E$43)>0,IF(MOD(INT(Cron_Uso!BA9/Premissas!$C$43)*Premissas!$C$43,N(Premissas!$E$43))=0,"B",IF(N(Premissas!$D$43)>0,IF(MOD(INT(Cron_Uso!BA9/Premissas!$C$43)*Premissas!$C$43,N(Premissas!$D$43))=0,"A","S"),"S")),IF(N(Premissas!$D$43)>0,IF(MOD(INT(Cron_Uso!BA9/Premissas!$C$43)*Premissas!$C$43,N(Premissas!$D$43))=0,"A","S"),"S"))),"")
A10: =Premissas!$A$44&" (×"&Premissas!$I$44&")" -> Pulverizador (×12) | B10: =IF(INT(Cron_Uso!B10/Premissas!$C$44)>INT(Premissas!$J$44/Premissas!$C$44),IF(N(Premissas!$F$44)>0,IF(MOD(INT(Cron_Uso!B10/Premissas!$C$44)*Premissas!$C$44,N(Premissas!$F$44))=0,"C",IF(N(Premissas!$E$44)>0,IF(MOD(INT(Cron_Uso!B10/Premissas!$C$44)*Premissas!$C$44,N(Premissas!$E$44))=0,"B",IF(N(Premissas!$D$44)>0,IF(MOD(INT(Cron_Uso!B10/Premissas!$C$44)*Premissas!$C$44,N(Premissas!$D$44))=0,"A","S"),"S")),IF(N(Premissas!$D$44)>0,IF(MOD(INT(Cron_Uso!B10/Premissas!$C$44)*Premissas!$C$44,N(Premissas!$D$44))=0,"A","S"),"S"))),IF(N(Premissas!$E$44)>0,IF(MOD(INT(Cron_Uso!B10/Premissas!$C$44)*Premissas!$C$44,N(Premissas!$E$44))=0,"B",IF(N(Premissas!$D$44)>0,IF(MOD(INT(Cron_Uso!B10/Premissas!$C$44)*Premissas!$C$44,N(Premissas!$D$44))=0,"A","S"),"S")),IF(N(Premissas!$D$44)>0,IF(MOD(INT(Cron_Uso!B10/Premissas!$C$44)*Premissas!$C$44,N(Premissas!$D$44))=0,"A","S"),"S"))),"") | C10: =IF(INT(Cron_Uso!C10/Premissas!$C$44)>INT(Cron_Uso!B10/Premissas!$C$44),IF(N(Premissas!$F$44)>0,IF(MOD(INT(Cron_Uso!C10/Premissas!$C$44)*Premissas!$C$44,N(Premissas!$F$44))=0,"C",IF(N(Premissas!$E$44)>0,IF(MOD(INT(Cron_Uso!C10/Premissas!$C$44)*Premissas!$C$44,N(Premissas!$E$44))=0,"B",IF(N(Premissas!$D$44)>0,IF(MOD(INT(Cron_Uso!C10/Premissas!$C$44)*Premissas!$C$44,N(Premissas!$D$44))=0,"A","S"),"S")),IF(N(Premissas!$D$44)>0,IF(MOD(INT(Cron_Uso!C10/Premissas!$C$44)*Premissas!$C$44,N(Premissas!$D$44))=0,"A","S"),"S"))),IF(N(Premissas!$E$44)>0,IF(MOD(INT(Cron_Uso!C10/Premissas!$C$44)*Premissas!$C$44,N(Premissas!$E$44))=0,"B",IF(N(Premissas!$D$44)>0,IF(MOD(INT(Cron_Uso!C10/Premissas!$C$44)*Premissas!$C$44,N(Premissas!$D$44))=0,"A","S"),"S")),IF(N(Premissas!$D$44)>0,IF(MOD(INT(Cron_Uso!C10/Premissas!$C$44)*Premissas!$C$44,N(Premissas!$D$44))=0,"A","S"),"S"))),"") | D10: =IF(INT(Cron_Uso!D10/Premissas!$C$44)>INT(Cron_Uso!C10/Premissas!$C$44),IF(N(Premissas!$F$44)>0,IF(MOD(INT(Cron_Uso!D10/Premissas!$C$44)*Premissas!$C$44,N(Premissas!$F$44))=0,"C",IF(N(Premissas!$E$44)>0,IF(MOD(INT(Cron_Uso!D10/Premissas!$C$44)*Premissas!$C$44,N(Premissas!$E$44))=0,"B",IF(N(Premissas!$D$44)>0,IF(MOD(INT(Cron_Uso!D10/Premissas!$C$44)*Premissas!$C$44,N(Premissas!$D$44))=0,"A","S"),"S")),IF(N(Premissas!$D$44)>0,IF(MOD(INT(Cron_Uso!D10/Premissas!$C$44)*Premissas!$C$44,N(Premissas!$D$44))=0,"A","S"),"S"))),IF(N(Premissas!$E$44)>0,IF(MOD(INT(Cron_Uso!D10/Premissas!$C$44)*Premissas!$C$44,N(Premissas!$E$44))=0,"B",IF(N(Premissas!$D$44)>0,IF(MOD(INT(Cron_Uso!D10/Premissas!$C$44)*Premissas!$C$44,N(Premissas!$D$44))=0,"A","S"),"S")),IF(N(Premissas!$D$44)>0,IF(MOD(INT(Cron_Uso!D10/Premissas!$C$44)*Premissas!$C$44,N(Premissas!$D$44))=0,"A","S"),"S"))),"") | E10: =IF(INT(Cron_Uso!E10/Premissas!$C$44)>INT(Cron_Uso!D10/Premissas!$C$44),IF(N(Premissas!$F$44)>0,IF(MOD(INT(Cron_Uso!E10/Premissas!$C$44)*Premissas!$C$44,N(Premissas!$F$44))=0,"C",IF(N(Premissas!$E$44)>0,IF(MOD(INT(Cron_Uso!E10/Premissas!$C$44)*Premissas!$C$44,N(Premissas!$E$44))=0,"B",IF(N(Premissas!$D$44)>0,IF(MOD(INT(Cron_Uso!E10/Premissas!$C$44)*Premissas!$C$44,N(Premissas!$D$44))=0,"A","S"),"S")),IF(N(Premissas!$D$44)>0,IF(MOD(INT(Cron_Uso!E10/Premissas!$C$44)*Premissas!$C$44,N(Premissas!$D$44))=0,"A","S"),"S"))),IF(N(Premissas!$E$44)>0,IF(MOD(INT(Cron_Uso!E10/Premissas!$C$44)*Premissas!$C$44,N(Premissas!$E$44))=0,"B",IF(N(Premissas!$D$44)>0,IF(MOD(INT(Cron_Uso!E10/Premissas!$C$44)*Premissas!$C$44,N(Premissas!$D$44))=0,"A","S"),"S")),IF(N(Premissas!$D$44)>0,IF(MOD(INT(Cron_Uso!E10/Premissas!$C$44)*Premissas!$C$44,N(Premissas!$D$44))=0,"A","S"),"S"))),"") | F10: =IF(INT(Cron_Uso!F10/Premissas!$C$44)>INT(Cron_Uso!E10/Premissas!$C$44),IF(N(Premissas!$F$44)>0,IF(MOD(INT(Cron_Uso!F10/Premissas!$C$44)*Premissas!$C$44,N(Premissas!$F$44))=0,"C",IF(N(Premissas!$E$44)>0,IF(MOD(INT(Cron_Uso!F10/Premissas!$C$44)*Premissas!$C$44,N(Premissas!$E$44))=0,"B",IF(N(Premissas!$D$44)>0,IF(MOD(INT(Cron_Uso!F10/Premissas!$C$44)*Premissas!$C$44,N(Premissas!$D$44))=0,"A","S"),"S")),IF(N(Premissas!$D$44)>0,IF(MOD(INT(Cron_Uso!F10/Premissas!$C$44)*Premissas!$C$44,N(Premissas!$D$44))=0,"A","S"),"S"))),IF(N(Premissas!$E$44)>0,IF(MOD(INT(Cron_Uso!F10/Premissas!$C$44)*Premissas!$C$44,N(Premissas!$E$44))=0,"B",IF(N(Premissas!$D$44)>0,IF(MOD(INT(Cron_Uso!F10/Premissas!$C$44)*Premissas!$C$44,N(Premissas!$D$44))=0,"A","S"),"S")),IF(N(Premissas!$D$44)>0,IF(MOD(INT(Cron_Uso!F10/Premissas!$C$44)*Premissas!$C$44,N(Premissas!$D$44))=0,"A","S"),"S"))),"") -> S | G10: =IF(INT(Cron_Uso!G10/Premissas!$C$44)>INT(Cron_Uso!F10/Premissas!$C$44),IF(N(Premissas!$F$44)>0,IF(MOD(INT(Cron_Uso!G10/Premissas!$C$44)*Premissas!$C$44,N(Premissas!$F$44))=0,"C",IF(N(Premissas!$E$44)>0,IF(MOD(INT(Cron_Uso!G10/Premissas!$C$44)*Premissas!$C$44,N(Premissas!$E$44))=0,"B",IF(N(Premissas!$D$44)>0,IF(MOD(INT(Cron_Uso!G10/Premissas!$C$44)*Premissas!$C$44,N(Premissas!$D$44))=0,"A","S"),"S")),IF(N(Premissas!$D$44)>0,IF(MOD(INT(Cron_Uso!G10/Premissas!$C$44)*Premissas!$C$44,N(Premissas!$D$44))=0,"A","S"),"S"))),IF(N(Premissas!$E$44)>0,IF(MOD(INT(Cron_Uso!G10/Premissas!$C$44)*Premissas!$C$44,N(Premissas!$E$44))=0,"B",IF(N(Premissas!$D$44)>0,IF(MOD(INT(Cron_Uso!G10/Premissas!$C$44)*Premissas!$C$44,N(Premissas!$D$44))=0,"A","S"),"S")),IF(N(Premissas!$D$44)>0,IF(MOD(INT(Cron_Uso!G10/Premissas!$C$44)*Premissas!$C$44,N(Premissas!$D$44))=0,"A","S"),"S"))),"") | H10: =IF(INT(Cron_Uso!H10/Premissas!$C$44)>INT(Cron_Uso!G10/Premissas!$C$44),IF(N(Premissas!$F$44)>0,IF(MOD(INT(Cron_Uso!H10/Premissas!$C$44)*Premissas!$C$44,N(Premissas!$F$44))=0,"C",IF(N(Premissas!$E$44)>0,IF(MOD(INT(Cron_Uso!H10/Premissas!$C$44)*Premissas!$C$44,N(Premissas!$E$44))=0,"B",IF(N(Premissas!$D$44)>0,IF(MOD(INT(Cron_Uso!H10/Premissas!$C$44)*Premissas!$C$44,N(Premissas!$D$44))=0,"A","S"),"S")),IF(N(Premissas!$D$44)>0,IF(MOD(INT(Cron_Uso!H10/Premissas!$C$44)*Premissas!$C$44,N(Premissas!$D$44))=0,"A","S"),"S"))),IF(N(Premissas!$E$44)>0,IF(MOD(INT(Cron_Uso!H10/Premissas!$C$44)*Premissas!$C$44,N(Premissas!$E$44))=0,"B",IF(N(Premissas!$D$44)>0,IF(MOD(INT(Cron_Uso!H10/Premissas!$C$44)*Premissas!$C$44,N(Premissas!$D$44))=0,"A","S"),"S")),IF(N(Premissas!$D$44)>0,IF(MOD(INT(Cron_Uso!H10/Premissas!$C$44)*Premissas!$C$44,N(Premissas!$D$44))=0,"A","S"),"S"))),"") | I10: =IF(INT(Cron_Uso!I10/Premissas!$C$44)>INT(Cron_Uso!H10/Premissas!$C$44),IF(N(Premissas!$F$44)>0,IF(MOD(INT(Cron_Uso!I10/Premissas!$C$44)*Premissas!$C$44,N(Premissas!$F$44))=0,"C",IF(N(Premissas!$E$44)>0,IF(MOD(INT(Cron_Uso!I10/Premissas!$C$44)*Premissas!$C$44,N(Premissas!$E$44))=0,"B",IF(N(Premissas!$D$44)>0,IF(MOD(INT(Cron_Uso!I10/Premissas!$C$44)*Premissas!$C$44,N(Premissas!$D$44))=0,"A","S"),"S")),IF(N(Premissas!$D$44)>0,IF(MOD(INT(Cron_Uso!I10/Premissas!$C$44)*Premissas!$C$44,N(Premissas!$D$44))=0,"A","S"),"S"))),IF(N(Premissas!$E$44)>0,IF(MOD(INT(Cron_Uso!I10/Premissas!$C$44)*Premissas!$C$44,N(Premissas!$E$44))=0,"B",IF(N(Premissas!$D$44)>0,IF(MOD(INT(Cron_Uso!I10/Premissas!$C$44)*Premissas!$C$44,N(Premissas!$D$44))=0,"A","S"),"S")),IF(N(Premissas!$D$44)>0,IF(MOD(INT(Cron_Uso!I10/Premissas!$C$44)*Premissas!$C$44,N(Premissas!$D$44))=0,"A","S"),"S"))),"") | J10: =IF(INT(Cron_Uso!J10/Premissas!$C$44)>INT(Cron_Uso!I10/Premissas!$C$44),IF(N(Premissas!$F$44)>0,IF(MOD(INT(Cron_Uso!J10/Premissas!$C$44)*Premissas!$C$44,N(Premissas!$F$44))=0,"C",IF(N(Premissas!$E$44)>0,IF(MOD(INT(Cron_Uso!J10/Premissas!$C$44)*Premissas!$C$44,N(Premissas!$E$44))=0,"B",IF(N(Premissas!$D$44)>0,IF(MOD(INT(Cron_Uso!J10/Premissas!$C$44)*Premissas!$C$44,N(Premissas!$D$44))=0,"A","S"),"S")),IF(N(Premissas!$D$44)>0,IF(MOD(INT(Cron_Uso!J10/Premissas!$C$44)*Premissas!$C$44,N(Premissas!$D$44))=0,"A","S"),"S"))),IF(N(Premissas!$E$44)>0,IF(MOD(INT(Cron_Uso!J10/Premissas!$C$44)*Premissas!$C$44,N(Premissas!$E$44))=0,"B",IF(N(Premissas!$D$44)>0,IF(MOD(INT(Cron_Uso!J10/Premissas!$C$44)*Premissas!$C$44,N(Premissas!$D$44))=0,"A","S"),"S")),IF(N(Premissas!$D$44)>0,IF(MOD(INT(Cron_Uso!J10/Premissas!$C$44)*Premissas!$C$44,N(Premissas!$D$44))=0,"A","S"),"S"))),"") | ... BA10: =IF(INT(Cron_Uso!BA10/Premissas!$C$44)>INT(Cron_Uso!AZ10/Premissas!$C$44),IF(N(Premissas!$F$44)>0,IF(MOD(INT(Cron_Uso!BA10/Premissas!$C$44)*Premissas!$C$44,N(Premissas!$F$44))=0,"C",IF(N(Premissas!$E$44)>0,IF(MOD(INT(Cron_Uso!BA10/Premissas!$C$44)*Premissas!$C$44,N(Premissas!$E$44))=0,"B",IF(N(Premissas!$D$44)>0,IF(MOD(INT(Cron_Uso!BA10/Premissas!$C$44)*Premissas!$C$44,N(Premissas!$D$44))=0,"A","S"),"S")),IF(N(Premissas!$D$44)>0,IF(MOD(INT(Cron_Uso!BA10/Premissas!$C$44)*Premissas!$C$44,N(Premissas!$D$44))=0,"A","S"),"S"))),IF(N(Premissas!$E$44)>0,IF(MOD(INT(Cron_Uso!BA10/Premissas!$C$44)*Premissas!$C$44,N(Premissas!$E$44))=0,"B",IF(N(Premissas!$D$44)>0,IF(MOD(INT(Cron_Uso!BA10/Premissas!$C$44)*Premissas!$C$44,N(Premissas!$D$44))=0,"A","S"),"S")),IF(N(Premissas!$D$44)>0,IF(MOD(INT(Cron_Uso!BA10/Premissas!$C$44)*Premissas!$C$44,N(Premissas!$D$44))=0,"A","S"),"S"))),"")
A11: =Premissas!$A$45&" (×"&Premissas!$I$45&")" -> Implemento (×18) | B11: =IF(INT(Cron_Uso!B11/Premissas!$C$45)>INT(Premissas!$J$45/Premissas!$C$45),IF(N(Premissas!$F$45)>0,IF(MOD(INT(Cron_Uso!B11/Premissas!$C$45)*Premissas!$C$45,N(Premissas!$F$45))=0,"C",IF(N(Premissas!$E$45)>0,IF(MOD(INT(Cron_Uso!B11/Premissas!$C$45)*Premissas!$C$45,N(Premissas!$E$45))=0,"B",IF(N(Premissas!$D$45)>0,IF(MOD(INT(Cron_Uso!B11/Premissas!$C$45)*Premissas!$C$45,N(Premissas!$D$45))=0,"A","S"),"S")),IF(N(Premissas!$D$45)>0,IF(MOD(INT(Cron_Uso!B11/Premissas!$C$45)*Premissas!$C$45,N(Premissas!$D$45))=0,"A","S"),"S"))),IF(N(Premissas!$E$45)>0,IF(MOD(INT(Cron_Uso!B11/Premissas!$C$45)*Premissas!$C$45,N(Premissas!$E$45))=0,"B",IF(N(Premissas!$D$45)>0,IF(MOD(INT(Cron_Uso!B11/Premissas!$C$45)*Premissas!$C$45,N(Premissas!$D$45))=0,"A","S"),"S")),IF(N(Premissas!$D$45)>0,IF(MOD(INT(Cron_Uso!B11/Premissas!$C$45)*Premissas!$C$45,N(Premissas!$D$45))=0,"A","S"),"S"))),"") | C11: =IF(INT(Cron_Uso!C11/Premissas!$C$45)>INT(Cron_Uso!B11/Premissas!$C$45),IF(N(Premissas!$F$45)>0,IF(MOD(INT(Cron_Uso!C11/Premissas!$C$45)*Premissas!$C$45,N(Premissas!$F$45))=0,"C",IF(N(Premissas!$E$45)>0,IF(MOD(INT(Cron_Uso!C11/Premissas!$C$45)*Premissas!$C$45,N(Premissas!$E$45))=0,"B",IF(N(Premissas!$D$45)>0,IF(MOD(INT(Cron_Uso!C11/Premissas!$C$45)*Premissas!$C$45,N(Premissas!$D$45))=0,"A","S"),"S")),IF(N(Premissas!$D$45)>0,IF(MOD(INT(Cron_Uso!C11/Premissas!$C$45)*Premissas!$C$45,N(Premissas!$D$45))=0,"A","S"),"S"))),IF(N(Premissas!$E$45)>0,IF(MOD(INT(Cron_Uso!C11/Premissas!$C$45)*Premissas!$C$45,N(Premissas!$E$45))=0,"B",IF(N(Premissas!$D$45)>0,IF(MOD(INT(Cron_Uso!C11/Premissas!$C$45)*Premissas!$C$45,N(Premissas!$D$45))=0,"A","S"),"S")),IF(N(Premissas!$D$45)>0,IF(MOD(INT(Cron_Uso!C11/Premissas!$C$45)*Premissas!$C$45,N(Premissas!$D$45))=0,"A","S"),"S"))),"") | D11: =IF(INT(Cron_Uso!D11/Premissas!$C$45)>INT(Cron_Uso!C11/Premissas!$C$45),IF(N(Premissas!$F$45)>0,IF(MOD(INT(Cron_Uso!D11/Premissas!$C$45)*Premissas!$C$45,N(Premissas!$F$45))=0,"C",IF(N(Premissas!$E$45)>0,IF(MOD(INT(Cron_Uso!D11/Premissas!$C$45)*Premissas!$C$45,N(Premissas!$E$45))=0,"B",IF(N(Premissas!$D$45)>0,IF(MOD(INT(Cron_Uso!D11/Premissas!$C$45)*Premissas!$C$45,N(Premissas!$D$45))=0,"A","S"),"S")),IF(N(Premissas!$D$45)>0,IF(MOD(INT(Cron_Uso!D11/Premissas!$C$45)*Premissas!$C$45,N(Premissas!$D$45))=0,"A","S"),"S"))),IF(N(Premissas!$E$45)>0,IF(MOD(INT(Cron_Uso!D11/Premissas!$C$45)*Premissas!$C$45,N(Premissas!$E$45))=0,"B",IF(N(Premissas!$D$45)>0,IF(MOD(INT(Cron_Uso!D11/Premissas!$C$45)*Premissas!$C$45,N(Premissas!$D$45))=0,"A","S"),"S")),IF(N(Premissas!$D$45)>0,IF(MOD(INT(Cron_Uso!D11/Premissas!$C$45)*Premissas!$C$45,N(Premissas!$D$45))=0,"A","S"),"S"))),"") | E11: =IF(INT(Cron_Uso!E11/Premissas!$C$45)>INT(Cron_Uso!D11/Premissas!$C$45),IF(N(Premissas!$F$45)>0,IF(MOD(INT(Cron_Uso!E11/Premissas!$C$45)*Premissas!$C$45,N(Premissas!$F$45))=0,"C",IF(N(Premissas!$E$45)>0,IF(MOD(INT(Cron_Uso!E11/Premissas!$C$45)*Premissas!$C$45,N(Premissas!$E$45))=0,"B",IF(N(Premissas!$D$45)>0,IF(MOD(INT(Cron_Uso!E11/Premissas!$C$45)*Premissas!$C$45,N(Premissas!$D$45))=0,"A","S"),"S")),IF(N(Premissas!$D$45)>0,IF(MOD(INT(Cron_Uso!E11/Premissas!$C$45)*Premissas!$C$45,N(Premissas!$D$45))=0,"A","S"),"S"))),IF(N(Premissas!$E$45)>0,IF(MOD(INT(Cron_Uso!E11/Premissas!$C$45)*Premissas!$C$45,N(Premissas!$E$45))=0,"B",IF(N(Premissas!$D$45)>0,IF(MOD(INT(Cron_Uso!E11/Premissas!$C$45)*Premissas!$C$45,N(Premissas!$D$45))=0,"A","S"),"S")),IF(N(Premissas!$D$45)>0,IF(MOD(INT(Cron_Uso!E11/Premissas!$C$45)*Premissas!$C$45,N(Premissas!$D$45))=0,"A","S"),"S"))),"") | F11: =IF(INT(Cron_Uso!F11/Premissas!$C$45)>INT(Cron_Uso!E11/Premissas!$C$45),IF(N(Premissas!$F$45)>0,IF(MOD(INT(Cron_Uso!F11/Premissas!$C$45)*Premissas!$C$45,N(Premissas!$F$45))=0,"C",IF(N(Premissas!$E$45)>0,IF(MOD(INT(Cron_Uso!F11/Premissas!$C$45)*Premissas!$C$45,N(Premissas!$E$45))=0,"B",IF(N(Premissas!$D$45)>0,IF(MOD(INT(Cron_Uso!F11/Premissas!$C$45)*Premissas!$C$45,N(Premissas!$D$45))=0,"A","S"),"S")),IF(N(Premissas!$D$45)>0,IF(MOD(INT(Cron_Uso!F11/Premissas!$C$45)*Premissas!$C$45,N(Premissas!$D$45))=0,"A","S"),"S"))),IF(N(Premissas!$E$45)>0,IF(MOD(INT(Cron_Uso!F11/Premissas!$C$45)*Premissas!$C$45,N(Premissas!$E$45))=0,"B",IF(N(Premissas!$D$45)>0,IF(MOD(INT(Cron_Uso!F11/Premissas!$C$45)*Premissas!$C$45,N(Premissas!$D$45))=0,"A","S"),"S")),IF(N(Premissas!$D$45)>0,IF(MOD(INT(Cron_Uso!F11/Premissas!$C$45)*Premissas!$C$45,N(Premissas!$D$45))=0,"A","S"),"S"))),"") | G11: =IF(INT(Cron_Uso!G11/Premissas!$C$45)>INT(Cron_Uso!F11/Premissas!$C$45),IF(N(Premissas!$F$45)>0,IF(MOD(INT(Cron_Uso!G11/Premissas!$C$45)*Premissas!$C$45,N(Premissas!$F$45))=0,"C",IF(N(Premissas!$E$45)>0,IF(MOD(INT(Cron_Uso!G11/Premissas!$C$45)*Premissas!$C$45,N(Premissas!$E$45))=0,"B",IF(N(Premissas!$D$45)>0,IF(MOD(INT(Cron_Uso!G11/Premissas!$C$45)*Premissas!$C$45,N(Premissas!$D$45))=0,"A","S"),"S")),IF(N(Premissas!$D$45)>0,IF(MOD(INT(Cron_Uso!G11/Premissas!$C$45)*Premissas!$C$45,N(Premissas!$D$45))=0,"A","S"),"S"))),IF(N(Premissas!$E$45)>0,IF(MOD(INT(Cron_Uso!G11/Premissas!$C$45)*Premissas!$C$45,N(Premissas!$E$45))=0,"B",IF(N(Premissas!$D$45)>0,IF(MOD(INT(Cron_Uso!G11/Premissas!$C$45)*Premissas!$C$45,N(Premissas!$D$45))=0,"A","S"),"S")),IF(N(Premissas!$D$45)>0,IF(MOD(INT(Cron_Uso!G11/Premissas!$C$45)*Premissas!$C$45,N(Premissas!$D$45))=0,"A","S"),"S"))),"") | H11: =IF(INT(Cron_Uso!H11/Premissas!$C$45)>INT(Cron_Uso!G11/Premissas!$C$45),IF(N(Premissas!$F$45)>0,IF(MOD(INT(Cron_Uso!H11/Premissas!$C$45)*Premissas!$C$45,N(Premissas!$F$45))=0,"C",IF(N(Premissas!$E$45)>0,IF(MOD(INT(Cron_Uso!H11/Premissas!$C$45)*Premissas!$C$45,N(Premissas!$E$45))=0,"B",IF(N(Premissas!$D$45)>0,IF(MOD(INT(Cron_Uso!H11/Premissas!$C$45)*Premissas!$C$45,N(Premissas!$D$45))=0,"A","S"),"S")),IF(N(Premissas!$D$45)>0,IF(MOD(INT(Cron_Uso!H11/Premissas!$C$45)*Premissas!$C$45,N(Premissas!$D$45))=0,"A","S"),"S"))),IF(N(Premissas!$E$45)>0,IF(MOD(INT(Cron_Uso!H11/Premissas!$C$45)*Premissas!$C$45,N(Premissas!$E$45))=0,"B",IF(N(Premissas!$D$45)>0,IF(MOD(INT(Cron_Uso!H11/Premissas!$C$45)*Premissas!$C$45,N(Premissas!$D$45))=0,"A","S"),"S")),IF(N(Premissas!$D$45)>0,IF(MOD(INT(Cron_Uso!H11/Premissas!$C$45)*Premissas!$C$45,N(Premissas!$D$45))=0,"A","S"),"S"))),"") | I11: =IF(INT(Cron_Uso!I11/Premissas!$C$45)>INT(Cron_Uso!H11/Premissas!$C$45),IF(N(Premissas!$F$45)>0,IF(MOD(INT(Cron_Uso!I11/Premissas!$C$45)*Premissas!$C$45,N(Premissas!$F$45))=0,"C",IF(N(Premissas!$E$45)>0,IF(MOD(INT(Cron_Uso!I11/Premissas!$C$45)*Premissas!$C$45,N(Premissas!$E$45))=0,"B",IF(N(Premissas!$D$45)>0,IF(MOD(INT(Cron_Uso!I11/Premissas!$C$45)*Premissas!$C$45,N(Premissas!$D$45))=0,"A","S"),"S")),IF(N(Premissas!$D$45)>0,IF(MOD(INT(Cron_Uso!I11/Premissas!$C$45)*Premissas!$C$45,N(Premissas!$D$45))=0,"A","S"),"S"))),IF(N(Premissas!$E$45)>0,IF(MOD(INT(Cron_Uso!I11/Premissas!$C$45)*Premissas!$C$45,N(Premissas!$E$45))=0,"B",IF(N(Premissas!$D$45)>0,IF(MOD(INT(Cron_Uso!I11/Premissas!$C$45)*Premissas!$C$45,N(Premissas!$D$45))=0,"A","S"),"S")),IF(N(Premissas!$D$45)>0,IF(MOD(INT(Cron_Uso!I11/Premissas!$C$45)*Premissas!$C$45,N(Premissas!$D$45))=0,"A","S"),"S"))),"") -> S | J11: =IF(INT(Cron_Uso!J11/Premissas!$C$45)>INT(Cron_Uso!I11/Premissas!$C$45),IF(N(Premissas!$F$45)>0,IF(MOD(INT(Cron_Uso!J11/Premissas!$C$45)*Premissas!$C$45,N(Premissas!$F$45))=0,"C",IF(N(Premissas!$E$45)>0,IF(MOD(INT(Cron_Uso!J11/Premissas!$C$45)*Premissas!$C$45,N(Premissas!$E$45))=0,"B",IF(N(Premissas!$D$45)>0,IF(MOD(INT(Cron_Uso!J11/Premissas!$C$45)*Premissas!$C$45,N(Premissas!$D$45))=0,"A","S"),"S")),IF(N(Premissas!$D$45)>0,IF(MOD(INT(Cron_Uso!J11/Premissas!$C$45)*Premissas!$C$45,N(Premissas!$D$45))=0,"A","S"),"S"))),IF(N(Premissas!$E$45)>0,IF(MOD(INT(Cron_Uso!J11/Premissas!$C$45)*Premissas!$C$45,N(Premissas!$E$45))=0,"B",IF(N(Premissas!$D$45)>0,IF(MOD(INT(Cron_Uso!J11/Premissas!$C$45)*Premissas!$C$45,N(Premissas!$D$45))=0,"A","S"),"S")),IF(N(Premissas!$D$45)>0,IF(MOD(INT(Cron_Uso!J11/Premissas!$C$45)*Premissas!$C$45,N(Premissas!$D$45))=0,"A","S"),"S"))),"") | ... BA11: =IF(INT(Cron_Uso!BA11/Premissas!$C$45)>INT(Cron_Uso!AZ11/Premissas!$C$45),IF(N(Premissas!$F$45)>0,IF(MOD(INT(Cron_Uso!BA11/Premissas!$C$45)*Premissas!$C$45,N(Premissas!$F$45))=0,"C",IF(N(Premissas!$E$45)>0,IF(MOD(INT(Cron_Uso!BA11/Premissas!$C$45)*Premissas!$C$45,N(Premissas!$E$45))=0,"B",IF(N(Premissas!$D$45)>0,IF(MOD(INT(Cron_Uso!BA11/Premissas!$C$45)*Premissas!$C$45,N(Premissas!$D$45))=0,"A","S"),"S")),IF(N(Premissas!$D$45)>0,IF(MOD(INT(Cron_Uso!BA11/Premissas!$C$45)*Premissas!$C$45,N(Premissas!$D$45))=0,"A","S"),"S"))),IF(N(Premissas!$E$45)>0,IF(MOD(INT(Cron_Uso!BA11/Premissas!$C$45)*Premissas!$C$45,N(Premissas!$E$45))=0,"B",IF(N(Premissas!$D$45)>0,IF(MOD(INT(Cron_Uso!BA11/Premissas!$C$45)*Premissas!$C$45,N(Premissas!$D$45))=0,"A","S"),"S")),IF(N(Premissas!$D$45)>0,IF(MOD(INT(Cron_Uso!BA11/Premissas!$C$45)*Premissas!$C$45,N(Premissas!$D$45))=0,"A","S"),"S"))),"")

Sheet Cronograma_Ativos
A1: CRONOGRAMA POR ATIVO — 384 ativos × 52 semanas (cada ativo segue o padrão da sua classe; individualiza ao receber horímetros) | BD1: ⌂ MENU
A2: S verde · A amarelo · B/C vermelho. Filtre pela coluna Classe ou Setor. Duplo clique nos títulos congela a navegação.
A4: Ativo | B4: Classe | C4: S01 | D4: S02 | E4: S03 | F4: S04 | G4: S05 | H4: S06 | I4: S07 | J4: S08 | K4: S09 | L4: S10 | M4: S11 | N4: S12 | O4: S13 | P4: S14 | Q4: S15 | R4: S16 | S4: S17 | T4: S18 | U4: S19 | V4: S20 | W4: S21 | X4: S22 | Y4: S23 | Z4: S24 | AA4: S25 | AB4: S26 | AC4: S27 | AD4: S28 | AE4: S29 | AF4: S30 | AG4: S31 | AH4: S32 | AI4: S33 | AJ4: S34 | AK4: S35 | AL4: S36 | AM4: S37 | AN4: S38 | AO4: S39 | AP4: S40 | AQ4: S41 | AR4: S42 | AS4: S43 | AT4: S44 | AU4: S45 | AV4: S46 | AW4: S47 | AX4: S48 | AY4: S49 | AZ4: S50 | BA4: S51 | BB4: S52
A5: =Frota!$B5&" — "&Frota!$A5 -> MB 1725 Atego — 101005 | B5: =Frota!$C5 -> Caminhão | C5: =INDEX(Cronograma!B$5:B$11,MATCH($B5,Premissas!$A$39:$A$45,0)) | D5: =INDEX(Cronograma!C$5:C$11,MATCH($B5,Premissas!$A$39:$A$45,0)) | E5: =INDEX(Cronograma!D$5:D$11,MATCH($B5,Premissas!$A$39:$A$45,0)) | F5: =INDEX(Cronograma!E$5:E$11,MATCH($B5,Premissas!$A$39:$A$45,0)) | G5: =INDEX(Cronograma!F$5:F$11,MATCH($B5,Premissas!$A$39:$A$45,0)) | H5: =INDEX(Cronograma!G$5:G$11,MATCH($B5,Premissas!$A$39:$A$45,0)) | I5: =INDEX(Cronograma!H$5:H$11,MATCH($B5,Premissas!$A$39:$A$45,0)) -> S | J5: =INDEX(Cronograma!I$5:I$11,MATCH($B5,Premissas!$A$39:$A$45,0)) | ... BB5: =INDEX(Cronograma!BA$5:BA$11,MATCH($B5,Premissas!$A$39:$A$45,0))
A6: =Frota!$B6&" — "&Frota!$A6 -> MB 710 4X2 — 101006 | B6: =Frota!$C6 -> Caminhão | C6: =INDEX(Cronograma!B$5:B$11,MATCH($B6,Premissas!$A$39:$A$45,0)) | D6: =INDEX(Cronograma!C$5:C$11,MATCH($B6,Premissas!$A$39:$A$45,0)) | E6: =INDEX(Cronograma!D$5:D$11,MATCH($B6,Premissas!$A$39:$A$45,0)) | F6: =INDEX(Cronograma!E$5:E$11,MATCH($B6,Premissas!$A$39:$A$45,0)) | G6: =INDEX(Cronograma!F$5:F$11,MATCH($B6,Premissas!$A$39:$A$45,0)) | H6: =INDEX(Cronograma!G$5:G$11,MATCH($B6,Premissas!$A$39:$A$45,0)) | I6: =INDEX(Cronograma!H$5:H$11,MATCH($B6,Premissas!$A$39:$A$45,0)) -> S | J6: =INDEX(Cronograma!I$5:I$11,MATCH($B6,Premissas!$A$39:$A$45,0)) | ... BB6: =INDEX(Cronograma!BA$5:BA$11,MATCH($B6,Premissas!$A$39:$A$45,0))
A7: =Frota!$B7&" — "&Frota!$A7 -> MB 1720 6x6 — 101011 | B7: =Frota!$C7 -> Caminhão | C7: =INDEX(Cronograma!B$5:B$11,MATCH($B7,Premissas!$A$39:$A$45,0)) | D7: =INDEX(Cronograma!C$5:C$11,MATCH($B7,Premissas!$A$39:$A$45,0)) | E7: =INDEX(Cronograma!D$5:D$11,MATCH($B7,Premissas!$A$39:$A$45,0)) | F7: =INDEX(Cronograma!E$5:E$11,MATCH($B7,Premissas!$A$39:$A$45,0)) | G7: =INDEX(Cronograma!F$5:F$11,MATCH($B7,Premissas!$A$39:$A$45,0)) | H7: =INDEX(Cronograma!G$5:G$11,MATCH($B7,Premissas!$A$39:$A$45,0)) | I7: =INDEX(Cronograma!H$5:H$11,MATCH($B7,Premissas!$A$39:$A$45,0)) -> S | J7: =INDEX(Cronograma!I$5:I$11,MATCH($B7,Premissas!$A$39:$A$45,0)) | ... BB7: =INDEX(Cronograma!BA$5:BA$11,MATCH($B7,Premissas!$A$39:$A$45,0))
A8: =Frota!$B8&" — "&Frota!$A8 -> MB 1113 4x2 — 101014 | B8: =Frota!$C8 -> Caminhão | C8: =INDEX(Cronograma!B$5:B$11,MATCH($B8,Premissas!$A$39:$A$45,0)) | D8: =INDEX(Cronograma!C$5:C$11,MATCH($B8,Premissas!$A$39:$A$45,0)) | E8: =INDEX(Cronograma!D$5:D$11,MATCH($B8,Premissas!$A$39:$A$45,0)) | F8: =INDEX(Cronograma!E$5:E$11,MATCH($B8,Premissas!$A$39:$A$45,0)) | G8: =INDEX(Cronograma!F$5:F$11,MATCH($B8,Premissas!$A$39:$A$45,0)) | H8: =INDEX(Cronograma!G$5:G$11,MATCH($B8,Premissas!$A$39:$A$45,0)) | I8: =INDEX(Cronograma!H$5:H$11,MATCH($B8,Premissas!$A$39:$A$45,0)) -> S | J8: =INDEX(Cronograma!I$5:I$11,MATCH($B8,Premissas!$A$39:$A$45,0)) | ... BB8: =INDEX(Cronograma!BA$5:BA$11,MATCH($B8,Premissas!$A$39:$A$45,0))
A9: =Frota!$B9&" — "&Frota!$A9 -> MB 2423 6x4 — 101016 | B9: =Frota!$C9 -> Caminhão | C9: =INDEX(Cronograma!B$5:B$11,MATCH($B9,Premissas!$A$39:$A$45,0)) | D9: =INDEX(Cronograma!C$5:C$11,MATCH($B9,Premissas!$A$39:$A$45,0)) | E9: =INDEX(Cronograma!D$5:D$11,MATCH($B9,Premissas!$A$39:$A$45,0)) | F9: =INDEX(Cronograma!E$5:E$11,MATCH($B9,Premissas!$A$39:$A$45,0)) | G9: =INDEX(Cronograma!F$5:F$11,MATCH($B9,Premissas!$A$39:$A$45,0)) | H9: =INDEX(Cronograma!G$5:G$11,MATCH($B9,Premissas!$A$39:$A$45,0)) | I9: =INDEX(Cronograma!H$5:H$11,MATCH($B9,Premissas!$A$39:$A$45,0)) -> S | J9: =INDEX(Cronograma!I$5:I$11,MATCH($B9,Premissas!$A$39:$A$45,0)) | ... BB9: =INDEX(Cronograma!BA$5:BA$11,MATCH($B9,Premissas!$A$39:$A$45,0))
A10: =Frota!$B10&" — "&Frota!$A10 -> MB 2423 6x4 — 101028 | B10: =Frota!$C10 -> Caminhão | C10: =INDEX(Cronograma!B$5:B$11,MATCH($B10,Premissas!$A$39:$A$45,0)) | D10: =INDEX(Cronograma!C$5:C$11,MATCH($B10,Premissas!$A$39:$A$45,0)) | E10: =INDEX(Cronograma!D$5:D$11,MATCH($B10,Premissas!$A$39:$A$45,0)) | F10: =INDEX(Cronograma!E$5:E$11,MATCH($B10,Premissas!$A$39:$A$45,0)) | G10: =INDEX(Cronograma!F$5:F$11,MATCH($B10,Premissas!$A$39:$A$45,0)) | H10: =INDEX(Cronograma!G$5:G$11,MATCH($B10,Premissas!$A$39:$A$45,0)) | I10: =INDEX(Cronograma!H$5:H$11,MATCH($B10,Premissas!$A$39:$A$45,0)) -> S | J10: =INDEX(Cronograma!I$5:I$11,MATCH($B10,Premissas!$A$39:$A$45,0)) | ... BB10: =INDEX(Cronograma!BA$5:BA$11,MATCH($B10,Premissas!$A$39:$A$45,0))
A11: =Frota!$B11&" — "&Frota!$A11 -> VW 31-320 — 101047 | B11: =Frota!$C11 -> Caminhão | C11: =INDEX(Cronograma!B$5:B$11,MATCH($B11,Premissas!$A$39:$A$45,0)) | D11: =INDEX(Cronograma!C$5:C$11,MATCH($B11,Premissas!$A$39:$A$45,0)) | E11: =INDEX(Cronograma!D$5:D$11,MATCH($B11,Premissas!$A$39:$A$45,0)) | F11: =INDEX(Cronograma!E$5:E$11,MATCH($B11,Premissas!$A$39:$A$45,0)) | G11: =INDEX(Cronograma!F$5:F$11,MATCH($B11,Premissas!$A$39:$A$45,0)) | H11: =INDEX(Cronograma!G$5:G$11,MATCH($B11,Premissas!$A$39:$A$45,0)) | I11: =INDEX(Cronograma!H$5:H$11,MATCH($B11,Premissas!$A$39:$A$45,0)) -> S | J11: =INDEX(Cronograma!I$5:I$11,MATCH($B11,Premissas!$A$39:$A$45,0)) | ... BB11: =INDEX(Cronograma!BA$5:BA$11,MATCH($B11,Premissas!$A$39:$A$45,0))
A12: =Frota!$B12&" — "&Frota!$A12 -> MB 3344 6x4 — 101048 | B12: =Frota!$C12 -> Caminhão | C12: =INDEX(Cronograma!B$5:B$11,MATCH($B12,Premissas!$A$39:$A$45,0)) | D12: =INDEX(Cronograma!C$5:C$11,MATCH($B12,Premissas!$A$39:$A$45,0)) | E12: =INDEX(Cronograma!D$5:D$11,MATCH($B12,Premissas!$A$39:$A$45,0)) | F12: =INDEX(Cronograma!E$5:E$11,MATCH($B12,Premissas!$A$39:$A$45,0)) | G12: =INDEX(Cronograma!F$5:F$11,MATCH($B12,Premissas!$A$39:$A$45,0)) | H12: =INDEX(Cronograma!G$5:G$11,MATCH($B12,Premissas!$A$39:$A$45,0)) | I12: =INDEX(Cronograma!H$5:H$11,MATCH($B12,Premissas!$A$39:$A$45,0)) -> S | J12: =INDEX(Cronograma!I$5:I$11,MATCH($B12,Premissas!$A$39:$A$45,0)) | ... BB12: =INDEX(Cronograma!BA$5:BA$11,MATCH($B12,Premissas!$A$39:$A$45,0))
A13: =Frota!$B13&" — "&Frota!$A13 -> MB 2729 6x4 — 101050 | B13: =Frota!$C13 -> Caminhão | C13: =INDEX(Cronograma!B$5:B$11,MATCH($B13,Premissas!$A$39:$A$45,0)) | D13: =INDEX(Cronograma!C$5:C$11,MATCH($B13,Premissas!$A$39:$A$45,0)) | E13: =INDEX(Cronograma!D$5:D$11,MATCH($B13,Premissas!$A$39:$A$45,0)) | F13: =INDEX(Cronograma!E$5:E$11,MATCH($B13,Premissas!$A$39:$A$45,0)) | G13: =INDEX(Cronograma!F$5:F$11,MATCH($B13,Premissas!$A$39:$A$45,0)) | H13: =INDEX(Cronograma!G$5:G$11,MATCH($B13,Premissas!$A$39:$A$45,0)) | I13: =INDEX(Cronograma!H$5:H$11,MATCH($B13,Premissas!$A$39:$A$45,0)) -> S | J13: =INDEX(Cronograma!I$5:I$11,MATCH($B13,Premissas!$A$39:$A$45,0)) | ... BB13: =INDEX(Cronograma!BA$5:BA$11,MATCH($B13,Premissas!$A$39:$A$45,0))
A14: =Frota!$B14&" — "&Frota!$A14 -> MB 2729 6x4 — 101051 | B14: =Frota!$C14 -> Caminhão | C14: =INDEX(Cronograma!B$5:B$11,MATCH($B14,Premissas!$A$39:$A$45,0)) | D14: =INDEX(Cronograma!C$5:C$11,MATCH($B14,Premissas!$A$39:$A$45,0)) | E14: =INDEX(Cronograma!D$5:D$11,MATCH($B14,Premissas!$A$39:$A$45,0)) | F14: =INDEX(Cronograma!E$5:E$11,MATCH($B14,Premissas!$A$39:$A$45,0)) | G14: =INDEX(Cronograma!F$5:F$11,MATCH($B14,Premissas!$A$39:$A$45,0)) | H14: =INDEX(Cronograma!G$5:G$11,MATCH($B14,Premissas!$A$39:$A$45,0)) | I14: =INDEX(Cronograma!H$5:H$11,MATCH($B14,Premissas!$A$39:$A$45,0)) -> S | J14: =INDEX(Cronograma!I$5:I$11,MATCH($B14,Premissas!$A$39:$A$45,0)) | ... BB14: =INDEX(Cronograma!BA$5:BA$11,MATCH($B14,Premissas!$A$39:$A$45,0))
A15: =Frota!$B15&" — "&Frota!$A15 -> MB 2729 6x4 — 101052 | B15: =Frota!$C15 -> Caminhão | C15: =INDEX(Cronograma!B$5:B$11,MATCH($B15,Premissas!$A$39:$A$45,0)) | D15: =INDEX(Cronograma!C$5:C$11,MATCH($B15,Premissas!$A$39:$A$45,0)) | E15: =INDEX(Cronograma!D$5:D$11,MATCH($B15,Premissas!$A$39:$A$45,0)) | F15: =INDEX(Cronograma!E$5:E$11,MATCH($B15,Premissas!$A$39:$A$45,0)) | G15: =INDEX(Cronograma!F$5:F$11,MATCH($B15,Premissas!$A$39:$A$45,0)) | H15: =INDEX(Cronograma!G$5:G$11,MATCH($B15,Premissas!$A$39:$A$45,0)) | I15: =INDEX(Cronograma!H$5:H$11,MATCH($B15,Premissas!$A$39:$A$45,0)) -> S | J15: =INDEX(Cronograma!I$5:I$11,MATCH($B15,Premissas!$A$39:$A$45,0)) | ... BB15: =INDEX(Cronograma!BA$5:BA$11,MATCH($B15,Premissas!$A$39:$A$45,0))
A16: =Frota!$B16&" — "&Frota!$A16 -> MB 2729 6x4 — 101053 | B16: =Frota!$C16 -> Caminhão | C16: =INDEX(Cronograma!B$5:B$11,MATCH($B16,Premissas!$A$39:$A$45,0)) | D16: =INDEX(Cronograma!C$5:C$11,MATCH($B16,Premissas!$A$39:$A$45,0)) | E16: =INDEX(Cronograma!D$5:D$11,MATCH($B16,Premissas!$A$39:$A$45,0)) | F16: =INDEX(Cronograma!E$5:E$11,MATCH($B16,Premissas!$A$39:$A$45,0)) | G16: =INDEX(Cronograma!F$5:F$11,MATCH($B16,Premissas!$A$39:$A$45,0)) | H16: =INDEX(Cronograma!G$5:G$11,MATCH($B16,Premissas!$A$39:$A$45,0)) | I16: =INDEX(Cronograma!H$5:H$11,MATCH($B16,Premissas!$A$39:$A$45,0)) -> S | J16: =INDEX(Cronograma!I$5:I$11,MATCH($B16,Premissas!$A$39:$A$45,0)) | ... BB16: =INDEX(Cronograma!BA$5:BA$11,MATCH($B16,Premissas!$A$39:$A$45,0))
... A388: =Frota!$B388&" — "&Frota!$A388 -> Chinesa — 580002 | B388: =Frota!$C388 -> Implemento | C388: =INDEX(Cronograma!B$5:B$11,MATCH($B388,Premissas!$A$39:$A$45,0)) | D388: =INDEX(Cronograma!C$5:C$11,MATCH($B388,Premissas!$A$39:$A$45,0)) | E388: =INDEX(Cronograma!D$5:D$11,MATCH($B388,Premissas!$A$39:$A$45,0)) | F388: =INDEX(Cronograma!E$5:E$11,MATCH($B388,Premissas!$A$39:$A$45,0)) | G388: =INDEX(Cronograma!F$5:F$11,MATCH($B388,Premissas!$A$39:$A$45,0)) | H388: =INDEX(Cronograma!G$5:G$11,MATCH($B388,Premissas!$A$39:$A$45,0)) | I388: =INDEX(Cronograma!H$5:H$11,MATCH($B388,Premissas!$A$39:$A$45,0)) | J388: =INDEX(Cronograma!I$5:I$11,MATCH($B388,Premissas!$A$39:$A$45,0)) -> S | ... BB388: =INDEX(Cronograma!BA$5:BA$11,MATCH($B388,Premissas!$A$39:$A$45,0))

Sheet Agenda
A1: AGENDA DE PREVENTIVAS — por ativo, em datas reais (como no app: dias úteis, oficina principal e responsável) | M1: ⌂ MENU
A2: Gerada do motor com as premissas de 06/07/2026 (datas e ativos = valores; HH e responsável = fórmulas vivas). Use os filtros (Trimestre, Mês, Classe, Setor, Tipo, Oficina). Responsável: "Equipe..." até a aba Pessoas ser preenchida — depois atribui automaticamente por rodízio. Se alterar gatilhos/uso semanal nas Premissas, pedir ao Claude para regenerar a Agenda.
M3: KPIs POR TRIMESTRE
M4: Trimestre | N4: Preventivas | O4: HH total | P4: Ativos distintos
A5: Data | B5: Semana | C5: Trim. | D5: Mês | E5: Safra | F5: Ativo | G5: Setor | H5: Classe | I5: Tipo | J5: HH | K5: Oficina executora | L5: Responsável | M5: T1 | N5: =COUNTIFS($C$6:$C$2106,1) -> 553 | O5: =ROUND(SUMIFS($J$6:$J$2106,$C$6:$C$2106,1),1) -> 1782 | P5: =SUMPRODUCT(($C$6:$C$2106=1)/COUNTIFS($F$6:$F$2106,$F$6:$F$2106&"",$C$6:$C$2106,$C$6:$C$2106)) -> 334
A6: 46280 | B6: 3 | C6: 1 | D6: 9 | E6: 🌾 Safra | F6: JD-CH-570 — 140012 | G6: Colheita | H6: Colhedora | I6: S | J6: =IFERROR(INDEX(Aux_HH!$J$4:$J$31,MATCH($H6&"|"&$I6,Aux_HH!$A$4:$A$31,0)),"") -> 3 | K6: Oficina Mecânica Central-Taisa | L6: =IF(COUNTIFS(Pessoas!$C$5:$C$44,$K6,Pessoas!$G$5:$G$44,"Ativo")=0,"Equipe "&$K6,INDEX(Pessoas!$A$5:$A$44,_xludf.aggregate(15,6,(ROW(Pessoas!$A$5:$A$44)-4)/((Pessoas!$C$5:$C$44=$K6)*(Pessoas!$G$5:$G$44="Ativo")),MOD(ROW()-6,MAX(1,COUNTIFS(Pessoas!$C$5:$C$44,$K6,Pessoas!$G$5:$G$44,"Ativo")))+1))) -> Equipe Oficina Mecânica Central-Taisa | M6: T2 | N6: =COUNTIFS($C$6:$C$2106,2) -> 754 | O6: =ROUND(SUMIFS($J$6:$J$2106,$C$6:$C$2106,2),1) -> 3151.5 | P6: =SUMPRODUCT(($C$6:$C$2106=2)/COUNTIFS($F$6:$F$2106,$F$6:$F$2106&"",$C$6:$C$2106,$C$6:$C$2106)) -> 384
A7: 46280 | B7: 3 | C7: 1 | D7: 9 | E7: 🌾 Safra | F7: JD-CH-570 — 140017 | G7: Colheita | H7: Colhedora | I7: S | J7: =IFERROR(INDEX(Aux_HH!$J$4:$J$31,MATCH($H7&"|"&$I7,Aux_HH!$A$4:$A$31,0)),"") -> 3 | K7: Oficina Mecânica Central-Taisa | L7: =IF(COUNTIFS(Pessoas!$C$5:$C$44,$K7,Pessoas!$G$5:$G$44,"Ativo")=0,"Equipe "&$K7,INDEX(Pessoas!$A$5:$A$44,_xludf.aggregate(15,6,(ROW(Pessoas!$A$5:$A$44)-4)/((Pessoas!$C$5:$C$44=$K7)*(Pessoas!$G$5:$G$44="Ativo")),MOD(ROW()-6,MAX(1,COUNTIFS(Pessoas!$C$5:$C$44,$K7,Pessoas!$G$5:$G$44,"Ativo")))+1))) -> Equipe Oficina Mecânica Central-Taisa | M7: T3 | N7: =COUNTIFS($C$6:$C$2106,3) -> 404 | O7: =ROUND(SUMIFS($J$6:$J$2106,$C$6:$C$2106,3),1) -> 1801.5 | P7: =SUMPRODUCT(($C$6:$C$2106=3)/COUNTIFS($F$6:$F$2106,$F$6:$F$2106&"",$C$6:$C$2106,$C$6:$C$2106)) -> 384
A8: 46281 | B8: 3 | C8: 1 | D8: 9 | E8: 🌾 Safra | F8: JD-CH-570 — 140013 | G8: Colheita | H8: Colhedora | I8: S | J8: =IFERROR(INDEX(Aux_HH!$J$4:$J$31,MATCH($H8&"|"&$I8,Aux_HH!$A$4:$A$31,0)),"") -> 3 | K8: Oficina Mecânica Central-Taisa | L8: =IF(COUNTIFS(Pessoas!$C$5:$C$44,$K8,Pessoas!$G$5:$G$44,"Ativo")=0,"Equipe "&$K8,INDEX(Pessoas!$A$5:$A$44,_xludf.aggregate(15,6,(ROW(Pessoas!$A$5:$A$44)-4)/((Pessoas!$C$5:$C$44=$K8)*(Pessoas!$G$5:$G$44="Ativo")),MOD(ROW()-6,MAX(1,COUNTIFS(Pessoas!$C$5:$C$44,$K8,Pessoas!$G$5:$G$44,"Ativo")))+1))) -> Equipe Oficina Mecânica Central-Taisa | M8: T4 | N8: =COUNTIFS($C$6:$C$2106,4) -> 390 | O8: =ROUND(SUMIFS($J$6:$J$2106,$C$6:$C$2106,4),1) -> 1248.5 | P8: =SUMPRODUCT(($C$6:$C$2106=4)/COUNTIFS($F$6:$F$2106,$F$6:$F$2106&"",$C$6:$C$2106,$C$6:$C$2106)) -> 366
A9: 46281 | B9: 3 | C9: 1 | D9: 9 | E9: 🌾 Safra | F9: JD-CH-570 — 140018 | G9: Motomecanização | H9: Colhedora | I9: S | J9: =IFERROR(INDEX(Aux_HH!$J$4:$J$31,MATCH($H9&"|"&$I9,Aux_HH!$A$4:$A$31,0)),"") -> 3 | K9: Oficina Mecânica Central-Taisa | L9: =IF(COUNTIFS(Pessoas!$C$5:$C$44,$K9,Pessoas!$G$5:$G$44,"Ativo")=0,"Equipe "&$K9,INDEX(Pessoas!$A$5:$A$44,_xludf.aggregate(15,6,(ROW(Pessoas!$A$5:$A$44)-4)/((Pessoas!$C$5:$C$44=$K9)*(Pessoas!$G$5:$G$44="Ativo")),MOD(ROW()-6,MAX(1,COUNTIFS(Pessoas!$C$5:$C$44,$K9,Pessoas!$G$5:$G$44,"Ativo")))+1))) -> Equipe Oficina Mecânica Central-Taisa
A10: 46282 | B10: 3 | C10: 1 | D10: 9 | E10: 🌾 Safra | F10: Case IH A9900 — 140014 | G10: Colheita | H10: Colhedora | I10: S | J10: =IFERROR(INDEX(Aux_HH!$J$4:$J$31,MATCH($H10&"|"&$I10,Aux_HH!$A$4:$A$31,0)),"") -> 3 | K10: Oficina Mecânica Central-Taisa | L10: =IF(COUNTIFS(Pessoas!$C$5:$C$44,$K10,Pessoas!$G$5:$G$44,"Ativo")=0,"Equipe "&$K10,INDEX(Pessoas!$A$5:$A$44,_xludf.aggregate(15,6,(ROW(Pessoas!$A$5:$A$44)-4)/((Pessoas!$C$5:$C$44=$K10)*(Pessoas!$G$5:$G$44="Ativo")),MOD(ROW()-6,MAX(1,COUNTIFS(Pessoas!$C$5:$C$44,$K10,Pessoas!$G$5:$G$44,"Ativo")))+1))) -> Equipe Oficina Mecânica Central-Taisa | M10: DENSIDADE MENSAL (o app abre no trimestre mais cheio — aqui veja o ano inteiro)
A11: 46282 | B11: 3 | C11: 1 | D11: 9 | E11: 🌾 Safra | F11: JD-CH-570 — 140019 | G11: Motomecanização | H11: Colhedora | I11: S | J11: =IFERROR(INDEX(Aux_HH!$J$4:$J$31,MATCH($H11&"|"&$I11,Aux_HH!$A$4:$A$31,0)),"") -> 3 | K11: Oficina Mecânica Central-Taisa | L11: =IF(COUNTIFS(Pessoas!$C$5:$C$44,$K11,Pessoas!$G$5:$G$44,"Ativo")=0,"Equipe "&$K11,INDEX(Pessoas!$A$5:$A$44,_xludf.aggregate(15,6,(ROW(Pessoas!$A$5:$A$44)-4)/((Pessoas!$C$5:$C$44=$K11)*(Pessoas!$G$5:$G$44="Ativo")),MOD(ROW()-6,MAX(1,COUNTIFS(Pessoas!$C$5:$C$44,$K11,Pessoas!$G$5:$G$44,"Ativo")))+1))) -> Equipe Oficina Mecânica Central-Taisa | M11: Mês | N11: Preventivas | O11: HH | P11: Ativos únicos
A12: 46283 | B12: 3 | C12: 1 | D12: 9 | E12: 🌾 Safra | F12: Case IH A9900 — 140015 | G12: Colheita | H12: Colhedora | I12: S | J12: =IFERROR(INDEX(Aux_HH!$J$4:$J$31,MATCH($H12&"|"&$I12,Aux_HH!$A$4:$A$31,0)),"") -> 3 | K12: Oficina Mecânica Central-Taisa | L12: =IF(COUNTIFS(Pessoas!$C$5:$C$44,$K12,Pessoas!$G$5:$G$44,"Ativo")=0,"Equipe "&$K12,INDEX(Pessoas!$A$5:$A$44,_xludf.aggregate(15,6,(ROW(Pessoas!$A$5:$A$44)-4)/((Pessoas!$C$5:$C$44=$K12)*(Pessoas!$G$5:$G$44="Ativo")),MOD(ROW()-6,MAX(1,COUNTIFS(Pessoas!$C$5:$C$44,$K12,Pessoas!$G$5:$G$44,"Ativo")))+1))) -> Equipe Oficina Mecânica Central-Taisa | M12: Jan | N12: =COUNTIFS($D$6:$D$2106,1) -> 245 | O12: =ROUND(SUMIFS($J$6:$J$2106,$D$6:$D$2106,1),0) -> 743 | P12: =SUMPRODUCT(($D$6:$D$2106=1)/COUNTIFS($F$6:$F$2106,$F$6:$F$2106&"",$D$6:$D$2106,$D$6:$D$2106)) -> 243
A13: 46286 | B13: 3 | C13: 1 | D13: 9 | E13: 🌾 Safra | F13: JD-CH-570 — 140016 | G13: Colheita | H13: Colhedora | I13: S | J13: =IFERROR(INDEX(Aux_HH!$J$4:$J$31,MATCH($H13&"|"&$I13,Aux_HH!$A$4:$A$31,0)),"") -> 3 | K13: Oficina Mecânica Central-Taisa | L13: =IF(COUNTIFS(Pessoas!$C$5:$C$44,$K13,Pessoas!$G$5:$G$44,"Ativo")=0,"Equipe "&$K13,INDEX(Pessoas!$A$5:$A$44,_xludf.aggregate(15,6,(ROW(Pessoas!$A$5:$A$44)-4)/((Pessoas!$C$5:$C$44=$K13)*(Pessoas!$G$5:$G$44="Ativo")),MOD(ROW()-6,MAX(1,COUNTIFS(Pessoas!$C$5:$C$44,$K13,Pessoas!$G$5:$G$44,"Ativo")))+1))) -> Equipe Oficina Mecânica Central-Taisa | M13: Fev | N13: =COUNTIFS($D$6:$D$2106,2) -> 221 | O13: =ROUND(SUMIFS($J$6:$J$2106,$D$6:$D$2106,2),0) -> 1523 | P13: =SUMPRODUCT(($D$6:$D$2106=2)/COUNTIFS($F$6:$F$2106,$F$6:$F$2106&"",$D$6:$D$2106,$D$6:$D$2106)) -> 213
A14: 46294 | B14: 5 | C14: 1 | D14: 9 | E14: 🌾 Safra | F14: JD-CH-570 — 140012 | G14: Colheita | H14: Colhedora | I14: A | J14: =IFERROR(INDEX(Aux_HH!$J$4:$J$31,MATCH($H14&"|"&$I14,Aux_HH!$A$4:$A$31,0)),"") -> 6 | K14: Oficina Mecânica Central-Taisa | L14: =IF(COUNTIFS(Pessoas!$C$5:$C$44,$K14,Pessoas!$G$5:$G$44,"Ativo")=0,"Equipe "&$K14,INDEX(Pessoas!$A$5:$A$44,_xludf.aggregate(15,6,(ROW(Pessoas!$A$5:$A$44)-4)/((Pessoas!$C$5:$C$44=$K14)*(Pessoas!$G$5:$G$44="Ativo")),MOD(ROW()-6,MAX(1,COUNTIFS(Pessoas!$C$5:$C$44,$K14,Pessoas!$G$5:$G$44,"Ativo")))+1))) -> Equipe Oficina Mecânica Central-Taisa | M14: Mar | N14: =COUNTIFS($D$6:$D$2106,3) -> 272 | O14: =ROUND(SUMIFS($J$6:$J$2106,$D$6:$D$2106,3),0) -> 1469 | P14: =SUMPRODUCT(($D$6:$D$2106=3)/COUNTIFS($F$6:$F$2106,$F$6:$F$2106&"",$D$6:$D$2106,$D$6:$D$2106)) -> 264
A15: 46294 | B15: 5 | C15: 1 | D15: 9 | E15: 🌾 Safra | F15: JD-CH-570 — 140017 | G15: Colheita | H15: Colhedora | I15: A | J15: =IFERROR(INDEX(Aux_HH!$J$4:$J$31,MATCH($H15&"|"&$I15,Aux_HH!$A$4:$A$31,0)),"") -> 6 | K15: Oficina Mecânica Central-Taisa | L15: =IF(COUNTIFS(Pessoas!$C$5:$C$44,$K15,Pessoas!$G$5:$G$44,"Ativo")=0,"Equipe "&$K15,INDEX(Pessoas!$A$5:$A$44,_xludf.aggregate(15,6,(ROW(Pessoas!$A$5:$A$44)-4)/((Pessoas!$C$5:$C$44=$K15)*(Pessoas!$G$5:$G$44="Ativo")),MOD(ROW()-6,MAX(1,COUNTIFS(Pessoas!$C$5:$C$44,$K15,Pessoas!$G$5:$G$44,"Ativo")))+1))) -> Equipe Oficina Mecânica Central-Taisa | M15: Abr | N15: =COUNTIFS($D$6:$D$2106,4) -> 112 | O15: =ROUND(SUMIFS($J$6:$J$2106,$D$6:$D$2106,4),0) -> 275 | P15: =SUMPRODUCT(($D$6:$D$2106=4)/COUNTIFS($F$6:$F$2106,$F$6:$F$2106&"",$D$6:$D$2106,$D$6:$D$2106)) -> 112
A16: 46294 | B16: 5 | C16: 1 | D16: 9 | E16: 🌾 Safra | F16: Pulverizador Manual — 171003 | G16: Agrícola | H16: Pulverizador | I16: S | J16: =IFERROR(INDEX(Aux_HH!$J$4:$J$31,MATCH($H16&"|"&$I16,Aux_HH!$A$4:$A$31,0)),"") -> 2 | K16: Oficina Mecânica Central-Taisa | L16: =IF(COUNTIFS(Pessoas!$C$5:$C$44,$K16,Pessoas!$G$5:$G$44,"Ativo")=0,"Equipe "&$K16,INDEX(Pessoas!$A$5:$A$44,_xludf.aggregate(15,6,(ROW(Pessoas!$A$5:$A$44)-4)/((Pessoas!$C$5:$C$44=$K16)*(Pessoas!$G$5:$G$44="Ativo")),MOD(ROW()-6,MAX(1,COUNTIFS(Pessoas!$C$5:$C$44,$K16,Pessoas!$G$5:$G$44,"Ativo")))+1))) -> Equipe Oficina Mecânica Central-Taisa | M16: Mai | N16: =COUNTIFS($D$6:$D$2106,5) -> 20 | O16: =ROUND(SUMIFS($J$6:$J$2106,$D$6:$D$2106,5),0) -> 58 | P16: =SUMPRODUCT(($D$6:$D$2106=5)/COUNTIFS($F$6:$F$2106,$F$6:$F$2106&"",$D$6:$D$2106,$D$6:$D$2106)) -> 20
A17: 46294 | B17: 5 | C17: 1 | D17: 9 | E17: 🌾 Safra | F17: Pulverizador Manual — 171008 | G17: Agrícola | H17: Pulverizador | I17: S | J17: =IFERROR(INDEX(Aux_HH!$J$4:$J$31,MATCH($H17&"|"&$I17,Aux_HH!$A$4:$A$31,0)),"") -> 2 | K17: Oficina Mecânica Central-Taisa | L17: =IF(COUNTIFS(Pessoas!$C$5:$C$44,$K17,Pessoas!$G$5:$G$44,"Ativo")=0,"Equipe "&$K17,INDEX(Pessoas!$A$5:$A$44,_xludf.aggregate(15,6,(ROW(Pessoas!$A$5:$A$44)-4)/((Pessoas!$C$5:$C$44=$K17)*(Pessoas!$G$5:$G$44="Ativo")),MOD(ROW()-6,MAX(1,COUNTIFS(Pessoas!$C$5:$C$44,$K17,Pessoas!$G$5:$G$44,"Ativo")))+1))) -> Equipe Oficina Mecânica Central-Taisa | M17: Jun | N17: =COUNTIFS($D$6:$D$2106,6) -> 206 | O17: =ROUND(SUMIFS($J$6:$J$2106,$D$6:$D$2106,6),0) -> 619 | P17: =SUMPRODUCT(($D$6:$D$2106=6)/COUNTIFS($F$6:$F$2106,$F$6:$F$2106&"",$D$6:$D$2106,$D$6:$D$2106)) -> 206
A18: 46295 | B18: 5 | C18: 1 | D18: 9 | E18: 🌾 Safra | F18: JD-CH-570 — 140013 | G18: Colheita | H18: Colhedora | I18: A | J18: =IFERROR(INDEX(Aux_HH!$J$4:$J$31,MATCH($H18&"|"&$I18,Aux_HH!$A$4:$A$31,0)),"") -> 6 | K18: Oficina Mecânica Central-Taisa | L18: =IF(COUNTIFS(Pessoas!$C$5:$C$44,$K18,Pessoas!$G$5:$G$44,"Ativo")=0,"Equipe "&$K18,INDEX(Pessoas!$A$5:$A$44,_xludf.aggregate(15,6,(ROW(Pessoas!$A$5:$A$44)-4)/((Pessoas!$C$5:$C$44=$K18)*(Pessoas!$G$5:$G$44="Ativo")),MOD(ROW()-6,MAX(1,COUNTIFS(Pessoas!$C$5:$C$44,$K18,Pessoas!$G$5:$G$44,"Ativo")))+1))) -> Equipe Oficina Mecânica Central-Taisa | M18: Jul | N18: =COUNTIFS($D$6:$D$2106,7) -> 52 | O18: =ROUND(SUMIFS($J$6:$J$2106,$D$6:$D$2106,7),0) -> 84 | P18: =SUMPRODUCT(($D$6:$D$2106=7)/COUNTIFS($F$6:$F$2106,$F$6:$F$2106&"",$D$6:$D$2106,$D$6:$D$2106)) -> 52
A19: 46295 | B19: 5 | C19: 1 | D19: 9 | E19: 🌾 Safra | F19: JD-CH-570 — 140018 | G19: Motomecanização | H19: Colhedora | I19: A | J19: =IFERROR(INDEX(Aux_HH!$J$4:$J$31,MATCH($H19&"|"&$I19,Aux_HH!$A$4:$A$31,0)),"") -> 6 | K19: Oficina Mecânica Central-Taisa | L19: =IF(COUNTIFS(Pessoas!$C$5:$C$44,$K19,Pessoas!$G$5:$G$44,"Ativo")=0,"Equipe "&$K19,INDEX(Pessoas!$A$5:$A$44,_xludf.aggregate(15,6,(ROW(Pessoas!$A$5:$A$44)-4)/((Pessoas!$C$5:$C$44=$K19)*(Pessoas!$G$5:$G$44="Ativo")),MOD(ROW()-6,MAX(1,COUNTIFS(Pessoas!$C$5:$C$44,$K19,Pessoas!$G$5:$G$44,"Ativo")))+1))) -> Equipe Oficina Mecânica Central-Taisa | M19: Ago | N19: =COUNTIFS($D$6:$D$2106,8) -> 132 | O19: =ROUND(SUMIFS($J$6:$J$2106,$D$6:$D$2106,8),0) -> 546 | P19: =SUMPRODUCT(($D$6:$D$2106=8)/COUNTIFS($F$6:$F$2106,$F$6:$F$2106&"",$D$6:$D$2106,$D$6:$D$2106)) -> 132
A20: 46295 | B20: 5 | C20: 1 | D20: 9 | E20: 🌾 Safra | F20: Pulverizador Manual — 171004 | G20: Agrícola | H20: Pulverizador | I20: S | J20: =IFERROR(INDEX(Aux_HH!$J$4:$J$31,MATCH($H20&"|"&$I20,Aux_HH!$A$4:$A$31,0)),"") -> 2 | K20: Oficina Mecânica Central-Taisa | L20: =IF(COUNTIFS(Pessoas!$C$5:$C$44,$K20,Pessoas!$G$5:$G$44,"Ativo")=0,"Equipe "&$K20,INDEX(Pessoas!$A$5:$A$44,_xludf.aggregate(15,6,(ROW(Pessoas!$A$5:$A$44)-4)/((Pessoas!$C$5:$C$44=$K20)*(Pessoas!$G$5:$G$44="Ativo")),MOD(ROW()-6,MAX(1,COUNTIFS(Pessoas!$C$5:$C$44,$K20,Pessoas!$G$5:$G$44,"Ativo")))+1))) -> Equipe Oficina Mecânica Central-Taisa | M20: Set | N20: =COUNTIFS($D$6:$D$2106,9) -> 16 | O20: =ROUND(SUMIFS($J$6:$J$2106,$D$6:$D$2106,9),0) -> 56 | P20: =SUMPRODUCT(($D$6:$D$2106=9)/COUNTIFS($F$6:$F$2106,$F$6:$F$2106&"",$D$6:$D$2106,$D$6:$D$2106)) -> 12
A21: 46295 | B21: 5 | C21: 1 | D21: 9 | E21: 🌾 Safra | F21: Pulverizador Manual — 171009 | G21: Agrícola | H21: Pulverizador | I21: S | J21: =IFERROR(INDEX(Aux_HH!$J$4:$J$31,MATCH($H21&"|"&$I21,Aux_HH!$A$4:$A$31,0)),"") -> 2 | K21: Oficina Mecânica Central-Taisa | L21: =IF(COUNTIFS(Pessoas!$C$5:$C$44,$K21,Pessoas!$G$5:$G$44,"Ativo")=0,"Equipe "&$K21,INDEX(Pessoas!$A$5:$A$44,_xludf.aggregate(15,6,(ROW(Pessoas!$A$5:$A$44)-4)/((Pessoas!$C$5:$C$44=$K21)*(Pessoas!$G$5:$G$44="Ativo")),MOD(ROW()-6,MAX(1,COUNTIFS(Pessoas!$C$5:$C$44,$K21,Pessoas!$G$5:$G$44,"Ativo")))+1))) -> Equipe Oficina Mecânica Central-Taisa | M21: Out | N21: =COUNTIFS($D$6:$D$2106,10) -> 334 | O21: =ROUND(SUMIFS($J$6:$J$2106,$D$6:$D$2106,10),0) -> 771 | P21: =SUMPRODUCT(($D$6:$D$2106=10)/COUNTIFS($F$6:$F$2106,$F$6:$F$2106&"",$D$6:$D$2106,$D$6:$D$2106)) -> 330
A22: 46296 | B22: 5 | C22: 1 | D22: 10 | E22: 🌾 Safra | F22: Case IH A9900 — 140014 | G22: Colheita | H22: Colhedora | I22: A | J22: =IFERROR(INDEX(Aux_HH!$J$4:$J$31,MATCH($H22&"|"&$I22,Aux_HH!$A$4:$A$31,0)),"") -> 6 | K22: Oficina Mecânica Central-Taisa | L22: =IF(COUNTIFS(Pessoas!$C$5:$C$44,$K22,Pessoas!$G$5:$G$44,"Ativo")=0,"Equipe "&$K22,INDEX(Pessoas!$A$5:$A$44,_xludf.aggregate(15,6,(ROW(Pessoas!$A$5:$A$44)-4)/((Pessoas!$C$5:$C$44=$K22)*(Pessoas!$G$5:$G$44="Ativo")),MOD(ROW()-6,MAX(1,COUNTIFS(Pessoas!$C$5:$C$44,$K22,Pessoas!$G$5:$G$44,"Ativo")))+1))) -> Equipe Oficina Mecânica Central-Taisa | M22: Nov | N22: =COUNTIFS($D$6:$D$2106,11) -> 203 | O22: =ROUND(SUMIFS($J$6:$J$2106,$D$6:$D$2106,11),0) -> 956 | P22: =SUMPRODUCT(($D$6:$D$2106=11)/COUNTIFS($F$6:$F$2106,$F$6:$F$2106&"",$D$6:$D$2106,$D$6:$D$2106)) -> 195
A23: 46296 | B23: 5 | C23: 1 | D23: 10 | E23: 🌾 Safra | F23: JD-CH-570 — 140019 | G23: Motomecanização | H23: Colhedora | I23: A | J23: =IFERROR(INDEX(Aux_HH!$J$4:$J$31,MATCH($H23&"|"&$I23,Aux_HH!$A$4:$A$31,0)),"") -> 6 | K23: Oficina Mecânica Central-Taisa | L23: =IF(COUNTIFS(Pessoas!$C$5:$C$44,$K23,Pessoas!$G$5:$G$44,"Ativo")=0,"Equipe "&$K23,INDEX(Pessoas!$A$5:$A$44,_xludf.aggregate(15,6,(ROW(Pessoas!$A$5:$A$44)-4)/((Pessoas!$C$5:$C$44=$K23)*(Pessoas!$G$5:$G$44="Ativo")),MOD(ROW()-6,MAX(1,COUNTIFS(Pessoas!$C$5:$C$44,$K23,Pessoas!$G$5:$G$44,"Ativo")))+1))) -> Equipe Oficina Mecânica Central-Taisa | M23: Dez | N23: =COUNTIFS($D$6:$D$2106,12) -> 288 | O23: =ROUND(SUMIFS($J$6:$J$2106,$D$6:$D$2106,12),0) -> 886 | P23: =SUMPRODUCT(($D$6:$D$2106=12)/COUNTIFS($F$6:$F$2106,$F$6:$F$2106&"",$D$6:$D$2106,$D$6:$D$2106)) -> 282
A24: 46296 | B24: 5 | C24: 1 | D24: 10 | E24: 🌾 Safra | F24: Pulverizador Manual — 171005 | G24: Agrícola | H24: Pulverizador | I24: S | J24: =IFERROR(INDEX(Aux_HH!$J$4:$J$31,MATCH($H24&"|"&$I24,Aux_HH!$A$4:$A$31,0)),"") -> 2 | K24: Oficina Mecânica Central-Taisa | L24: =IF(COUNTIFS(Pessoas!$C$5:$C$44,$K24,Pessoas!$G$5:$G$44,"Ativo")=0,"Equipe "&$K24,INDEX(Pessoas!$A$5:$A$44,_xludf.aggregate(15,6,(ROW(Pessoas!$A$5:$A$44)-4)/((Pessoas!$C$5:$C$44=$K24)*(Pessoas!$G$5:$G$44="Ativo")),MOD(ROW()-6,MAX(1,COUNTIFS(Pessoas!$C$5:$C$44,$K24,Pessoas!$G$5:$G$44,"Ativo")))+1))) -> Equipe Oficina Mecânica Central-Taisa | M24: ANO | N24: =COUNTA($I$6:$I$2106) -> 2101 | O24: =ROUND(SUM($J$6:$J$2106),0) -> 7984 | P24: 384
A25: 46296 | B25: 5 | C25: 1 | D25: 10 | E25: 🌾 Safra | F25: Pulverizador Manual — 173005 | G25: Agrícola | H25: Pulverizador | I25: S | J25: =IFERROR(INDEX(Aux_HH!$J$4:$J$31,MATCH($H25&"|"&$I25,Aux_HH!$A$4:$A$31,0)),"") -> 2 | K25: Oficina Mecânica Central-Taisa | L25: =IF(COUNTIFS(Pessoas!$C$5:$C$44,$K25,Pessoas!$G$5:$G$44,"Ativo")=0,"Equipe "&$K25,INDEX(Pessoas!$A$5:$A$44,_xludf.aggregate(15,6,(ROW(Pessoas!$A$5:$A$44)-4)/((Pessoas!$C$5:$C$44=$K25)*(Pessoas!$G$5:$G$44="Ativo")),MOD(ROW()-6,MAX(1,COUNTIFS(Pessoas!$C$5:$C$44,$K25,Pessoas!$G$5:$G$44,"Ativo")))+1))) -> Equipe Oficina Mecânica Central-Taisa
A26: 46297 | B26: 5 | C26: 1 | D26: 10 | E26: 🌾 Safra | F26: Case IH A9900 — 140015 | G26: Colheita | H26: Colhedora | I26: A | J26: =IFERROR(INDEX(Aux_HH!$J$4:$J$31,MATCH($H26&"|"&$I26,Aux_HH!$A$4:$A$31,0)),"") -> 6 | K26: Oficina Mecânica Central-Taisa | L26: =IF(COUNTIFS(Pessoas!$C$5:$C$44,$K26,Pessoas!$G$5:$G$44,"Ativo")=0,"Equipe "&$K26,INDEX(Pessoas!$A$5:$A$44,_xludf.aggregate(15,6,(ROW(Pessoas!$A$5:$A$44)-4)/((Pessoas!$C$5:$C$44=$K26)*(Pessoas!$G$5:$G$44="Ativo")),MOD(ROW()-6,MAX(1,COUNTIFS(Pessoas!$C$5:$C$44,$K26,Pessoas!$G$5:$G$44,"Ativo")))+1))) -> Equipe Oficina Mecânica Central-Taisa
A27: 46297 | B27: 5 | C27: 1 | D27: 10 | E27: 🌾 Safra | F27: Pulverizador Manual — 171001 | G27: Agrícola | H27: Pulverizador | I27: S | J27: =IFERROR(INDEX(Aux_HH!$J$4:$J$31,MATCH($H27&"|"&$I27,Aux_HH!$A$4:$A$31,0)),"") -> 2 | K27: Oficina Mecânica Central-Taisa | L27: =IF(COUNTIFS(Pessoas!$C$5:$C$44,$K27,Pessoas!$G$5:$G$44,"Ativo")=0,"Equipe "&$K27,INDEX(Pessoas!$A$5:$A$44,_xludf.aggregate(15,6,(ROW(Pessoas!$A$5:$A$44)-4)/((Pessoas!$C$5:$C$44=$K27)*(Pessoas!$G$5:$G$44="Ativo")),MOD(ROW()-6,MAX(1,COUNTIFS(Pessoas!$C$5:$C$44,$K27,Pessoas!$G$5:$G$44,"Ativo")))+1))) -> Equipe Oficina Mecânica Central-Taisa
A28: 46297 | B28: 5 | C28: 1 | D28: 10 | E28: 🌾 Safra | F28: Pulverizador Manual — 171006 | G28: Agrícola | H28: Pulverizador | I28: S | J28: =IFERROR(INDEX(Aux_HH!$J$4:$J$31,MATCH($H28&"|"&$I28,Aux_HH!$A$4:$A$31,0)),"") -> 2 | K28: Oficina Mecânica Central-Taisa | L28: =IF(COUNTIFS(Pessoas!$C$5:$C$44,$K28,Pessoas!$G$5:$G$44,"Ativo")=0,"Equipe "&$K28,INDEX(Pessoas!$A$5:$A$44,_xludf.aggregate(15,6,(ROW(Pessoas!$A$5:$A$44)-4)/((Pessoas!$C$5:$C$44=$K28)*(Pessoas!$G$5:$G$44="Ativo")),MOD(ROW()-6,MAX(1,COUNTIFS(Pessoas!$C$5:$C$44,$K28,Pessoas!$G$5:$G$44,"Ativo")))+1))) -> Equipe Oficina Mecânica Central-Taisa
A29: 46297 | B29: 5 | C29: 1 | D29: 10 | E29: 🌾 Safra | F29: Pulverizador Manual — 173006 | G29: Agrícola | H29: Pulverizador | I29: S | J29: =IFERROR(INDEX(Aux_HH!$J$4:$J$31,MATCH($H29&"|"&$I29,Aux_HH!$A$4:$A$31,0)),"") -> 2 | K29: Oficina Mecânica Central-Taisa | L29: =IF(COUNTIFS(Pessoas!$C$5:$C$44,$K29,Pessoas!$G$5:$G$44,"Ativo")=0,"Equipe "&$K29,INDEX(Pessoas!$A$5:$A$44,_xludf.aggregate(15,6,(ROW(Pessoas!$A$5:$A$44)-4)/((Pessoas!$C$5:$C$44=$K29)*(Pessoas!$G$5:$G$44="Ativo")),MOD(ROW()-6,MAX(1,COUNTIFS(Pessoas!$C$5:$C$44,$K29,Pessoas!$G$5:$G$44,"Ativo")))+1))) -> Equipe Oficina Mecânica Central-Taisa
A30: 46300 | B30: 5 | C30: 1 | D30: 10 | E30: 🌾 Safra | F30: JD-CH-570 — 140016 | G30: Colheita | H30: Colhedora | I30: A | J30: =IFERROR(INDEX(Aux_HH!$J$4:$J$31,MATCH($H30&"|"&$I30,Aux_HH!$A$4:$A$31,0)),"") -> 6 | K30: Oficina Mecânica Central-Taisa | L30: =IF(COUNTIFS(Pessoas!$C$5:$C$44,$K30,Pessoas!$G$5:$G$44,"Ativo")=0,"Equipe "&$K30,INDEX(Pessoas!$A$5:$A$44,_xludf.aggregate(15,6,(ROW(Pessoas!$A$5:$A$44)-4)/((Pessoas!$C$5:$C$44=$K30)*(Pessoas!$G$5:$G$44="Ativo")),MOD(ROW()-6,MAX(1,COUNTIFS(Pessoas!$C$5:$C$44,$K30,Pessoas!$G$5:$G$44,"Ativo")))+1))) -> Equipe Oficina Mecânica Central-Taisa
A31: 46300 | B31: 5 | C31: 1 | D31: 10 | E31: 🌾 Safra | F31: Pulverizador Manual — 171002 | G31: Agrícola | H31: Pulverizador | I31: S | J31: =IFERROR(INDEX(Aux_HH!$J$4:$J$31,MATCH($H31&"|"&$I31,Aux_HH!$A$4:$A$31,0)),"") -> 2 | K31: Oficina Mecânica Central-Taisa | L31: =IF(COUNTIFS(Pessoas!$C$5:$C$44,$K31,Pessoas!$G$5:$G$44,"Ativo")=0,"Equipe "&$K31,INDEX(Pessoas!$A$5:$A$44,_xludf.aggregate(15,6,(ROW(Pessoas!$A$5:$A$44)-4)/((Pessoas!$C$5:$C$44=$K31)*(Pessoas!$G$5:$G$44="Ativo")),MOD(ROW()-6,MAX(1,COUNTIFS(Pessoas!$C$5:$C$44,$K31,Pessoas!$G$5:$G$44,"Ativo")))+1))) -> Equipe Oficina Mecânica Central-Taisa
A32: 46300 | B32: 5 | C32: 1 | D32: 10 | E32: 🌾 Safra | F32: Pulverizador Manual — 171007 | G32: Agrícola | H32: Pulverizador | I32: S | J32: =IFERROR(INDEX(Aux_HH!$J$4:$J$31,MATCH($H32&"|"&$I32,Aux_HH!$A$4:$A$31,0)),"") -> 2 | K32: Oficina Mecânica Central-Taisa | L32: =IF(COUNTIFS(Pessoas!$C$5:$C$44,$K32,Pessoas!$G$5:$G$44,"Ativo")=0,"Equipe "&$K32,INDEX(Pessoas!$A$5:$A$44,_xludf.aggregate(15,6,(ROW(Pessoas!$A$5:$A$44)-4)/((Pessoas!$C$5:$C$44=$K32)*(Pessoas!$G$5:$G$44="Ativo")),MOD(ROW()-6,MAX(1,COUNTIFS(Pessoas!$C$5:$C$44,$K32,Pessoas!$G$5:$G$44,"Ativo")))+1))) -> Equipe Oficina Mecânica Central-Taisa
A33: 46300 | B33: 5 | C33: 1 | D33: 10 | E33: 🌾 Safra | F33: Pulverizador Manual — 173007 | G33: Agrícola | H33: Pulverizador | I33: S | J33: =IFERROR(INDEX(Aux_HH!$J$4:$J$31,MATCH($H33&"|"&$I33,Aux_HH!$A$4:$A$31,0)),"") -> 2 | K33: Oficina Mecânica Central-Taisa | L33: =IF(COUNTIFS(Pessoas!$C$5:$C$44,$K33,Pessoas!$G$5:$G$44,"Ativo")=0,"Equipe "&$K33,INDEX(Pessoas!$A$5:$A$44,_xludf.aggregate(15,6,(ROW(Pessoas!$A$5:$A$44)-4)/((Pessoas!$C$5:$C$44=$K33)*(Pessoas!$G$5:$G$44="Ativo")),MOD(ROW()-6,MAX(1,COUNTIFS(Pessoas!$C$5:$C$44,$K33,Pessoas!$G$5:$G$44,"Ativo")))+1))) -> Equipe Oficina Mecânica Central-Taisa
A34: 46301 | B34: 6 | C34: 1 | D34: 10 | E34: 🌾 Safra | F34: 310 L — 116104 | G34: Motomecanização | H34: Carregadeira/Pesada | I34: S | J34: =IFERROR(INDEX(Aux_HH!$J$4:$J$31,MATCH($H34&"|"&$I34,Aux_HH!$A$4:$A$31,0)),"") -> 2.5 | K34: Oficina Mecânica Central-Taisa | L34: =IF(COUNTIFS(Pessoas!$C$5:$C$44,$K34,Pessoas!$G$5:$G$44,"Ativo")=0,"Equipe "&$K34,INDEX(Pessoas!$A$5:$A$44,_xludf.aggregate(15,6,(ROW(Pessoas!$A$5:$A$44)-4)/((Pessoas!$C$5:$C$44=$K34)*(Pessoas!$G$5:$G$44="Ativo")),MOD(ROW()-6,MAX(1,COUNTIFS(Pessoas!$C$5:$C$44,$K34,Pessoas!$G$5:$G$44,"Ativo")))+1))) -> Equipe Oficina Mecânica Central-Taisa
A35: 46301 | B35: 6 | C35: 1 | D35: 10 | E35: 🌾 Safra | F35: Bell SC-800 — 164002 | G35: Colheita | H35: Carregadeira/Pesada | I35: S | J35: =IFERROR(INDEX(Aux_HH!$J$4:$J$31,MATCH($H35&"|"&$I35,Aux_HH!$A$4:$A$31,0)),"") -> 2.5 | K35: Oficina Mecânica Central-Taisa | L35: =IF(COUNTIFS(Pessoas!$C$5:$C$44,$K35,Pessoas!$G$5:$G$44,"Ativo")=0,"Equipe "&$K35,INDEX(Pessoas!$A$5:$A$44,_xludf.aggregate(15,6,(ROW(Pessoas!$A$5:$A$44)-4)/((Pessoas!$C$5:$C$44=$K35)*(Pessoas!$G$5:$G$44="Ativo")),MOD(ROW()-6,MAX(1,COUNTIFS(Pessoas!$C$5:$C$44,$K35,Pessoas!$G$5:$G$44,"Ativo")))+1))) -> Equipe Oficina Mecânica Central-Taisa
A36: 46301 | B36: 6 | C36: 1 | D36: 10 | E36: 🌾 Safra | F36: Bell SC-800 — 164008 | G36: Colheita | H36: Carregadeira/Pesada | I36: S | J36: =IFERROR(INDEX(Aux_HH!$J$4:$J$31,MATCH($H36&"|"&$I36,Aux_HH!$A$4:$A$31,0)),"") -> 2.5 | K36: Oficina Mecânica Central-Taisa | L36: =IF(COUNTIFS(Pessoas!$C$5:$C$44,$K36,Pessoas!$G$5:$G$44,"Ativo")=0,"Equipe "&$K36,INDEX(Pessoas!$A$5:$A$44,_xludf.aggregate(15,6,(ROW(Pessoas!$A$5:$A$44)-4)/((Pessoas!$C$5:$C$44=$K36)*(Pessoas!$G$5:$G$44="Ativo")),MOD(ROW()-6,MAX(1,COUNTIFS(Pessoas!$C$5:$C$44,$K36,Pessoas!$G$5:$G$44,"Ativo")))+1))) -> Equipe Oficina Mecânica Central-Taisa
... A2106: 46615 | B2106: 50 | C2106: 4 | D2106: 8 | E2106: Entressafra | F2106: Pulverizador Manual — 173005 | G2106: Agrícola | H2106: Pulverizador | I2106: A | J2106: =IFERROR(INDEX(Aux_HH!$J$4:$J$31,MATCH($H2106&"|"&$I2106,Aux_HH!$A$4:$A$31,0)),"") -> 4 | K2106: Oficina Mecânica Central-Taisa | L2106: =IF(COUNTIFS(Pessoas!$C$5:$C$44,$K2106,Pessoas!$G$5:$G$44,"Ativo")=0,"Equipe "&$K2106,INDEX(Pessoas!$A$5:$A$44,_xludf.aggregate(15,6,(ROW(Pessoas!$A$5:$A$44)-4)/((Pessoas!$C$5:$C$44=$K2106)*(Pessoas!$G$5:$G$44="Ativo")),MOD(ROW()-6,MAX(1,COUNTIFS(Pessoas!$C$5:$C$44,$K2106,Pessoas!$G$5:$G$44,"Ativo")))+1))) -> Equipe Oficina Mecânica Central-Taisa

Sheet Mapa_Preventivas
A1: MAPA DE PREVENTIVAS — CLASSE × MÊS (contagem de eventos; verde=vazio → vermelho=pico, atenção à capacidade) | P1: ⌂ MENU
A3: Classe | B3: Jan | C3: Fev | D3: Mar | E3: Abr | F3: Mai | G3: Jun | H3: Jul | I3: Ago | J3: Set | K3: Out | L3: Nov | M3: Dez | N3: TOTAL
A4: Colhedora | B4: =COUNTIFS(Agenda!$H$6:$H$2106,$A4,Agenda!$D$6:$D$2106,1) -> 10 | C4: =COUNTIFS(Agenda!$H$6:$H$2106,$A4,Agenda!$D$6:$D$2106,2) -> 16 | D4: =COUNTIFS(Agenda!$H$6:$H$2106,$A4,Agenda!$D$6:$D$2106,3) -> 16 | E4: =COUNTIFS(Agenda!$H$6:$H$2106,$A4,Agenda!$D$6:$D$2106,4) -> 0 | F4: =COUNTIFS(Agenda!$H$6:$H$2106,$A4,Agenda!$D$6:$D$2106,5) -> 0 | G4: =COUNTIFS(Agenda!$H$6:$H$2106,$A4,Agenda!$D$6:$D$2106,6) -> 0 | H4: =COUNTIFS(Agenda!$H$6:$H$2106,$A4,Agenda!$D$6:$D$2106,7) -> 0 | I4: =COUNTIFS(Agenda!$H$6:$H$2106,$A4,Agenda!$D$6:$D$2106,8) -> 8 | J4: =COUNTIFS(Agenda!$H$6:$H$2106,$A4,Agenda!$D$6:$D$2106,9) -> 12 | K4: =COUNTIFS(Agenda!$H$6:$H$2106,$A4,Agenda!$D$6:$D$2106,10) -> 12 | L4: =COUNTIFS(Agenda!$H$6:$H$2106,$A4,Agenda!$D$6:$D$2106,11) -> 16 | M4: =COUNTIFS(Agenda!$H$6:$H$2106,$A4,Agenda!$D$6:$D$2106,12) -> 14 | N4: =SUM(B4:M4) -> 104
A5: Trator | B5: =COUNTIFS(Agenda!$H$6:$H$2106,$A5,Agenda!$D$6:$D$2106,1) -> 102 | C5: =COUNTIFS(Agenda!$H$6:$H$2106,$A5,Agenda!$D$6:$D$2106,2) -> 102 | D5: =COUNTIFS(Agenda!$H$6:$H$2106,$A5,Agenda!$D$6:$D$2106,3) -> 0 | E5: =COUNTIFS(Agenda!$H$6:$H$2106,$A5,Agenda!$D$6:$D$2106,4) -> 102 | F5: =COUNTIFS(Agenda!$H$6:$H$2106,$A5,Agenda!$D$6:$D$2106,5) -> 0 | G5: =COUNTIFS(Agenda!$H$6:$H$2106,$A5,Agenda!$D$6:$D$2106,6) -> 0 | H5: =COUNTIFS(Agenda!$H$6:$H$2106,$A5,Agenda!$D$6:$D$2106,7) -> 0 | I5: =COUNTIFS(Agenda!$H$6:$H$2106,$A5,Agenda!$D$6:$D$2106,8) -> 102 | J5: =COUNTIFS(Agenda!$H$6:$H$2106,$A5,Agenda!$D$6:$D$2106,9) -> 0 | K5: =COUNTIFS(Agenda!$H$6:$H$2106,$A5,Agenda!$D$6:$D$2106,10) -> 102 | L5: =COUNTIFS(Agenda!$H$6:$H$2106,$A5,Agenda!$D$6:$D$2106,11) -> 102 | M5: =COUNTIFS(Agenda!$H$6:$H$2106,$A5,Agenda!$D$6:$D$2106,12) -> 0 | N5: =SUM(B5:M5) -> 612
A6: Caminhão | B6: =COUNTIFS(Agenda!$H$6:$H$2106,$A6,Agenda!$D$6:$D$2106,1) -> 121 | C6: =COUNTIFS(Agenda!$H$6:$H$2106,$A6,Agenda!$D$6:$D$2106,2) -> 0 | D6: =COUNTIFS(Agenda!$H$6:$H$2106,$A6,Agenda!$D$6:$D$2106,3) -> 121 | E6: =COUNTIFS(Agenda!$H$6:$H$2106,$A6,Agenda!$D$6:$D$2106,4) -> 0 | F6: =COUNTIFS(Agenda!$H$6:$H$2106,$A6,Agenda!$D$6:$D$2106,5) -> 0 | G6: =COUNTIFS(Agenda!$H$6:$H$2106,$A6,Agenda!$D$6:$D$2106,6) -> 121 | H6: =COUNTIFS(Agenda!$H$6:$H$2106,$A6,Agenda!$D$6:$D$2106,7) -> 0 | I6: =COUNTIFS(Agenda!$H$6:$H$2106,$A6,Agenda!$D$6:$D$2106,8) -> 0 | J6: =COUNTIFS(Agenda!$H$6:$H$2106,$A6,Agenda!$D$6:$D$2106,9) -> 0 | K6: =COUNTIFS(Agenda!$H$6:$H$2106,$A6,Agenda!$D$6:$D$2106,10) -> 121 | L6: =COUNTIFS(Agenda!$H$6:$H$2106,$A6,Agenda!$D$6:$D$2106,11) -> 0 | M6: =COUNTIFS(Agenda!$H$6:$H$2106,$A6,Agenda!$D$6:$D$2106,12) -> 121 | N6: =SUM(B6:M6) -> 605
A7: Carregadeira/Pesada | B7: =COUNTIFS(Agenda!$H$6:$H$2106,$A7,Agenda!$D$6:$D$2106,1) -> 0 | C7: =COUNTIFS(Agenda!$H$6:$H$2106,$A7,Agenda!$D$6:$D$2106,2) -> 73 | D7: =COUNTIFS(Agenda!$H$6:$H$2106,$A7,Agenda!$D$6:$D$2106,3) -> 73 | E7: =COUNTIFS(Agenda!$H$6:$H$2106,$A7,Agenda!$D$6:$D$2106,4) -> 0 | F7: =COUNTIFS(Agenda!$H$6:$H$2106,$A7,Agenda!$D$6:$D$2106,5) -> 0 | G7: =COUNTIFS(Agenda!$H$6:$H$2106,$A7,Agenda!$D$6:$D$2106,6) -> 73 | H7: =COUNTIFS(Agenda!$H$6:$H$2106,$A7,Agenda!$D$6:$D$2106,7) -> 0 | I7: =COUNTIFS(Agenda!$H$6:$H$2106,$A7,Agenda!$D$6:$D$2106,8) -> 0 | J7: =COUNTIFS(Agenda!$H$6:$H$2106,$A7,Agenda!$D$6:$D$2106,9) -> 0 | K7: =COUNTIFS(Agenda!$H$6:$H$2106,$A7,Agenda!$D$6:$D$2106,10) -> 73 | L7: =COUNTIFS(Agenda!$H$6:$H$2106,$A7,Agenda!$D$6:$D$2106,11) -> 73 | M7: =COUNTIFS(Agenda!$H$6:$H$2106,$A7,Agenda!$D$6:$D$2106,12) -> 73 | N7: =SUM(B7:M7) -> 438
A8: Veículo Leve | B8: =COUNTIFS(Agenda!$H$6:$H$2106,$A8,Agenda!$D$6:$D$2106,1) -> 0 | C8: =COUNTIFS(Agenda!$H$6:$H$2106,$A8,Agenda!$D$6:$D$2106,2) -> 0 | D8: =COUNTIFS(Agenda!$H$6:$H$2106,$A8,Agenda!$D$6:$D$2106,3) -> 50 | E8: =COUNTIFS(Agenda!$H$6:$H$2106,$A8,Agenda!$D$6:$D$2106,4) -> 0 | F8: =COUNTIFS(Agenda!$H$6:$H$2106,$A8,Agenda!$D$6:$D$2106,5) -> 0 | G8: =COUNTIFS(Agenda!$H$6:$H$2106,$A8,Agenda!$D$6:$D$2106,6) -> 0 | H8: =COUNTIFS(Agenda!$H$6:$H$2106,$A8,Agenda!$D$6:$D$2106,7) -> 40 | I8: =COUNTIFS(Agenda!$H$6:$H$2106,$A8,Agenda!$D$6:$D$2106,8) -> 10 | J8: =COUNTIFS(Agenda!$H$6:$H$2106,$A8,Agenda!$D$6:$D$2106,9) -> 0 | K8: =COUNTIFS(Agenda!$H$6:$H$2106,$A8,Agenda!$D$6:$D$2106,10) -> 0 | L8: =COUNTIFS(Agenda!$H$6:$H$2106,$A8,Agenda!$D$6:$D$2106,11) -> 0 | M8: =COUNTIFS(Agenda!$H$6:$H$2106,$A8,Agenda!$D$6:$D$2106,12) -> 50 | N8: =SUM(B8:M8) -> 150
A9: Pulverizador | B9: =COUNTIFS(Agenda!$H$6:$H$2106,$A9,Agenda!$D$6:$D$2106,1) -> 12 | C9: =COUNTIFS(Agenda!$H$6:$H$2106,$A9,Agenda!$D$6:$D$2106,2) -> 12 | D9: =COUNTIFS(Agenda!$H$6:$H$2106,$A9,Agenda!$D$6:$D$2106,3) -> 12 | E9: =COUNTIFS(Agenda!$H$6:$H$2106,$A9,Agenda!$D$6:$D$2106,4) -> 10 | F9: =COUNTIFS(Agenda!$H$6:$H$2106,$A9,Agenda!$D$6:$D$2106,5) -> 2 | G9: =COUNTIFS(Agenda!$H$6:$H$2106,$A9,Agenda!$D$6:$D$2106,6) -> 12 | H9: =COUNTIFS(Agenda!$H$6:$H$2106,$A9,Agenda!$D$6:$D$2106,7) -> 12 | I9: =COUNTIFS(Agenda!$H$6:$H$2106,$A9,Agenda!$D$6:$D$2106,8) -> 12 | J9: =COUNTIFS(Agenda!$H$6:$H$2106,$A9,Agenda!$D$6:$D$2106,9) -> 4 | K9: =COUNTIFS(Agenda!$H$6:$H$2106,$A9,Agenda!$D$6:$D$2106,10) -> 8 | L9: =COUNTIFS(Agenda!$H$6:$H$2106,$A9,Agenda!$D$6:$D$2106,11) -> 12 | M9: =COUNTIFS(Agenda!$H$6:$H$2106,$A9,Agenda!$D$6:$D$2106,12) -> 12 | N9: =SUM(B9:M9) -> 120
A10: Implemento | B10: =COUNTIFS(Agenda!$H$6:$H$2106,$A10,Agenda!$D$6:$D$2106,1) -> 0 | C10: =COUNTIFS(Agenda!$H$6:$H$2106,$A10,Agenda!$D$6:$D$2106,2) -> 18 | D10: =COUNTIFS(Agenda!$H$6:$H$2106,$A10,Agenda!$D$6:$D$2106,3) -> 0 | E10: =COUNTIFS(Agenda!$H$6:$H$2106,$A10,Agenda!$D$6:$D$2106,4) -> 0 | F10: =COUNTIFS(Agenda!$H$6:$H$2106,$A10,Agenda!$D$6:$D$2106,5) -> 18 | G10: =COUNTIFS(Agenda!$H$6:$H$2106,$A10,Agenda!$D$6:$D$2106,6) -> 0 | H10: =COUNTIFS(Agenda!$H$6:$H$2106,$A10,Agenda!$D$6:$D$2106,7) -> 0 | I10: =COUNTIFS(Agenda!$H$6:$H$2106,$A10,Agenda!$D$6:$D$2106,8) -> 0 | J10: =COUNTIFS(Agenda!$H$6:$H$2106,$A10,Agenda!$D$6:$D$2106,9) -> 0 | K10: =COUNTIFS(Agenda!$H$6:$H$2106,$A10,Agenda!$D$6:$D$2106,10) -> 18 | L10: =COUNTIFS(Agenda!$H$6:$H$2106,$A10,Agenda!$D$6:$D$2106,11) -> 0 | M10: =COUNTIFS(Agenda!$H$6:$H$2106,$A10,Agenda!$D$6:$D$2106,12) -> 18 | N10: =SUM(B10:M10) -> 72
A11: TOTAL | B11: =SUM(B4:B10) -> 245 | C11: =SUM(C4:C10) -> 221 | D11: =SUM(D4:D10) -> 272 | E11: =SUM(E4:E10) -> 112 | F11: =SUM(F4:F10) -> 20 | G11: =SUM(G4:G10) -> 206 | H11: =SUM(H4:H10) -> 52 | I11: =SUM(I4:I10) -> 132 | ... N11: =SUM(N4:N10) -> 2101
A13: HH por mês | B13: =ROUND(SUMIFS(Agenda!$J$6:$J$2106,Agenda!$D$6:$D$2106,1),0) -> 743 | C13: =ROUND(SUMIFS(Agenda!$J$6:$J$2106,Agenda!$D$6:$D$2106,2),0) -> 1523 | D13: =ROUND(SUMIFS(Agenda!$J$6:$J$2106,Agenda!$D$6:$D$2106,3),0) -> 1469 | E13: =ROUND(SUMIFS(Agenda!$J$6:$J$2106,Agenda!$D$6:$D$2106,4),0) -> 275 | F13: =ROUND(SUMIFS(Agenda!$J$6:$J$2106,Agenda!$D$6:$D$2106,5),0) -> 58 | G13: =ROUND(SUMIFS(Agenda!$J$6:$J$2106,Agenda!$D$6:$D$2106,6),0) -> 619 | H13: =ROUND(SUMIFS(Agenda!$J$6:$J$2106,Agenda!$D$6:$D$2106,7),0) -> 84 | I13: =ROUND(SUMIFS(Agenda!$J$6:$J$2106,Agenda!$D$6:$D$2106,8),0) -> 546 | J13: =ROUND(SUMIFS(Agenda!$J$6:$J$2106,Agenda!$D$6:$D$2106,9),0) -> 56 | K13: =ROUND(SUMIFS(Agenda!$J$6:$J$2106,Agenda!$D$6:$D$2106,10),0) -> 771 | L13: =ROUND(SUMIFS(Agenda!$J$6:$J$2106,Agenda!$D$6:$D$2106,11),0) -> 956 | M13: =ROUND(SUMIFS(Agenda!$J$6:$J$2106,Agenda!$D$6:$D$2106,12),0) -> 886 | N13: =SUM(B13:M13) -> 7986

Sheet Plan_Prev
A1: PLANO DE PREVENTIVAS — HH por oficina × mês (hoje 100% em Central-Taisa — validar distribuição) | P1: ⌂ MENU
A3: Oficina | B3: Jan | C3: Fev | D3: Mar | E3: Abr | F3: Mai | G3: Jun | H3: Jul | I3: Ago | J3: Set | K3: Out | L3: Nov | M3: Dez | N3: TOTAL ANO
A4: Oficina Mecânica Central-Taisa | B4: =ROUND(SUMIFS(Eventos!$G$4:$G$367,Eventos!$C$4:$C$367,1),1) -> 737 | C4: =ROUND(SUMIFS(Eventos!$G$4:$G$367,Eventos!$C$4:$C$367,2),1) -> 1523 | D4: =ROUND(SUMIFS(Eventos!$G$4:$G$367,Eventos!$C$4:$C$367,3),1) -> 1468.5 | E4: =ROUND(SUMIFS(Eventos!$G$4:$G$367,Eventos!$C$4:$C$367,4),1) -> 279 | F4: =ROUND(SUMIFS(Eventos!$G$4:$G$367,Eventos!$C$4:$C$367,5),1) -> 54 | G4: =ROUND(SUMIFS(Eventos!$G$4:$G$367,Eventos!$C$4:$C$367,6),1) -> 618.5 | H4: =ROUND(SUMIFS(Eventos!$G$4:$G$367,Eventos!$C$4:$C$367,7),1) -> 99 | I4: =ROUND(SUMIFS(Eventos!$G$4:$G$367,Eventos!$C$4:$C$367,8),1) -> 531 | J4: =ROUND(SUMIFS(Eventos!$G$4:$G$367,Eventos!$C$4:$C$367,9),1) -> 96 | K4: =ROUND(SUMIFS(Eventos!$G$4:$G$367,Eventos!$C$4:$C$367,10),1) -> 730.5 | L4: =ROUND(SUMIFS(Eventos!$G$4:$G$367,Eventos!$C$4:$C$367,11),1) -> 955.5 | M4: =ROUND(SUMIFS(Eventos!$G$4:$G$367,Eventos!$C$4:$C$367,12),1) -> 891.5 | N4: =ROUND(SUM(B4:M4),1) -> 7983.5
A5: Oficina Volante-Socorro | B5: =ROUND(SUMIFS(Eventos!$H$4:$H$367,Eventos!$C$4:$C$367,1),1) -> 0 | C5: =ROUND(SUMIFS(Eventos!$H$4:$H$367,Eventos!$C$4:$C$367,2),1) -> 0 | D5: =ROUND(SUMIFS(Eventos!$H$4:$H$367,Eventos!$C$4:$C$367,3),1) -> 0 | E5: =ROUND(SUMIFS(Eventos!$H$4:$H$367,Eventos!$C$4:$C$367,4),1) -> 0 | F5: =ROUND(SUMIFS(Eventos!$H$4:$H$367,Eventos!$C$4:$C$367,5),1) -> 0 | G5: =ROUND(SUMIFS(Eventos!$H$4:$H$367,Eventos!$C$4:$C$367,6),1) -> 0 | H5: =ROUND(SUMIFS(Eventos!$H$4:$H$367,Eventos!$C$4:$C$367,7),1) -> 0 | I5: =ROUND(SUMIFS(Eventos!$H$4:$H$367,Eventos!$C$4:$C$367,8),1) -> 0 | J5: =ROUND(SUMIFS(Eventos!$H$4:$H$367,Eventos!$C$4:$C$367,9),1) -> 0 | K5: =ROUND(SUMIFS(Eventos!$H$4:$H$367,Eventos!$C$4:$C$367,10),1) -> 0 | L5: =ROUND(SUMIFS(Eventos!$H$4:$H$367,Eventos!$C$4:$C$367,11),1) -> 0 | M5: =ROUND(SUMIFS(Eventos!$H$4:$H$367,Eventos!$C$4:$C$367,12),1) -> 0 | N5: =ROUND(SUM(B5:M5),1) -> 0
A6: Oficina Implementos Rodoviários | B6: =ROUND(SUMIFS(Eventos!$I$4:$I$367,Eventos!$C$4:$C$367,1),1) -> 0 | C6: =ROUND(SUMIFS(Eventos!$I$4:$I$367,Eventos!$C$4:$C$367,2),1) -> 0 | D6: =ROUND(SUMIFS(Eventos!$I$4:$I$367,Eventos!$C$4:$C$367,3),1) -> 0 | E6: =ROUND(SUMIFS(Eventos!$I$4:$I$367,Eventos!$C$4:$C$367,4),1) -> 0 | F6: =ROUND(SUMIFS(Eventos!$I$4:$I$367,Eventos!$C$4:$C$367,5),1) -> 0 | G6: =ROUND(SUMIFS(Eventos!$I$4:$I$367,Eventos!$C$4:$C$367,6),1) -> 0 | H6: =ROUND(SUMIFS(Eventos!$I$4:$I$367,Eventos!$C$4:$C$367,7),1) -> 0 | I6: =ROUND(SUMIFS(Eventos!$I$4:$I$367,Eventos!$C$4:$C$367,8),1) -> 0 | J6: =ROUND(SUMIFS(Eventos!$I$4:$I$367,Eventos!$C$4:$C$367,9),1) -> 0 | K6: =ROUND(SUMIFS(Eventos!$I$4:$I$367,Eventos!$C$4:$C$367,10),1) -> 0 | L6: =ROUND(SUMIFS(Eventos!$I$4:$I$367,Eventos!$C$4:$C$367,11),1) -> 0 | M6: =ROUND(SUMIFS(Eventos!$I$4:$I$367,Eventos!$C$4:$C$367,12),1) -> 0 | N6: =ROUND(SUM(B6:M6),1) -> 0
A7: Oficina Mecânica Externa | B7: =ROUND(SUMIFS(Eventos!$J$4:$J$367,Eventos!$C$4:$C$367,1),1) -> 0 | C7: =ROUND(SUMIFS(Eventos!$J$4:$J$367,Eventos!$C$4:$C$367,2),1) -> 0 | D7: =ROUND(SUMIFS(Eventos!$J$4:$J$367,Eventos!$C$4:$C$367,3),1) -> 0 | E7: =ROUND(SUMIFS(Eventos!$J$4:$J$367,Eventos!$C$4:$C$367,4),1) -> 0 | F7: =ROUND(SUMIFS(Eventos!$J$4:$J$367,Eventos!$C$4:$C$367,5),1) -> 0 | G7: =ROUND(SUMIFS(Eventos!$J$4:$J$367,Eventos!$C$4:$C$367,6),1) -> 0 | H7: =ROUND(SUMIFS(Eventos!$J$4:$J$367,Eventos!$C$4:$C$367,7),1) -> 0 | I7: =ROUND(SUMIFS(Eventos!$J$4:$J$367,Eventos!$C$4:$C$367,8),1) -> 0 | J7: =ROUND(SUMIFS(Eventos!$J$4:$J$367,Eventos!$C$4:$C$367,9),1) -> 0 | K7: =ROUND(SUMIFS(Eventos!$J$4:$J$367,Eventos!$C$4:$C$367,10),1) -> 0 | L7: =ROUND(SUMIFS(Eventos!$J$4:$J$367,Eventos!$C$4:$C$367,11),1) -> 0 | M7: =ROUND(SUMIFS(Eventos!$J$4:$J$367,Eventos!$C$4:$C$367,12),1) -> 0 | N7: =ROUND(SUM(B7:M7),1) -> 0
A8: Oficina Implementos Agrícolas | B8: =ROUND(SUMIFS(Eventos!$K$4:$K$367,Eventos!$C$4:$C$367,1),1) -> 0 | C8: =ROUND(SUMIFS(Eventos!$K$4:$K$367,Eventos!$C$4:$C$367,2),1) -> 0 | D8: =ROUND(SUMIFS(Eventos!$K$4:$K$367,Eventos!$C$4:$C$367,3),1) -> 0 | E8: =ROUND(SUMIFS(Eventos!$K$4:$K$367,Eventos!$C$4:$C$367,4),1) -> 0 | F8: =ROUND(SUMIFS(Eventos!$K$4:$K$367,Eventos!$C$4:$C$367,5),1) -> 0 | G8: =ROUND(SUMIFS(Eventos!$K$4:$K$367,Eventos!$C$4:$C$367,6),1) -> 0 | H8: =ROUND(SUMIFS(Eventos!$K$4:$K$367,Eventos!$C$4:$C$367,7),1) -> 0 | I8: =ROUND(SUMIFS(Eventos!$K$4:$K$367,Eventos!$C$4:$C$367,8),1) -> 0 | J8: =ROUND(SUMIFS(Eventos!$K$4:$K$367,Eventos!$C$4:$C$367,9),1) -> 0 | K8: =ROUND(SUMIFS(Eventos!$K$4:$K$367,Eventos!$C$4:$C$367,10),1) -> 0 | L8: =ROUND(SUMIFS(Eventos!$K$4:$K$367,Eventos!$C$4:$C$367,11),1) -> 0 | M8: =ROUND(SUMIFS(Eventos!$K$4:$K$367,Eventos!$C$4:$C$367,12),1) -> 0 | N8: =ROUND(SUM(B8:M8),1) -> 0
A9: PitStop | B9: =ROUND(SUMIFS(Eventos!$L$4:$L$367,Eventos!$C$4:$C$367,1),1) -> 0 | C9: =ROUND(SUMIFS(Eventos!$L$4:$L$367,Eventos!$C$4:$C$367,2),1) -> 0 | D9: =ROUND(SUMIFS(Eventos!$L$4:$L$367,Eventos!$C$4:$C$367,3),1) -> 0 | E9: =ROUND(SUMIFS(Eventos!$L$4:$L$367,Eventos!$C$4:$C$367,4),1) -> 0 | F9: =ROUND(SUMIFS(Eventos!$L$4:$L$367,Eventos!$C$4:$C$367,5),1) -> 0 | G9: =ROUND(SUMIFS(Eventos!$L$4:$L$367,Eventos!$C$4:$C$367,6),1) -> 0 | H9: =ROUND(SUMIFS(Eventos!$L$4:$L$367,Eventos!$C$4:$C$367,7),1) -> 0 | I9: =ROUND(SUMIFS(Eventos!$L$4:$L$367,Eventos!$C$4:$C$367,8),1) -> 0 | J9: =ROUND(SUMIFS(Eventos!$L$4:$L$367,Eventos!$C$4:$C$367,9),1) -> 0 | K9: =ROUND(SUMIFS(Eventos!$L$4:$L$367,Eventos!$C$4:$C$367,10),1) -> 0 | L9: =ROUND(SUMIFS(Eventos!$L$4:$L$367,Eventos!$C$4:$C$367,11),1) -> 0 | M9: =ROUND(SUMIFS(Eventos!$L$4:$L$367,Eventos!$C$4:$C$367,12),1) -> 0 | N9: =ROUND(SUM(B9:M9),1) -> 0
A10: TOTAL | B10: =ROUND(SUM(B4:B9),1) -> 737 | C10: =ROUND(SUM(C4:C9),1) -> 1523 | D10: =ROUND(SUM(D4:D9),1) -> 1468.5 | E10: =ROUND(SUM(E4:E9),1) -> 279 | F10: =ROUND(SUM(F4:F9),1) -> 54 | G10: =ROUND(SUM(G4:G9),1) -> 618.5 | H10: =ROUND(SUM(H4:H9),1) -> 99 | I10: =ROUND(SUM(I4:I9),1) -> 531 | ... N10: =ROUND(SUM(N4:N9),1) -> 7983.5

Sheet Plan_Corr
A1: PLANO DE CORRETIVAS — Prev × (corr/prev) × deflator progressivo × sazonalidade calibrada | P1: ⌂ MENU
A3: Oficina | B3: Jan | C3: Fev | D3: Mar | E3: Abr | F3: Mai | G3: Jun | H3: Jul | I3: Ago | J3: Set | K3: Out | L3: Nov | M3: Dez | N3: TOTAL ANO
A4: Oficina Mecânica Central-Taisa | B4: =ROUND(MAX(0,Plan_Prev!B4*(Premissas!$C$5/MAX(0.01,Premissas!$B$5))*(1-(Premissas!$E$5/100)*((0)/11+0.5)*0.5)*Premissas!$C$23),1) -> 2320.6 | C4: =ROUND(MAX(0,Plan_Prev!C4*(Premissas!$C$5/MAX(0.01,Premissas!$B$5))*(1-(Premissas!$E$5/100)*((1)/11+0.5)*0.5)*Premissas!$C$24),1) -> 4630.1 | D4: =ROUND(MAX(0,Plan_Prev!D4*(Premissas!$C$5/MAX(0.01,Premissas!$B$5))*(1-(Premissas!$E$5/100)*((2)/11+0.5)*0.5)*Premissas!$C$25),1) -> 4045.8 | E4: =ROUND(MAX(0,Plan_Prev!E4*(Premissas!$C$5/MAX(0.01,Premissas!$B$5))*(1-(Premissas!$E$5/100)*((3)/11+0.5)*0.5)*Premissas!$C$26),1) -> 485.5 | F4: =ROUND(MAX(0,Plan_Prev!F4*(Premissas!$C$5/MAX(0.01,Premissas!$B$5))*(1-(Premissas!$E$5/100)*((4)/11+0.5)*0.5)*Premissas!$C$27),1) -> 67.9 | G4: =ROUND(MAX(0,Plan_Prev!G4*(Premissas!$C$5/MAX(0.01,Premissas!$B$5))*(1-(Premissas!$E$5/100)*((5)/11+0.5)*0.5)*Premissas!$C$28),1) -> 558.9 | H4: =ROUND(MAX(0,Plan_Prev!H4*(Premissas!$C$5/MAX(0.01,Premissas!$B$5))*(1-(Premissas!$E$5/100)*((6)/11+0.5)*0.5)*Premissas!$C$29),1) -> 114 | I4: =ROUND(MAX(0,Plan_Prev!I4*(Premissas!$C$5/MAX(0.01,Premissas!$B$5))*(1-(Premissas!$E$5/100)*((7)/11+0.5)*0.5)*Premissas!$C$30),1) -> 1406.2 | J4: =ROUND(MAX(0,Plan_Prev!J4*(Premissas!$C$5/MAX(0.01,Premissas!$B$5))*(1-(Premissas!$E$5/100)*((8)/11+0.5)*0.5)*Premissas!$C$31),1) -> 299.1 | K4: =ROUND(MAX(0,Plan_Prev!K4*(Premissas!$C$5/MAX(0.01,Premissas!$B$5))*(1-(Premissas!$E$5/100)*((9)/11+0.5)*0.5)*Premissas!$C$32),1) -> 2579.5 | L4: =ROUND(MAX(0,Plan_Prev!L4*(Premissas!$C$5/MAX(0.01,Premissas!$B$5))*(1-(Premissas!$E$5/100)*((10)/11+0.5)*0.5)*Premissas!$C$33),1) -> 3318.6 | M4: =ROUND(MAX(0,Plan_Prev!M4*(Premissas!$C$5/MAX(0.01,Premissas!$B$5))*(1-(Premissas!$E$5/100)*((11)/11+0.5)*0.5)*Premissas!$C$34),1) -> 2934.6 | N4: =ROUND(SUM(B4:M4),1) -> 22760.8
A5: Oficina Volante-Socorro | B5: =ROUND(MAX(0,Plan_Prev!B5*(Premissas!$C$6/MAX(0.01,Premissas!$B$6))*(1-(Premissas!$E$6/100)*((0)/11+0.5)*0.5)*Premissas!$C$23),1) -> 0 | C5: =ROUND(MAX(0,Plan_Prev!C5*(Premissas!$C$6/MAX(0.01,Premissas!$B$6))*(1-(Premissas!$E$6/100)*((1)/11+0.5)*0.5)*Premissas!$C$24),1) -> 0 | D5: =ROUND(MAX(0,Plan_Prev!D5*(Premissas!$C$6/MAX(0.01,Premissas!$B$6))*(1-(Premissas!$E$6/100)*((2)/11+0.5)*0.5)*Premissas!$C$25),1) -> 0 | E5: =ROUND(MAX(0,Plan_Prev!E5*(Premissas!$C$6/MAX(0.01,Premissas!$B$6))*(1-(Premissas!$E$6/100)*((3)/11+0.5)*0.5)*Premissas!$C$26),1) -> 0 | F5: =ROUND(MAX(0,Plan_Prev!F5*(Premissas!$C$6/MAX(0.01,Premissas!$B$6))*(1-(Premissas!$E$6/100)*((4)/11+0.5)*0.5)*Premissas!$C$27),1) -> 0 | G5: =ROUND(MAX(0,Plan_Prev!G5*(Premissas!$C$6/MAX(0.01,Premissas!$B$6))*(1-(Premissas!$E$6/100)*((5)/11+0.5)*0.5)*Premissas!$C$28),1) -> 0 | H5: =ROUND(MAX(0,Plan_Prev!H5*(Premissas!$C$6/MAX(0.01,Premissas!$B$6))*(1-(Premissas!$E$6/100)*((6)/11+0.5)*0.5)*Premissas!$C$29),1) -> 0 | I5: =ROUND(MAX(0,Plan_Prev!I5*(Premissas!$C$6/MAX(0.01,Premissas!$B$6))*(1-(Premissas!$E$6/100)*((7)/11+0.5)*0.5)*Premissas!$C$30),1) -> 0 | J5: =ROUND(MAX(0,Plan_Prev!J5*(Premissas!$C$6/MAX(0.01,Premissas!$B$6))*(1-(Premissas!$E$6/100)*((8)/11+0.5)*0.5)*Premissas!$C$31),1) -> 0 | K5: =ROUND(MAX(0,Plan_Prev!K5*(Premissas!$C$6/MAX(0.01,Premissas!$B$6))*(1-(Premissas!$E$6/100)*((9)/11+0.5)*0.5)*Premissas!$C$32),1) -> 0 | L5: =ROUND(MAX(0,Plan_Prev!L5*(Premissas!$C$6/MAX(0.01,Premissas!$B$6))*(1-(Premissas!$E$6/100)*((10)/11+0.5)*0.5)*Premissas!$C$33),1) -> 0 | M5: =ROUND(MAX(0,Plan_Prev!M5*(Premissas!$C$6/MAX(0.01,Premissas!$B$6))*(1-(Premissas!$E$6/100)*((11)/11+0.5)*0.5)*Premissas!$C$34),1) -> 0 | N5: =ROUND(SUM(B5:M5),1) -> 0
A6: Oficina Implementos Rodoviários | B6: =ROUND(MAX(0,Plan_Prev!B6*(Premissas!$C$7/MAX(0.01,Premissas!$B$7))*(1-(Premissas!$E$7/100)*((0)/11+0.5)*0.5)*Premissas!$C$23),1) -> 0 | C6: =ROUND(MAX(0,Plan_Prev!C6*(Premissas!$C$7/MAX(0.01,Premissas!$B$7))*(1-(Premissas!$E$7/100)*((1)/11+0.5)*0.5)*Premissas!$C$24),1) -> 0 | D6: =ROUND(MAX(0,Plan_Prev!D6*(Premissas!$C$7/MAX(0.01,Premissas!$B$7))*(1-(Premissas!$E$7/100)*((2)/11+0.5)*0.5)*Premissas!$C$25),1) -> 0 | E6: =ROUND(MAX(0,Plan_Prev!E6*(Premissas!$C$7/MAX(0.01,Premissas!$B$7))*(1-(Premissas!$E$7/100)*((3)/11+0.5)*0.5)*Premissas!$C$26),1) -> 0 | F6: =ROUND(MAX(0,Plan_Prev!F6*(Premissas!$C$7/MAX(0.01,Premissas!$B$7))*(1-(Premissas!$E$7/100)*((4)/11+0.5)*0.5)*Premissas!$C$27),1) -> 0 | G6: =ROUND(MAX(0,Plan_Prev!G6*(Premissas!$C$7/MAX(0.01,Premissas!$B$7))*(1-(Premissas!$E$7/100)*((5)/11+0.5)*0.5)*Premissas!$C$28),1) -> 0 | H6: =ROUND(MAX(0,Plan_Prev!H6*(Premissas!$C$7/MAX(0.01,Premissas!$B$7))*(1-(Premissas!$E$7/100)*((6)/11+0.5)*0.5)*Premissas!$C$29),1) -> 0 | I6: =ROUND(MAX(0,Plan_Prev!I6*(Premissas!$C$7/MAX(0.01,Premissas!$B$7))*(1-(Premissas!$E$7/100)*((7)/11+0.5)*0.5)*Premissas!$C$30),1) -> 0 | J6: =ROUND(MAX(0,Plan_Prev!J6*(Premissas!$C$7/MAX(0.01,Premissas!$B$7))*(1-(Premissas!$E$7/100)*((8)/11+0.5)*0.5)*Premissas!$C$31),1) -> 0 | K6: =ROUND(MAX(0,Plan_Prev!K6*(Premissas!$C$7/MAX(0.01,Premissas!$B$7))*(1-(Premissas!$E$7/100)*((9)/11+0.5)*0.5)*Premissas!$C$32),1) -> 0 | L6: =ROUND(MAX(0,Plan_Prev!L6*(Premissas!$C$7/MAX(0.01,Premissas!$B$7))*(1-(Premissas!$E$7/100)*((10)/11+0.5)*0.5)*Premissas!$C$33),1) -> 0 | M6: =ROUND(MAX(0,Plan_Prev!M6*(Premissas!$C$7/MAX(0.01,Premissas!$B$7))*(1-(Premissas!$E$7/100)*((11)/11+0.5)*0.5)*Premissas!$C$34),1) -> 0 | N6: =ROUND(SUM(B6:M6),1) -> 0
A7: Oficina Mecânica Externa | B7: =ROUND(MAX(0,Plan_Prev!B7*(Premissas!$C$8/MAX(0.01,Premissas!$B$8))*(1-(Premissas!$E$8/100)*((0)/11+0.5)*0.5)*Premissas!$C$23),1) -> 0 | C7: =ROUND(MAX(0,Plan_Prev!C7*(Premissas!$C$8/MAX(0.01,Premissas!$B$8))*(1-(Premissas!$E$8/100)*((1)/11+0.5)*0.5)*Premissas!$C$24),1) -> 0 | D7: =ROUND(MAX(0,Plan_Prev!D7*(Premissas!$C$8/MAX(0.01,Premissas!$B$8))*(1-(Premissas!$E$8/100)*((2)/11+0.5)*0.5)*Premissas!$C$25),1) -> 0 | E7: =ROUND(MAX(0,Plan_Prev!E7*(Premissas!$C$8/MAX(0.01,Premissas!$B$8))*(1-(Premissas!$E$8/100)*((3)/11+0.5)*0.5)*Premissas!$C$26),1) -> 0 | F7: =ROUND(MAX(0,Plan_Prev!F7*(Premissas!$C$8/MAX(0.01,Premissas!$B$8))*(1-(Premissas!$E$8/100)*((4)/11+0.5)*0.5)*Premissas!$C$27),1) -> 0 | G7: =ROUND(MAX(0,Plan_Prev!G7*(Premissas!$C$8/MAX(0.01,Premissas!$B$8))*(1-(Premissas!$E$8/100)*((5)/11+0.5)*0.5)*Premissas!$C$28),1) -> 0 | H7: =ROUND(MAX(0,Plan_Prev!H7*(Premissas!$C$8/MAX(0.01,Premissas!$B$8))*(1-(Premissas!$E$8/100)*((6)/11+0.5)*0.5)*Premissas!$C$29),1) -> 0 | I7: =ROUND(MAX(0,Plan_Prev!I7*(Premissas!$C$8/MAX(0.01,Premissas!$B$8))*(1-(Premissas!$E$8/100)*((7)/11+0.5)*0.5)*Premissas!$C$30),1) -> 0 | J7: =ROUND(MAX(0,Plan_Prev!J7*(Premissas!$C$8/MAX(0.01,Premissas!$B$8))*(1-(Premissas!$E$8/100)*((8)/11+0.5)*0.5)*Premissas!$C$31),1) -> 0 | K7: =ROUND(MAX(0,Plan_Prev!K7*(Premissas!$C$8/MAX(0.01,Premissas!$B$8))*(1-(Premissas!$E$8/100)*((9)/11+0.5)*0.5)*Premissas!$C$32),1) -> 0 | L7: =ROUND(MAX(0,Plan_Prev!L7*(Premissas!$C$8/MAX(0.01,Premissas!$B$8))*(1-(Premissas!$E$8/100)*((10)/11+0.5)*0.5)*Premissas!$C$33),1) -> 0 | M7: =ROUND(MAX(0,Plan_Prev!M7*(Premissas!$C$8/MAX(0.01,Premissas!$B$8))*(1-(Premissas!$E$8/100)*((11)/11+0.5)*0.5)*Premissas!$C$34),1) -> 0 | N7: =ROUND(SUM(B7:M7),1) -> 0
A8: Oficina Implementos Agrícolas | B8: =ROUND(MAX(0,Plan_Prev!B8*(Premissas!$C$9/MAX(0.01,Premissas!$B$9))*(1-(Premissas!$E$9/100)*((0)/11+0.5)*0.5)*Premissas!$C$23),1) -> 0 | C8: =ROUND(MAX(0,Plan_Prev!C8*(Premissas!$C$9/MAX(0.01,Premissas!$B$9))*(1-(Premissas!$E$9/100)*((1)/11+0.5)*0.5)*Premissas!$C$24),1) -> 0 | D8: =ROUND(MAX(0,Plan_Prev!D8*(Premissas!$C$9/MAX(0.01,Premissas!$B$9))*(1-(Premissas!$E$9/100)*((2)/11+0.5)*0.5)*Premissas!$C$25),1) -> 0 | E8: =ROUND(MAX(0,Plan_Prev!E8*(Premissas!$C$9/MAX(0.01,Premissas!$B$9))*(1-(Premissas!$E$9/100)*((3)/11+0.5)*0.5)*Premissas!$C$26),1) -> 0 | F8: =ROUND(MAX(0,Plan_Prev!F8*(Premissas!$C$9/MAX(0.01,Premissas!$B$9))*(1-(Premissas!$E$9/100)*((4)/11+0.5)*0.5)*Premissas!$C$27),1) -> 0 | G8: =ROUND(MAX(0,Plan_Prev!G8*(Premissas!$C$9/MAX(0.01,Premissas!$B$9))*(1-(Premissas!$E$9/100)*((5)/11+0.5)*0.5)*Premissas!$C$28),1) -> 0 | H8: =ROUND(MAX(0,Plan_Prev!H8*(Premissas!$C$9/MAX(0.01,Premissas!$B$9))*(1-(Premissas!$E$9/100)*((6)/11+0.5)*0.5)*Premissas!$C$29),1) -> 0 | I8: =ROUND(MAX(0,Plan_Prev!I8*(Premissas!$C$9/MAX(0.01,Premissas!$B$9))*(1-(Premissas!$E$9/100)*((7)/11+0.5)*0.5)*Premissas!$C$30),1) -> 0 | J8: =ROUND(MAX(0,Plan_Prev!J8*(Premissas!$C$9/MAX(0.01,Premissas!$B$9))*(1-(Premissas!$E$9/100)*((8)/11+0.5)*0.5)*Premissas!$C$31),1) -> 0 | K8: =ROUND(MAX(0,Plan_Prev!K8*(Premissas!$C$9/MAX(0.01,Premissas!$B$9))*(1-(Premissas!$E$9/100)*((9)/11+0.5)*0.5)*Premissas!$C$32),1) -> 0 | L8: =ROUND(MAX(0,Plan_Prev!L8*(Premissas!$C$9/MAX(0.01,Premissas!$B$9))*(1-(Premissas!$E$9/100)*((10)/11+0.5)*0.5)*Premissas!$C$33),1) -> 0 | M8: =ROUND(MAX(0,Plan_Prev!M8*(Premissas!$C$9/MAX(0.01,Premissas!$B$9))*(1-(Premissas!$E$9/100)*((11)/11+0.5)*0.5)*Premissas!$C$34),1) -> 0 | N8: =ROUND(SUM(B8:M8),1) -> 0
A9: PitStop | B9: =ROUND(MAX(0,Plan_Prev!B9*(Premissas!$C$10/MAX(0.01,Premissas!$B$10))*(1-(Premissas!$E$10/100)*((0)/11+0.5)*0.5)*Premissas!$C$23),1) -> 0 | C9: =ROUND(MAX(0,Plan_Prev!C9*(Premissas!$C$10/MAX(0.01,Premissas!$B$10))*(1-(Premissas!$E$10/100)*((1)/11+0.5)*0.5)*Premissas!$C$24),1) -> 0 | D9: =ROUND(MAX(0,Plan_Prev!D9*(Premissas!$C$10/MAX(0.01,Premissas!$B$10))*(1-(Premissas!$E$10/100)*((2)/11+0.5)*0.5)*Premissas!$C$25),1) -> 0 | E9: =ROUND(MAX(0,Plan_Prev!E9*(Premissas!$C$10/MAX(0.01,Premissas!$B$10))*(1-(Premissas!$E$10/100)*((3)/11+0.5)*0.5)*Premissas!$C$26),1) -> 0 | F9: =ROUND(MAX(0,Plan_Prev!F9*(Premissas!$C$10/MAX(0.01,Premissas!$B$10))*(1-(Premissas!$E$10/100)*((4)/11+0.5)*0.5)*Premissas!$C$27),1) -> 0 | G9: =ROUND(MAX(0,Plan_Prev!G9*(Premissas!$C$10/MAX(0.01,Premissas!$B$10))*(1-(Premissas!$E$10/100)*((5)/11+0.5)*0.5)*Premissas!$C$28),1) -> 0 | H9: =ROUND(MAX(0,Plan_Prev!H9*(Premissas!$C$10/MAX(0.01,Premissas!$B$10))*(1-(Premissas!$E$10/100)*((6)/11+0.5)*0.5)*Premissas!$C$29),1) -> 0 | I9: =ROUND(MAX(0,Plan_Prev!I9*(Premissas!$C$10/MAX(0.01,Premissas!$B$10))*(1-(Premissas!$E$10/100)*((7)/11+0.5)*0.5)*Premissas!$C$30),1) -> 0 | J9: =ROUND(MAX(0,Plan_Prev!J9*(Premissas!$C$10/MAX(0.01,Premissas!$B$10))*(1-(Premissas!$E$10/100)*((8)/11+0.5)*0.5)*Premissas!$C$31),1) -> 0 | K9: =ROUND(MAX(0,Plan_Prev!K9*(Premissas!$C$10/MAX(0.01,Premissas!$B$10))*(1-(Premissas!$E$10/100)*((9)/11+0.5)*0.5)*Premissas!$C$32),1) -> 0 | L9: =ROUND(MAX(0,Plan_Prev!L9*(Premissas!$C$10/MAX(0.01,Premissas!$B$10))*(1-(Premissas!$E$10/100)*((10)/11+0.5)*0.5)*Premissas!$C$33),1) -> 0 | M9: =ROUND(MAX(0,Plan_Prev!M9*(Premissas!$C$10/MAX(0.01,Premissas!$B$10))*(1-(Premissas!$E$10/100)*((11)/11+0.5)*0.5)*Premissas!$C$34),1) -> 0 | N9: =ROUND(SUM(B9:M9),1) -> 0
A10: TOTAL | B10: =ROUND(SUM(B4:B9),1) -> 2320.6 | C10: =ROUND(SUM(C4:C9),1) -> 4630.1 | D10: =ROUND(SUM(D4:D9),1) -> 4045.8 | E10: =ROUND(SUM(E4:E9),1) -> 485.5 | F10: =ROUND(SUM(F4:F9),1) -> 67.9 | G10: =ROUND(SUM(G4:G9),1) -> 558.9 | H10: =ROUND(SUM(H4:H9),1) -> 114 | I10: =ROUND(SUM(I4:I9),1) -> 1406.2 | ... N10: =ROUND(SUM(N4:N9),1) -> 22760.8

Sheet Disponibilidade
A1: DISPONIBILIDADE — capacidade vs. demanda (ZERADA até preencher a aba Pessoas — pendência Evandro) | P1: ⌂ MENU
A2: Saldo VERMELHO = déficit · AMARELO = margem < 10% · VERDE = ok.
A4: HH DISPONÍVEL | B4: Jan | C4: Fev | D4: Mar | E4: Abr | F4: Mai | G4: Jun | H4: Jul | I4: Ago | J4: Set | K4: Out | L4: Nov | M4: Dez | N4: TOTAL ANO
A5: Oficina Mecânica Central-Taisa | B5: =ROUND(COUNTIFS(Pessoas!$C$5:$C$44,$A5,Pessoas!$G$5:$G$44,"Ativo")*Premissas!$B$23*VLOOKUP($A5,Premissas!$A$14:$K$19,11,0),1) -> 0 | C5: =ROUND(COUNTIFS(Pessoas!$C$5:$C$44,$A5,Pessoas!$G$5:$G$44,"Ativo")*Premissas!$B$24*VLOOKUP($A5,Premissas!$A$14:$K$19,11,0),1) -> 0 | D5: =ROUND(COUNTIFS(Pessoas!$C$5:$C$44,$A5,Pessoas!$G$5:$G$44,"Ativo")*Premissas!$B$25*VLOOKUP($A5,Premissas!$A$14:$K$19,11,0),1) -> 0 | E5: =ROUND(COUNTIFS(Pessoas!$C$5:$C$44,$A5,Pessoas!$G$5:$G$44,"Ativo")*Premissas!$B$26*VLOOKUP($A5,Premissas!$A$14:$K$19,11,0),1) -> 0 | F5: =ROUND(COUNTIFS(Pessoas!$C$5:$C$44,$A5,Pessoas!$G$5:$G$44,"Ativo")*Premissas!$B$27*VLOOKUP($A5,Premissas!$A$14:$K$19,11,0),1) -> 0 | G5: =ROUND(COUNTIFS(Pessoas!$C$5:$C$44,$A5,Pessoas!$G$5:$G$44,"Ativo")*Premissas!$B$28*VLOOKUP($A5,Premissas!$A$14:$K$19,11,0),1) -> 0 | H5: =ROUND(COUNTIFS(Pessoas!$C$5:$C$44,$A5,Pessoas!$G$5:$G$44,"Ativo")*Premissas!$B$29*VLOOKUP($A5,Premissas!$A$14:$K$19,11,0),1) -> 0 | I5: =ROUND(COUNTIFS(Pessoas!$C$5:$C$44,$A5,Pessoas!$G$5:$G$44,"Ativo")*Premissas!$B$30*VLOOKUP($A5,Premissas!$A$14:$K$19,11,0),1) -> 0 | J5: =ROUND(COUNTIFS(Pessoas!$C$5:$C$44,$A5,Pessoas!$G$5:$G$44,"Ativo")*Premissas!$B$31*VLOOKUP($A5,Premissas!$A$14:$K$19,11,0),1) -> 0 | K5: =ROUND(COUNTIFS(Pessoas!$C$5:$C$44,$A5,Pessoas!$G$5:$G$44,"Ativo")*Premissas!$B$32*VLOOKUP($A5,Premissas!$A$14:$K$19,11,0),1) -> 0 | L5: =ROUND(COUNTIFS(Pessoas!$C$5:$C$44,$A5,Pessoas!$G$5:$G$44,"Ativo")*Premissas!$B$33*VLOOKUP($A5,Premissas!$A$14:$K$19,11,0),1) -> 0 | M5: =ROUND(COUNTIFS(Pessoas!$C$5:$C$44,$A5,Pessoas!$G$5:$G$44,"Ativo")*Premissas!$B$34*VLOOKUP($A5,Premissas!$A$14:$K$19,11,0),1) -> 0 | N5: =ROUND(SUM(B5:M5),1) -> 0
A6: Oficina Volante-Socorro | B6: =ROUND(COUNTIFS(Pessoas!$C$5:$C$44,$A6,Pessoas!$G$5:$G$44,"Ativo")*Premissas!$B$23*VLOOKUP($A6,Premissas!$A$14:$K$19,11,0),1) -> 0 | C6: =ROUND(COUNTIFS(Pessoas!$C$5:$C$44,$A6,Pessoas!$G$5:$G$44,"Ativo")*Premissas!$B$24*VLOOKUP($A6,Premissas!$A$14:$K$19,11,0),1) -> 0 | D6: =ROUND(COUNTIFS(Pessoas!$C$5:$C$44,$A6,Pessoas!$G$5:$G$44,"Ativo")*Premissas!$B$25*VLOOKUP($A6,Premissas!$A$14:$K$19,11,0),1) -> 0 | E6: =ROUND(COUNTIFS(Pessoas!$C$5:$C$44,$A6,Pessoas!$G$5:$G$44,"Ativo")*Premissas!$B$26*VLOOKUP($A6,Premissas!$A$14:$K$19,11,0),1) -> 0 | F6: =ROUND(COUNTIFS(Pessoas!$C$5:$C$44,$A6,Pessoas!$G$5:$G$44,"Ativo")*Premissas!$B$27*VLOOKUP($A6,Premissas!$A$14:$K$19,11,0),1) -> 0 | G6: =ROUND(COUNTIFS(Pessoas!$C$5:$C$44,$A6,Pessoas!$G$5:$G$44,"Ativo")*Premissas!$B$28*VLOOKUP($A6,Premissas!$A$14:$K$19,11,0),1) -> 0 | H6: =ROUND(COUNTIFS(Pessoas!$C$5:$C$44,$A6,Pessoas!$G$5:$G$44,"Ativo")*Premissas!$B$29*VLOOKUP($A6,Premissas!$A$14:$K$19,11,0),1) -> 0 | I6: =ROUND(COUNTIFS(Pessoas!$C$5:$C$44,$A6,Pessoas!$G$5:$G$44,"Ativo")*Premissas!$B$30*VLOOKUP($A6,Premissas!$A$14:$K$19,11,0),1) -> 0 | J6: =ROUND(COUNTIFS(Pessoas!$C$5:$C$44,$A6,Pessoas!$G$5:$G$44,"Ativo")*Premissas!$B$31*VLOOKUP($A6,Premissas!$A$14:$K$19,11,0),1) -> 0 | K6: =ROUND(COUNTIFS(Pessoas!$C$5:$C$44,$A6,Pessoas!$G$5:$G$44,"Ativo")*Premissas!$B$32*VLOOKUP($A6,Premissas!$A$14:$K$19,11,0),1) -> 0 | L6: =ROUND(COUNTIFS(Pessoas!$C$5:$C$44,$A6,Pessoas!$G$5:$G$44,"Ativo")*Premissas!$B$33*VLOOKUP($A6,Premissas!$A$14:$K$19,11,0),1) -> 0 | M6: =ROUND(COUNTIFS(Pessoas!$C$5:$C$44,$A6,Pessoas!$G$5:$G$44,"Ativo")*Premissas!$B$34*VLOOKUP($A6,Premissas!$A$14:$K$19,11,0),1) -> 0 | N6: =ROUND(SUM(B6:M6),1) -> 0
A7: Oficina Implementos Rodoviários | B7: =ROUND(COUNTIFS(Pessoas!$C$5:$C$44,$A7,Pessoas!$G$5:$G$44,"Ativo")*Premissas!$B$23*VLOOKUP($A7,Premissas!$A$14:$K$19,11,0),1) -> 0 | C7: =ROUND(COUNTIFS(Pessoas!$C$5:$C$44,$A7,Pessoas!$G$5:$G$44,"Ativo")*Premissas!$B$24*VLOOKUP($A7,Premissas!$A$14:$K$19,11,0),1) -> 0 | D7: =ROUND(COUNTIFS(Pessoas!$C$5:$C$44,$A7,Pessoas!$G$5:$G$44,"Ativo")*Premissas!$B$25*VLOOKUP($A7,Premissas!$A$14:$K$19,11,0),1) -> 0 | E7: =ROUND(COUNTIFS(Pessoas!$C$5:$C$44,$A7,Pessoas!$G$5:$G$44,"Ativo")*Premissas!$B$26*VLOOKUP($A7,Premissas!$A$14:$K$19,11,0),1) -> 0 | F7: =ROUND(COUNTIFS(Pessoas!$C$5:$C$44,$A7,Pessoas!$G$5:$G$44,"Ativo")*Premissas!$B$27*VLOOKUP($A7,Premissas!$A$14:$K$19,11,0),1) -> 0 | G7: =ROUND(COUNTIFS(Pessoas!$C$5:$C$44,$A7,Pessoas!$G$5:$G$44,"Ativo")*Premissas!$B$28*VLOOKUP($A7,Premissas!$A$14:$K$19,11,0),1) -> 0 | H7: =ROUND(COUNTIFS(Pessoas!$C$5:$C$44,$A7,Pessoas!$G$5:$G$44,"Ativo")*Premissas!$B$29*VLOOKUP($A7,Premissas!$A$14:$K$19,11,0),1) -> 0 | I7: =ROUND(COUNTIFS(Pessoas!$C$5:$C$44,$A7,Pessoas!$G$5:$G$44,"Ativo")*Premissas!$B$30*VLOOKUP($A7,Premissas!$A$14:$K$19,11,0),1) -> 0 | J7: =ROUND(COUNTIFS(Pessoas!$C$5:$C$44,$A7,Pessoas!$G$5:$G$44,"Ativo")*Premissas!$B$31*VLOOKUP($A7,Premissas!$A$14:$K$19,11,0),1) -> 0 | K7: =ROUND(COUNTIFS(Pessoas!$C$5:$C$44,$A7,Pessoas!$G$5:$G$44,"Ativo")*Premissas!$B$32*VLOOKUP($A7,Premissas!$A$14:$K$19,11,0),1) -> 0 | L7: =ROUND(COUNTIFS(Pessoas!$C$5:$C$44,$A7,Pessoas!$G$5:$G$44,"Ativo")*Premissas!$B$33*VLOOKUP($A7,Premissas!$A$14:$K$19,11,0),1) -> 0 | M7: =ROUND(COUNTIFS(Pessoas!$C$5:$C$44,$A7,Pessoas!$G$5:$G$44,"Ativo")*Premissas!$B$34*VLOOKUP($A7,Premissas!$A$14:$K$19,11,0),1) -> 0 | N7: =ROUND(SUM(B7:M7),1) -> 0
A8: Oficina Mecânica Externa | B8: =ROUND(COUNTIFS(Pessoas!$C$5:$C$44,$A8,Pessoas!$G$5:$G$44,"Ativo")*Premissas!$B$23*VLOOKUP($A8,Premissas!$A$14:$K$19,11,0),1) -> 0 | C8: =ROUND(COUNTIFS(Pessoas!$C$5:$C$44,$A8,Pessoas!$G$5:$G$44,"Ativo")*Premissas!$B$24*VLOOKUP($A8,Premissas!$A$14:$K$19,11,0),1) -> 0 | D8: =ROUND(COUNTIFS(Pessoas!$C$5:$C$44,$A8,Pessoas!$G$5:$G$44,"Ativo")*Premissas!$B$25*VLOOKUP($A8,Premissas!$A$14:$K$19,11,0),1) -> 0 | E8: =ROUND(COUNTIFS(Pessoas!$C$5:$C$44,$A8,Pessoas!$G$5:$G$44,"Ativo")*Premissas!$B$26*VLOOKUP($A8,Premissas!$A$14:$K$19,11,0),1) -> 0 | F8: =ROUND(COUNTIFS(Pessoas!$C$5:$C$44,$A8,Pessoas!$G$5:$G$44,"Ativo")*Premissas!$B$27*VLOOKUP($A8,Premissas!$A$14:$K$19,11,0),1) -> 0 | G8: =ROUND(COUNTIFS(Pessoas!$C$5:$C$44,$A8,Pessoas!$G$5:$G$44,"Ativo")*Premissas!$B$28*VLOOKUP($A8,Premissas!$A$14:$K$19,11,0),1) -> 0 | H8: =ROUND(COUNTIFS(Pessoas!$C$5:$C$44,$A8,Pessoas!$G$5:$G$44,"Ativo")*Premissas!$B$29*VLOOKUP($A8,Premissas!$A$14:$K$19,11,0),1) -> 0 | I8: =ROUND(COUNTIFS(Pessoas!$C$5:$C$44,$A8,Pessoas!$G$5:$G$44,"Ativo")*Premissas!$B$30*VLOOKUP($A8,Premissas!$A$14:$K$19,11,0),1) -> 0 | J8: =ROUND(COUNTIFS(Pessoas!$C$5:$C$44,$A8,Pessoas!$G$5:$G$44,"Ativo")*Premissas!$B$31*VLOOKUP($A8,Premissas!$A$14:$K$19,11,0),1) -> 0 | K8: =ROUND(COUNTIFS(Pessoas!$C$5:$C$44,$A8,Pessoas!$G$5:$G$44,"Ativo")*Premissas!$B$32*VLOOKUP($A8,Premissas!$A$14:$K$19,11,0),1) -> 0 | L8: =ROUND(COUNTIFS(Pessoas!$C$5:$C$44,$A8,Pessoas!$G$5:$G$44,"Ativo")*Premissas!$B$33*VLOOKUP($A8,Premissas!$A$14:$K$19,11,0),1) -> 0 | M8: =ROUND(COUNTIFS(Pessoas!$C$5:$C$44,$A8,Pessoas!$G$5:$G$44,"Ativo")*Premissas!$B$34*VLOOKUP($A8,Premissas!$A$14:$K$19,11,0),1) -> 0 | N8: =ROUND(SUM(B8:M8),1) -> 0
A9: Oficina Implementos Agrícolas | B9: =ROUND(COUNTIFS(Pessoas!$C$5:$C$44,$A9,Pessoas!$G$5:$G$44,"Ativo")*Premissas!$B$23*VLOOKUP($A9,Premissas!$A$14:$K$19,11,0),1) -> 0 | C9: =ROUND(COUNTIFS(Pessoas!$C$5:$C$44,$A9,Pessoas!$G$5:$G$44,"Ativo")*Premissas!$B$24*VLOOKUP($A9,Premissas!$A$14:$K$19,11,0),1) -> 0 | D9: =ROUND(COUNTIFS(Pessoas!$C$5:$C$44,$A9,Pessoas!$G$5:$G$44,"Ativo")*Premissas!$B$25*VLOOKUP($A9,Premissas!$A$14:$K$19,11,0),1) -> 0 | E9: =ROUND(COUNTIFS(Pessoas!$C$5:$C$44,$A9,Pessoas!$G$5:$G$44,"Ativo")*Premissas!$B$26*VLOOKUP($A9,Premissas!$A$14:$K$19,11,0),1) -> 0 | F9: =ROUND(COUNTIFS(Pessoas!$C$5:$C$44,$A9,Pessoas!$G$5:$G$44,"Ativo")*Premissas!$B$27*VLOOKUP($A9,Premissas!$A$14:$K$19,11,0),1) -> 0 | G9: =ROUND(COUNTIFS(Pessoas!$C$5:$C$44,$A9,Pessoas!$G$5:$G$44,"Ativo")*Premissas!$B$28*VLOOKUP($A9,Premissas!$A$14:$K$19,11,0),1) -> 0 | H9: =ROUND(COUNTIFS(Pessoas!$C$5:$C$44,$A9,Pessoas!$G$5:$G$44,"Ativo")*Premissas!$B$29*VLOOKUP($A9,Premissas!$A$14:$K$19,11,0),1) -> 0 | I9: =ROUND(COUNTIFS(Pessoas!$C$5:$C$44,$A9,Pessoas!$G$5:$G$44,"Ativo")*Premissas!$B$30*VLOOKUP($A9,Premissas!$A$14:$K$19,11,0),1) -> 0 | J9: =ROUND(COUNTIFS(Pessoas!$C$5:$C$44,$A9,Pessoas!$G$5:$G$44,"Ativo")*Premissas!$B$31*VLOOKUP($A9,Premissas!$A$14:$K$19,11,0),1) -> 0 | K9: =ROUND(COUNTIFS(Pessoas!$C$5:$C$44,$A9,Pessoas!$G$5:$G$44,"Ativo")*Premissas!$B$32*VLOOKUP($A9,Premissas!$A$14:$K$19,11,0),1) -> 0 | L9: =ROUND(COUNTIFS(Pessoas!$C$5:$C$44,$A9,Pessoas!$G$5:$G$44,"Ativo")*Premissas!$B$33*VLOOKUP($A9,Premissas!$A$14:$K$19,11,0),1) -> 0 | M9: =ROUND(COUNTIFS(Pessoas!$C$5:$C$44,$A9,Pessoas!$G$5:$G$44,"Ativo")*Premissas!$B$34*VLOOKUP($A9,Premissas!$A$14:$K$19,11,0),1) -> 0 | N9: =ROUND(SUM(B9:M9),1) -> 0
A10: PitStop | B10: =ROUND(COUNTIFS(Pessoas!$C$5:$C$44,$A10,Pessoas!$G$5:$G$44,"Ativo")*Premissas!$B$23*VLOOKUP($A10,Premissas!$A$14:$K$19,11,0),1) -> 0 | C10: =ROUND(COUNTIFS(Pessoas!$C$5:$C$44,$A10,Pessoas!$G$5:$G$44,"Ativo")*Premissas!$B$24*VLOOKUP($A10,Premissas!$A$14:$K$19,11,0),1) -> 0 | D10: =ROUND(COUNTIFS(Pessoas!$C$5:$C$44,$A10,Pessoas!$G$5:$G$44,"Ativo")*Premissas!$B$25*VLOOKUP($A10,Premissas!$A$14:$K$19,11,0),1) -> 0 | E10: =ROUND(COUNTIFS(Pessoas!$C$5:$C$44,$A10,Pessoas!$G$5:$G$44,"Ativo")*Premissas!$B$26*VLOOKUP($A10,Premissas!$A$14:$K$19,11,0),1) -> 0 | F10: =ROUND(COUNTIFS(Pessoas!$C$5:$C$44,$A10,Pessoas!$G$5:$G$44,"Ativo")*Premissas!$B$27*VLOOKUP($A10,Premissas!$A$14:$K$19,11,0),1) -> 0 | G10: =ROUND(COUNTIFS(Pessoas!$C$5:$C$44,$A10,Pessoas!$G$5:$G$44,"Ativo")*Premissas!$B$28*VLOOKUP($A10,Premissas!$A$14:$K$19,11,0),1) -> 0 | H10: =ROUND(COUNTIFS(Pessoas!$C$5:$C$44,$A10,Pessoas!$G$5:$G$44,"Ativo")*Premissas!$B$29*VLOOKUP($A10,Premissas!$A$14:$K$19,11,0),1) -> 0 | I10: =ROUND(COUNTIFS(Pessoas!$C$5:$C$44,$A10,Pessoas!$G$5:$G$44,"Ativo")*Premissas!$B$30*VLOOKUP($A10,Premissas!$A$14:$K$19,11,0),1) -> 0 | J10: =ROUND(COUNTIFS(Pessoas!$C$5:$C$44,$A10,Pessoas!$G$5:$G$44,"Ativo")*Premissas!$B$31*VLOOKUP($A10,Premissas!$A$14:$K$19,11,0),1) -> 0 | K10: =ROUND(COUNTIFS(Pessoas!$C$5:$C$44,$A10,Pessoas!$G$5:$G$44,"Ativo")*Premissas!$B$32*VLOOKUP($A10,Premissas!$A$14:$K$19,11,0),1) -> 0 | L10: =ROUND(COUNTIFS(Pessoas!$C$5:$C$44,$A10,Pessoas!$G$5:$G$44,"Ativo")*Premissas!$B$33*VLOOKUP($A10,Premissas!$A$14:$K$19,11,0),1) -> 0 | M10: =ROUND(COUNTIFS(Pessoas!$C$5:$C$44,$A10,Pessoas!$G$5:$G$44,"Ativo")*Premissas!$B$34*VLOOKUP($A10,Premissas!$A$14:$K$19,11,0),1) -> 0 | N10: =ROUND(SUM(B10:M10),1) -> 0
A11: TOTAL | B11: =ROUND(SUM(B5:B10),1) -> 0 | C11: =ROUND(SUM(C5:C10),1) -> 0 | D11: =ROUND(SUM(D5:D10),1) -> 0 | E11: =ROUND(SUM(E5:E10),1) -> 0 | F11: =ROUND(SUM(F5:F10),1) -> 0 | G11: =ROUND(SUM(G5:G10),1) -> 0 | H11: =ROUND(SUM(H5:H10),1) -> 0 | I11: =ROUND(SUM(I5:I10),1) -> 0 | ... N11: =ROUND(SUM(N5:N10),1) -> 0
A13: HH NECESSÁRIA | B13: Jan | C13: Fev | D13: Mar | E13: Abr | F13: Mai | G13: Jun | H13: Jul | I13: Ago | J13: Set | K13: Out | L13: Nov | M13: Dez | N13: TOTAL ANO
A14: Oficina Mecânica Central-Taisa | B14: =ROUND(Plan_Prev!B4+Plan_Corr!B4,1) -> 3057.6 | C14: =ROUND(Plan_Prev!C4+Plan_Corr!C4,1) -> 6153.1 | D14: =ROUND(Plan_Prev!D4+Plan_Corr!D4,1) -> 5514.3 | E14: =ROUND(Plan_Prev!E4+Plan_Corr!E4,1) -> 764.5 | F14: =ROUND(Plan_Prev!F4+Plan_Corr!F4,1) -> 121.9 | G14: =ROUND(Plan_Prev!G4+Plan_Corr!G4,1) -> 1177.4 | H14: =ROUND(Plan_Prev!H4+Plan_Corr!H4,1) -> 213 | I14: =ROUND(Plan_Prev!I4+Plan_Corr!I4,1) -> 1937.2 | ... M14: =ROUND(Plan_Prev!M4+Plan_Corr!M4,1) -> 3826.1 | N14: =ROUND(SUM(B14:M14),1) -> 30744.3
A15: Oficina Volante-Socorro | B15: =ROUND(Plan_Prev!B5+Plan_Corr!B5,1) -> 0 | C15: =ROUND(Plan_Prev!C5+Plan_Corr!C5,1) -> 0 | D15: =ROUND(Plan_Prev!D5+Plan_Corr!D5,1) -> 0 | E15: =ROUND(Plan_Prev!E5+Plan_Corr!E5,1) -> 0 | F15: =ROUND(Plan_Prev!F5+Plan_Corr!F5,1) -> 0 | G15: =ROUND(Plan_Prev!G5+Plan_Corr!G5,1) -> 0 | H15: =ROUND(Plan_Prev!H5+Plan_Corr!H5,1) -> 0 | I15: =ROUND(Plan_Prev!I5+Plan_Corr!I5,1) -> 0 | ... M15: =ROUND(Plan_Prev!M5+Plan_Corr!M5,1) -> 0 | N15: =ROUND(SUM(B15:M15),1) -> 0
A16: Oficina Implementos Rodoviários | B16: =ROUND(Plan_Prev!B6+Plan_Corr!B6,1) -> 0 | C16: =ROUND(Plan_Prev!C6+Plan_Corr!C6,1) -> 0 | D16: =ROUND(Plan_Prev!D6+Plan_Corr!D6,1) -> 0 | E16: =ROUND(Plan_Prev!E6+Plan_Corr!E6,1) -> 0 | F16: =ROUND(Plan_Prev!F6+Plan_Corr!F6,1) -> 0 | G16: =ROUND(Plan_Prev!G6+Plan_Corr!G6,1) -> 0 | H16: =ROUND(Plan_Prev!H6+Plan_Corr!H6,1) -> 0 | I16: =ROUND(Plan_Prev!I6+Plan_Corr!I6,1) -> 0 | ... M16: =ROUND(Plan_Prev!M6+Plan_Corr!M6,1) -> 0 | N16: =ROUND(SUM(B16:M16),1) -> 0
A17: Oficina Mecânica Externa | B17: =ROUND(Plan_Prev!B7+Plan_Corr!B7,1) -> 0 | C17: =ROUND(Plan_Prev!C7+Plan_Corr!C7,1) -> 0 | D17: =ROUND(Plan_Prev!D7+Plan_Corr!D7,1) -> 0 | E17: =ROUND(Plan_Prev!E7+Plan_Corr!E7,1) -> 0 | F17: =ROUND(Plan_Prev!F7+Plan_Corr!F7,1) -> 0 | G17: =ROUND(Plan_Prev!G7+Plan_Corr!G7,1) -> 0 | H17: =ROUND(Plan_Prev!H7+Plan_Corr!H7,1) -> 0 | I17: =ROUND(Plan_Prev!I7+Plan_Corr!I7,1) -> 0 | ... M17: =ROUND(Plan_Prev!M7+Plan_Corr!M7,1) -> 0 | N17: =ROUND(SUM(B17:M17),1) -> 0
A18: Oficina Implementos Agrícolas | B18: =ROUND(Plan_Prev!B8+Plan_Corr!B8,1) -> 0 | C18: =ROUND(Plan_Prev!C8+Plan_Corr!C8,1) -> 0 | D18: =ROUND(Plan_Prev!D8+Plan_Corr!D8,1) -> 0 | E18: =ROUND(Plan_Prev!E8+Plan_Corr!E8,1) -> 0 | F18: =ROUND(Plan_Prev!F8+Plan_Corr!F8,1) -> 0 | G18: =ROUND(Plan_Prev!G8+Plan_Corr!G8,1) -> 0 | H18: =ROUND(Plan_Prev!H8+Plan_Corr!H8,1) -> 0 | I18: =ROUND(Plan_Prev!I8+Plan_Corr!I8,1) -> 0 | ... M18: =ROUND(Plan_Prev!M8+Plan_Corr!M8,1) -> 0 | N18: =ROUND(SUM(B18:M18),1) -> 0
A19: PitStop | B19: =ROUND(Plan_Prev!B9+Plan_Corr!B9,1) -> 0 | C19: =ROUND(Plan_Prev!C9+Plan_Corr!C9,1) -> 0 | D19: =ROUND(Plan_Prev!D9+Plan_Corr!D9,1) -> 0 | E19: =ROUND(Plan_Prev!E9+Plan_Corr!E9,1) -> 0 | F19: =ROUND(Plan_Prev!F9+Plan_Corr!F9,1) -> 0 | G19: =ROUND(Plan_Prev!G9+Plan_Corr!G9,1) -> 0 | H19: =ROUND(Plan_Prev!H9+Plan_Corr!H9,1) -> 0 | I19: =ROUND(Plan_Prev!I9+Plan_Corr!I9,1) -> 0 | ... M19: =ROUND(Plan_Prev!M9+Plan_Corr!M9,1) -> 0 | N19: =ROUND(SUM(B19:M19),1) -> 0
A20: TOTAL | B20: =ROUND(SUM(B14:B19),1) -> 3057.6 | C20: =ROUND(SUM(C14:C19),1) -> 6153.1 | D20: =ROUND(SUM(D14:D19),1) -> 5514.3 | E20: =ROUND(SUM(E14:E19),1) -> 764.5 | F20: =ROUND(SUM(F14:F19),1) -> 121.9 | G20: =ROUND(SUM(G14:G19),1) -> 1177.4 | H20: =ROUND(SUM(H14:H19),1) -> 213 | I20: =ROUND(SUM(I14:I19),1) -> 1937.2 | ... N20: =ROUND(SUM(N14:N19),1) -> 30744.3
A22: SALDO (disp − nec) | B22: Jan | C22: Fev | D22: Mar | E22: Abr | F22: Mai | G22: Jun | H22: Jul | I22: Ago | J22: Set | K22: Out | L22: Nov | M22: Dez | N22: TOTAL ANO
A23: Oficina Mecânica Central-Taisa | B23: =ROUND(B5-B14,1) -> -3057.6 | C23: =ROUND(C5-C14,1) -> -6153.1 | D23: =ROUND(D5-D14,1) -> -5514.3 | E23: =ROUND(E5-E14,1) -> -764.5 | F23: =ROUND(F5-F14,1) -> -121.9 | G23: =ROUND(G5-G14,1) -> -1177.4 | H23: =ROUND(H5-H14,1) -> -213 | I23: =ROUND(I5-I14,1) -> -1937.2 | ... M23: =ROUND(M5-M14,1) -> -3826.1 | N23: =ROUND(SUM(B23:M23),1) -> -30744.3
A24: Oficina Volante-Socorro | B24: =ROUND(B6-B15,1) -> 0 | C24: =ROUND(C6-C15,1) -> 0 | D24: =ROUND(D6-D15,1) -> 0 | E24: =ROUND(E6-E15,1) -> 0 | F24: =ROUND(F6-F15,1) -> 0 | G24: =ROUND(G6-G15,1) -> 0 | H24: =ROUND(H6-H15,1) -> 0 | I24: =ROUND(I6-I15,1) -> 0 | ... M24: =ROUND(M6-M15,1) -> 0 | N24: =ROUND(SUM(B24:M24),1) -> 0
A25: Oficina Implementos Rodoviários | B25: =ROUND(B7-B16,1) -> 0 | C25: =ROUND(C7-C16,1) -> 0 | D25: =ROUND(D7-D16,1) -> 0 | E25: =ROUND(E7-E16,1) -> 0 | F25: =ROUND(F7-F16,1) -> 0 | G25: =ROUND(G7-G16,1) -> 0 | H25: =ROUND(H7-H16,1) -> 0 | I25: =ROUND(I7-I16,1) -> 0 | ... M25: =ROUND(M7-M16,1) -> 0 | N25: =ROUND(SUM(B25:M25),1) -> 0
A26: Oficina Mecânica Externa | B26: =ROUND(B8-B17,1) -> 0 | C26: =ROUND(C8-C17,1) -> 0 | D26: =ROUND(D8-D17,1) -> 0 | E26: =ROUND(E8-E17,1) -> 0 | F26: =ROUND(F8-F17,1) -> 0 | G26: =ROUND(G8-G17,1) -> 0 | H26: =ROUND(H8-H17,1) -> 0 | I26: =ROUND(I8-I17,1) -> 0 | ... M26: =ROUND(M8-M17,1) -> 0 | N26: =ROUND(SUM(B26:M26),1) -> 0
A27: Oficina Implementos Agrícolas | B27: =ROUND(B9-B18,1) -> 0 | C27: =ROUND(C9-C18,1) -> 0 | D27: =ROUND(D9-D18,1) -> 0 | E27: =ROUND(E9-E18,1) -> 0 | F27: =ROUND(F9-F18,1) -> 0 | G27: =ROUND(G9-G18,1) -> 0 | H27: =ROUND(H9-H18,1) -> 0 | I27: =ROUND(I9-I18,1) -> 0 | ... M27: =ROUND(M9-M18,1) -> 0 | N27: =ROUND(SUM(B27:M27),1) -> 0
A28: PitStop | B28: =ROUND(B10-B19,1) -> 0 | C28: =ROUND(C10-C19,1) -> 0 | D28: =ROUND(D10-D19,1) -> 0 | E28: =ROUND(E10-E19,1) -> 0 | F28: =ROUND(F10-F19,1) -> 0 | G28: =ROUND(G10-G19,1) -> 0 | H28: =ROUND(H10-H19,1) -> 0 | I28: =ROUND(I10-I19,1) -> 0 | ... M28: =ROUND(M10-M19,1) -> 0 | N28: =ROUND(SUM(B28:M28),1) -> 0
A29: TOTAL | B29: =ROUND(SUM(B23:B28),1) -> -3057.6 | C29: =ROUND(SUM(C23:C28),1) -> -6153.1 | D29: =ROUND(SUM(D23:D28),1) -> -5514.3 | E29: =ROUND(SUM(E23:E28),1) -> -764.5 | F29: =ROUND(SUM(F23:F28),1) -> -121.9 | G29: =ROUND(SUM(G23:G28),1) -> -1177.4 | H29: =ROUND(SUM(H23:H28),1) -> -213 | I29: =ROUND(SUM(I23:I28),1) -> -1937.2 | ... N29: =ROUND(SUM(N23:N28),1) -> -30744.3

Sheet Recursos
A1: RECURSOS — headcount necessário por oficina × mês (comparar com quadro atual quando Pessoas chegar) | P1: ⌂ MENU
A4: HC NECESSÁRIO | B4: Jan | C4: Fev | D4: Mar | E4: Abr | F4: Mai | G4: Jun | H4: Jul | I4: Ago | J4: Set | K4: Out | L4: Nov | M4: Dez | N4: TOTAL ANO
A5: Oficina Mecânica Central-Taisa | B5: =ROUND((Plan_Prev!B4+Plan_Corr!B4)/MAX(1,Premissas!$B$23*VLOOKUP($A5,Premissas!$A$14:$K$19,11,0)),1) -> 25.9 | C5: =ROUND((Plan_Prev!C4+Plan_Corr!C4)/MAX(1,Premissas!$B$24*VLOOKUP($A5,Premissas!$A$14:$K$19,11,0)),1) -> 57.3 | D5: =ROUND((Plan_Prev!D4+Plan_Corr!D4)/MAX(1,Premissas!$B$25*VLOOKUP($A5,Premissas!$A$14:$K$19,11,0)),1) -> 46.7 | E5: =ROUND((Plan_Prev!E4+Plan_Corr!E4)/MAX(1,Premissas!$B$26*VLOOKUP($A5,Premissas!$A$14:$K$19,11,0)),1) -> 7.1 | F5: =ROUND((Plan_Prev!F4+Plan_Corr!F4)/MAX(1,Premissas!$B$27*VLOOKUP($A5,Premissas!$A$14:$K$19,11,0)),1) -> 1.1 | G5: =ROUND((Plan_Prev!G4+Plan_Corr!G4)/MAX(1,Premissas!$B$28*VLOOKUP($A5,Premissas!$A$14:$K$19,11,0)),1) -> 10 | H5: =ROUND((Plan_Prev!H4+Plan_Corr!H4)/MAX(1,Premissas!$B$29*VLOOKUP($A5,Premissas!$A$14:$K$19,11,0)),1) -> 1.9 | I5: =ROUND((Plan_Prev!I4+Plan_Corr!I4)/MAX(1,Premissas!$B$30*VLOOKUP($A5,Premissas!$A$14:$K$19,11,0)),1) -> 18 | J5: =ROUND((Plan_Prev!J4+Plan_Corr!J4)/MAX(1,Premissas!$B$31*VLOOKUP($A5,Premissas!$A$14:$K$19,11,0)),1) -> 3.2 | K5: =ROUND((Plan_Prev!K4+Plan_Corr!K4)/MAX(1,Premissas!$B$32*VLOOKUP($A5,Premissas!$A$14:$K$19,11,0)),1) -> 28 | L5: =ROUND((Plan_Prev!L4+Plan_Corr!L4)/MAX(1,Premissas!$B$33*VLOOKUP($A5,Premissas!$A$14:$K$19,11,0)),1) -> 37.9 | M5: =ROUND((Plan_Prev!M4+Plan_Corr!M4)/MAX(1,Premissas!$B$34*VLOOKUP($A5,Premissas!$A$14:$K$19,11,0)),1) -> 31 | N5: =ROUND(SUM(B5:M5),1) -> 268.1
A6: Oficina Volante-Socorro | B6: =ROUND((Plan_Prev!B5+Plan_Corr!B5)/MAX(1,Premissas!$B$23*VLOOKUP($A6,Premissas!$A$14:$K$19,11,0)),1) -> 0 | C6: =ROUND((Plan_Prev!C5+Plan_Corr!C5)/MAX(1,Premissas!$B$24*VLOOKUP($A6,Premissas!$A$14:$K$19,11,0)),1) -> 0 | D6: =ROUND((Plan_Prev!D5+Plan_Corr!D5)/MAX(1,Premissas!$B$25*VLOOKUP($A6,Premissas!$A$14:$K$19,11,0)),1) -> 0 | E6: =ROUND((Plan_Prev!E5+Plan_Corr!E5)/MAX(1,Premissas!$B$26*VLOOKUP($A6,Premissas!$A$14:$K$19,11,0)),1) -> 0 | F6: =ROUND((Plan_Prev!F5+Plan_Corr!F5)/MAX(1,Premissas!$B$27*VLOOKUP($A6,Premissas!$A$14:$K$19,11,0)),1) -> 0 | G6: =ROUND((Plan_Prev!G5+Plan_Corr!G5)/MAX(1,Premissas!$B$28*VLOOKUP($A6,Premissas!$A$14:$K$19,11,0)),1) -> 0 | H6: =ROUND((Plan_Prev!H5+Plan_Corr!H5)/MAX(1,Premissas!$B$29*VLOOKUP($A6,Premissas!$A$14:$K$19,11,0)),1) -> 0 | I6: =ROUND((Plan_Prev!I5+Plan_Corr!I5)/MAX(1,Premissas!$B$30*VLOOKUP($A6,Premissas!$A$14:$K$19,11,0)),1) -> 0 | J6: =ROUND((Plan_Prev!J5+Plan_Corr!J5)/MAX(1,Premissas!$B$31*VLOOKUP($A6,Premissas!$A$14:$K$19,11,0)),1) -> 0 | K6: =ROUND((Plan_Prev!K5+Plan_Corr!K5)/MAX(1,Premissas!$B$32*VLOOKUP($A6,Premissas!$A$14:$K$19,11,0)),1) -> 0 | L6: =ROUND((Plan_Prev!L5+Plan_Corr!L5)/MAX(1,Premissas!$B$33*VLOOKUP($A6,Premissas!$A$14:$K$19,11,0)),1) -> 0 | M6: =ROUND((Plan_Prev!M5+Plan_Corr!M5)/MAX(1,Premissas!$B$34*VLOOKUP($A6,Premissas!$A$14:$K$19,11,0)),1) -> 0 | N6: =ROUND(SUM(B6:M6),1) -> 0
A7: Oficina Implementos Rodoviários | B7: =ROUND((Plan_Prev!B6+Plan_Corr!B6)/MAX(1,Premissas!$B$23*VLOOKUP($A7,Premissas!$A$14:$K$19,11,0)),1) -> 0 | C7: =ROUND((Plan_Prev!C6+Plan_Corr!C6)/MAX(1,Premissas!$B$24*VLOOKUP($A7,Premissas!$A$14:$K$19,11,0)),1) -> 0 | D7: =ROUND((Plan_Prev!D6+Plan_Corr!D6)/MAX(1,Premissas!$B$25*VLOOKUP($A7,Premissas!$A$14:$K$19,11,0)),1) -> 0 | E7: =ROUND((Plan_Prev!E6+Plan_Corr!E6)/MAX(1,Premissas!$B$26*VLOOKUP($A7,Premissas!$A$14:$K$19,11,0)),1) -> 0 | F7: =ROUND((Plan_Prev!F6+Plan_Corr!F6)/MAX(1,Premissas!$B$27*VLOOKUP($A7,Premissas!$A$14:$K$19,11,0)),1) -> 0 | G7: =ROUND((Plan_Prev!G6+Plan_Corr!G6)/MAX(1,Premissas!$B$28*VLOOKUP($A7,Premissas!$A$14:$K$19,11,0)),1) -> 0 | H7: =ROUND((Plan_Prev!H6+Plan_Corr!H6)/MAX(1,Premissas!$B$29*VLOOKUP($A7,Premissas!$A$14:$K$19,11,0)),1) -> 0 | I7: =ROUND((Plan_Prev!I6+Plan_Corr!I6)/MAX(1,Premissas!$B$30*VLOOKUP($A7,Premissas!$A$14:$K$19,11,0)),1) -> 0 | J7: =ROUND((Plan_Prev!J6+Plan_Corr!J6)/MAX(1,Premissas!$B$31*VLOOKUP($A7,Premissas!$A$14:$K$19,11,0)),1) -> 0 | K7: =ROUND((Plan_Prev!K6+Plan_Corr!K6)/MAX(1,Premissas!$B$32*VLOOKUP($A7,Premissas!$A$14:$K$19,11,0)),1) -> 0 | L7: =ROUND((Plan_Prev!L6+Plan_Corr!L6)/MAX(1,Premissas!$B$33*VLOOKUP($A7,Premissas!$A$14:$K$19,11,0)),1) -> 0 | M7: =ROUND((Plan_Prev!M6+Plan_Corr!M6)/MAX(1,Premissas!$B$34*VLOOKUP($A7,Premissas!$A$14:$K$19,11,0)),1) -> 0 | N7: =ROUND(SUM(B7:M7),1) -> 0
A8: Oficina Mecânica Externa | B8: =ROUND((Plan_Prev!B7+Plan_Corr!B7)/MAX(1,Premissas!$B$23*VLOOKUP($A8,Premissas!$A$14:$K$19,11,0)),1) -> 0 | C8: =ROUND((Plan_Prev!C7+Plan_Corr!C7)/MAX(1,Premissas!$B$24*VLOOKUP($A8,Premissas!$A$14:$K$19,11,0)),1) -> 0 | D8: =ROUND((Plan_Prev!D7+Plan_Corr!D7)/MAX(1,Premissas!$B$25*VLOOKUP($A8,Premissas!$A$14:$K$19,11,0)),1) -> 0 | E8: =ROUND((Plan_Prev!E7+Plan_Corr!E7)/MAX(1,Premissas!$B$26*VLOOKUP($A8,Premissas!$A$14:$K$19,11,0)),1) -> 0 | F8: =ROUND((Plan_Prev!F7+Plan_Corr!F7)/MAX(1,Premissas!$B$27*VLOOKUP($A8,Premissas!$A$14:$K$19,11,0)),1) -> 0 | G8: =ROUND((Plan_Prev!G7+Plan_Corr!G7)/MAX(1,Premissas!$B$28*VLOOKUP($A8,Premissas!$A$14:$K$19,11,0)),1) -> 0 | H8: =ROUND((Plan_Prev!H7+Plan_Corr!H7)/MAX(1,Premissas!$B$29*VLOOKUP($A8,Premissas!$A$14:$K$19,11,0)),1) -> 0 | I8: =ROUND((Plan_Prev!I7+Plan_Corr!I7)/MAX(1,Premissas!$B$30*VLOOKUP($A8,Premissas!$A$14:$K$19,11,0)),1) -> 0 | J8: =ROUND((Plan_Prev!J7+Plan_Corr!J7)/MAX(1,Premissas!$B$31*VLOOKUP($A8,Premissas!$A$14:$K$19,11,0)),1) -> 0 | K8: =ROUND((Plan_Prev!K7+Plan_Corr!K7)/MAX(1,Premissas!$B$32*VLOOKUP($A8,Premissas!$A$14:$K$19,11,0)),1) -> 0 | L8: =ROUND((Plan_Prev!L7+Plan_Corr!L7)/MAX(1,Premissas!$B$33*VLOOKUP($A8,Premissas!$A$14:$K$19,11,0)),1) -> 0 | M8: =ROUND((Plan_Prev!M7+Plan_Corr!M7)/MAX(1,Premissas!$B$34*VLOOKUP($A8,Premissas!$A$14:$K$19,11,0)),1) -> 0 | N8: =ROUND(SUM(B8:M8),1) -> 0
A9: Oficina Implementos Agrícolas | B9: =ROUND((Plan_Prev!B8+Plan_Corr!B8)/MAX(1,Premissas!$B$23*VLOOKUP($A9,Premissas!$A$14:$K$19,11,0)),1) -> 0 | C9: =ROUND((Plan_Prev!C8+Plan_Corr!C8)/MAX(1,Premissas!$B$24*VLOOKUP($A9,Premissas!$A$14:$K$19,11,0)),1) -> 0 | D9: =ROUND((Plan_Prev!D8+Plan_Corr!D8)/MAX(1,Premissas!$B$25*VLOOKUP($A9,Premissas!$A$14:$K$19,11,0)),1) -> 0 | E9: =ROUND((Plan_Prev!E8+Plan_Corr!E8)/MAX(1,Premissas!$B$26*VLOOKUP($A9,Premissas!$A$14:$K$19,11,0)),1) -> 0 | F9: =ROUND((Plan_Prev!F8+Plan_Corr!F8)/MAX(1,Premissas!$B$27*VLOOKUP($A9,Premissas!$A$14:$K$19,11,0)),1) -> 0 | G9: =ROUND((Plan_Prev!G8+Plan_Corr!G8)/MAX(1,Premissas!$B$28*VLOOKUP($A9,Premissas!$A$14:$K$19,11,0)),1) -> 0 | H9: =ROUND((Plan_Prev!H8+Plan_Corr!H8)/MAX(1,Premissas!$B$29*VLOOKUP($A9,Premissas!$A$14:$K$19,11,0)),1) -> 0 | I9: =ROUND((Plan_Prev!I8+Plan_Corr!I8)/MAX(1,Premissas!$B$30*VLOOKUP($A9,Premissas!$A$14:$K$19,11,0)),1) -> 0 | J9: =ROUND((Plan_Prev!J8+Plan_Corr!J8)/MAX(1,Premissas!$B$31*VLOOKUP($A9,Premissas!$A$14:$K$19,11,0)),1) -> 0 | K9: =ROUND((Plan_Prev!K8+Plan_Corr!K8)/MAX(1,Premissas!$B$32*VLOOKUP($A9,Premissas!$A$14:$K$19,11,0)),1) -> 0 | L9: =ROUND((Plan_Prev!L8+Plan_Corr!L8)/MAX(1,Premissas!$B$33*VLOOKUP($A9,Premissas!$A$14:$K$19,11,0)),1) -> 0 | M9: =ROUND((Plan_Prev!M8+Plan_Corr!M8)/MAX(1,Premissas!$B$34*VLOOKUP($A9,Premissas!$A$14:$K$19,11,0)),1) -> 0 | N9: =ROUND(SUM(B9:M9),1) -> 0
A10: PitStop | B10: =ROUND((Plan_Prev!B9+Plan_Corr!B9)/MAX(1,Premissas!$B$23*VLOOKUP($A10,Premissas!$A$14:$K$19,11,0)),1) -> 0 | C10: =ROUND((Plan_Prev!C9+Plan_Corr!C9)/MAX(1,Premissas!$B$24*VLOOKUP($A10,Premissas!$A$14:$K$19,11,0)),1) -> 0 | D10: =ROUND((Plan_Prev!D9+Plan_Corr!D9)/MAX(1,Premissas!$B$25*VLOOKUP($A10,Premissas!$A$14:$K$19,11,0)),1) -> 0 | E10: =ROUND((Plan_Prev!E9+Plan_Corr!E9)/MAX(1,Premissas!$B$26*VLOOKUP($A10,Premissas!$A$14:$K$19,11,0)),1) -> 0 | F10: =ROUND((Plan_Prev!F9+Plan_Corr!F9)/MAX(1,Premissas!$B$27*VLOOKUP($A10,Premissas!$A$14:$K$19,11,0)),1) -> 0 | G10: =ROUND((Plan_Prev!G9+Plan_Corr!G9)/MAX(1,Premissas!$B$28*VLOOKUP($A10,Premissas!$A$14:$K$19,11,0)),1) -> 0 | H10: =ROUND((Plan_Prev!H9+Plan_Corr!H9)/MAX(1,Premissas!$B$29*VLOOKUP($A10,Premissas!$A$14:$K$19,11,0)),1) -> 0 | I10: =ROUND((Plan_Prev!I9+Plan_Corr!I9)/MAX(1,Premissas!$B$30*VLOOKUP($A10,Premissas!$A$14:$K$19,11,0)),1) -> 0 | J10: =ROUND((Plan_Prev!J9+Plan_Corr!J9)/MAX(1,Premissas!$B$31*VLOOKUP($A10,Premissas!$A$14:$K$19,11,0)),1) -> 0 | K10: =ROUND((Plan_Prev!K9+Plan_Corr!K9)/MAX(1,Premissas!$B$32*VLOOKUP($A10,Premissas!$A$14:$K$19,11,0)),1) -> 0 | L10: =ROUND((Plan_Prev!L9+Plan_Corr!L9)/MAX(1,Premissas!$B$33*VLOOKUP($A10,Premissas!$A$14:$K$19,11,0)),1) -> 0 | M10: =ROUND((Plan_Prev!M9+Plan_Corr!M9)/MAX(1,Premissas!$B$34*VLOOKUP($A10,Premissas!$A$14:$K$19,11,0)),1) -> 0 | N10: =ROUND(SUM(B10:M10),1) -> 0
A11: TOTAL | B11: =ROUND(SUM(B5:B10),1) -> 25.9 | C11: =ROUND(SUM(C5:C10),1) -> 57.3 | D11: =ROUND(SUM(D5:D10),1) -> 46.7 | E11: =ROUND(SUM(E5:E10),1) -> 7.1 | F11: =ROUND(SUM(F5:F10),1) -> 1.1 | G11: =ROUND(SUM(G5:G10),1) -> 10 | H11: =ROUND(SUM(H5:H10),1) -> 1.9 | I11: =ROUND(SUM(I5:I10),1) -> 18 | ... N11: =ROUND(SUM(N5:N10),1) -> 268.1
A13: HC ATUAL − NECESSÁRIO (gap) | B13: Jan | C13: Fev | D13: Mar | E13: Abr | F13: Mai | G13: Jun | H13: Jul | I13: Ago | J13: Set | K13: Out | L13: Nov | M13: Dez | N13: —
A14: Oficina Mecânica Central-Taisa | B14: =ROUND(COUNTIFS(Pessoas!$C$5:$C$44,$A14,Pessoas!$G$5:$G$44,"Ativo")-B5,1) -> -25.9 | C14: =ROUND(COUNTIFS(Pessoas!$C$5:$C$44,$A14,Pessoas!$G$5:$G$44,"Ativo")-C5,1) -> -57.3 | D14: =ROUND(COUNTIFS(Pessoas!$C$5:$C$44,$A14,Pessoas!$G$5:$G$44,"Ativo")-D5,1) -> -46.7 | E14: =ROUND(COUNTIFS(Pessoas!$C$5:$C$44,$A14,Pessoas!$G$5:$G$44,"Ativo")-E5,1) -> -7.1 | F14: =ROUND(COUNTIFS(Pessoas!$C$5:$C$44,$A14,Pessoas!$G$5:$G$44,"Ativo")-F5,1) -> -1.1 | G14: =ROUND(COUNTIFS(Pessoas!$C$5:$C$44,$A14,Pessoas!$G$5:$G$44,"Ativo")-G5,1) -> -10 | H14: =ROUND(COUNTIFS(Pessoas!$C$5:$C$44,$A14,Pessoas!$G$5:$G$44,"Ativo")-H5,1) -> -1.9 | I14: =ROUND(COUNTIFS(Pessoas!$C$5:$C$44,$A14,Pessoas!$G$5:$G$44,"Ativo")-I5,1) -> -18 | ... M14: =ROUND(COUNTIFS(Pessoas!$C$5:$C$44,$A14,Pessoas!$G$5:$G$44,"Ativo")-M5,1) -> -31
A15: Oficina Volante-Socorro | B15: =ROUND(COUNTIFS(Pessoas!$C$5:$C$44,$A15,Pessoas!$G$5:$G$44,"Ativo")-B6,1) -> 0 | C15: =ROUND(COUNTIFS(Pessoas!$C$5:$C$44,$A15,Pessoas!$G$5:$G$44,"Ativo")-C6,1) -> 0 | D15: =ROUND(COUNTIFS(Pessoas!$C$5:$C$44,$A15,Pessoas!$G$5:$G$44,"Ativo")-D6,1) -> 0 | E15: =ROUND(COUNTIFS(Pessoas!$C$5:$C$44,$A15,Pessoas!$G$5:$G$44,"Ativo")-E6,1) -> 0 | F15: =ROUND(COUNTIFS(Pessoas!$C$5:$C$44,$A15,Pessoas!$G$5:$G$44,"Ativo")-F6,1) -> 0 | G15: =ROUND(COUNTIFS(Pessoas!$C$5:$C$44,$A15,Pessoas!$G$5:$G$44,"Ativo")-G6,1) -> 0 | H15: =ROUND(COUNTIFS(Pessoas!$C$5:$C$44,$A15,Pessoas!$G$5:$G$44,"Ativo")-H6,1) -> 0 | I15: =ROUND(COUNTIFS(Pessoas!$C$5:$C$44,$A15,Pessoas!$G$5:$G$44,"Ativo")-I6,1) -> 0 | ... M15: =ROUND(COUNTIFS(Pessoas!$C$5:$C$44,$A15,Pessoas!$G$5:$G$44,"Ativo")-M6,1) -> 0
A16: Oficina Implementos Rodoviários | B16: =ROUND(COUNTIFS(Pessoas!$C$5:$C$44,$A16,Pessoas!$G$5:$G$44,"Ativo")-B7,1) -> 0 | C16: =ROUND(COUNTIFS(Pessoas!$C$5:$C$44,$A16,Pessoas!$G$5:$G$44,"Ativo")-C7,1) -> 0 | D16: =ROUND(COUNTIFS(Pessoas!$C$5:$C$44,$A16,Pessoas!$G$5:$G$44,"Ativo")-D7,1) -> 0 | E16: =ROUND(COUNTIFS(Pessoas!$C$5:$C$44,$A16,Pessoas!$G$5:$G$44,"Ativo")-E7,1) -> 0 | F16: =ROUND(COUNTIFS(Pessoas!$C$5:$C$44,$A16,Pessoas!$G$5:$G$44,"Ativo")-F7,1) -> 0 | G16: =ROUND(COUNTIFS(Pessoas!$C$5:$C$44,$A16,Pessoas!$G$5:$G$44,"Ativo")-G7,1) -> 0 | H16: =ROUND(COUNTIFS(Pessoas!$C$5:$C$44,$A16,Pessoas!$G$5:$G$44,"Ativo")-H7,1) -> 0 | I16: =ROUND(COUNTIFS(Pessoas!$C$5:$C$44,$A16,Pessoas!$G$5:$G$44,"Ativo")-I7,1) -> 0 | ... M16: =ROUND(COUNTIFS(Pessoas!$C$5:$C$44,$A16,Pessoas!$G$5:$G$44,"Ativo")-M7,1) -> 0
A17: Oficina Mecânica Externa | B17: =ROUND(COUNTIFS(Pessoas!$C$5:$C$44,$A17,Pessoas!$G$5:$G$44,"Ativo")-B8,1) -> 0 | C17: =ROUND(COUNTIFS(Pessoas!$C$5:$C$44,$A17,Pessoas!$G$5:$G$44,"Ativo")-C8,1) -> 0 | D17: =ROUND(COUNTIFS(Pessoas!$C$5:$C$44,$A17,Pessoas!$G$5:$G$44,"Ativo")-D8,1) -> 0 | E17: =ROUND(COUNTIFS(Pessoas!$C$5:$C$44,$A17,Pessoas!$G$5:$G$44,"Ativo")-E8,1) -> 0 | F17: =ROUND(COUNTIFS(Pessoas!$C$5:$C$44,$A17,Pessoas!$G$5:$G$44,"Ativo")-F8,1) -> 0 | G17: =ROUND(COUNTIFS(Pessoas!$C$5:$C$44,$A17,Pessoas!$G$5:$G$44,"Ativo")-G8,1) -> 0 | H17: =ROUND(COUNTIFS(Pessoas!$C$5:$C$44,$A17,Pessoas!$G$5:$G$44,"Ativo")-H8,1) -> 0 | I17: =ROUND(COUNTIFS(Pessoas!$C$5:$C$44,$A17,Pessoas!$G$5:$G$44,"Ativo")-I8,1) -> 0 | ... M17: =ROUND(COUNTIFS(Pessoas!$C$5:$C$44,$A17,Pessoas!$G$5:$G$44,"Ativo")-M8,1) -> 0
A18: Oficina Implementos Agrícolas | B18: =ROUND(COUNTIFS(Pessoas!$C$5:$C$44,$A18,Pessoas!$G$5:$G$44,"Ativo")-B9,1) -> 0 | C18: =ROUND(COUNTIFS(Pessoas!$C$5:$C$44,$A18,Pessoas!$G$5:$G$44,"Ativo")-C9,1) -> 0 | D18: =ROUND(COUNTIFS(Pessoas!$C$5:$C$44,$A18,Pessoas!$G$5:$G$44,"Ativo")-D9,1) -> 0 | E18: =ROUND(COUNTIFS(Pessoas!$C$5:$C$44,$A18,Pessoas!$G$5:$G$44,"Ativo")-E9,1) -> 0 | F18: =ROUND(COUNTIFS(Pessoas!$C$5:$C$44,$A18,Pessoas!$G$5:$G$44,"Ativo")-F9,1) -> 0 | G18: =ROUND(COUNTIFS(Pessoas!$C$5:$C$44,$A18,Pessoas!$G$5:$G$44,"Ativo")-G9,1) -> 0 | H18: =ROUND(COUNTIFS(Pessoas!$C$5:$C$44,$A18,Pessoas!$G$5:$G$44,"Ativo")-H9,1) -> 0 | I18: =ROUND(COUNTIFS(Pessoas!$C$5:$C$44,$A18,Pessoas!$G$5:$G$44,"Ativo")-I9,1) -> 0 | ... M18: =ROUND(COUNTIFS(Pessoas!$C$5:$C$44,$A18,Pessoas!$G$5:$G$44,"Ativo")-M9,1) -> 0
A19: PitStop | B19: =ROUND(COUNTIFS(Pessoas!$C$5:$C$44,$A19,Pessoas!$G$5:$G$44,"Ativo")-B10,1) -> 0 | C19: =ROUND(COUNTIFS(Pessoas!$C$5:$C$44,$A19,Pessoas!$G$5:$G$44,"Ativo")-C10,1) -> 0 | D19: =ROUND(COUNTIFS(Pessoas!$C$5:$C$44,$A19,Pessoas!$G$5:$G$44,"Ativo")-D10,1) -> 0 | E19: =ROUND(COUNTIFS(Pessoas!$C$5:$C$44,$A19,Pessoas!$G$5:$G$44,"Ativo")-E10,1) -> 0 | F19: =ROUND(COUNTIFS(Pessoas!$C$5:$C$44,$A19,Pessoas!$G$5:$G$44,"Ativo")-F10,1) -> 0 | G19: =ROUND(COUNTIFS(Pessoas!$C$5:$C$44,$A19,Pessoas!$G$5:$G$44,"Ativo")-G10,1) -> 0 | H19: =ROUND(COUNTIFS(Pessoas!$C$5:$C$44,$A19,Pessoas!$G$5:$G$44,"Ativo")-H10,1) -> 0 | I19: =ROUND(COUNTIFS(Pessoas!$C$5:$C$44,$A19,Pessoas!$G$5:$G$44,"Ativo")-I10,1) -> 0 | ... M19: =ROUND(COUNTIFS(Pessoas!$C$5:$C$44,$A19,Pessoas!$G$5:$G$44,"Ativo")-M10,1) -> 0
A21: Gap fica vermelho (falta gente) ou verde (adequado) assim que a aba Pessoas for preenchida. Hoje HC atual = 0 (pendência).

Sheet Insumos
A1: INSUMOS & PEÇAS — execuções/ano por classe × tipo (base p/ vincular os 5.171 itens de materiais — pendência) | J1: ⌂ MENU
A2: O histórico de materiais (MATERIAIS AGO24–JUL25, 5.171 itens) está sem vínculo com as atividades. Preencha as colunas F–H para estimar demanda: Demanda/ano = Qtd por execução × Execuções/ano (herança: item de S conta em S, A, B e C).
A4: Classe | B4: Tipo | C4: Execuções/ano (do plano) | D4: Execuções herdadas/ano | E4: Item (preencher) | F4: Qtd por execução | G4: Un | H4: Demanda/ano
A5: Colhedora | B5: S | C5: =ROUND(SUMIFS(Eventos!$F$4:$F$367,Eventos!$A$4:$A$367,$A5,Eventos!$D$4:$D$367,$B5),0) -> 56 | D5: =ROUND(SUMIFS(Eventos!$F$4:$F$367,Eventos!$A$4:$A$367,$A5,Eventos!$D$4:$D$367,"S")+SUMIFS(Eventos!$F$4:$F$367,Eventos!$A$4:$A$367,$A5,Eventos!$D$4:$D$367,"A")+SUMIFS(Eventos!$F$4:$F$367,Eventos!$A$4:$A$367,$A5,Eventos!$D$4:$D$367,"B")+SUMIFS(Eventos!$F$4:$F$367,Eventos!$A$4:$A$367,$A5,Eventos!$D$4:$D$367,"C"),0) -> 104 | H5: =IF(OR($E5="",$F5=""),"",ROUND($F5*$D5,1))
A6: Colhedora | B6: A | C6: =ROUND(SUMIFS(Eventos!$F$4:$F$367,Eventos!$A$4:$A$367,$A6,Eventos!$D$4:$D$367,$B6),0) -> 24 | D6: =ROUND(SUMIFS(Eventos!$F$4:$F$367,Eventos!$A$4:$A$367,$A6,Eventos!$D$4:$D$367,"A")+SUMIFS(Eventos!$F$4:$F$367,Eventos!$A$4:$A$367,$A6,Eventos!$D$4:$D$367,"B")+SUMIFS(Eventos!$F$4:$F$367,Eventos!$A$4:$A$367,$A6,Eventos!$D$4:$D$367,"C"),0) -> 48 | H6: =IF(OR($E6="",$F6=""),"",ROUND($F6*$D6,1))
A7: Colhedora | B7: B | C7: =ROUND(SUMIFS(Eventos!$F$4:$F$367,Eventos!$A$4:$A$367,$A7,Eventos!$D$4:$D$367,$B7),0) -> 16 | D7: =ROUND(SUMIFS(Eventos!$F$4:$F$367,Eventos!$A$4:$A$367,$A7,Eventos!$D$4:$D$367,"B")+SUMIFS(Eventos!$F$4:$F$367,Eventos!$A$4:$A$367,$A7,Eventos!$D$4:$D$367,"C"),0) -> 24 | H7: =IF(OR($E7="",$F7=""),"",ROUND($F7*$D7,1))
A8: Colhedora | B8: C | C8: =ROUND(SUMIFS(Eventos!$F$4:$F$367,Eventos!$A$4:$A$367,$A8,Eventos!$D$4:$D$367,$B8),0) -> 8 | D8: =ROUND(SUMIFS(Eventos!$F$4:$F$367,Eventos!$A$4:$A$367,$A8,Eventos!$D$4:$D$367,"C"),0) -> 8 | H8: =IF(OR($E8="",$F8=""),"",ROUND($F8*$D8,1))
A9: Trator | B9: S | C9: =ROUND(SUMIFS(Eventos!$F$4:$F$367,Eventos!$A$4:$A$367,$A9,Eventos!$D$4:$D$367,$B9),0) -> 306 | D9: =ROUND(SUMIFS(Eventos!$F$4:$F$367,Eventos!$A$4:$A$367,$A9,Eventos!$D$4:$D$367,"S")+SUMIFS(Eventos!$F$4:$F$367,Eventos!$A$4:$A$367,$A9,Eventos!$D$4:$D$367,"A")+SUMIFS(Eventos!$F$4:$F$367,Eventos!$A$4:$A$367,$A9,Eventos!$D$4:$D$367,"B")+SUMIFS(Eventos!$F$4:$F$367,Eventos!$A$4:$A$367,$A9,Eventos!$D$4:$D$367,"C"),0) -> 612 | H9: =IF(OR($E9="",$F9=""),"",ROUND($F9*$D9,1))
A10: Trator | B10: A | C10: =ROUND(SUMIFS(Eventos!$F$4:$F$367,Eventos!$A$4:$A$367,$A10,Eventos!$D$4:$D$367,$B10),0) -> 204 | D10: =ROUND(SUMIFS(Eventos!$F$4:$F$367,Eventos!$A$4:$A$367,$A10,Eventos!$D$4:$D$367,"A")+SUMIFS(Eventos!$F$4:$F$367,Eventos!$A$4:$A$367,$A10,Eventos!$D$4:$D$367,"B")+SUMIFS(Eventos!$F$4:$F$367,Eventos!$A$4:$A$367,$A10,Eventos!$D$4:$D$367,"C"),0) -> 306 | H10: =IF(OR($E10="",$F10=""),"",ROUND($F10*$D10,1))
A11: Trator | B11: B | C11: =ROUND(SUMIFS(Eventos!$F$4:$F$367,Eventos!$A$4:$A$367,$A11,Eventos!$D$4:$D$367,$B11),0) -> 102 | D11: =ROUND(SUMIFS(Eventos!$F$4:$F$367,Eventos!$A$4:$A$367,$A11,Eventos!$D$4:$D$367,"B")+SUMIFS(Eventos!$F$4:$F$367,Eventos!$A$4:$A$367,$A11,Eventos!$D$4:$D$367,"C"),0) -> 102 | H11: =IF(OR($E11="",$F11=""),"",ROUND($F11*$D11,1))
A12: Trator | B12: C | C12: =ROUND(SUMIFS(Eventos!$F$4:$F$367,Eventos!$A$4:$A$367,$A12,Eventos!$D$4:$D$367,$B12),0) -> 0 | D12: =ROUND(SUMIFS(Eventos!$F$4:$F$367,Eventos!$A$4:$A$367,$A12,Eventos!$D$4:$D$367,"C"),0) -> 0 | H12: =IF(OR($E12="",$F12=""),"",ROUND($F12*$D12,1))
A13: Caminhão | B13: S | C13: =ROUND(SUMIFS(Eventos!$F$4:$F$367,Eventos!$A$4:$A$367,$A13,Eventos!$D$4:$D$367,$B13),0) -> 363 | D13: =ROUND(SUMIFS(Eventos!$F$4:$F$367,Eventos!$A$4:$A$367,$A13,Eventos!$D$4:$D$367,"S")+SUMIFS(Eventos!$F$4:$F$367,Eventos!$A$4:$A$367,$A13,Eventos!$D$4:$D$367,"A")+SUMIFS(Eventos!$F$4:$F$367,Eventos!$A$4:$A$367,$A13,Eventos!$D$4:$D$367,"B")+SUMIFS(Eventos!$F$4:$F$367,Eventos!$A$4:$A$367,$A13,Eventos!$D$4:$D$367,"C"),0) -> 605 | H13: =IF(OR($E13="",$F13=""),"",ROUND($F13*$D13,1))
A14: Caminhão | B14: A | C14: =ROUND(SUMIFS(Eventos!$F$4:$F$367,Eventos!$A$4:$A$367,$A14,Eventos!$D$4:$D$367,$B14),0) -> 121 | D14: =ROUND(SUMIFS(Eventos!$F$4:$F$367,Eventos!$A$4:$A$367,$A14,Eventos!$D$4:$D$367,"A")+SUMIFS(Eventos!$F$4:$F$367,Eventos!$A$4:$A$367,$A14,Eventos!$D$4:$D$367,"B")+SUMIFS(Eventos!$F$4:$F$367,Eventos!$A$4:$A$367,$A14,Eventos!$D$4:$D$367,"C"),0) -> 242 | H14: =IF(OR($E14="",$F14=""),"",ROUND($F14*$D14,1))
A15: Caminhão | B15: B | C15: =ROUND(SUMIFS(Eventos!$F$4:$F$367,Eventos!$A$4:$A$367,$A15,Eventos!$D$4:$D$367,$B15),0) -> 121 | D15: =ROUND(SUMIFS(Eventos!$F$4:$F$367,Eventos!$A$4:$A$367,$A15,Eventos!$D$4:$D$367,"B")+SUMIFS(Eventos!$F$4:$F$367,Eventos!$A$4:$A$367,$A15,Eventos!$D$4:$D$367,"C"),0) -> 121 | H15: =IF(OR($E15="",$F15=""),"",ROUND($F15*$D15,1))
A16: Caminhão | B16: C | C16: =ROUND(SUMIFS(Eventos!$F$4:$F$367,Eventos!$A$4:$A$367,$A16,Eventos!$D$4:$D$367,$B16),0) -> 0 | D16: =ROUND(SUMIFS(Eventos!$F$4:$F$367,Eventos!$A$4:$A$367,$A16,Eventos!$D$4:$D$367,"C"),0) -> 0 | H16: =IF(OR($E16="",$F16=""),"",ROUND($F16*$D16,1))
A17: Carregadeira/Pesada | B17: S | C17: =ROUND(SUMIFS(Eventos!$F$4:$F$367,Eventos!$A$4:$A$367,$A17,Eventos!$D$4:$D$367,$B17),0) -> 219 | D17: =ROUND(SUMIFS(Eventos!$F$4:$F$367,Eventos!$A$4:$A$367,$A17,Eventos!$D$4:$D$367,"S")+SUMIFS(Eventos!$F$4:$F$367,Eventos!$A$4:$A$367,$A17,Eventos!$D$4:$D$367,"A")+SUMIFS(Eventos!$F$4:$F$367,Eventos!$A$4:$A$367,$A17,Eventos!$D$4:$D$367,"B")+SUMIFS(Eventos!$F$4:$F$367,Eventos!$A$4:$A$367,$A17,Eventos!$D$4:$D$367,"C"),0) -> 438 | H17: =IF(OR($E17="",$F17=""),"",ROUND($F17*$D17,1))
A18: Carregadeira/Pesada | B18: A | C18: =ROUND(SUMIFS(Eventos!$F$4:$F$367,Eventos!$A$4:$A$367,$A18,Eventos!$D$4:$D$367,$B18),0) -> 146 | D18: =ROUND(SUMIFS(Eventos!$F$4:$F$367,Eventos!$A$4:$A$367,$A18,Eventos!$D$4:$D$367,"A")+SUMIFS(Eventos!$F$4:$F$367,Eventos!$A$4:$A$367,$A18,Eventos!$D$4:$D$367,"B")+SUMIFS(Eventos!$F$4:$F$367,Eventos!$A$4:$A$367,$A18,Eventos!$D$4:$D$367,"C"),0) -> 219 | H18: =IF(OR($E18="",$F18=""),"",ROUND($F18*$D18,1))
A19: Carregadeira/Pesada | B19: B | C19: =ROUND(SUMIFS(Eventos!$F$4:$F$367,Eventos!$A$4:$A$367,$A19,Eventos!$D$4:$D$367,$B19),0) -> 73 | D19: =ROUND(SUMIFS(Eventos!$F$4:$F$367,Eventos!$A$4:$A$367,$A19,Eventos!$D$4:$D$367,"B")+SUMIFS(Eventos!$F$4:$F$367,Eventos!$A$4:$A$367,$A19,Eventos!$D$4:$D$367,"C"),0) -> 73 | H19: =IF(OR($E19="",$F19=""),"",ROUND($F19*$D19,1))
A20: Carregadeira/Pesada | B20: C | C20: =ROUND(SUMIFS(Eventos!$F$4:$F$367,Eventos!$A$4:$A$367,$A20,Eventos!$D$4:$D$367,$B20),0) -> 0 | D20: =ROUND(SUMIFS(Eventos!$F$4:$F$367,Eventos!$A$4:$A$367,$A20,Eventos!$D$4:$D$367,"C"),0) -> 0 | H20: =IF(OR($E20="",$F20=""),"",ROUND($F20*$D20,1))
A21: Veículo Leve | B21: S | C21: =ROUND(SUMIFS(Eventos!$F$4:$F$367,Eventos!$A$4:$A$367,$A21,Eventos!$D$4:$D$367,$B21),0) -> 100 | D21: =ROUND(SUMIFS(Eventos!$F$4:$F$367,Eventos!$A$4:$A$367,$A21,Eventos!$D$4:$D$367,"S")+SUMIFS(Eventos!$F$4:$F$367,Eventos!$A$4:$A$367,$A21,Eventos!$D$4:$D$367,"A")+SUMIFS(Eventos!$F$4:$F$367,Eventos!$A$4:$A$367,$A21,Eventos!$D$4:$D$367,"B")+SUMIFS(Eventos!$F$4:$F$367,Eventos!$A$4:$A$367,$A21,Eventos!$D$4:$D$367,"C"),0) -> 150 | H21: =IF(OR($E21="",$F21=""),"",ROUND($F21*$D21,1))
A22: Veículo Leve | B22: A | C22: =ROUND(SUMIFS(Eventos!$F$4:$F$367,Eventos!$A$4:$A$367,$A22,Eventos!$D$4:$D$367,$B22),0) -> 50 | D22: =ROUND(SUMIFS(Eventos!$F$4:$F$367,Eventos!$A$4:$A$367,$A22,Eventos!$D$4:$D$367,"A")+SUMIFS(Eventos!$F$4:$F$367,Eventos!$A$4:$A$367,$A22,Eventos!$D$4:$D$367,"B")+SUMIFS(Eventos!$F$4:$F$367,Eventos!$A$4:$A$367,$A22,Eventos!$D$4:$D$367,"C"),0) -> 50 | H22: =IF(OR($E22="",$F22=""),"",ROUND($F22*$D22,1))
A23: Veículo Leve | B23: B | C23: =ROUND(SUMIFS(Eventos!$F$4:$F$367,Eventos!$A$4:$A$367,$A23,Eventos!$D$4:$D$367,$B23),0) -> 0 | D23: =ROUND(SUMIFS(Eventos!$F$4:$F$367,Eventos!$A$4:$A$367,$A23,Eventos!$D$4:$D$367,"B")+SUMIFS(Eventos!$F$4:$F$367,Eventos!$A$4:$A$367,$A23,Eventos!$D$4:$D$367,"C"),0) -> 0 | H23: =IF(OR($E23="",$F23=""),"",ROUND($F23*$D23,1))
A24: Veículo Leve | B24: C | C24: =ROUND(SUMIFS(Eventos!$F$4:$F$367,Eventos!$A$4:$A$367,$A24,Eventos!$D$4:$D$367,$B24),0) -> 0 | D24: =ROUND(SUMIFS(Eventos!$F$4:$F$367,Eventos!$A$4:$A$367,$A24,Eventos!$D$4:$D$367,"C"),0) -> 0 | H24: =IF(OR($E24="",$F24=""),"",ROUND($F24*$D24,1))
A25: Pulverizador | B25: S | C25: =ROUND(SUMIFS(Eventos!$F$4:$F$367,Eventos!$A$4:$A$367,$A25,Eventos!$D$4:$D$367,$B25),0) -> 60 | D25: =ROUND(SUMIFS(Eventos!$F$4:$F$367,Eventos!$A$4:$A$367,$A25,Eventos!$D$4:$D$367,"S")+SUMIFS(Eventos!$F$4:$F$367,Eventos!$A$4:$A$367,$A25,Eventos!$D$4:$D$367,"A")+SUMIFS(Eventos!$F$4:$F$367,Eventos!$A$4:$A$367,$A25,Eventos!$D$4:$D$367,"B")+SUMIFS(Eventos!$F$4:$F$367,Eventos!$A$4:$A$367,$A25,Eventos!$D$4:$D$367,"C"),0) -> 120 | H25: =IF(OR($E25="",$F25=""),"",ROUND($F25*$D25,1))
A26: Pulverizador | B26: A | C26: =ROUND(SUMIFS(Eventos!$F$4:$F$367,Eventos!$A$4:$A$367,$A26,Eventos!$D$4:$D$367,$B26),0) -> 60 | D26: =ROUND(SUMIFS(Eventos!$F$4:$F$367,Eventos!$A$4:$A$367,$A26,Eventos!$D$4:$D$367,"A")+SUMIFS(Eventos!$F$4:$F$367,Eventos!$A$4:$A$367,$A26,Eventos!$D$4:$D$367,"B")+SUMIFS(Eventos!$F$4:$F$367,Eventos!$A$4:$A$367,$A26,Eventos!$D$4:$D$367,"C"),0) -> 60 | H26: =IF(OR($E26="",$F26=""),"",ROUND($F26*$D26,1))
A27: Pulverizador | B27: B | C27: =ROUND(SUMIFS(Eventos!$F$4:$F$367,Eventos!$A$4:$A$367,$A27,Eventos!$D$4:$D$367,$B27),0) -> 0 | D27: =ROUND(SUMIFS(Eventos!$F$4:$F$367,Eventos!$A$4:$A$367,$A27,Eventos!$D$4:$D$367,"B")+SUMIFS(Eventos!$F$4:$F$367,Eventos!$A$4:$A$367,$A27,Eventos!$D$4:$D$367,"C"),0) -> 0 | H27: =IF(OR($E27="",$F27=""),"",ROUND($F27*$D27,1))
A28: Pulverizador | B28: C | C28: =ROUND(SUMIFS(Eventos!$F$4:$F$367,Eventos!$A$4:$A$367,$A28,Eventos!$D$4:$D$367,$B28),0) -> 0 | D28: =ROUND(SUMIFS(Eventos!$F$4:$F$367,Eventos!$A$4:$A$367,$A28,Eventos!$D$4:$D$367,"C"),0) -> 0 | H28: =IF(OR($E28="",$F28=""),"",ROUND($F28*$D28,1))
A29: Implemento | B29: S | C29: =ROUND(SUMIFS(Eventos!$F$4:$F$367,Eventos!$A$4:$A$367,$A29,Eventos!$D$4:$D$367,$B29),0) -> 36 | D29: =ROUND(SUMIFS(Eventos!$F$4:$F$367,Eventos!$A$4:$A$367,$A29,Eventos!$D$4:$D$367,"S")+SUMIFS(Eventos!$F$4:$F$367,Eventos!$A$4:$A$367,$A29,Eventos!$D$4:$D$367,"A")+SUMIFS(Eventos!$F$4:$F$367,Eventos!$A$4:$A$367,$A29,Eventos!$D$4:$D$367,"B")+SUMIFS(Eventos!$F$4:$F$367,Eventos!$A$4:$A$367,$A29,Eventos!$D$4:$D$367,"C"),0) -> 72 | H29: =IF(OR($E29="",$F29=""),"",ROUND($F29*$D29,1))
A30: Implemento | B30: A | C30: =ROUND(SUMIFS(Eventos!$F$4:$F$367,Eventos!$A$4:$A$367,$A30,Eventos!$D$4:$D$367,$B30),0) -> 36 | D30: =ROUND(SUMIFS(Eventos!$F$4:$F$367,Eventos!$A$4:$A$367,$A30,Eventos!$D$4:$D$367,"A")+SUMIFS(Eventos!$F$4:$F$367,Eventos!$A$4:$A$367,$A30,Eventos!$D$4:$D$367,"B")+SUMIFS(Eventos!$F$4:$F$367,Eventos!$A$4:$A$367,$A30,Eventos!$D$4:$D$367,"C"),0) -> 36 | H30: =IF(OR($E30="",$F30=""),"",ROUND($F30*$D30,1))
A31: Implemento | B31: B | C31: =ROUND(SUMIFS(Eventos!$F$4:$F$367,Eventos!$A$4:$A$367,$A31,Eventos!$D$4:$D$367,$B31),0) -> 0 | D31: =ROUND(SUMIFS(Eventos!$F$4:$F$367,Eventos!$A$4:$A$367,$A31,Eventos!$D$4:$D$367,"B")+SUMIFS(Eventos!$F$4:$F$367,Eventos!$A$4:$A$367,$A31,Eventos!$D$4:$D$367,"C"),0) -> 0 | H31: =IF(OR($E31="",$F31=""),"",ROUND($F31*$D31,1))
A32: Implemento | B32: C | C32: =ROUND(SUMIFS(Eventos!$F$4:$F$367,Eventos!$A$4:$A$367,$A32,Eventos!$D$4:$D$367,$B32),0) -> 0 | D32: =ROUND(SUMIFS(Eventos!$F$4:$F$367,Eventos!$A$4:$A$367,$A32,Eventos!$D$4:$D$367,"C"),0) -> 0 | H32: =IF(OR($E32="",$F32=""),"",ROUND($F32*$D32,1))

Sheet Saving
A1: SAVING — baseline (sem deflator) vs. plano · valorizado em R$ quando Pessoas/custo-hora chegar | P1: ⌂ MENU
A4: HH CORR BASELINE | B4: Jan | C4: Fev | D4: Mar | E4: Abr | F4: Mai | G4: Jun | H4: Jul | I4: Ago | J4: Set | K4: Out | L4: Nov | M4: Dez | N4: TOTAL ANO
A5: Oficina Mecânica Central-Taisa | B5: =ROUND(MAX(0,Plan_Prev!B4*(Premissas!$C$5/MAX(0.01,Premissas!$B$5))*Premissas!$C$23),1) -> 2350 | C5: =ROUND(MAX(0,Plan_Prev!C4*(Premissas!$C$5/MAX(0.01,Premissas!$B$5))*Premissas!$C$24),1) -> 4699.5 | D5: =ROUND(MAX(0,Plan_Prev!D4*(Premissas!$C$5/MAX(0.01,Premissas!$B$5))*Premissas!$C$25),1) -> 4116 | E5: =ROUND(MAX(0,Plan_Prev!E4*(Premissas!$C$5/MAX(0.01,Premissas!$B$5))*Premissas!$C$26),1) -> 495 | F5: =ROUND(MAX(0,Plan_Prev!F4*(Premissas!$C$5/MAX(0.01,Premissas!$B$5))*Premissas!$C$27),1) -> 69.4 | G5: =ROUND(MAX(0,Plan_Prev!G4*(Premissas!$C$5/MAX(0.01,Premissas!$B$5))*Premissas!$C$28),1) -> 572.6 | H5: =ROUND(MAX(0,Plan_Prev!H4*(Premissas!$C$5/MAX(0.01,Premissas!$B$5))*Premissas!$C$29),1) -> 117.1 | I5: =ROUND(MAX(0,Plan_Prev!I4*(Premissas!$C$5/MAX(0.01,Premissas!$B$5))*Premissas!$C$30),1) -> 1447.4 | J5: =ROUND(MAX(0,Plan_Prev!J4*(Premissas!$C$5/MAX(0.01,Premissas!$B$5))*Premissas!$C$31),1) -> 308.6 | K5: =ROUND(MAX(0,Plan_Prev!K4*(Premissas!$C$5/MAX(0.01,Premissas!$B$5))*Premissas!$C$32),1) -> 2667.4 | L5: =ROUND(MAX(0,Plan_Prev!L4*(Premissas!$C$5/MAX(0.01,Premissas!$B$5))*Premissas!$C$33),1) -> 3439.8 | M5: =ROUND(MAX(0,Plan_Prev!M4*(Premissas!$C$5/MAX(0.01,Premissas!$B$5))*Premissas!$C$34),1) -> 3048.9 | N5: =ROUND(SUM(B5:M5),1) -> 23331.7
A6: Oficina Volante-Socorro | B6: =ROUND(MAX(0,Plan_Prev!B5*(Premissas!$C$6/MAX(0.01,Premissas!$B$6))*Premissas!$C$23),1) -> 0 | C6: =ROUND(MAX(0,Plan_Prev!C5*(Premissas!$C$6/MAX(0.01,Premissas!$B$6))*Premissas!$C$24),1) -> 0 | D6: =ROUND(MAX(0,Plan_Prev!D5*(Premissas!$C$6/MAX(0.01,Premissas!$B$6))*Premissas!$C$25),1) -> 0 | E6: =ROUND(MAX(0,Plan_Prev!E5*(Premissas!$C$6/MAX(0.01,Premissas!$B$6))*Premissas!$C$26),1) -> 0 | F6: =ROUND(MAX(0,Plan_Prev!F5*(Premissas!$C$6/MAX(0.01,Premissas!$B$6))*Premissas!$C$27),1) -> 0 | G6: =ROUND(MAX(0,Plan_Prev!G5*(Premissas!$C$6/MAX(0.01,Premissas!$B$6))*Premissas!$C$28),1) -> 0 | H6: =ROUND(MAX(0,Plan_Prev!H5*(Premissas!$C$6/MAX(0.01,Premissas!$B$6))*Premissas!$C$29),1) -> 0 | I6: =ROUND(MAX(0,Plan_Prev!I5*(Premissas!$C$6/MAX(0.01,Premissas!$B$6))*Premissas!$C$30),1) -> 0 | J6: =ROUND(MAX(0,Plan_Prev!J5*(Premissas!$C$6/MAX(0.01,Premissas!$B$6))*Premissas!$C$31),1) -> 0 | K6: =ROUND(MAX(0,Plan_Prev!K5*(Premissas!$C$6/MAX(0.01,Premissas!$B$6))*Premissas!$C$32),1) -> 0 | L6: =ROUND(MAX(0,Plan_Prev!L5*(Premissas!$C$6/MAX(0.01,Premissas!$B$6))*Premissas!$C$33),1) -> 0 | M6: =ROUND(MAX(0,Plan_Prev!M5*(Premissas!$C$6/MAX(0.01,Premissas!$B$6))*Premissas!$C$34),1) -> 0 | N6: =ROUND(SUM(B6:M6),1) -> 0
A7: Oficina Implementos Rodoviários | B7: =ROUND(MAX(0,Plan_Prev!B6*(Premissas!$C$7/MAX(0.01,Premissas!$B$7))*Premissas!$C$23),1) -> 0 | C7: =ROUND(MAX(0,Plan_Prev!C6*(Premissas!$C$7/MAX(0.01,Premissas!$B$7))*Premissas!$C$24),1) -> 0 | D7: =ROUND(MAX(0,Plan_Prev!D6*(Premissas!$C$7/MAX(0.01,Premissas!$B$7))*Premissas!$C$25),1) -> 0 | E7: =ROUND(MAX(0,Plan_Prev!E6*(Premissas!$C$7/MAX(0.01,Premissas!$B$7))*Premissas!$C$26),1) -> 0 | F7: =ROUND(MAX(0,Plan_Prev!F6*(Premissas!$C$7/MAX(0.01,Premissas!$B$7))*Premissas!$C$27),1) -> 0 | G7: =ROUND(MAX(0,Plan_Prev!G6*(Premissas!$C$7/MAX(0.01,Premissas!$B$7))*Premissas!$C$28),1) -> 0 | H7: =ROUND(MAX(0,Plan_Prev!H6*(Premissas!$C$7/MAX(0.01,Premissas!$B$7))*Premissas!$C$29),1) -> 0 | I7: =ROUND(MAX(0,Plan_Prev!I6*(Premissas!$C$7/MAX(0.01,Premissas!$B$7))*Premissas!$C$30),1) -> 0 | J7: =ROUND(MAX(0,Plan_Prev!J6*(Premissas!$C$7/MAX(0.01,Premissas!$B$7))*Premissas!$C$31),1) -> 0 | K7: =ROUND(MAX(0,Plan_Prev!K6*(Premissas!$C$7/MAX(0.01,Premissas!$B$7))*Premissas!$C$32),1) -> 0 | L7: =ROUND(MAX(0,Plan_Prev!L6*(Premissas!$C$7/MAX(0.01,Premissas!$B$7))*Premissas!$C$33),1) -> 0 | M7: =ROUND(MAX(0,Plan_Prev!M6*(Premissas!$C$7/MAX(0.01,Premissas!$B$7))*Premissas!$C$34),1) -> 0 | N7: =ROUND(SUM(B7:M7),1) -> 0
A8: Oficina Mecânica Externa | B8: =ROUND(MAX(0,Plan_Prev!B7*(Premissas!$C$8/MAX(0.01,Premissas!$B$8))*Premissas!$C$23),1) -> 0 | C8: =ROUND(MAX(0,Plan_Prev!C7*(Premissas!$C$8/MAX(0.01,Premissas!$B$8))*Premissas!$C$24),1) -> 0 | D8: =ROUND(MAX(0,Plan_Prev!D7*(Premissas!$C$8/MAX(0.01,Premissas!$B$8))*Premissas!$C$25),1) -> 0 | E8: =ROUND(MAX(0,Plan_Prev!E7*(Premissas!$C$8/MAX(0.01,Premissas!$B$8))*Premissas!$C$26),1) -> 0 | F8: =ROUND(MAX(0,Plan_Prev!F7*(Premissas!$C$8/MAX(0.01,Premissas!$B$8))*Premissas!$C$27),1) -> 0 | G8: =ROUND(MAX(0,Plan_Prev!G7*(Premissas!$C$8/MAX(0.01,Premissas!$B$8))*Premissas!$C$28),1) -> 0 | H8: =ROUND(MAX(0,Plan_Prev!H7*(Premissas!$C$8/MAX(0.01,Premissas!$B$8))*Premissas!$C$29),1) -> 0 | I8: =ROUND(MAX(0,Plan_Prev!I7*(Premissas!$C$8/MAX(0.01,Premissas!$B$8))*Premissas!$C$30),1) -> 0 | J8: =ROUND(MAX(0,Plan_Prev!J7*(Premissas!$C$8/MAX(0.01,Premissas!$B$8))*Premissas!$C$31),1) -> 0 | K8: =ROUND(MAX(0,Plan_Prev!K7*(Premissas!$C$8/MAX(0.01,Premissas!$B$8))*Premissas!$C$32),1) -> 0 | L8: =ROUND(MAX(0,Plan_Prev!L7*(Premissas!$C$8/MAX(0.01,Premissas!$B$8))*Premissas!$C$33),1) -> 0 | M8: =ROUND(MAX(0,Plan_Prev!M7*(Premissas!$C$8/MAX(0.01,Premissas!$B$8))*Premissas!$C$34),1) -> 0 | N8: =ROUND(SUM(B8:M8),1) -> 0
A9: Oficina Implementos Agrícolas | B9: =ROUND(MAX(0,Plan_Prev!B8*(Premissas!$C$9/MAX(0.01,Premissas!$B$9))*Premissas!$C$23),1) -> 0 | C9: =ROUND(MAX(0,Plan_Prev!C8*(Premissas!$C$9/MAX(0.01,Premissas!$B$9))*Premissas!$C$24),1) -> 0 | D9: =ROUND(MAX(0,Plan_Prev!D8*(Premissas!$C$9/MAX(0.01,Premissas!$B$9))*Premissas!$C$25),1) -> 0 | E9: =ROUND(MAX(0,Plan_Prev!E8*(Premissas!$C$9/MAX(0.01,Premissas!$B$9))*Premissas!$C$26),1) -> 0 | F9: =ROUND(MAX(0,Plan_Prev!F8*(Premissas!$C$9/MAX(0.01,Premissas!$B$9))*Premissas!$C$27),1) -> 0 | G9: =ROUND(MAX(0,Plan_Prev!G8*(Premissas!$C$9/MAX(0.01,Premissas!$B$9))*Premissas!$C$28),1) -> 0 | H9: =ROUND(MAX(0,Plan_Prev!H8*(Premissas!$C$9/MAX(0.01,Premissas!$B$9))*Premissas!$C$29),1) -> 0 | I9: =ROUND(MAX(0,Plan_Prev!I8*(Premissas!$C$9/MAX(0.01,Premissas!$B$9))*Premissas!$C$30),1) -> 0 | J9: =ROUND(MAX(0,Plan_Prev!J8*(Premissas!$C$9/MAX(0.01,Premissas!$B$9))*Premissas!$C$31),1) -> 0 | K9: =ROUND(MAX(0,Plan_Prev!K8*(Premissas!$C$9/MAX(0.01,Premissas!$B$9))*Premissas!$C$32),1) -> 0 | L9: =ROUND(MAX(0,Plan_Prev!L8*(Premissas!$C$9/MAX(0.01,Premissas!$B$9))*Premissas!$C$33),1) -> 0 | M9: =ROUND(MAX(0,Plan_Prev!M8*(Premissas!$C$9/MAX(0.01,Premissas!$B$9))*Premissas!$C$34),1) -> 0 | N9: =ROUND(SUM(B9:M9),1) -> 0
A10: PitStop | B10: =ROUND(MAX(0,Plan_Prev!B9*(Premissas!$C$10/MAX(0.01,Premissas!$B$10))*Premissas!$C$23),1) -> 0 | C10: =ROUND(MAX(0,Plan_Prev!C9*(Premissas!$C$10/MAX(0.01,Premissas!$B$10))*Premissas!$C$24),1) -> 0 | D10: =ROUND(MAX(0,Plan_Prev!D9*(Premissas!$C$10/MAX(0.01,Premissas!$B$10))*Premissas!$C$25),1) -> 0 | E10: =ROUND(MAX(0,Plan_Prev!E9*(Premissas!$C$10/MAX(0.01,Premissas!$B$10))*Premissas!$C$26),1) -> 0 | F10: =ROUND(MAX(0,Plan_Prev!F9*(Premissas!$C$10/MAX(0.01,Premissas!$B$10))*Premissas!$C$27),1) -> 0 | G10: =ROUND(MAX(0,Plan_Prev!G9*(Premissas!$C$10/MAX(0.01,Premissas!$B$10))*Premissas!$C$28),1) -> 0 | H10: =ROUND(MAX(0,Plan_Prev!H9*(Premissas!$C$10/MAX(0.01,Premissas!$B$10))*Premissas!$C$29),1) -> 0 | I10: =ROUND(MAX(0,Plan_Prev!I9*(Premissas!$C$10/MAX(0.01,Premissas!$B$10))*Premissas!$C$30),1) -> 0 | J10: =ROUND(MAX(0,Plan_Prev!J9*(Premissas!$C$10/MAX(0.01,Premissas!$B$10))*Premissas!$C$31),1) -> 0 | K10: =ROUND(MAX(0,Plan_Prev!K9*(Premissas!$C$10/MAX(0.01,Premissas!$B$10))*Premissas!$C$32),1) -> 0 | L10: =ROUND(MAX(0,Plan_Prev!L9*(Premissas!$C$10/MAX(0.01,Premissas!$B$10))*Premissas!$C$33),1) -> 0 | M10: =ROUND(MAX(0,Plan_Prev!M9*(Premissas!$C$10/MAX(0.01,Premissas!$B$10))*Premissas!$C$34),1) -> 0 | N10: =ROUND(SUM(B10:M10),1) -> 0
A11: TOTAL | B11: =ROUND(SUM(B5:B10),1) -> 2350 | C11: =ROUND(SUM(C5:C10),1) -> 4699.5 | D11: =ROUND(SUM(D5:D10),1) -> 4116 | E11: =ROUND(SUM(E5:E10),1) -> 495 | F11: =ROUND(SUM(F5:F10),1) -> 69.4 | G11: =ROUND(SUM(G5:G10),1) -> 572.6 | H11: =ROUND(SUM(H5:H10),1) -> 117.1 | I11: =ROUND(SUM(I5:I10),1) -> 1447.4 | ... N11: =ROUND(SUM(N5:N10),1) -> 23331.7
A13: Δ HH (baseline − plano) | B13: Jan | C13: Fev | D13: Mar | E13: Abr | F13: Mai | G13: Jun | H13: Jul | I13: Ago | J13: Set | K13: Out | L13: Nov | M13: Dez | N13: TOTAL ANO
A14: Oficina Mecânica Central-Taisa | B14: =ROUND(MAX(0,B5-Plan_Corr!B4),1) -> 29.4 | C14: =ROUND(MAX(0,C5-Plan_Corr!C4),1) -> 69.4 | D14: =ROUND(MAX(0,D5-Plan_Corr!D4),1) -> 70.2 | E14: =ROUND(MAX(0,E5-Plan_Corr!E4),1) -> 9.5 | F14: =ROUND(MAX(0,F5-Plan_Corr!F4),1) -> 1.5 | G14: =ROUND(MAX(0,G5-Plan_Corr!G4),1) -> 13.7 | H14: =ROUND(MAX(0,H5-Plan_Corr!H4),1) -> 3.1 | I14: =ROUND(MAX(0,I5-Plan_Corr!I4),1) -> 41.2 | ... M14: =ROUND(MAX(0,M5-Plan_Corr!M4),1) -> 114.3 | N14: =ROUND(SUM(B14:M14),1) -> 570.9
A15: Oficina Volante-Socorro | B15: =ROUND(MAX(0,B6-Plan_Corr!B5),1) -> 0 | C15: =ROUND(MAX(0,C6-Plan_Corr!C5),1) -> 0 | D15: =ROUND(MAX(0,D6-Plan_Corr!D5),1) -> 0 | E15: =ROUND(MAX(0,E6-Plan_Corr!E5),1) -> 0 | F15: =ROUND(MAX(0,F6-Plan_Corr!F5),1) -> 0 | G15: =ROUND(MAX(0,G6-Plan_Corr!G5),1) -> 0 | H15: =ROUND(MAX(0,H6-Plan_Corr!H5),1) -> 0 | I15: =ROUND(MAX(0,I6-Plan_Corr!I5),1) -> 0 | ... M15: =ROUND(MAX(0,M6-Plan_Corr!M5),1) -> 0 | N15: =ROUND(SUM(B15:M15),1) -> 0
A16: Oficina Implementos Rodoviários | B16: =ROUND(MAX(0,B7-Plan_Corr!B6),1) -> 0 | C16: =ROUND(MAX(0,C7-Plan_Corr!C6),1) -> 0 | D16: =ROUND(MAX(0,D7-Plan_Corr!D6),1) -> 0 | E16: =ROUND(MAX(0,E7-Plan_Corr!E6),1) -> 0 | F16: =ROUND(MAX(0,F7-Plan_Corr!F6),1) -> 0 | G16: =ROUND(MAX(0,G7-Plan_Corr!G6),1) -> 0 | H16: =ROUND(MAX(0,H7-Plan_Corr!H6),1) -> 0 | I16: =ROUND(MAX(0,I7-Plan_Corr!I6),1) -> 0 | ... M16: =ROUND(MAX(0,M7-Plan_Corr!M6),1) -> 0 | N16: =ROUND(SUM(B16:M16),1) -> 0
A17: Oficina Mecânica Externa | B17: =ROUND(MAX(0,B8-Plan_Corr!B7),1) -> 0 | C17: =ROUND(MAX(0,C8-Plan_Corr!C7),1) -> 0 | D17: =ROUND(MAX(0,D8-Plan_Corr!D7),1) -> 0 | E17: =ROUND(MAX(0,E8-Plan_Corr!E7),1) -> 0 | F17: =ROUND(MAX(0,F8-Plan_Corr!F7),1) -> 0 | G17: =ROUND(MAX(0,G8-Plan_Corr!G7),1) -> 0 | H17: =ROUND(MAX(0,H8-Plan_Corr!H7),1) -> 0 | I17: =ROUND(MAX(0,I8-Plan_Corr!I7),1) -> 0 | ... M17: =ROUND(MAX(0,M8-Plan_Corr!M7),1) -> 0 | N17: =ROUND(SUM(B17:M17),1) -> 0
A18: Oficina Implementos Agrícolas | B18: =ROUND(MAX(0,B9-Plan_Corr!B8),1) -> 0 | C18: =ROUND(MAX(0,C9-Plan_Corr!C8),1) -> 0 | D18: =ROUND(MAX(0,D9-Plan_Corr!D8),1) -> 0 | E18: =ROUND(MAX(0,E9-Plan_Corr!E8),1) -> 0 | F18: =ROUND(MAX(0,F9-Plan_Corr!F8),1) -> 0 | G18: =ROUND(MAX(0,G9-Plan_Corr!G8),1) -> 0 | H18: =ROUND(MAX(0,H9-Plan_Corr!H8),1) -> 0 | I18: =ROUND(MAX(0,I9-Plan_Corr!I8),1) -> 0 | ... M18: =ROUND(MAX(0,M9-Plan_Corr!M8),1) -> 0 | N18: =ROUND(SUM(B18:M18),1) -> 0
A19: PitStop | B19: =ROUND(MAX(0,B10-Plan_Corr!B9),1) -> 0 | C19: =ROUND(MAX(0,C10-Plan_Corr!C9),1) -> 0 | D19: =ROUND(MAX(0,D10-Plan_Corr!D9),1) -> 0 | E19: =ROUND(MAX(0,E10-Plan_Corr!E9),1) -> 0 | F19: =ROUND(MAX(0,F10-Plan_Corr!F9),1) -> 0 | G19: =ROUND(MAX(0,G10-Plan_Corr!G9),1) -> 0 | H19: =ROUND(MAX(0,H10-Plan_Corr!H9),1) -> 0 | I19: =ROUND(MAX(0,I10-Plan_Corr!I9),1) -> 0 | ... M19: =ROUND(MAX(0,M10-Plan_Corr!M9),1) -> 0 | N19: =ROUND(SUM(B19:M19),1) -> 0
A20: Δ HH TOTAL | B20: =ROUND(SUM(B14:B19),1) -> 29.4 | C20: =ROUND(SUM(C14:C19),1) -> 69.4 | D20: =ROUND(SUM(D14:D19),1) -> 70.2 | E20: =ROUND(SUM(E14:E19),1) -> 9.5 | F20: =ROUND(SUM(F14:F19),1) -> 1.5 | G20: =ROUND(SUM(G14:G19),1) -> 13.7 | H20: =ROUND(SUM(H14:H19),1) -> 3.1 | I20: =ROUND(SUM(I14:I19),1) -> 41.2 | ... N20: =ROUND(SUM(N14:N19),1) -> 570.9
A22: Saving em R$ = Δ HH × custo médio/HH da oficina (calculado automaticamente quando a aba Pessoas for preenchida).
A23: SAVING (R$) TOTAL/ANO | B23: =ROUND(N14*IFERROR(AVERAGEIFS(Pessoas!$I$5:$I$44,Pessoas!$C$5:$C$44,"Oficina Mecânica Central-Taisa",Pessoas!$G$5:$G$44,"Ativo"),0)+N15*IFERROR(AVERAGEIFS(Pessoas!$I$5:$I$44,Pessoas!$C$5:$C$44,"Oficina Volante-Socorro",Pessoas!$G$5:$G$44,"Ativo"),0)+N16*IFERROR(AVERAGEIFS(Pessoas!$I$5:$I$44,Pessoas!$C$5:$C$44,"Oficina Implementos Rodoviários",Pessoas!$G$5:$G$44,"Ativo"),0)+N17*IFERROR(AVERAGEIFS(Pessoas!$I$5:$I$44,Pessoas!$C$5:$C$44,"Oficina Mecânica Externa",Pessoas!$G$5:$G$44,"Ativo"),0)+N18*IFERROR(AVERAGEIFS(Pessoas!$I$5:$I$44,Pessoas!$C$5:$C$44,"Oficina Implementos Agrícolas",Pessoas!$G$5:$G$44,"Ativo"),0)+N19*IFERROR(AVERAGEIFS(Pessoas!$I$5:$I$44,Pessoas!$C$5:$C$44,"PitStop",Pessoas!$G$5:$G$44,"Ativo"),0),0) -> 0

Sheet Resumo
A1: RESUMO EXECUTIVO — USINA PETRIBÚ (validar contra o app: 2.102 prev · 7.988 HH prev · 22.783 HH corr) | F1: ⌂ MENU
A3: KPI | B3: Valor | C3: Unidade | D3: Fonte / status
A4: Ativos no escopo garagem | B4: =COUNTA(Frota!$A$5:$A$388) -> 384 | C4: ativos | D4: Frota real (template_frota_Dados)
A5: Preventivas programadas / 12 meses | B5: =SUM(Eventos!$F$4:$F$367) -> 2101 | C5: preventivas | D5: Cronograma × qtd por classe
A6: HH Preventiva / ano | B6: =Plan_Prev!N10 -> 7983.5 | C6: HH | D6: Plan_Prev
A7: HH Corretiva esperada / ano | B7: =Plan_Corr!N10 -> 22760.8 | C7: HH | D7: Plan_Corr (calibrada pelo histórico)
A8: HH Disponível / ano | B8: =Disponibilidade!N11 -> 0 | C8: HH | D8: ZERADO — pendente aba Pessoas
A9: Saldo HH anual (disp − nec) | B9: =Disponibilidade!N29 -> -30744.3 | C9: HH | D9: ZERADO — pendente aba Pessoas
A10: Δ HH corretiva evitada / ano | B10: =Saving!N20 -> 570.9 | C10: HH | D10: Saving (efeito do deflator)
A11: Equipe cadastrada | B11: =COUNTIFS(Pessoas!$G$5:$G$44,"Ativo",Pessoas!$A$5:$A$44,"<>") -> 0 | C11: pessoas | D11: PENDENTE — Evandro
A12: Custo de MO mensal | B12: =ROUND(SUMPRODUCT((Pessoas!$G$5:$G$44="Ativo")*N(Pessoas!$E$5:$E$44)*(1+N(Pessoas!$F$5:$F$44)/100)),0) -> 0 | C12: R$/mês | D12: ZERADO — pendente aba Pessoas
A13: Saving projetado / ano | B13: =Saving!B23 -> 0 | C13: R$ | D13: ZERADO — pendente custo/HH (Pessoas)
A15: PREVENTIVAS POR TIPO / ANO | B15: Qtd | C15: HH/ano
A16: Revisão S | B16: =SUMIFS(Eventos!$F$4:$F$367,Eventos!$D$4:$D$367,"S") -> 1140 | C16: =ROUND(SUMIFS(Eventos!$G$4:$G$367,Eventos!$D$4:$D$367,"S")+SUMIFS(Eventos!$H$4:$H$367,Eventos!$D$4:$D$367,"S")+SUMIFS(Eventos!$I$4:$I$367,Eventos!$D$4:$D$367,"S")+SUMIFS(Eventos!$J$4:$J$367,Eventos!$D$4:$D$367,"S")+SUMIFS(Eventos!$K$4:$K$367,Eventos!$D$4:$D$367,"S")+SUMIFS(Eventos!$L$4:$L$367,Eventos!$D$4:$D$367,"S"),0) -> 2531
A17: Revisão A | B17: =SUMIFS(Eventos!$F$4:$F$367,Eventos!$D$4:$D$367,"A") -> 641 | C17: =ROUND(SUMIFS(Eventos!$G$4:$G$367,Eventos!$D$4:$D$367,"A")+SUMIFS(Eventos!$H$4:$H$367,Eventos!$D$4:$D$367,"A")+SUMIFS(Eventos!$I$4:$I$367,Eventos!$D$4:$D$367,"A")+SUMIFS(Eventos!$J$4:$J$367,Eventos!$D$4:$D$367,"A")+SUMIFS(Eventos!$K$4:$K$367,Eventos!$D$4:$D$367,"A")+SUMIFS(Eventos!$L$4:$L$367,Eventos!$D$4:$D$367,"A"),0) -> 2701
A18: Revisão B | B18: =SUMIFS(Eventos!$F$4:$F$367,Eventos!$D$4:$D$367,"B") -> 312 | C18: =ROUND(SUMIFS(Eventos!$G$4:$G$367,Eventos!$D$4:$D$367,"B")+SUMIFS(Eventos!$H$4:$H$367,Eventos!$D$4:$D$367,"B")+SUMIFS(Eventos!$I$4:$I$367,Eventos!$D$4:$D$367,"B")+SUMIFS(Eventos!$J$4:$J$367,Eventos!$D$4:$D$367,"B")+SUMIFS(Eventos!$K$4:$K$367,Eventos!$D$4:$D$367,"B")+SUMIFS(Eventos!$L$4:$L$367,Eventos!$D$4:$D$367,"B"),0) -> 2560
A19: Revisão C | B19: =SUMIFS(Eventos!$F$4:$F$367,Eventos!$D$4:$D$367,"C") -> 8 | C19: =ROUND(SUMIFS(Eventos!$G$4:$G$367,Eventos!$D$4:$D$367,"C")+SUMIFS(Eventos!$H$4:$H$367,Eventos!$D$4:$D$367,"C")+SUMIFS(Eventos!$I$4:$I$367,Eventos!$D$4:$D$367,"C")+SUMIFS(Eventos!$J$4:$J$367,Eventos!$D$4:$D$367,"C")+SUMIFS(Eventos!$K$4:$K$367,Eventos!$D$4:$D$367,"C")+SUMIFS(Eventos!$L$4:$L$367,Eventos!$D$4:$D$367,"C"),0) -> 192
A21: HH PREVENTIVA POR CLASSE / ANO | B21: Qtd ativos | C21: HH/ano
A22: Colhedora | B22: =Premissas!$I$39 -> 8 | C22: =ROUND(SUMIFS(Eventos!$G$4:$G$367,Eventos!$A$4:$A$367,"Colhedora")+SUMIFS(Eventos!$H$4:$H$367,Eventos!$A$4:$A$367,"Colhedora")+SUMIFS(Eventos!$I$4:$I$367,Eventos!$A$4:$A$367,"Colhedora")+SUMIFS(Eventos!$J$4:$J$367,Eventos!$A$4:$A$367,"Colhedora")+SUMIFS(Eventos!$K$4:$K$367,Eventos!$A$4:$A$367,"Colhedora")+SUMIFS(Eventos!$L$4:$L$367,Eventos!$A$4:$A$367,"Colhedora"),0) -> 696
A23: Trator | B23: =Premissas!$I$40 -> 102 | C23: =ROUND(SUMIFS(Eventos!$G$4:$G$367,Eventos!$A$4:$A$367,"Trator")+SUMIFS(Eventos!$H$4:$H$367,Eventos!$A$4:$A$367,"Trator")+SUMIFS(Eventos!$I$4:$I$367,Eventos!$A$4:$A$367,"Trator")+SUMIFS(Eventos!$J$4:$J$367,Eventos!$A$4:$A$367,"Trator")+SUMIFS(Eventos!$K$4:$K$367,Eventos!$A$4:$A$367,"Trator")+SUMIFS(Eventos!$L$4:$L$367,Eventos!$A$4:$A$367,"Trator"),0) -> 2499
A24: Caminhão | B24: =Premissas!$I$41 -> 121 | C24: =ROUND(SUMIFS(Eventos!$G$4:$G$367,Eventos!$A$4:$A$367,"Caminhão")+SUMIFS(Eventos!$H$4:$H$367,Eventos!$A$4:$A$367,"Caminhão")+SUMIFS(Eventos!$I$4:$I$367,Eventos!$A$4:$A$367,"Caminhão")+SUMIFS(Eventos!$J$4:$J$367,Eventos!$A$4:$A$367,"Caminhão")+SUMIFS(Eventos!$K$4:$K$367,Eventos!$A$4:$A$367,"Caminhão")+SUMIFS(Eventos!$L$4:$L$367,Eventos!$A$4:$A$367,"Caminhão"),0) -> 2178
A25: Carregadeira/Pesada | B25: =Premissas!$I$42 -> 73 | C25: =ROUND(SUMIFS(Eventos!$G$4:$G$367,Eventos!$A$4:$A$367,"Carregadeira/Pesada")+SUMIFS(Eventos!$H$4:$H$367,Eventos!$A$4:$A$367,"Carregadeira/Pesada")+SUMIFS(Eventos!$I$4:$I$367,Eventos!$A$4:$A$367,"Carregadeira/Pesada")+SUMIFS(Eventos!$J$4:$J$367,Eventos!$A$4:$A$367,"Carregadeira/Pesada")+SUMIFS(Eventos!$K$4:$K$367,Eventos!$A$4:$A$367,"Carregadeira/Pesada")+SUMIFS(Eventos!$L$4:$L$367,Eventos!$A$4:$A$367,"Carregadeira/Pesada"),0) -> 1789
A26: Veículo Leve | B26: =Premissas!$I$43 -> 50 | C26: =ROUND(SUMIFS(Eventos!$G$4:$G$367,Eventos!$A$4:$A$367,"Veículo Leve")+SUMIFS(Eventos!$H$4:$H$367,Eventos!$A$4:$A$367,"Veículo Leve")+SUMIFS(Eventos!$I$4:$I$367,Eventos!$A$4:$A$367,"Veículo Leve")+SUMIFS(Eventos!$J$4:$J$367,Eventos!$A$4:$A$367,"Veículo Leve")+SUMIFS(Eventos!$K$4:$K$367,Eventos!$A$4:$A$367,"Veículo Leve")+SUMIFS(Eventos!$L$4:$L$367,Eventos!$A$4:$A$367,"Veículo Leve"),0) -> 300
