Workbook

Sheet Leia-me
A1: PLANEJAMENTO DE MANUTENÇÃO — RÉPLICA FUNCIONAL DO APP AGROVECTOR v4.2
A3: 1 | B3: O que é | C3: Réplica em Excel do motor de cálculo do app (agrovector_manutencao_v4.2). Altere Premissas, Frota, Pessoas ou Checklist — Cronograma, Planos, Disponibilidade, Recursos, Insumos, Saving e Resumo recalculam automaticamente, com as MESMAS fórmulas do app.
A4: 2 | B4: Abas de entrada (editar) | C4: Premissas · Frota · Pessoas · Checklist. Preencha apenas células brancas; use os menus suspensos. Dados atuais = demonstração do app (substituir pelos do cliente).
A5: 3 | B5: Abas de resultado (não editar) | C5: Cronograma · Plan_Prev · Plan_Corr · Disponibilidade · Recursos · Insumos · Saving · Resumo — 100% fórmulas.
A6: 4 | B6: Abas auxiliares (não mexer) | C6: Semanas, Cron_Uso, Eventos e Aux_HH são o motor de cálculo (uso acumulado semanal, herança de checklists, contagem de eventos).
A7: 5 | B7: Lógica do motor | C7: 52 semanas a partir do Início da Safra; uso acumulado semanal (safra/entressafra) dispara preventiva ao cruzar múltiplo do intervalo; tipo S/A/B pelo maior gatilho divisível; HH com herança cumulativa (B executa S+A+B); corretiva = preventiva × (corr/prev) × deflator progressivo × sazonalidade mensal; disponibilidade = pessoas ativas × dias úteis × horas líquidas; saving = corretiva sem deflator (baseline) − corretiva com plano, valorizada pelo custo/HH médio da oficina.
A8: 6 | B8: Simplificações | C8: Máx. 1 preventiva por ativo/semana (válido quando uso semanal << intervalo) · Tipos S/A/B (C/D podem ser acrescentados nos gatilhos e checklists) · Capacidade: 30 ativos, 40 pessoas, 100 atividades de checklist (linhas já formatadas).
A9: 7 | B9: Carga no app | C9: Após validar aqui, use a planilha Parametrizacao_AgroVector_v4.2.xlsx (abas Frota/Pessoas/Checklist → CSV UTF-8 → botões 📥 Importar do app). Premissas são digitadas na aba 📐 do app.
A10: 8 | B10: Cores Fabio | C10: VERDE #00FF00 = OK · AMARELO #FFFF00 = atenção · VERMELHO #FF3300 = crítico (fonte branca). Aplicadas nos saldos, gaps e no cronograma (S=verde, A=amarelo, B=vermelho).

Sheet Premissas
A1: PREMISSAS — ponto de partida de todos os cálculos
A3: ÍNDICES POR OFICINA
A4: Oficina | B4: % Preventiva | C4: % Corretiva | D4: Check % | E4: Deflator (% a.a.) | F4: % Terceiros
A5: Mec. Oficina | B5: 60 | C5: 40 | D5: =IF(B5+C5=100,"OK","≠100") -> OK | E5: 5 | F5: 10
A6: Mec. Campo | B6: 40 | C6: 60 | D6: =IF(B6+C6=100,"OK","≠100") -> OK | E6: 8 | F6: 5
A7: Elétrica | B7: 55 | C7: 45 | D7: =IF(B7+C7=100,"OK","≠100") -> OK | E7: 5 | F7: 15
A8: Lubrificação | B8: 100 | C8: 0 | D8: =IF(B8+C8=100,"OK","≠100") -> OK | E8: 0 | F8: 0
A9: Borracharia | B9: 30 | C9: 70 | D9: =IF(B9+C9=100,"OK","≠100") -> OK | E9: 5 | F9: 20
A10: Caldeiraria | B10: 20 | C10: 80 | D10: =IF(B10+C10=100,"OK","≠100") -> OK | E10: 3 | F10: 30
A12: DISPONIBILIDADE DE MÃO DE OBRA (fórmula idêntica ao app)
A13: Oficina | B13: H.Brutas/dia | C13: Almoço (h) | D13: Café (h) | E13: Abertura OS (h) | F13: Produtividade % | G13: Absenteísmo % | H13: Férias % | I13: Trein. (h/ano) | J13: H.Efetivas/dia | K13: H.Líquidas/dia
A14: Mec. Oficina | B14: 8.8 | C14: 1.2 | D14: 0.17 | E14: 0.25 | F14: 80 | G14: 5 | H14: 8.33 | I14: 16 | J14: =MAX(0,B14-C14-D14-E14) -> 7.18 | K14: =ROUND(J14*(1-MIN(G14/100+H14/100/12+I14/MAX(1,252*J14),0.99))*(F14/100),2) -> 5.37
A15: Mec. Campo | B15: 9 | C15: 1 | D15: 0.17 | E15: 0.17 | F15: 75 | G15: 6 | H15: 8.33 | I15: 12 | J15: =MAX(0,B15-C15-D15-E15) -> 7.66 | K15: =ROUND(J15*(1-MIN(G15/100+H15/100/12+I15/MAX(1,252*J15),0.99))*(F15/100),2) -> 5.32
A16: Elétrica | B16: 8.8 | C16: 1.2 | D16: 0.17 | E16: 0.25 | F16: 80 | G16: 5 | H16: 8.33 | I16: 16 | J16: =MAX(0,B16-C16-D16-E16) -> 7.18 | K16: =ROUND(J16*(1-MIN(G16/100+H16/100/12+I16/MAX(1,252*J16),0.99))*(F16/100),2) -> 5.37
A17: Lubrificação | B17: 8.8 | C17: 1 | D17: 0.17 | E17: 0.17 | F17: 85 | G17: 4 | H17: 8.33 | I17: 8 | J17: =MAX(0,B17-C17-D17-E17) -> 7.46 | K17: =ROUND(J17*(1-MIN(G17/100+H17/100/12+I17/MAX(1,252*J17),0.99))*(F17/100),2) -> 6.02
A18: Borracharia | B18: 8.8 | C18: 1 | D18: 0.17 | E18: 0.17 | F18: 82 | G18: 5 | H18: 8.33 | I18: 8 | J18: =MAX(0,B18-C18-D18-E18) -> 7.46 | K18: =ROUND(J18*(1-MIN(G18/100+H18/100/12+I18/MAX(1,252*J18),0.99))*(F18/100),2) -> 5.74
A19: Caldeiraria | B19: 8.8 | C19: 1.2 | D19: 0.17 | E19: 0.25 | F19: 78 | G19: 5 | H19: 8.33 | I19: 16 | J19: =MAX(0,B19-C19-D19-E19) -> 7.18 | K19: =ROUND(J19*(1-MIN(G19/100+H19/100/12+I19/MAX(1,252*J19),0.99))*(F19/100),2) -> 5.23
A21: CALENDÁRIO E SAZONALIDADE | F21: Início da safra | G21: 2025-04-01
A22: Mês | B22: Dias úteis | C22: Fator sazonal corretivas | D22: Safra (informativo) | F22: Fim da safra | G22: 2025-11-30
A23: Jan | B23: 22 | C23: 1.8 | D23: Sim
A24: Fev | B24: 20 | C24: 1.5 | D24: Sim
A25: Mar | B25: 22 | C25: 1.3 | D25: Sim
A26: Abr | B26: 20 | C26: 1.2 | D26: Sim
A27: Mai | B27: 20 | C27: 1.1 | D27: Sim
A28: Jun | B28: 22 | C28: 1 | D28: Sim
A29: Jul | B29: 21 | C29: 0.7 | D29: Não
A30: Ago | B30: 20 | C30: 0.6 | D30: Não
A31: Set | B31: 23 | C31: 0.7 | D31: Não
A32: Out | B32: 22 | C32: 0.9 | D32: Não
A33: Nov | B33: 21 | C33: 1 | D33: Não
A34: Dez | B34: 23 | C34: 1.4 | D34: Sim
A35: TOTAL/MÉDIA | B35: =SUM(B23:B34) -> 256 | C35: =ROUND(AVERAGE(C23:C34),2) -> 1.1
A37: GATILHOS DE PREVENTIVA POR CLASSE (herança cumulativa S ⊂ A ⊂ B)
A38: Classe | B38: Tipo gatilho | C38: Intervalo S | D38: Intervalo A | E38: Intervalo B
A39: Colhedora | B39: Horas | C39: 250 | D39: 500 | E39: 1000
A40: Trator | B40: Horas | C40: 250 | D40: 500 | E40: 1000
A41: Caminhão | B41: KM | C41: 10000 | D41: 20000 | E41: 40000
A42: Implemento | B42: Horas | C42: 300 | D42: 600
A43: Veículo Leve | B43: KM | C43: 10000 | D43: 20000

Sheet Frota
A1: FROTA — cadastro de ativos (motor usa: Status=Ativo, Uso Atual, Uso Semanal Safra/Entressafra, Intervalo)
A2: Uso semanal na unidade do gatilho (Horas ou KM). Intervalo = gatilho S do ativo. Linhas em branco são ignoradas.
A4: Nome | B4: Classe | C4: Modelo | D4: Fabricante | E4: Ano | F4: Filial | G4: Status | H4: Tipo Gatilho | I4: Uso Atual | J4: Uso Semanal Safra | K4: Uso Semanal Entressafra | L4: Intervalo Preventiva | M4: Garantia
A5: Colhedora CASE A8810 — 1035 | B5: Colhedora | C5: CASE A8810 | D5: CASE | E5: 2018 | F5: Sede | G5: Ativo | H5: Horas | I5: 5780 | J5: 45 | K5: 8 | L5: 250 | M5: false
A6: Colhedora CASE A8810 — 1036 | B6: Colhedora | C6: CASE A8810 | D6: CASE | E6: 2019 | F6: Sede | G6: Ativo | H6: Horas | I6: 4490 | J6: 44 | K6: 8 | L6: 250 | M6: false
A7: Colhedora JD CH570 — 1027 | B7: Colhedora | C7: JD CH570 | D7: John Deere | E7: 2017 | F7: Sede | G7: Ativo | H7: Horas | I7: 8860 | J7: 41 | K7: 8 | L7: 250 | M7: false
A8: Colhedora CASE A9000 — 1043 | B8: Colhedora | C8: CASE A9000 | D8: CASE | E8: 2021 | F8: Sede | G8: Ativo | H8: Horas | I8: 1200 | J8: 48 | K8: 8 | L8: 250 | M8: true
A9: Trator NH T7.315 — 401 | B9: Trator | C9: NH T7.315 | D9: New Holland | E9: 2020 | F9: Sede | G9: Ativo | H9: Horas | I9: 3200 | J9: 50 | K9: 12 | L9: 250 | M9: false
A10: Trator NH T7.315 — 402 | B10: Trator | C10: NH T7.315 | D10: New Holland | E10: 2021 | F10: Sede | G10: Ativo | H10: Horas | I10: 2100 | J10: 49 | K10: 12 | L10: 250 | M10: true
A11: Trator Case Puma 175 — 403 | B11: Trator | C11: Case Puma 175 | D11: CASE | E11: 2019 | F11: Sede | G11: Ativo | H11: Horas | I11: 4100 | J11: 46 | K11: 12 | L11: 250 | M11: false
A12: Caminhão Scania G480 — 2748 | B12: Caminhão | C12: Scania G 480 | D12: Scania | E12: 2015 | F12: Sede | G12: Ativo | H12: KM | I12: 304000 | J12: 1400 | K12: 500 | L12: 10000 | M12: false
A13: Caminhão Scania G540 — 2763 | B13: Caminhão | C13: Scania G 540 | D13: Scania | E13: 2020 | F13: Sede | G13: Ativo | H13: KM | I13: 85000 | J13: 1350 | K13: 480 | L13: 10000 | M13: true
A14: Transbordo Mambra 20t — 801 | B14: Implemento | C14: Transbordo 20t | D14: Mambra | E14: 2018 | F14: Sede | G14: Ativo | H14: Horas | I14: 4200 | J14: 40 | K14: 8 | L14: 300 | M14: false
A15: Implemento Distribuidor — 802 | B15: Implemento | C15: Dist. Calcário | D15: Siltres | E15: 2019 | F15: Sede | G15: Ativo | H15: Horas | I15: 2800 | J15: 32 | K15: 6 | L15: 300 | M15: false
A16: Fiat Toro — 5001 | B16: Veículo Leve | C16: Toro Endurance | D16: Fiat | E16: 2022 | F16: Sede | G16: Ativo | H16: KM | I16: 32000 | J16: 700 | K16: 400 | L16: 10000 | M16: true
A17: Toyota Hilux — 5002 | B17: Veículo Leve | C17: Hilux SR | D17: Toyota | E17: 2021 | F17: Sede | G17: Ativo | H17: KM | I17: 48000 | J17: 850 | K17: 450 | L17: 10000 | M17: false

Sheet Pessoas
A1: PESSOAS — equipe de manutenção (custo mensal e custo/hora idênticos ao app)
A4: Nome | B4: Cargo | C4: Oficina | D4: Turno | E4: Salário | F4: Encargos % | G4: Status | H4: Custo Mensal (R$) | I4: Custo/Hora (R$)
A5: Eduardo Lima | B5: Líder de Manutenção | C5: Mec. Oficina | D5: Diurno | E5: 7500 | F5: 72 | G5: Ativo | H5: =IF($A5="","",ROUND(E5*(1+F5/100),2)) -> 12900 | I5: =IF($A5="","",ROUND(H5/MAX(1,(Premissas!$B$35/12)*VLOOKUP(C5,Premissas!$A$14:$K$19,11,0)),2)) -> 112.6
A6: Carlos Rodrigues | B6: Mecânico Sênior | C6: Mec. Oficina | D6: Diurno | E6: 4500 | F6: 72 | G6: Ativo | H6: =IF($A6="","",ROUND(E6*(1+F6/100),2)) -> 7740 | I6: =IF($A6="","",ROUND(H6/MAX(1,(Premissas!$B$35/12)*VLOOKUP(C6,Premissas!$A$14:$K$19,11,0)),2)) -> 67.56
A7: Marcos Ferreira | B7: Mecânico Pleno | C7: Mec. Oficina | D7: Diurno | E7: 3800 | F7: 72 | G7: Ativo | H7: =IF($A7="","",ROUND(E7*(1+F7/100),2)) -> 6536 | I7: =IF($A7="","",ROUND(H7/MAX(1,(Premissas!$B$35/12)*VLOOKUP(C7,Premissas!$A$14:$K$19,11,0)),2)) -> 57.05
A8: João Alves | B8: Mecânico Júnior | C8: Mec. Oficina | D8: Noturno | E8: 3200 | F8: 72 | G8: Ativo | H8: =IF($A8="","",ROUND(E8*(1+F8/100),2)) -> 5504 | I8: =IF($A8="","",ROUND(H8/MAX(1,(Premissas!$B$35/12)*VLOOKUP(C8,Premissas!$A$14:$K$19,11,0)),2)) -> 48.04
A9: André Souza | B9: Mecânico Socorrista | C9: Mec. Campo | D9: Safra | E9: 3800 | F9: 72 | G9: Ativo | H9: =IF($A9="","",ROUND(E9*(1+F9/100),2)) -> 6536 | I9: =IF($A9="","",ROUND(H9/MAX(1,(Premissas!$B$35/12)*VLOOKUP(C9,Premissas!$A$14:$K$19,11,0)),2)) -> 57.59
A10: Paulo Carvalho | B10: Mecânico Socorrista | C10: Mec. Campo | D10: Safra | E10: 3800 | F10: 72 | G10: Ativo | H10: =IF($A10="","",ROUND(E10*(1+F10/100),2)) -> 6536 | I10: =IF($A10="","",ROUND(H10/MAX(1,(Premissas!$B$35/12)*VLOOKUP(C10,Premissas!$A$14:$K$19,11,0)),2)) -> 57.59
A11: Roberto Santos | B11: Eletricista Sênior | C11: Elétrica | D11: Diurno | E11: 5000 | F11: 72 | G11: Ativo | H11: =IF($A11="","",ROUND(E11*(1+F11/100),2)) -> 8600 | I11: =IF($A11="","",ROUND(H11/MAX(1,(Premissas!$B$35/12)*VLOOKUP(C11,Premissas!$A$14:$K$19,11,0)),2)) -> 75.07
A12: Diego Costa | B12: Eletricista Pleno | C12: Elétrica | D12: Diurno | E12: 4200 | F12: 72 | G12: Ativo | H12: =IF($A12="","",ROUND(E12*(1+F12/100),2)) -> 7224 | I12: =IF($A12="","",ROUND(H12/MAX(1,(Premissas!$B$35/12)*VLOOKUP(C12,Premissas!$A$14:$K$19,11,0)),2)) -> 63.06
A13: Marcos Vieira | B13: Lubrificador | C13: Lubrificação | D13: Diurno | E13: 2800 | F13: 72 | G13: Ativo | H13: =IF($A13="","",ROUND(E13*(1+F13/100),2)) -> 4816 | I13: =IF($A13="","",ROUND(H13/MAX(1,(Premissas!$B$35/12)*VLOOKUP(C13,Premissas!$A$14:$K$19,11,0)),2)) -> 37.5
A14: Fábio Nascimento | B14: Lubrificador | C14: Lubrificação | D14: Noturno | E14: 2800 | F14: 72 | G14: Ativo | H14: =IF($A14="","",ROUND(E14*(1+F14/100),2)) -> 4816 | I14: =IF($A14="","",ROUND(H14/MAX(1,(Premissas!$B$35/12)*VLOOKUP(C14,Premissas!$A$14:$K$19,11,0)),2)) -> 37.5
A15: João Borges | B15: Borracheiro | C15: Borracharia | D15: Diurno | E15: 3100 | F15: 72 | G15: Ativo | H15: =IF($A15="","",ROUND(E15*(1+F15/100),2)) -> 5332 | I15: =IF($A15="","",ROUND(H15/MAX(1,(Premissas!$B$35/12)*VLOOKUP(C15,Premissas!$A$14:$K$19,11,0)),2)) -> 43.54
A16: Sérgio Monteiro | B16: Soldador/Caldeireiro Sr. | C16: Caldeiraria | D16: Diurno | E16: 4200 | F16: 72 | G16: Ativo | H16: =IF($A16="","",ROUND(E16*(1+F16/100),2)) -> 7224 | I16: =IF($A16="","",ROUND(H16/MAX(1,(Premissas!$B$35/12)*VLOOKUP(C16,Premissas!$A$14:$K$19,11,0)),2)) -> 64.75
A17: Antônio Silva | B17: Soldador Pleno | C17: Caldeiraria | D17: Diurno | E17: 3500 | F17: 72 | G17: Ativo | H17: =IF($A17="","",ROUND(E17*(1+F17/100),2)) -> 6020 | I17: =IF($A17="","",ROUND(H17/MAX(1,(Premissas!$B$35/12)*VLOOKUP(C17,Premissas!$A$14:$K$19,11,0)),2)) -> 53.96
H18: =IF($A18="","",ROUND(E18*(1+F18/100),2)) | I18: =IF($A18="","",ROUND(H18/MAX(1,(Premissas!$B$35/12)*VLOOKUP(C18,Premissas!$A$14:$K$19,11,0)),2))
H19: =IF($A19="","",ROUND(E19*(1+F19/100),2)) | I19: =IF($A19="","",ROUND(H19/MAX(1,(Premissas!$B$35/12)*VLOOKUP(C19,Premissas!$A$14:$K$19,11,0)),2))
H20: =IF($A20="","",ROUND(E20*(1+F20/100),2)) | I20: =IF($A20="","",ROUND(H20/MAX(1,(Premissas!$B$35/12)*VLOOKUP(C20,Premissas!$A$14:$K$19,11,0)),2))
H21: =IF($A21="","",ROUND(E21*(1+F21/100),2)) | I21: =IF($A21="","",ROUND(H21/MAX(1,(Premissas!$B$35/12)*VLOOKUP(C21,Premissas!$A$14:$K$19,11,0)),2))
H22: =IF($A22="","",ROUND(E22*(1+F22/100),2)) | I22: =IF($A22="","",ROUND(H22/MAX(1,(Premissas!$B$35/12)*VLOOKUP(C22,Premissas!$A$14:$K$19,11,0)),2))
H23: =IF($A23="","",ROUND(E23*(1+F23/100),2)) | I23: =IF($A23="","",ROUND(H23/MAX(1,(Premissas!$B$35/12)*VLOOKUP(C23,Premissas!$A$14:$K$19,11,0)),2))
H24: =IF($A24="","",ROUND(E24*(1+F24/100),2)) | I24: =IF($A24="","",ROUND(H24/MAX(1,(Premissas!$B$35/12)*VLOOKUP(C24,Premissas!$A$14:$K$19,11,0)),2))
H25: =IF($A25="","",ROUND(E25*(1+F25/100),2)) | I25: =IF($A25="","",ROUND(H25/MAX(1,(Premissas!$B$35/12)*VLOOKUP(C25,Premissas!$A$14:$K$19,11,0)),2))
H26: =IF($A26="","",ROUND(E26*(1+F26/100),2)) | I26: =IF($A26="","",ROUND(H26/MAX(1,(Premissas!$B$35/12)*VLOOKUP(C26,Premissas!$A$14:$K$19,11,0)),2))
H27: =IF($A27="","",ROUND(E27*(1+F27/100),2)) | I27: =IF($A27="","",ROUND(H27/MAX(1,(Premissas!$B$35/12)*VLOOKUP(C27,Premissas!$A$14:$K$19,11,0)),2))
H28: =IF($A28="","",ROUND(E28*(1+F28/100),2)) | I28: =IF($A28="","",ROUND(H28/MAX(1,(Premissas!$B$35/12)*VLOOKUP(C28,Premissas!$A$14:$K$19,11,0)),2))
H29: =IF($A29="","",ROUND(E29*(1+F29/100),2)) | I29: =IF($A29="","",ROUND(H29/MAX(1,(Premissas!$B$35/12)*VLOOKUP(C29,Premissas!$A$14:$K$19,11,0)),2))
... H44: =IF($A44="","",ROUND(E44*(1+F44/100),2)) | I44: =IF($A44="","",ROUND(H44/MAX(1,(Premissas!$B$35/12)*VLOOKUP(C44,Premissas!$A$14:$K$19,11,0)),2))

Sheet Checklist
A1: CHECKLIST — atividades por classe × tipo de preventiva (HH alimenta o cronograma com herança cumulativa)
A4: Checklist | B4: Tipo Prev | C4: Classe | D4: Oficina | E4: Atividade | F4: Cargo | G4: Tipo Ativ | H4: HH | I4: Insumo | J4: Qtd Insumo | K4: Un | L4: Peça | M4: Qtd Peça
A5: Rev. S — Colhedora (250h) | B5: S | C5: Colhedora | D5: Mec. Oficina | E5: Troca de óleo do motor | F5: Mecânico Sr. | G5: Troca | H5: 1.5 | I5: Óleo Motor 15W40 | J5: 20 | K5: L | L5: Filtro de óleo | M5: 1
A6: Rev. S — Colhedora (250h) | B6: S | C6: Colhedora | D6: Mec. Oficina | E6: Troca filtro de combustível | F6: Mecânico Pleno | G6: Troca | H6: 0.5 | J6: 0 | L6: Filtro combustível | M6: 1
A7: Rev. S — Colhedora (250h) | B7: S | C7: Colhedora | D7: Mec. Oficina | E7: Inspeção sistema hidráulico | F7: Mecânico Sr. | G7: Inspeção | H7: 1 | J7: 0 | M7: 0
A8: Rev. S — Colhedora (250h) | B8: S | C8: Colhedora | D8: Mec. Oficina | E8: Verificação tensão correntes/correias | F8: Mecânico Pleno | G8: Verificação | H8: 0.75 | J8: 0 | M8: 0
A9: Rev. S — Colhedora (250h) | B9: S | C9: Colhedora | D9: Lubrificação | E9: Lubrificação de pontos fixos | F9: Lubrificador | G9: Lubrificação | H9: 0.75 | I9: Graxa EP2 | J9: 0.5 | K9: kg | M9: 0
A10: Rev. S — Colhedora (250h) | B10: S | C10: Colhedora | D10: Elétrica | E10: Inspeção elétrica geral | F10: Eletricista | G10: Inspeção | H10: 1 | J10: 0 | M10: 0
A11: Rev. A — Colhedora (500h) | B11: A | C11: Colhedora | D11: Mec. Oficina | E11: Troca óleo motor + hidráulico + filtros | F11: Mecânico Sr. | G11: Troca | H11: 3 | I11: Óleo Motor 15W40 | J11: 20 | K11: L | L11: Kit filtros (3 un) | M11: 3
A12: Rev. A — Colhedora (500h) | B12: A | C12: Colhedora | D12: Mec. Oficina | E12: Regulagem sistema de corte | F12: Mecânico Sr. | G12: Regulagem | H12: 2 | J12: 0 | M12: 0
A13: Rev. A — Colhedora (500h) | B13: A | C13: Colhedora | D13: Mec. Oficina | E13: Inspeção e ajuste caixa de câmbio | F13: Mecânico Sr. | G13: Ajuste | H13: 1.5 | I13: Óleo câmbio SAE 90 | J13: 5 | K13: L | M13: 0
A14: Rev. A — Colhedora (500h) | B14: A | C14: Colhedora | D14: Elétrica | E14: Verificação sistema elétrico completo | F14: Eletricista Sr. | G14: Verificação | H14: 2 | J14: 0 | M14: 0
A15: Rev. A — Colhedora (500h) | B15: A | C15: Colhedora | D15: Lubrificação | E15: Lubrificação e troca graxa pivôs | F15: Lubrificador | G15: Lubrificação | H15: 1 | I15: Graxa EP2 | J15: 1 | K15: kg | M15: 0
A16: Rev. S — Trator (250h) | B16: S | C16: Trator | D16: Mec. Oficina | E16: Troca óleo motor | F16: Mecânico Pleno | G16: Troca | H16: 1 | I16: Óleo Motor 10W40 | J16: 12 | K16: L | L16: Filtro de óleo | M16: 1
A17: Rev. S — Trator (250h) | B17: S | C17: Trator | D17: Mec. Oficina | E17: Verificação freios e embreagem | F17: Mecânico Pleno | G17: Verificação | H17: 0.5 | J17: 0 | M17: 0
A18: Rev. S — Trator (250h) | B18: S | C18: Trator | D18: Lubrificação | E18: Lubrificação pontos fixos | F18: Lubrificador | G18: Lubrificação | H18: 0.5 | I18: Graxa EP2 | J18: 0.3 | K18: kg | M18: 0
A19: Rev. S — Caminhão (10Kkm) | B19: S | C19: Caminhão | D19: Mec. Oficina | E19: Troca óleo motor + filtro | F19: Mecânico Pleno | G19: Troca | H19: 1.5 | I19: Óleo Motor 15W40 | J19: 25 | K19: L | L19: Filtro de óleo | M19: 1
A20: Rev. S — Caminhão (10Kkm) | B20: S | C20: Caminhão | D20: Mec. Oficina | E20: Inspeção sistema de freios | F20: Mecânico Pleno | G20: Inspeção | H20: 0.75 | J20: 0 | M20: 0
A21: Rev. S — Caminhão (10Kkm) | B21: S | C21: Caminhão | D21: Borracharia | E21: Calibragem e inspeção de pneus | F21: Borracheiro | G21: Calibragem | H21: 0.5 | J21: 0 | M21: 0
A22: Rev. S — Caminhão (10Kkm) | B22: S | C22: Caminhão | D22: Lubrificação | E22: Lubrificação chassi e 5ª roda | F22: Lubrificador | G22: Lubrificação | H22: 0.5 | I22: Graxa EP2 | J22: 0.5 | K22: kg | M22: 0
A23: Rev. A — Caminhão (20Kkm) | B23: A | C23: Caminhão | D23: Mec. Oficina | E23: Troca óleo + filtros + filtro ar | F23: Mecânico Sr. | G23: Troca | H23: 2.5 | I23: Óleo Motor 15W40 | J23: 25 | K23: L | L23: Kit filtros (2un) | M23: 2
A24: Rev. A — Caminhão (20Kkm) | B24: A | C24: Caminhão | D24: Mec. Oficina | E24: Regulagem freios e embreagem | F24: Mecânico Sr. | G24: Regulagem | H24: 1.5 | I24: Fluido de freio | J24: 0.5 | K24: L | M24: 0
A25: Rev. A — Caminhão (20Kkm) | B25: A | C25: Caminhão | D25: Elétrica | E25: Verificação sistema elétrico + bateria | F25: Eletricista | G25: Verificação | H25: 1 | J25: 0 | M25: 0
A26: Rev. S — Implemento (300h) | B26: S | C26: Implemento | D26: Caldeiraria | E26: Inspeção estrutural e solda | F26: Soldador Sr. | G26: Inspeção | H26: 1.5 | J26: 0 | M26: 0
A27: Rev. S — Implemento (300h) | B27: S | C27: Implemento | D27: Mec. Oficina | E27: Verificação sistema hidráulico | F27: Mecânico Pleno | G27: Verificação | H27: 0.75 | I27: Óleo hidráulico | J27: 2 | K27: L | M27: 0
A28: Rev. S — Implemento (300h) | B28: S | C28: Implemento | D28: Lubrificação | E28: Lubrificação rolamentos e articulações | F28: Lubrificador | G28: Lubrificação | H28: 0.5 | I28: Graxa EP2 | J28: 0.3 | K28: kg | M28: 0

Sheet Semanas
A1: AUXILIAR — 52 semanas a partir do início da safra
A2: Semana | B2: Data início | C2: Data fim | D2: Safra (1/0) | E2: Mês (1-12)
A3: 1 | B3: =DATE(VALUE(LEFT(Premissas!$G$21,4)),VALUE(MID(Premissas!$G$21,6,2)),VALUE(RIGHT(Premissas!$G$21,2))) -> 45748 | C3: =B3+6 -> 45754 | D3: =IF(AND(B3>=$B$3,B3<=DATE(VALUE(LEFT(Premissas!$G$22,4)),VALUE(MID(Premissas!$G$22,6,2)),VALUE(RIGHT(Premissas!$G$22,2)))),1,0) -> 1 | E3: =MONTH(B3) -> 4
A4: 2 | B4: =B3+7 -> 45755 | C4: =B4+6 -> 45761 | D4: =IF(AND(B4>=$B$3,B4<=DATE(VALUE(LEFT(Premissas!$G$22,4)),VALUE(MID(Premissas!$G$22,6,2)),VALUE(RIGHT(Premissas!$G$22,2)))),1,0) -> 1 | E4: =MONTH(B4) -> 4
A5: 3 | B5: =B4+7 -> 45762 | C5: =B5+6 -> 45768 | D5: =IF(AND(B5>=$B$3,B5<=DATE(VALUE(LEFT(Premissas!$G$22,4)),VALUE(MID(Premissas!$G$22,6,2)),VALUE(RIGHT(Premissas!$G$22,2)))),1,0) -> 1 | E5: =MONTH(B5) -> 4
A6: 4 | B6: =B5+7 -> 45769 | C6: =B6+6 -> 45775 | D6: =IF(AND(B6>=$B$3,B6<=DATE(VALUE(LEFT(Premissas!$G$22,4)),VALUE(MID(Premissas!$G$22,6,2)),VALUE(RIGHT(Premissas!$G$22,2)))),1,0) -> 1 | E6: =MONTH(B6) -> 4
A7: 5 | B7: =B6+7 -> 45776 | C7: =B7+6 -> 45782 | D7: =IF(AND(B7>=$B$3,B7<=DATE(VALUE(LEFT(Premissas!$G$22,4)),VALUE(MID(Premissas!$G$22,6,2)),VALUE(RIGHT(Premissas!$G$22,2)))),1,0) -> 1 | E7: =MONTH(B7) -> 4
A8: 6 | B8: =B7+7 -> 45783 | C8: =B8+6 -> 45789 | D8: =IF(AND(B8>=$B$3,B8<=DATE(VALUE(LEFT(Premissas!$G$22,4)),VALUE(MID(Premissas!$G$22,6,2)),VALUE(RIGHT(Premissas!$G$22,2)))),1,0) -> 1 | E8: =MONTH(B8) -> 5
A9: 7 | B9: =B8+7 -> 45790 | C9: =B9+6 -> 45796 | D9: =IF(AND(B9>=$B$3,B9<=DATE(VALUE(LEFT(Premissas!$G$22,4)),VALUE(MID(Premissas!$G$22,6,2)),VALUE(RIGHT(Premissas!$G$22,2)))),1,0) -> 1 | E9: =MONTH(B9) -> 5
A10: 8 | B10: =B9+7 -> 45797 | C10: =B10+6 -> 45803 | D10: =IF(AND(B10>=$B$3,B10<=DATE(VALUE(LEFT(Premissas!$G$22,4)),VALUE(MID(Premissas!$G$22,6,2)),VALUE(RIGHT(Premissas!$G$22,2)))),1,0) -> 1 | E10: =MONTH(B10) -> 5
A11: 9 | B11: =B10+7 -> 45804 | C11: =B11+6 -> 45810 | D11: =IF(AND(B11>=$B$3,B11<=DATE(VALUE(LEFT(Premissas!$G$22,4)),VALUE(MID(Premissas!$G$22,6,2)),VALUE(RIGHT(Premissas!$G$22,2)))),1,0) -> 1 | E11: =MONTH(B11) -> 5
A12: 10 | B12: =B11+7 -> 45811 | C12: =B12+6 -> 45817 | D12: =IF(AND(B12>=$B$3,B12<=DATE(VALUE(LEFT(Premissas!$G$22,4)),VALUE(MID(Premissas!$G$22,6,2)),VALUE(RIGHT(Premissas!$G$22,2)))),1,0) -> 1 | E12: =MONTH(B12) -> 6
A13: 11 | B13: =B12+7 -> 45818 | C13: =B13+6 -> 45824 | D13: =IF(AND(B13>=$B$3,B13<=DATE(VALUE(LEFT(Premissas!$G$22,4)),VALUE(MID(Premissas!$G$22,6,2)),VALUE(RIGHT(Premissas!$G$22,2)))),1,0) -> 1 | E13: =MONTH(B13) -> 6
A14: 12 | B14: =B13+7 -> 45825 | C14: =B14+6 -> 45831 | D14: =IF(AND(B14>=$B$3,B14<=DATE(VALUE(LEFT(Premissas!$G$22,4)),VALUE(MID(Premissas!$G$22,6,2)),VALUE(RIGHT(Premissas!$G$22,2)))),1,0) -> 1 | E14: =MONTH(B14) -> 6
A15: 13 | B15: =B14+7 -> 45832 | C15: =B15+6 -> 45838 | D15: =IF(AND(B15>=$B$3,B15<=DATE(VALUE(LEFT(Premissas!$G$22,4)),VALUE(MID(Premissas!$G$22,6,2)),VALUE(RIGHT(Premissas!$G$22,2)))),1,0) -> 1 | E15: =MONTH(B15) -> 6
... A54: 52 | B54: =B53+7 -> 46105 | C54: =B54+6 -> 46111 | D54: =IF(AND(B54>=$B$3,B54<=DATE(VALUE(LEFT(Premissas!$G$22,4)),VALUE(MID(Premissas!$G$22,6,2)),VALUE(RIGHT(Premissas!$G$22,2)))),1,0) -> 0 | E54: =MONTH(B54) -> 3

Sheet Cron_Uso
A1: AUXILIAR — uso acumulado por ativo × semana (fim da semana)
A2: Mês → | B2: =INDEX(Semanas!$E$3:$E$54,1) -> 4 | C2: =INDEX(Semanas!$E$3:$E$54,2) -> 4 | D2: =INDEX(Semanas!$E$3:$E$54,3) -> 4 | E2: =INDEX(Semanas!$E$3:$E$54,4) -> 4 | F2: =INDEX(Semanas!$E$3:$E$54,5) -> 4 | G2: =INDEX(Semanas!$E$3:$E$54,6) -> 5 | H2: =INDEX(Semanas!$E$3:$E$54,7) -> 5 | I2: =INDEX(Semanas!$E$3:$E$54,8) -> 5 | J2: =INDEX(Semanas!$E$3:$E$54,9) -> 5 | K2: =INDEX(Semanas!$E$3:$E$54,10) -> 6 | L2: =INDEX(Semanas!$E$3:$E$54,11) -> 6 | M2: =INDEX(Semanas!$E$3:$E$54,12) -> 6 | N2: =INDEX(Semanas!$E$3:$E$54,13) -> 6 | O2: =INDEX(Semanas!$E$3:$E$54,14) -> 7 | P2: =INDEX(Semanas!$E$3:$E$54,15) -> 7 | Q2: =INDEX(Semanas!$E$3:$E$54,16) -> 7 | R2: =INDEX(Semanas!$E$3:$E$54,17) -> 7 | S2: =INDEX(Semanas!$E$3:$E$54,18) -> 7 | T2: =INDEX(Semanas!$E$3:$E$54,19) -> 8 | U2: =INDEX(Semanas!$E$3:$E$54,20) -> 8 | V2: =INDEX(Semanas!$E$3:$E$54,21) -> 8 | W2: =INDEX(Semanas!$E$3:$E$54,22) -> 8 | X2: =INDEX(Semanas!$E$3:$E$54,23) -> 9 | Y2: =INDEX(Semanas!$E$3:$E$54,24) -> 9 | Z2: =INDEX(Semanas!$E$3:$E$54,25) -> 9 | AA2: =INDEX(Semanas!$E$3:$E$54,26) -> 9 | AB2: =INDEX(Semanas!$E$3:$E$54,27) -> 9 | AC2: =INDEX(Semanas!$E$3:$E$54,28) -> 10 | AD2: =INDEX(Semanas!$E$3:$E$54,29) -> 10 | AE2: =INDEX(Semanas!$E$3:$E$54,30) -> 10 | AF2: =INDEX(Semanas!$E$3:$E$54,31) -> 10 | AG2: =INDEX(Semanas!$E$3:$E$54,32) -> 11 | AH2: =INDEX(Semanas!$E$3:$E$54,33) -> 11 | AI2: =INDEX(Semanas!$E$3:$E$54,34) -> 11 | AJ2: =INDEX(Semanas!$E$3:$E$54,35) -> 11 | AK2: =INDEX(Semanas!$E$3:$E$54,36) -> 12 | AL2: =INDEX(Semanas!$E$3:$E$54,37) -> 12 | AM2: =INDEX(Semanas!$E$3:$E$54,38) -> 12 | AN2: =INDEX(Semanas!$E$3:$E$54,39) -> 12 | AO2: =INDEX(Semanas!$E$3:$E$54,40) -> 12 | AP2: =INDEX(Semanas!$E$3:$E$54,41) -> 1 | AQ2: =INDEX(Semanas!$E$3:$E$54,42) -> 1 | AR2: =INDEX(Semanas!$E$3:$E$54,43) -> 1 | AS2: =INDEX(Semanas!$E$3:$E$54,44) -> 1 | AT2: =INDEX(Semanas!$E$3:$E$54,45) -> 2 | AU2: =INDEX(Semanas!$E$3:$E$54,46) -> 2 | AV2: =INDEX(Semanas!$E$3:$E$54,47) -> 2 | AW2: =INDEX(Semanas!$E$3:$E$54,48) -> 2 | AX2: =INDEX(Semanas!$E$3:$E$54,49) -> 3 | AY2: =INDEX(Semanas!$E$3:$E$54,50) -> 3 | AZ2: =INDEX(Semanas!$E$3:$E$54,51) -> 3 | BA2: =INDEX(Semanas!$E$3:$E$54,52) -> 3
A3: Safra → | B3: =INDEX(Semanas!$D$3:$D$54,1) -> 1 | C3: =INDEX(Semanas!$D$3:$D$54,2) -> 1 | D3: =INDEX(Semanas!$D$3:$D$54,3) -> 1 | E3: =INDEX(Semanas!$D$3:$D$54,4) -> 1 | F3: =INDEX(Semanas!$D$3:$D$54,5) -> 1 | G3: =INDEX(Semanas!$D$3:$D$54,6) -> 1 | H3: =INDEX(Semanas!$D$3:$D$54,7) -> 1 | I3: =INDEX(Semanas!$D$3:$D$54,8) -> 1 | J3: =INDEX(Semanas!$D$3:$D$54,9) -> 1 | K3: =INDEX(Semanas!$D$3:$D$54,10) -> 1 | L3: =INDEX(Semanas!$D$3:$D$54,11) -> 1 | M3: =INDEX(Semanas!$D$3:$D$54,12) -> 1 | N3: =INDEX(Semanas!$D$3:$D$54,13) -> 1 | O3: =INDEX(Semanas!$D$3:$D$54,14) -> 1 | P3: =INDEX(Semanas!$D$3:$D$54,15) -> 1 | Q3: =INDEX(Semanas!$D$3:$D$54,16) -> 1 | R3: =INDEX(Semanas!$D$3:$D$54,17) -> 1 | S3: =INDEX(Semanas!$D$3:$D$54,18) -> 1 | T3: =INDEX(Semanas!$D$3:$D$54,19) -> 1 | U3: =INDEX(Semanas!$D$3:$D$54,20) -> 1 | V3: =INDEX(Semanas!$D$3:$D$54,21) -> 1 | W3: =INDEX(Semanas!$D$3:$D$54,22) -> 1 | X3: =INDEX(Semanas!$D$3:$D$54,23) -> 1 | Y3: =INDEX(Semanas!$D$3:$D$54,24) -> 1 | Z3: =INDEX(Semanas!$D$3:$D$54,25) -> 1 | AA3: =INDEX(Semanas!$D$3:$D$54,26) -> 1 | AB3: =INDEX(Semanas!$D$3:$D$54,27) -> 1 | AC3: =INDEX(Semanas!$D$3:$D$54,28) -> 1 | AD3: =INDEX(Semanas!$D$3:$D$54,29) -> 1 | AE3: =INDEX(Semanas!$D$3:$D$54,30) -> 1 | AF3: =INDEX(Semanas!$D$3:$D$54,31) -> 1 | AG3: =INDEX(Semanas!$D$3:$D$54,32) -> 1 | AH3: =INDEX(Semanas!$D$3:$D$54,33) -> 1 | AI3: =INDEX(Semanas!$D$3:$D$54,34) -> 1 | AJ3: =INDEX(Semanas!$D$3:$D$54,35) -> 1 | AK3: =INDEX(Semanas!$D$3:$D$54,36) -> 0 | AL3: =INDEX(Semanas!$D$3:$D$54,37) -> 0 | AM3: =INDEX(Semanas!$D$3:$D$54,38) -> 0 | AN3: =INDEX(Semanas!$D$3:$D$54,39) -> 0 | AO3: =INDEX(Semanas!$D$3:$D$54,40) -> 0 | AP3: =INDEX(Semanas!$D$3:$D$54,41) -> 0 | AQ3: =INDEX(Semanas!$D$3:$D$54,42) -> 0 | AR3: =INDEX(Semanas!$D$3:$D$54,43) -> 0 | AS3: =INDEX(Semanas!$D$3:$D$54,44) -> 0 | AT3: =INDEX(Semanas!$D$3:$D$54,45) -> 0 | AU3: =INDEX(Semanas!$D$3:$D$54,46) -> 0 | AV3: =INDEX(Semanas!$D$3:$D$54,47) -> 0 | AW3: =INDEX(Semanas!$D$3:$D$54,48) -> 0 | AX3: =INDEX(Semanas!$D$3:$D$54,49) -> 0 | AY3: =INDEX(Semanas!$D$3:$D$54,50) -> 0 | AZ3: =INDEX(Semanas!$D$3:$D$54,51) -> 0 | BA3: =INDEX(Semanas!$D$3:$D$54,52) -> 0
A4: Ativo | B4: S01 | C4: S02 | D4: S03 | E4: S04 | F4: S05 | G4: S06 | H4: S07 | I4: S08 | J4: S09 | K4: S10 | L4: S11 | M4: S12 | N4: S13 | O4: S14 | P4: S15 | Q4: S16 | R4: S17 | S4: S18 | T4: S19 | U4: S20 | V4: S21 | W4: S22 | X4: S23 | Y4: S24 | Z4: S25 | AA4: S26 | AB4: S27 | AC4: S28 | AD4: S29 | AE4: S30 | AF4: S31 | AG4: S32 | AH4: S33 | AI4: S34 | AJ4: S35 | AK4: S36 | AL4: S37 | AM4: S38 | AN4: S39 | AO4: S40 | AP4: S41 | AQ4: S42 | AR4: S43 | AS4: S44 | AT4: S45 | AU4: S46 | AV4: S47 | AW4: S48 | AX4: S49 | AY4: S50 | AZ4: S51 | BA4: S52
A5: =IF(Frota!$A5="","",Frota!$A5) -> Colhedora CASE A8810 — 1035 | B5: =IF(OR(Frota!$A5="",Frota!$G5<>"Ativo",N(Frota!$L5)=0),"",ROUND(Frota!$I5+IF(B$3=1,N(Frota!$J5),N(Frota!$K5)),2)) -> 5825 | C5: =IF(B5="","",ROUND(B5+IF(C$3=1,N(Frota!$J5),N(Frota!$K5)),2)) -> 5870 | D5: =IF(C5="","",ROUND(C5+IF(D$3=1,N(Frota!$J5),N(Frota!$K5)),2)) -> 5915 | E5: =IF(D5="","",ROUND(D5+IF(E$3=1,N(Frota!$J5),N(Frota!$K5)),2)) -> 5960 | F5: =IF(E5="","",ROUND(E5+IF(F$3=1,N(Frota!$J5),N(Frota!$K5)),2)) -> 6005 | G5: =IF(F5="","",ROUND(F5+IF(G$3=1,N(Frota!$J5),N(Frota!$K5)),2)) -> 6050 | H5: =IF(G5="","",ROUND(G5+IF(H$3=1,N(Frota!$J5),N(Frota!$K5)),2)) -> 6095 | I5: =IF(H5="","",ROUND(H5+IF(I$3=1,N(Frota!$J5),N(Frota!$K5)),2)) -> 6140 | J5: =IF(I5="","",ROUND(I5+IF(J$3=1,N(Frota!$J5),N(Frota!$K5)),2)) -> 6185 | ... BA5: =IF(AZ5="","",ROUND(AZ5+IF(BA$3=1,N(Frota!$J5),N(Frota!$K5)),2)) -> 7491
A6: =IF(Frota!$A6="","",Frota!$A6) -> Colhedora CASE A8810 — 1036 | B6: =IF(OR(Frota!$A6="",Frota!$G6<>"Ativo",N(Frota!$L6)=0),"",ROUND(Frota!$I6+IF(B$3=1,N(Frota!$J6),N(Frota!$K6)),2)) -> 4534 | C6: =IF(B6="","",ROUND(B6+IF(C$3=1,N(Frota!$J6),N(Frota!$K6)),2)) -> 4578 | D6: =IF(C6="","",ROUND(C6+IF(D$3=1,N(Frota!$J6),N(Frota!$K6)),2)) -> 4622 | E6: =IF(D6="","",ROUND(D6+IF(E$3=1,N(Frota!$J6),N(Frota!$K6)),2)) -> 4666 | F6: =IF(E6="","",ROUND(E6+IF(F$3=1,N(Frota!$J6),N(Frota!$K6)),2)) -> 4710 | G6: =IF(F6="","",ROUND(F6+IF(G$3=1,N(Frota!$J6),N(Frota!$K6)),2)) -> 4754 | H6: =IF(G6="","",ROUND(G6+IF(H$3=1,N(Frota!$J6),N(Frota!$K6)),2)) -> 4798 | I6: =IF(H6="","",ROUND(H6+IF(I$3=1,N(Frota!$J6),N(Frota!$K6)),2)) -> 4842 | J6: =IF(I6="","",ROUND(I6+IF(J$3=1,N(Frota!$J6),N(Frota!$K6)),2)) -> 4886 | ... BA6: =IF(AZ6="","",ROUND(AZ6+IF(BA$3=1,N(Frota!$J6),N(Frota!$K6)),2)) -> 6166
A7: =IF(Frota!$A7="","",Frota!$A7) -> Colhedora JD CH570 — 1027 | B7: =IF(OR(Frota!$A7="",Frota!$G7<>"Ativo",N(Frota!$L7)=0),"",ROUND(Frota!$I7+IF(B$3=1,N(Frota!$J7),N(Frota!$K7)),2)) -> 8901 | C7: =IF(B7="","",ROUND(B7+IF(C$3=1,N(Frota!$J7),N(Frota!$K7)),2)) -> 8942 | D7: =IF(C7="","",ROUND(C7+IF(D$3=1,N(Frota!$J7),N(Frota!$K7)),2)) -> 8983 | E7: =IF(D7="","",ROUND(D7+IF(E$3=1,N(Frota!$J7),N(Frota!$K7)),2)) -> 9024 | F7: =IF(E7="","",ROUND(E7+IF(F$3=1,N(Frota!$J7),N(Frota!$K7)),2)) -> 9065 | G7: =IF(F7="","",ROUND(F7+IF(G$3=1,N(Frota!$J7),N(Frota!$K7)),2)) -> 9106 | H7: =IF(G7="","",ROUND(G7+IF(H$3=1,N(Frota!$J7),N(Frota!$K7)),2)) -> 9147 | I7: =IF(H7="","",ROUND(H7+IF(I$3=1,N(Frota!$J7),N(Frota!$K7)),2)) -> 9188 | J7: =IF(I7="","",ROUND(I7+IF(J$3=1,N(Frota!$J7),N(Frota!$K7)),2)) -> 9229 | ... BA7: =IF(AZ7="","",ROUND(AZ7+IF(BA$3=1,N(Frota!$J7),N(Frota!$K7)),2)) -> 10431
A8: =IF(Frota!$A8="","",Frota!$A8) -> Colhedora CASE A9000 — 1043 | B8: =IF(OR(Frota!$A8="",Frota!$G8<>"Ativo",N(Frota!$L8)=0),"",ROUND(Frota!$I8+IF(B$3=1,N(Frota!$J8),N(Frota!$K8)),2)) -> 1248 | C8: =IF(B8="","",ROUND(B8+IF(C$3=1,N(Frota!$J8),N(Frota!$K8)),2)) -> 1296 | D8: =IF(C8="","",ROUND(C8+IF(D$3=1,N(Frota!$J8),N(Frota!$K8)),2)) -> 1344 | E8: =IF(D8="","",ROUND(D8+IF(E$3=1,N(Frota!$J8),N(Frota!$K8)),2)) -> 1392 | F8: =IF(E8="","",ROUND(E8+IF(F$3=1,N(Frota!$J8),N(Frota!$K8)),2)) -> 1440 | G8: =IF(F8="","",ROUND(F8+IF(G$3=1,N(Frota!$J8),N(Frota!$K8)),2)) -> 1488 | H8: =IF(G8="","",ROUND(G8+IF(H$3=1,N(Frota!$J8),N(Frota!$K8)),2)) -> 1536 | I8: =IF(H8="","",ROUND(H8+IF(I$3=1,N(Frota!$J8),N(Frota!$K8)),2)) -> 1584 | J8: =IF(I8="","",ROUND(I8+IF(J$3=1,N(Frota!$J8),N(Frota!$K8)),2)) -> 1632 | ... BA8: =IF(AZ8="","",ROUND(AZ8+IF(BA$3=1,N(Frota!$J8),N(Frota!$K8)),2)) -> 3016
A9: =IF(Frota!$A9="","",Frota!$A9) -> Trator NH T7.315 — 401 | B9: =IF(OR(Frota!$A9="",Frota!$G9<>"Ativo",N(Frota!$L9)=0),"",ROUND(Frota!$I9+IF(B$3=1,N(Frota!$J9),N(Frota!$K9)),2)) -> 3250 | C9: =IF(B9="","",ROUND(B9+IF(C$3=1,N(Frota!$J9),N(Frota!$K9)),2)) -> 3300 | D9: =IF(C9="","",ROUND(C9+IF(D$3=1,N(Frota!$J9),N(Frota!$K9)),2)) -> 3350 | E9: =IF(D9="","",ROUND(D9+IF(E$3=1,N(Frota!$J9),N(Frota!$K9)),2)) -> 3400 | F9: =IF(E9="","",ROUND(E9+IF(F$3=1,N(Frota!$J9),N(Frota!$K9)),2)) -> 3450 | G9: =IF(F9="","",ROUND(F9+IF(G$3=1,N(Frota!$J9),N(Frota!$K9)),2)) -> 3500 | H9: =IF(G9="","",ROUND(G9+IF(H$3=1,N(Frota!$J9),N(Frota!$K9)),2)) -> 3550 | I9: =IF(H9="","",ROUND(H9+IF(I$3=1,N(Frota!$J9),N(Frota!$K9)),2)) -> 3600 | J9: =IF(I9="","",ROUND(I9+IF(J$3=1,N(Frota!$J9),N(Frota!$K9)),2)) -> 3650 | ... BA9: =IF(AZ9="","",ROUND(AZ9+IF(BA$3=1,N(Frota!$J9),N(Frota!$K9)),2)) -> 5154
A10: =IF(Frota!$A10="","",Frota!$A10) -> Trator NH T7.315 — 402 | B10: =IF(OR(Frota!$A10="",Frota!$G10<>"Ativo",N(Frota!$L10)=0),"",ROUND(Frota!$I10+IF(B$3=1,N(Frota!$J10),N(Frota!$K10)),2)) -> 2149 | C10: =IF(B10="","",ROUND(B10+IF(C$3=1,N(Frota!$J10),N(Frota!$K10)),2)) -> 2198 | D10: =IF(C10="","",ROUND(C10+IF(D$3=1,N(Frota!$J10),N(Frota!$K10)),2)) -> 2247 | E10: =IF(D10="","",ROUND(D10+IF(E$3=1,N(Frota!$J10),N(Frota!$K10)),2)) -> 2296 | F10: =IF(E10="","",ROUND(E10+IF(F$3=1,N(Frota!$J10),N(Frota!$K10)),2)) -> 2345 | G10: =IF(F10="","",ROUND(F10+IF(G$3=1,N(Frota!$J10),N(Frota!$K10)),2)) -> 2394 | H10: =IF(G10="","",ROUND(G10+IF(H$3=1,N(Frota!$J10),N(Frota!$K10)),2)) -> 2443 | I10: =IF(H10="","",ROUND(H10+IF(I$3=1,N(Frota!$J10),N(Frota!$K10)),2)) -> 2492 | J10: =IF(I10="","",ROUND(I10+IF(J$3=1,N(Frota!$J10),N(Frota!$K10)),2)) -> 2541 | ... BA10: =IF(AZ10="","",ROUND(AZ10+IF(BA$3=1,N(Frota!$J10),N(Frota!$K10)),2)) -> 4019
A11: =IF(Frota!$A11="","",Frota!$A11) -> Trator Case Puma 175 — 403 | B11: =IF(OR(Frota!$A11="",Frota!$G11<>"Ativo",N(Frota!$L11)=0),"",ROUND(Frota!$I11+IF(B$3=1,N(Frota!$J11),N(Frota!$K11)),2)) -> 4146 | C11: =IF(B11="","",ROUND(B11+IF(C$3=1,N(Frota!$J11),N(Frota!$K11)),2)) -> 4192 | D11: =IF(C11="","",ROUND(C11+IF(D$3=1,N(Frota!$J11),N(Frota!$K11)),2)) -> 4238 | E11: =IF(D11="","",ROUND(D11+IF(E$3=1,N(Frota!$J11),N(Frota!$K11)),2)) -> 4284 | F11: =IF(E11="","",ROUND(E11+IF(F$3=1,N(Frota!$J11),N(Frota!$K11)),2)) -> 4330 | G11: =IF(F11="","",ROUND(F11+IF(G$3=1,N(Frota!$J11),N(Frota!$K11)),2)) -> 4376 | H11: =IF(G11="","",ROUND(G11+IF(H$3=1,N(Frota!$J11),N(Frota!$K11)),2)) -> 4422 | I11: =IF(H11="","",ROUND(H11+IF(I$3=1,N(Frota!$J11),N(Frota!$K11)),2)) -> 4468 | J11: =IF(I11="","",ROUND(I11+IF(J$3=1,N(Frota!$J11),N(Frota!$K11)),2)) -> 4514 | ... BA11: =IF(AZ11="","",ROUND(AZ11+IF(BA$3=1,N(Frota!$J11),N(Frota!$K11)),2)) -> 5914
A12: =IF(Frota!$A12="","",Frota!$A12) -> Caminhão Scania G480 — 2748 | B12: =IF(OR(Frota!$A12="",Frota!$G12<>"Ativo",N(Frota!$L12)=0),"",ROUND(Frota!$I12+IF(B$3=1,N(Frota!$J12),N(Frota!$K12)),2)) -> 305400 | C12: =IF(B12="","",ROUND(B12+IF(C$3=1,N(Frota!$J12),N(Frota!$K12)),2)) -> 306800 | D12: =IF(C12="","",ROUND(C12+IF(D$3=1,N(Frota!$J12),N(Frota!$K12)),2)) -> 308200 | E12: =IF(D12="","",ROUND(D12+IF(E$3=1,N(Frota!$J12),N(Frota!$K12)),2)) -> 309600 | F12: =IF(E12="","",ROUND(E12+IF(F$3=1,N(Frota!$J12),N(Frota!$K12)),2)) -> 311000 | G12: =IF(F12="","",ROUND(F12+IF(G$3=1,N(Frota!$J12),N(Frota!$K12)),2)) -> 312400 | H12: =IF(G12="","",ROUND(G12+IF(H$3=1,N(Frota!$J12),N(Frota!$K12)),2)) -> 313800 | I12: =IF(H12="","",ROUND(H12+IF(I$3=1,N(Frota!$J12),N(Frota!$K12)),2)) -> 315200 | J12: =IF(I12="","",ROUND(I12+IF(J$3=1,N(Frota!$J12),N(Frota!$K12)),2)) -> 316600 | ... BA12: =IF(AZ12="","",ROUND(AZ12+IF(BA$3=1,N(Frota!$J12),N(Frota!$K12)),2)) -> 361500
A13: =IF(Frota!$A13="","",Frota!$A13) -> Caminhão Scania G540 — 2763 | B13: =IF(OR(Frota!$A13="",Frota!$G13<>"Ativo",N(Frota!$L13)=0),"",ROUND(Frota!$I13+IF(B$3=1,N(Frota!$J13),N(Frota!$K13)),2)) -> 86350 | C13: =IF(B13="","",ROUND(B13+IF(C$3=1,N(Frota!$J13),N(Frota!$K13)),2)) -> 87700 | D13: =IF(C13="","",ROUND(C13+IF(D$3=1,N(Frota!$J13),N(Frota!$K13)),2)) -> 89050 | E13: =IF(D13="","",ROUND(D13+IF(E$3=1,N(Frota!$J13),N(Frota!$K13)),2)) -> 90400 | F13: =IF(E13="","",ROUND(E13+IF(F$3=1,N(Frota!$J13),N(Frota!$K13)),2)) -> 91750 | G13: =IF(F13="","",ROUND(F13+IF(G$3=1,N(Frota!$J13),N(Frota!$K13)),2)) -> 93100 | H13: =IF(G13="","",ROUND(G13+IF(H$3=1,N(Frota!$J13),N(Frota!$K13)),2)) -> 94450 | I13: =IF(H13="","",ROUND(H13+IF(I$3=1,N(Frota!$J13),N(Frota!$K13)),2)) -> 95800 | J13: =IF(I13="","",ROUND(I13+IF(J$3=1,N(Frota!$J13),N(Frota!$K13)),2)) -> 97150 | ... BA13: =IF(AZ13="","",ROUND(AZ13+IF(BA$3=1,N(Frota!$J13),N(Frota!$K13)),2)) -> 140410
A14: =IF(Frota!$A14="","",Frota!$A14) -> Transbordo Mambra 20t — 801 | B14: =IF(OR(Frota!$A14="",Frota!$G14<>"Ativo",N(Frota!$L14)=0),"",ROUND(Frota!$I14+IF(B$3=1,N(Frota!$J14),N(Frota!$K14)),2)) -> 4240 | C14: =IF(B14="","",ROUND(B14+IF(C$3=1,N(Frota!$J14),N(Frota!$K14)),2)) -> 4280 | D14: =IF(C14="","",ROUND(C14+IF(D$3=1,N(Frota!$J14),N(Frota!$K14)),2)) -> 4320 | E14: =IF(D14="","",ROUND(D14+IF(E$3=1,N(Frota!$J14),N(Frota!$K14)),2)) -> 4360 | F14: =IF(E14="","",ROUND(E14+IF(F$3=1,N(Frota!$J14),N(Frota!$K14)),2)) -> 4400 | G14: =IF(F14="","",ROUND(F14+IF(G$3=1,N(Frota!$J14),N(Frota!$K14)),2)) -> 4440 | H14: =IF(G14="","",ROUND(G14+IF(H$3=1,N(Frota!$J14),N(Frota!$K14)),2)) -> 4480 | I14: =IF(H14="","",ROUND(H14+IF(I$3=1,N(Frota!$J14),N(Frota!$K14)),2)) -> 4520 | J14: =IF(I14="","",ROUND(I14+IF(J$3=1,N(Frota!$J14),N(Frota!$K14)),2)) -> 4560 | ... BA14: =IF(AZ14="","",ROUND(AZ14+IF(BA$3=1,N(Frota!$J14),N(Frota!$K14)),2)) -> 5736
A15: =IF(Frota!$A15="","",Frota!$A15) -> Implemento Distribuidor — 802 | B15: =IF(OR(Frota!$A15="",Frota!$G15<>"Ativo",N(Frota!$L15)=0),"",ROUND(Frota!$I15+IF(B$3=1,N(Frota!$J15),N(Frota!$K15)),2)) -> 2832 | C15: =IF(B15="","",ROUND(B15+IF(C$3=1,N(Frota!$J15),N(Frota!$K15)),2)) -> 2864 | D15: =IF(C15="","",ROUND(C15+IF(D$3=1,N(Frota!$J15),N(Frota!$K15)),2)) -> 2896 | E15: =IF(D15="","",ROUND(D15+IF(E$3=1,N(Frota!$J15),N(Frota!$K15)),2)) -> 2928 | F15: =IF(E15="","",ROUND(E15+IF(F$3=1,N(Frota!$J15),N(Frota!$K15)),2)) -> 2960 | G15: =IF(F15="","",ROUND(F15+IF(G$3=1,N(Frota!$J15),N(Frota!$K15)),2)) -> 2992 | H15: =IF(G15="","",ROUND(G15+IF(H$3=1,N(Frota!$J15),N(Frota!$K15)),2)) -> 3024 | I15: =IF(H15="","",ROUND(H15+IF(I$3=1,N(Frota!$J15),N(Frota!$K15)),2)) -> 3056 | J15: =IF(I15="","",ROUND(I15+IF(J$3=1,N(Frota!$J15),N(Frota!$K15)),2)) -> 3088 | ... BA15: =IF(AZ15="","",ROUND(AZ15+IF(BA$3=1,N(Frota!$J15),N(Frota!$K15)),2)) -> 4022
A16: =IF(Frota!$A16="","",Frota!$A16) -> Fiat Toro — 5001 | B16: =IF(OR(Frota!$A16="",Frota!$G16<>"Ativo",N(Frota!$L16)=0),"",ROUND(Frota!$I16+IF(B$3=1,N(Frota!$J16),N(Frota!$K16)),2)) -> 32700 | C16: =IF(B16="","",ROUND(B16+IF(C$3=1,N(Frota!$J16),N(Frota!$K16)),2)) -> 33400 | D16: =IF(C16="","",ROUND(C16+IF(D$3=1,N(Frota!$J16),N(Frota!$K16)),2)) -> 34100 | E16: =IF(D16="","",ROUND(D16+IF(E$3=1,N(Frota!$J16),N(Frota!$K16)),2)) -> 34800 | F16: =IF(E16="","",ROUND(E16+IF(F$3=1,N(Frota!$J16),N(Frota!$K16)),2)) -> 35500 | G16: =IF(F16="","",ROUND(F16+IF(G$3=1,N(Frota!$J16),N(Frota!$K16)),2)) -> 36200 | H16: =IF(G16="","",ROUND(G16+IF(H$3=1,N(Frota!$J16),N(Frota!$K16)),2)) -> 36900 | I16: =IF(H16="","",ROUND(H16+IF(I$3=1,N(Frota!$J16),N(Frota!$K16)),2)) -> 37600 | J16: =IF(I16="","",ROUND(I16+IF(J$3=1,N(Frota!$J16),N(Frota!$K16)),2)) -> 38300 | ... BA16: =IF(AZ16="","",ROUND(AZ16+IF(BA$3=1,N(Frota!$J16),N(Frota!$K16)),2)) -> 63300
... A34: =IF(Frota!$A34="","",Frota!$A34) | B34: =IF(OR(Frota!$A34="",Frota!$G34<>"Ativo",N(Frota!$L34)=0),"",ROUND(Frota!$I34+IF(B$3=1,N(Frota!$J34),N(Frota!$K34)),2)) | C34: =IF(B34="","",ROUND(B34+IF(C$3=1,N(Frota!$J34),N(Frota!$K34)),2)) | D34: =IF(C34="","",ROUND(C34+IF(D$3=1,N(Frota!$J34),N(Frota!$K34)),2)) | E34: =IF(D34="","",ROUND(D34+IF(E$3=1,N(Frota!$J34),N(Frota!$K34)),2)) | F34: =IF(E34="","",ROUND(E34+IF(F$3=1,N(Frota!$J34),N(Frota!$K34)),2)) | G34: =IF(F34="","",ROUND(F34+IF(G$3=1,N(Frota!$J34),N(Frota!$K34)),2)) | H34: =IF(G34="","",ROUND(G34+IF(H$3=1,N(Frota!$J34),N(Frota!$K34)),2)) | I34: =IF(H34="","",ROUND(H34+IF(I$3=1,N(Frota!$J34),N(Frota!$K34)),2)) | J34: =IF(I34="","",ROUND(I34+IF(J$3=1,N(Frota!$J34),N(Frota!$K34)),2)) | ... BA34: =IF(AZ34="","",ROUND(AZ34+IF(BA$3=1,N(Frota!$J34),N(Frota!$K34)),2))

Sheet Cronograma
A1: CRONOGRAMA — grade Ativo × 52 Semanas (tipo de preventiva disparada; herança cumulativa aplicada no HH)
A2: S = verde · A = amarelo · B = vermelho (cores Fabio). Semana com fundo escuro no cabeçalho = safra. Gerado automaticamente do uso acumulado × gatilhos.
A4: Ativo | B4: S01 | C4: S02 | D4: S03 | E4: S04 | F4: S05 | G4: S06 | H4: S07 | I4: S08 | J4: S09 | K4: S10 | L4: S11 | M4: S12 | N4: S13 | O4: S14 | P4: S15 | Q4: S16 | R4: S17 | S4: S18 | T4: S19 | U4: S20 | V4: S21 | W4: S22 | X4: S23 | Y4: S24 | Z4: S25 | AA4: S26 | AB4: S27 | AC4: S28 | AD4: S29 | AE4: S30 | AF4: S31 | AG4: S32 | AH4: S33 | AI4: S34 | AJ4: S35 | AK4: S36 | AL4: S37 | AM4: S38 | AN4: S39 | AO4: S40 | AP4: S41 | AQ4: S42 | AR4: S43 | AS4: S44 | AT4: S45 | AU4: S46 | AV4: S47 | AW4: S48 | AX4: S49 | AY4: S50 | AZ4: S51 | BA4: S52
A5: =IF(Frota!$A5="","",Frota!$A5) -> Colhedora CASE A8810 — 1035 | B5: =IF(Cron_Uso!B5="","",IF(INT(Cron_Uso!B5/Frota!$L5)>INT(Frota!$I5/Frota!$L5),IF(N(VLOOKUP(Frota!$B5,Premissas!$A$39:$E$43,5,0))>0,IF(MOD(INT(Cron_Uso!B5/Frota!$L5)*Frota!$L5,N(VLOOKUP(Frota!$B5,Premissas!$A$39:$E$43,5,0)))=0,"B",IF(N(VLOOKUP(Frota!$B5,Premissas!$A$39:$E$43,4,0))>0,IF(MOD(INT(Cron_Uso!B5/Frota!$L5)*Frota!$L5,N(VLOOKUP(Frota!$B5,Premissas!$A$39:$E$43,4,0)))=0,"A","S"),"S")),IF(N(VLOOKUP(Frota!$B5,Premissas!$A$39:$E$43,4,0))>0,IF(MOD(INT(Cron_Uso!B5/Frota!$L5)*Frota!$L5,N(VLOOKUP(Frota!$B5,Premissas!$A$39:$E$43,4,0)))=0,"A","S"),"S")),"")) | C5: =IF(Cron_Uso!C5="","",IF(INT(Cron_Uso!C5/Frota!$L5)>INT(Cron_Uso!B5/Frota!$L5),IF(N(VLOOKUP(Frota!$B5,Premissas!$A$39:$E$43,5,0))>0,IF(MOD(INT(Cron_Uso!C5/Frota!$L5)*Frota!$L5,N(VLOOKUP(Frota!$B5,Premissas!$A$39:$E$43,5,0)))=0,"B",IF(N(VLOOKUP(Frota!$B5,Premissas!$A$39:$E$43,4,0))>0,IF(MOD(INT(Cron_Uso!C5/Frota!$L5)*Frota!$L5,N(VLOOKUP(Frota!$B5,Premissas!$A$39:$E$43,4,0)))=0,"A","S"),"S")),IF(N(VLOOKUP(Frota!$B5,Premissas!$A$39:$E$43,4,0))>0,IF(MOD(INT(Cron_Uso!C5/Frota!$L5)*Frota!$L5,N(VLOOKUP(Frota!$B5,Premissas!$A$39:$E$43,4,0)))=0,"A","S"),"S")),"")) | D5: =IF(Cron_Uso!D5="","",IF(INT(Cron_Uso!D5/Frota!$L5)>INT(Cron_Uso!C5/Frota!$L5),IF(N(VLOOKUP(Frota!$B5,Premissas!$A$39:$E$43,5,0))>0,IF(MOD(INT(Cron_Uso!D5/Frota!$L5)*Frota!$L5,N(VLOOKUP(Frota!$B5,Premissas!$A$39:$E$43,5,0)))=0,"B",IF(N(VLOOKUP(Frota!$B5,Premissas!$A$39:$E$43,4,0))>0,IF(MOD(INT(Cron_Uso!D5/Frota!$L5)*Frota!$L5,N(VLOOKUP(Frota!$B5,Premissas!$A$39:$E$43,4,0)))=0,"A","S"),"S")),IF(N(VLOOKUP(Frota!$B5,Premissas!$A$39:$E$43,4,0))>0,IF(MOD(INT(Cron_Uso!D5/Frota!$L5)*Frota!$L5,N(VLOOKUP(Frota!$B5,Premissas!$A$39:$E$43,4,0)))=0,"A","S"),"S")),"")) | E5: =IF(Cron_Uso!E5="","",IF(INT(Cron_Uso!E5/Frota!$L5)>INT(Cron_Uso!D5/Frota!$L5),IF(N(VLOOKUP(Frota!$B5,Premissas!$A$39:$E$43,5,0))>0,IF(MOD(INT(Cron_Uso!E5/Frota!$L5)*Frota!$L5,N(VLOOKUP(Frota!$B5,Premissas!$A$39:$E$43,5,0)))=0,"B",IF(N(VLOOKUP(Frota!$B5,Premissas!$A$39:$E$43,4,0))>0,IF(MOD(INT(Cron_Uso!E5/Frota!$L5)*Frota!$L5,N(VLOOKUP(Frota!$B5,Premissas!$A$39:$E$43,4,0)))=0,"A","S"),"S")),IF(N(VLOOKUP(Frota!$B5,Premissas!$A$39:$E$43,4,0))>0,IF(MOD(INT(Cron_Uso!E5/Frota!$L5)*Frota!$L5,N(VLOOKUP(Frota!$B5,Premissas!$A$39:$E$43,4,0)))=0,"A","S"),"S")),"")) | F5: =IF(Cron_Uso!F5="","",IF(INT(Cron_Uso!F5/Frota!$L5)>INT(Cron_Uso!E5/Frota!$L5),IF(N(VLOOKUP(Frota!$B5,Premissas!$A$39:$E$43,5,0))>0,IF(MOD(INT(Cron_Uso!F5/Frota!$L5)*Frota!$L5,N(VLOOKUP(Frota!$B5,Premissas!$A$39:$E$43,5,0)))=0,"B",IF(N(VLOOKUP(Frota!$B5,Premissas!$A$39:$E$43,4,0))>0,IF(MOD(INT(Cron_Uso!F5/Frota!$L5)*Frota!$L5,N(VLOOKUP(Frota!$B5,Premissas!$A$39:$E$43,4,0)))=0,"A","S"),"S")),IF(N(VLOOKUP(Frota!$B5,Premissas!$A$39:$E$43,4,0))>0,IF(MOD(INT(Cron_Uso!F5/Frota!$L5)*Frota!$L5,N(VLOOKUP(Frota!$B5,Premissas!$A$39:$E$43,4,0)))=0,"A","S"),"S")),"")) -> B | G5: =IF(Cron_Uso!G5="","",IF(INT(Cron_Uso!G5/Frota!$L5)>INT(Cron_Uso!F5/Frota!$L5),IF(N(VLOOKUP(Frota!$B5,Premissas!$A$39:$E$43,5,0))>0,IF(MOD(INT(Cron_Uso!G5/Frota!$L5)*Frota!$L5,N(VLOOKUP(Frota!$B5,Premissas!$A$39:$E$43,5,0)))=0,"B",IF(N(VLOOKUP(Frota!$B5,Premissas!$A$39:$E$43,4,0))>0,IF(MOD(INT(Cron_Uso!G5/Frota!$L5)*Frota!$L5,N(VLOOKUP(Frota!$B5,Premissas!$A$39:$E$43,4,0)))=0,"A","S"),"S")),IF(N(VLOOKUP(Frota!$B5,Premissas!$A$39:$E$43,4,0))>0,IF(MOD(INT(Cron_Uso!G5/Frota!$L5)*Frota!$L5,N(VLOOKUP(Frota!$B5,Premissas!$A$39:$E$43,4,0)))=0,"A","S"),"S")),"")) | H5: =IF(Cron_Uso!H5="","",IF(INT(Cron_Uso!H5/Frota!$L5)>INT(Cron_Uso!G5/Frota!$L5),IF(N(VLOOKUP(Frota!$B5,Premissas!$A$39:$E$43,5,0))>0,IF(MOD(INT(Cron_Uso!H5/Frota!$L5)*Frota!$L5,N(VLOOKUP(Frota!$B5,Premissas!$A$39:$E$43,5,0)))=0,"B",IF(N(VLOOKUP(Frota!$B5,Premissas!$A$39:$E$43,4,0))>0,IF(MOD(INT(Cron_Uso!H5/Frota!$L5)*Frota!$L5,N(VLOOKUP(Frota!$B5,Premissas!$A$39:$E$43,4,0)))=0,"A","S"),"S")),IF(N(VLOOKUP(Frota!$B5,Premissas!$A$39:$E$43,4,0))>0,IF(MOD(INT(Cron_Uso!H5/Frota!$L5)*Frota!$L5,N(VLOOKUP(Frota!$B5,Premissas!$A$39:$E$43,4,0)))=0,"A","S"),"S")),"")) | I5: =IF(Cron_Uso!I5="","",IF(INT(Cron_Uso!I5/Frota!$L5)>INT(Cron_Uso!H5/Frota!$L5),IF(N(VLOOKUP(Frota!$B5,Premissas!$A$39:$E$43,5,0))>0,IF(MOD(INT(Cron_Uso!I5/Frota!$L5)*Frota!$L5,N(VLOOKUP(Frota!$B5,Premissas!$A$39:$E$43,5,0)))=0,"B",IF(N(VLOOKUP(Frota!$B5,Premissas!$A$39:$E$43,4,0))>0,IF(MOD(INT(Cron_Uso!I5/Frota!$L5)*Frota!$L5,N(VLOOKUP(Frota!$B5,Premissas!$A$39:$E$43,4,0)))=0,"A","S"),"S")),IF(N(VLOOKUP(Frota!$B5,Premissas!$A$39:$E$43,4,0))>0,IF(MOD(INT(Cron_Uso!I5/Frota!$L5)*Frota!$L5,N(VLOOKUP(Frota!$B5,Premissas!$A$39:$E$43,4,0)))=0,"A","S"),"S")),"")) | J5: =IF(Cron_Uso!J5="","",IF(INT(Cron_Uso!J5/Frota!$L5)>INT(Cron_Uso!I5/Frota!$L5),IF(N(VLOOKUP(Frota!$B5,Premissas!$A$39:$E$43,5,0))>0,IF(MOD(INT(Cron_Uso!J5/Frota!$L5)*Frota!$L5,N(VLOOKUP(Frota!$B5,Premissas!$A$39:$E$43,5,0)))=0,"B",IF(N(VLOOKUP(Frota!$B5,Premissas!$A$39:$E$43,4,0))>0,IF(MOD(INT(Cron_Uso!J5/Frota!$L5)*Frota!$L5,N(VLOOKUP(Frota!$B5,Premissas!$A$39:$E$43,4,0)))=0,"A","S"),"S")),IF(N(VLOOKUP(Frota!$B5,Premissas!$A$39:$E$43,4,0))>0,IF(MOD(INT(Cron_Uso!J5/Frota!$L5)*Frota!$L5,N(VLOOKUP(Frota!$B5,Premissas!$A$39:$E$43,4,0)))=0,"A","S"),"S")),"")) | ... BA5: =IF(Cron_Uso!BA5="","",IF(INT(Cron_Uso!BA5/Frota!$L5)>INT(Cron_Uso!AZ5/Frota!$L5),IF(N(VLOOKUP(Frota!$B5,Premissas!$A$39:$E$43,5,0))>0,IF(MOD(INT(Cron_Uso!BA5/Frota!$L5)*Frota!$L5,N(VLOOKUP(Frota!$B5,Premissas!$A$39:$E$43,5,0)))=0,"B",IF(N(VLOOKUP(Frota!$B5,Premissas!$A$39:$E$43,4,0))>0,IF(MOD(INT(Cron_Uso!BA5/Frota!$L5)*Frota!$L5,N(VLOOKUP(Frota!$B5,Premissas!$A$39:$E$43,4,0)))=0,"A","S"),"S")),IF(N(VLOOKUP(Frota!$B5,Premissas!$A$39:$E$43,4,0))>0,IF(MOD(INT(Cron_Uso!BA5/Frota!$L5)*Frota!$L5,N(VLOOKUP(Frota!$B5,Premissas!$A$39:$E$43,4,0)))=0,"A","S"),"S")),""))
A6: =IF(Frota!$A6="","",Frota!$A6) -> Colhedora CASE A8810 — 1036 | B6: =IF(Cron_Uso!B6="","",IF(INT(Cron_Uso!B6/Frota!$L6)>INT(Frota!$I6/Frota!$L6),IF(N(VLOOKUP(Frota!$B6,Premissas!$A$39:$E$43,5,0))>0,IF(MOD(INT(Cron_Uso!B6/Frota!$L6)*Frota!$L6,N(VLOOKUP(Frota!$B6,Premissas!$A$39:$E$43,5,0)))=0,"B",IF(N(VLOOKUP(Frota!$B6,Premissas!$A$39:$E$43,4,0))>0,IF(MOD(INT(Cron_Uso!B6/Frota!$L6)*Frota!$L6,N(VLOOKUP(Frota!$B6,Premissas!$A$39:$E$43,4,0)))=0,"A","S"),"S")),IF(N(VLOOKUP(Frota!$B6,Premissas!$A$39:$E$43,4,0))>0,IF(MOD(INT(Cron_Uso!B6/Frota!$L6)*Frota!$L6,N(VLOOKUP(Frota!$B6,Premissas!$A$39:$E$43,4,0)))=0,"A","S"),"S")),"")) -> A | C6: =IF(Cron_Uso!C6="","",IF(INT(Cron_Uso!C6/Frota!$L6)>INT(Cron_Uso!B6/Frota!$L6),IF(N(VLOOKUP(Frota!$B6,Premissas!$A$39:$E$43,5,0))>0,IF(MOD(INT(Cron_Uso!C6/Frota!$L6)*Frota!$L6,N(VLOOKUP(Frota!$B6,Premissas!$A$39:$E$43,5,0)))=0,"B",IF(N(VLOOKUP(Frota!$B6,Premissas!$A$39:$E$43,4,0))>0,IF(MOD(INT(Cron_Uso!C6/Frota!$L6)*Frota!$L6,N(VLOOKUP(Frota!$B6,Premissas!$A$39:$E$43,4,0)))=0,"A","S"),"S")),IF(N(VLOOKUP(Frota!$B6,Premissas!$A$39:$E$43,4,0))>0,IF(MOD(INT(Cron_Uso!C6/Frota!$L6)*Frota!$L6,N(VLOOKUP(Frota!$B6,Premissas!$A$39:$E$43,4,0)))=0,"A","S"),"S")),"")) | D6: =IF(Cron_Uso!D6="","",IF(INT(Cron_Uso!D6/Frota!$L6)>INT(Cron_Uso!C6/Frota!$L6),IF(N(VLOOKUP(Frota!$B6,Premissas!$A$39:$E$43,5,0))>0,IF(MOD(INT(Cron_Uso!D6/Frota!$L6)*Frota!$L6,N(VLOOKUP(Frota!$B6,Premissas!$A$39:$E$43,5,0)))=0,"B",IF(N(VLOOKUP(Frota!$B6,Premissas!$A$39:$E$43,4,0))>0,IF(MOD(INT(Cron_Uso!D6/Frota!$L6)*Frota!$L6,N(VLOOKUP(Frota!$B6,Premissas!$A$39:$E$43,4,0)))=0,"A","S"),"S")),IF(N(VLOOKUP(Frota!$B6,Premissas!$A$39:$E$43,4,0))>0,IF(MOD(INT(Cron_Uso!D6/Frota!$L6)*Frota!$L6,N(VLOOKUP(Frota!$B6,Premissas!$A$39:$E$43,4,0)))=0,"A","S"),"S")),"")) | E6: =IF(Cron_Uso!E6="","",IF(INT(Cron_Uso!E6/Frota!$L6)>INT(Cron_Uso!D6/Frota!$L6),IF(N(VLOOKUP(Frota!$B6,Premissas!$A$39:$E$43,5,0))>0,IF(MOD(INT(Cron_Uso!E6/Frota!$L6)*Frota!$L6,N(VLOOKUP(Frota!$B6,Premissas!$A$39:$E$43,5,0)))=0,"B",IF(N(VLOOKUP(Frota!$B6,Premissas!$A$39:$E$43,4,0))>0,IF(MOD(INT(Cron_Uso!E6/Frota!$L6)*Frota!$L6,N(VLOOKUP(Frota!$B6,Premissas!$A$39:$E$43,4,0)))=0,"A","S"),"S")),IF(N(VLOOKUP(Frota!$B6,Premissas!$A$39:$E$43,4,0))>0,IF(MOD(INT(Cron_Uso!E6/Frota!$L6)*Frota!$L6,N(VLOOKUP(Frota!$B6,Premissas!$A$39:$E$43,4,0)))=0,"A","S"),"S")),"")) | F6: =IF(Cron_Uso!F6="","",IF(INT(Cron_Uso!F6/Frota!$L6)>INT(Cron_Uso!E6/Frota!$L6),IF(N(VLOOKUP(Frota!$B6,Premissas!$A$39:$E$43,5,0))>0,IF(MOD(INT(Cron_Uso!F6/Frota!$L6)*Frota!$L6,N(VLOOKUP(Frota!$B6,Premissas!$A$39:$E$43,5,0)))=0,"B",IF(N(VLOOKUP(Frota!$B6,Premissas!$A$39:$E$43,4,0))>0,IF(MOD(INT(Cron_Uso!F6/Frota!$L6)*Frota!$L6,N(VLOOKUP(Frota!$B6,Premissas!$A$39:$E$43,4,0)))=0,"A","S"),"S")),IF(N(VLOOKUP(Frota!$B6,Premissas!$A$39:$E$43,4,0))>0,IF(MOD(INT(Cron_Uso!F6/Frota!$L6)*Frota!$L6,N(VLOOKUP(Frota!$B6,Premissas!$A$39:$E$43,4,0)))=0,"A","S"),"S")),"")) | G6: =IF(Cron_Uso!G6="","",IF(INT(Cron_Uso!G6/Frota!$L6)>INT(Cron_Uso!F6/Frota!$L6),IF(N(VLOOKUP(Frota!$B6,Premissas!$A$39:$E$43,5,0))>0,IF(MOD(INT(Cron_Uso!G6/Frota!$L6)*Frota!$L6,N(VLOOKUP(Frota!$B6,Premissas!$A$39:$E$43,5,0)))=0,"B",IF(N(VLOOKUP(Frota!$B6,Premissas!$A$39:$E$43,4,0))>0,IF(MOD(INT(Cron_Uso!G6/Frota!$L6)*Frota!$L6,N(VLOOKUP(Frota!$B6,Premissas!$A$39:$E$43,4,0)))=0,"A","S"),"S")),IF(N(VLOOKUP(Frota!$B6,Premissas!$A$39:$E$43,4,0))>0,IF(MOD(INT(Cron_Uso!G6/Frota!$L6)*Frota!$L6,N(VLOOKUP(Frota!$B6,Premissas!$A$39:$E$43,4,0)))=0,"A","S"),"S")),"")) -> S | H6: =IF(Cron_Uso!H6="","",IF(INT(Cron_Uso!H6/Frota!$L6)>INT(Cron_Uso!G6/Frota!$L6),IF(N(VLOOKUP(Frota!$B6,Premissas!$A$39:$E$43,5,0))>0,IF(MOD(INT(Cron_Uso!H6/Frota!$L6)*Frota!$L6,N(VLOOKUP(Frota!$B6,Premissas!$A$39:$E$43,5,0)))=0,"B",IF(N(VLOOKUP(Frota!$B6,Premissas!$A$39:$E$43,4,0))>0,IF(MOD(INT(Cron_Uso!H6/Frota!$L6)*Frota!$L6,N(VLOOKUP(Frota!$B6,Premissas!$A$39:$E$43,4,0)))=0,"A","S"),"S")),IF(N(VLOOKUP(Frota!$B6,Premissas!$A$39:$E$43,4,0))>0,IF(MOD(INT(Cron_Uso!H6/Frota!$L6)*Frota!$L6,N(VLOOKUP(Frota!$B6,Premissas!$A$39:$E$43,4,0)))=0,"A","S"),"S")),"")) | I6: =IF(Cron_Uso!I6="","",IF(INT(Cron_Uso!I6/Frota!$L6)>INT(Cron_Uso!H6/Frota!$L6),IF(N(VLOOKUP(Frota!$B6,Premissas!$A$39:$E$43,5,0))>0,IF(MOD(INT(Cron_Uso!I6/Frota!$L6)*Frota!$L6,N(VLOOKUP(Frota!$B6,Premissas!$A$39:$E$43,5,0)))=0,"B",IF(N(VLOOKUP(Frota!$B6,Premissas!$A$39:$E$43,4,0))>0,IF(MOD(INT(Cron_Uso!I6/Frota!$L6)*Frota!$L6,N(VLOOKUP(Frota!$B6,Premissas!$A$39:$E$43,4,0)))=0,"A","S"),"S")),IF(N(VLOOKUP(Frota!$B6,Premissas!$A$39:$E$43,4,0))>0,IF(MOD(INT(Cron_Uso!I6/Frota!$L6)*Frota!$L6,N(VLOOKUP(Frota!$B6,Premissas!$A$39:$E$43,4,0)))=0,"A","S"),"S")),"")) | J6: =IF(Cron_Uso!J6="","",IF(INT(Cron_Uso!J6/Frota!$L6)>INT(Cron_Uso!I6/Frota!$L6),IF(N(VLOOKUP(Frota!$B6,Premissas!$A$39:$E$43,5,0))>0,IF(MOD(INT(Cron_Uso!J6/Frota!$L6)*Frota!$L6,N(VLOOKUP(Frota!$B6,Premissas!$A$39:$E$43,5,0)))=0,"B",IF(N(VLOOKUP(Frota!$B6,Premissas!$A$39:$E$43,4,0))>0,IF(MOD(INT(Cron_Uso!J6/Frota!$L6)*Frota!$L6,N(VLOOKUP(Frota!$B6,Premissas!$A$39:$E$43,4,0)))=0,"A","S"),"S")),IF(N(VLOOKUP(Frota!$B6,Premissas!$A$39:$E$43,4,0))>0,IF(MOD(INT(Cron_Uso!J6/Frota!$L6)*Frota!$L6,N(VLOOKUP(Frota!$B6,Premissas!$A$39:$E$43,4,0)))=0,"A","S"),"S")),"")) | ... BA6: =IF(Cron_Uso!BA6="","",IF(INT(Cron_Uso!BA6/Frota!$L6)>INT(Cron_Uso!AZ6/Frota!$L6),IF(N(VLOOKUP(Frota!$B6,Premissas!$A$39:$E$43,5,0))>0,IF(MOD(INT(Cron_Uso!BA6/Frota!$L6)*Frota!$L6,N(VLOOKUP(Frota!$B6,Premissas!$A$39:$E$43,5,0)))=0,"B",IF(N(VLOOKUP(Frota!$B6,Premissas!$A$39:$E$43,4,0))>0,IF(MOD(INT(Cron_Uso!BA6/Frota!$L6)*Frota!$L6,N(VLOOKUP(Frota!$B6,Premissas!$A$39:$E$43,4,0)))=0,"A","S"),"S")),IF(N(VLOOKUP(Frota!$B6,Premissas!$A$39:$E$43,4,0))>0,IF(MOD(INT(Cron_Uso!BA6/Frota!$L6)*Frota!$L6,N(VLOOKUP(Frota!$B6,Premissas!$A$39:$E$43,4,0)))=0,"A","S"),"S")),""))
A7: =IF(Frota!$A7="","",Frota!$A7) -> Colhedora JD CH570 — 1027 | B7: =IF(Cron_Uso!B7="","",IF(INT(Cron_Uso!B7/Frota!$L7)>INT(Frota!$I7/Frota!$L7),IF(N(VLOOKUP(Frota!$B7,Premissas!$A$39:$E$43,5,0))>0,IF(MOD(INT(Cron_Uso!B7/Frota!$L7)*Frota!$L7,N(VLOOKUP(Frota!$B7,Premissas!$A$39:$E$43,5,0)))=0,"B",IF(N(VLOOKUP(Frota!$B7,Premissas!$A$39:$E$43,4,0))>0,IF(MOD(INT(Cron_Uso!B7/Frota!$L7)*Frota!$L7,N(VLOOKUP(Frota!$B7,Premissas!$A$39:$E$43,4,0)))=0,"A","S"),"S")),IF(N(VLOOKUP(Frota!$B7,Premissas!$A$39:$E$43,4,0))>0,IF(MOD(INT(Cron_Uso!B7/Frota!$L7)*Frota!$L7,N(VLOOKUP(Frota!$B7,Premissas!$A$39:$E$43,4,0)))=0,"A","S"),"S")),"")) | C7: =IF(Cron_Uso!C7="","",IF(INT(Cron_Uso!C7/Frota!$L7)>INT(Cron_Uso!B7/Frota!$L7),IF(N(VLOOKUP(Frota!$B7,Premissas!$A$39:$E$43,5,0))>0,IF(MOD(INT(Cron_Uso!C7/Frota!$L7)*Frota!$L7,N(VLOOKUP(Frota!$B7,Premissas!$A$39:$E$43,5,0)))=0,"B",IF(N(VLOOKUP(Frota!$B7,Premissas!$A$39:$E$43,4,0))>0,IF(MOD(INT(Cron_Uso!C7/Frota!$L7)*Frota!$L7,N(VLOOKUP(Frota!$B7,Premissas!$A$39:$E$43,4,0)))=0,"A","S"),"S")),IF(N(VLOOKUP(Frota!$B7,Premissas!$A$39:$E$43,4,0))>0,IF(MOD(INT(Cron_Uso!C7/Frota!$L7)*Frota!$L7,N(VLOOKUP(Frota!$B7,Premissas!$A$39:$E$43,4,0)))=0,"A","S"),"S")),"")) | D7: =IF(Cron_Uso!D7="","",IF(INT(Cron_Uso!D7/Frota!$L7)>INT(Cron_Uso!C7/Frota!$L7),IF(N(VLOOKUP(Frota!$B7,Premissas!$A$39:$E$43,5,0))>0,IF(MOD(INT(Cron_Uso!D7/Frota!$L7)*Frota!$L7,N(VLOOKUP(Frota!$B7,Premissas!$A$39:$E$43,5,0)))=0,"B",IF(N(VLOOKUP(Frota!$B7,Premissas!$A$39:$E$43,4,0))>0,IF(MOD(INT(Cron_Uso!D7/Frota!$L7)*Frota!$L7,N(VLOOKUP(Frota!$B7,Premissas!$A$39:$E$43,4,0)))=0,"A","S"),"S")),IF(N(VLOOKUP(Frota!$B7,Premissas!$A$39:$E$43,4,0))>0,IF(MOD(INT(Cron_Uso!D7/Frota!$L7)*Frota!$L7,N(VLOOKUP(Frota!$B7,Premissas!$A$39:$E$43,4,0)))=0,"A","S"),"S")),"")) | E7: =IF(Cron_Uso!E7="","",IF(INT(Cron_Uso!E7/Frota!$L7)>INT(Cron_Uso!D7/Frota!$L7),IF(N(VLOOKUP(Frota!$B7,Premissas!$A$39:$E$43,5,0))>0,IF(MOD(INT(Cron_Uso!E7/Frota!$L7)*Frota!$L7,N(VLOOKUP(Frota!$B7,Premissas!$A$39:$E$43,5,0)))=0,"B",IF(N(VLOOKUP(Frota!$B7,Premissas!$A$39:$E$43,4,0))>0,IF(MOD(INT(Cron_Uso!E7/Frota!$L7)*Frota!$L7,N(VLOOKUP(Frota!$B7,Premissas!$A$39:$E$43,4,0)))=0,"A","S"),"S")),IF(N(VLOOKUP(Frota!$B7,Premissas!$A$39:$E$43,4,0))>0,IF(MOD(INT(Cron_Uso!E7/Frota!$L7)*Frota!$L7,N(VLOOKUP(Frota!$B7,Premissas!$A$39:$E$43,4,0)))=0,"A","S"),"S")),"")) -> B | F7: =IF(Cron_Uso!F7="","",IF(INT(Cron_Uso!F7/Frota!$L7)>INT(Cron_Uso!E7/Frota!$L7),IF(N(VLOOKUP(Frota!$B7,Premissas!$A$39:$E$43,5,0))>0,IF(MOD(INT(Cron_Uso!F7/Frota!$L7)*Frota!$L7,N(VLOOKUP(Frota!$B7,Premissas!$A$39:$E$43,5,0)))=0,"B",IF(N(VLOOKUP(Frota!$B7,Premissas!$A$39:$E$43,4,0))>0,IF(MOD(INT(Cron_Uso!F7/Frota!$L7)*Frota!$L7,N(VLOOKUP(Frota!$B7,Premissas!$A$39:$E$43,4,0)))=0,"A","S"),"S")),IF(N(VLOOKUP(Frota!$B7,Premissas!$A$39:$E$43,4,0))>0,IF(MOD(INT(Cron_Uso!F7/Frota!$L7)*Frota!$L7,N(VLOOKUP(Frota!$B7,Premissas!$A$39:$E$43,4,0)))=0,"A","S"),"S")),"")) | G7: =IF(Cron_Uso!G7="","",IF(INT(Cron_Uso!G7/Frota!$L7)>INT(Cron_Uso!F7/Frota!$L7),IF(N(VLOOKUP(Frota!$B7,Premissas!$A$39:$E$43,5,0))>0,IF(MOD(INT(Cron_Uso!G7/Frota!$L7)*Frota!$L7,N(VLOOKUP(Frota!$B7,Premissas!$A$39:$E$43,5,0)))=0,"B",IF(N(VLOOKUP(Frota!$B7,Premissas!$A$39:$E$43,4,0))>0,IF(MOD(INT(Cron_Uso!G7/Frota!$L7)*Frota!$L7,N(VLOOKUP(Frota!$B7,Premissas!$A$39:$E$43,4,0)))=0,"A","S"),"S")),IF(N(VLOOKUP(Frota!$B7,Premissas!$A$39:$E$43,4,0))>0,IF(MOD(INT(Cron_Uso!G7/Frota!$L7)*Frota!$L7,N(VLOOKUP(Frota!$B7,Premissas!$A$39:$E$43,4,0)))=0,"A","S"),"S")),"")) | H7: =IF(Cron_Uso!H7="","",IF(INT(Cron_Uso!H7/Frota!$L7)>INT(Cron_Uso!G7/Frota!$L7),IF(N(VLOOKUP(Frota!$B7,Premissas!$A$39:$E$43,5,0))>0,IF(MOD(INT(Cron_Uso!H7/Frota!$L7)*Frota!$L7,N(VLOOKUP(Frota!$B7,Premissas!$A$39:$E$43,5,0)))=0,"B",IF(N(VLOOKUP(Frota!$B7,Premissas!$A$39:$E$43,4,0))>0,IF(MOD(INT(Cron_Uso!H7/Frota!$L7)*Frota!$L7,N(VLOOKUP(Frota!$B7,Premissas!$A$39:$E$43,4,0)))=0,"A","S"),"S")),IF(N(VLOOKUP(Frota!$B7,Premissas!$A$39:$E$43,4,0))>0,IF(MOD(INT(Cron_Uso!H7/Frota!$L7)*Frota!$L7,N(VLOOKUP(Frota!$B7,Premissas!$A$39:$E$43,4,0)))=0,"A","S"),"S")),"")) | I7: =IF(Cron_Uso!I7="","",IF(INT(Cron_Uso!I7/Frota!$L7)>INT(Cron_Uso!H7/Frota!$L7),IF(N(VLOOKUP(Frota!$B7,Premissas!$A$39:$E$43,5,0))>0,IF(MOD(INT(Cron_Uso!I7/Frota!$L7)*Frota!$L7,N(VLOOKUP(Frota!$B7,Premissas!$A$39:$E$43,5,0)))=0,"B",IF(N(VLOOKUP(Frota!$B7,Premissas!$A$39:$E$43,4,0))>0,IF(MOD(INT(Cron_Uso!I7/Frota!$L7)*Frota!$L7,N(VLOOKUP(Frota!$B7,Premissas!$A$39:$E$43,4,0)))=0,"A","S"),"S")),IF(N(VLOOKUP(Frota!$B7,Premissas!$A$39:$E$43,4,0))>0,IF(MOD(INT(Cron_Uso!I7/Frota!$L7)*Frota!$L7,N(VLOOKUP(Frota!$B7,Premissas!$A$39:$E$43,4,0)))=0,"A","S"),"S")),"")) | J7: =IF(Cron_Uso!J7="","",IF(INT(Cron_Uso!J7/Frota!$L7)>INT(Cron_Uso!I7/Frota!$L7),IF(N(VLOOKUP(Frota!$B7,Premissas!$A$39:$E$43,5,0))>0,IF(MOD(INT(Cron_Uso!J7/Frota!$L7)*Frota!$L7,N(VLOOKUP(Frota!$B7,Premissas!$A$39:$E$43,5,0)))=0,"B",IF(N(VLOOKUP(Frota!$B7,Premissas!$A$39:$E$43,4,0))>0,IF(MOD(INT(Cron_Uso!J7/Frota!$L7)*Frota!$L7,N(VLOOKUP(Frota!$B7,Premissas!$A$39:$E$43,4,0)))=0,"A","S"),"S")),IF(N(VLOOKUP(Frota!$B7,Premissas!$A$39:$E$43,4,0))>0,IF(MOD(INT(Cron_Uso!J7/Frota!$L7)*Frota!$L7,N(VLOOKUP(Frota!$B7,Premissas!$A$39:$E$43,4,0)))=0,"A","S"),"S")),"")) | ... BA7: =IF(Cron_Uso!BA7="","",IF(INT(Cron_Uso!BA7/Frota!$L7)>INT(Cron_Uso!AZ7/Frota!$L7),IF(N(VLOOKUP(Frota!$B7,Premissas!$A$39:$E$43,5,0))>0,IF(MOD(INT(Cron_Uso!BA7/Frota!$L7)*Frota!$L7,N(VLOOKUP(Frota!$B7,Premissas!$A$39:$E$43,5,0)))=0,"B",IF(N(VLOOKUP(Frota!$B7,Premissas!$A$39:$E$43,4,0))>0,IF(MOD(INT(Cron_Uso!BA7/Frota!$L7)*Frota!$L7,N(VLOOKUP(Frota!$B7,Premissas!$A$39:$E$43,4,0)))=0,"A","S"),"S")),IF(N(VLOOKUP(Frota!$B7,Premissas!$A$39:$E$43,4,0))>0,IF(MOD(INT(Cron_Uso!BA7/Frota!$L7)*Frota!$L7,N(VLOOKUP(Frota!$B7,Premissas!$A$39:$E$43,4,0)))=0,"A","S"),"S")),""))
A8: =IF(Frota!$A8="","",Frota!$A8) -> Colhedora CASE A9000 — 1043 | B8: =IF(Cron_Uso!B8="","",IF(INT(Cron_Uso!B8/Frota!$L8)>INT(Frota!$I8/Frota!$L8),IF(N(VLOOKUP(Frota!$B8,Premissas!$A$39:$E$43,5,0))>0,IF(MOD(INT(Cron_Uso!B8/Frota!$L8)*Frota!$L8,N(VLOOKUP(Frota!$B8,Premissas!$A$39:$E$43,5,0)))=0,"B",IF(N(VLOOKUP(Frota!$B8,Premissas!$A$39:$E$43,4,0))>0,IF(MOD(INT(Cron_Uso!B8/Frota!$L8)*Frota!$L8,N(VLOOKUP(Frota!$B8,Premissas!$A$39:$E$43,4,0)))=0,"A","S"),"S")),IF(N(VLOOKUP(Frota!$B8,Premissas!$A$39:$E$43,4,0))>0,IF(MOD(INT(Cron_Uso!B8/Frota!$L8)*Frota!$L8,N(VLOOKUP(Frota!$B8,Premissas!$A$39:$E$43,4,0)))=0,"A","S"),"S")),"")) | C8: =IF(Cron_Uso!C8="","",IF(INT(Cron_Uso!C8/Frota!$L8)>INT(Cron_Uso!B8/Frota!$L8),IF(N(VLOOKUP(Frota!$B8,Premissas!$A$39:$E$43,5,0))>0,IF(MOD(INT(Cron_Uso!C8/Frota!$L8)*Frota!$L8,N(VLOOKUP(Frota!$B8,Premissas!$A$39:$E$43,5,0)))=0,"B",IF(N(VLOOKUP(Frota!$B8,Premissas!$A$39:$E$43,4,0))>0,IF(MOD(INT(Cron_Uso!C8/Frota!$L8)*Frota!$L8,N(VLOOKUP(Frota!$B8,Premissas!$A$39:$E$43,4,0)))=0,"A","S"),"S")),IF(N(VLOOKUP(Frota!$B8,Premissas!$A$39:$E$43,4,0))>0,IF(MOD(INT(Cron_Uso!C8/Frota!$L8)*Frota!$L8,N(VLOOKUP(Frota!$B8,Premissas!$A$39:$E$43,4,0)))=0,"A","S"),"S")),"")) -> S | D8: =IF(Cron_Uso!D8="","",IF(INT(Cron_Uso!D8/Frota!$L8)>INT(Cron_Uso!C8/Frota!$L8),IF(N(VLOOKUP(Frota!$B8,Premissas!$A$39:$E$43,5,0))>0,IF(MOD(INT(Cron_Uso!D8/Frota!$L8)*Frota!$L8,N(VLOOKUP(Frota!$B8,Premissas!$A$39:$E$43,5,0)))=0,"B",IF(N(VLOOKUP(Frota!$B8,Premissas!$A$39:$E$43,4,0))>0,IF(MOD(INT(Cron_Uso!D8/Frota!$L8)*Frota!$L8,N(VLOOKUP(Frota!$B8,Premissas!$A$39:$E$43,4,0)))=0,"A","S"),"S")),IF(N(VLOOKUP(Frota!$B8,Premissas!$A$39:$E$43,4,0))>0,IF(MOD(INT(Cron_Uso!D8/Frota!$L8)*Frota!$L8,N(VLOOKUP(Frota!$B8,Premissas!$A$39:$E$43,4,0)))=0,"A","S"),"S")),"")) | E8: =IF(Cron_Uso!E8="","",IF(INT(Cron_Uso!E8/Frota!$L8)>INT(Cron_Uso!D8/Frota!$L8),IF(N(VLOOKUP(Frota!$B8,Premissas!$A$39:$E$43,5,0))>0,IF(MOD(INT(Cron_Uso!E8/Frota!$L8)*Frota!$L8,N(VLOOKUP(Frota!$B8,Premissas!$A$39:$E$43,5,0)))=0,"B",IF(N(VLOOKUP(Frota!$B8,Premissas!$A$39:$E$43,4,0))>0,IF(MOD(INT(Cron_Uso!E8/Frota!$L8)*Frota!$L8,N(VLOOKUP(Frota!$B8,Premissas!$A$39:$E$43,4,0)))=0,"A","S"),"S")),IF(N(VLOOKUP(Frota!$B8,Premissas!$A$39:$E$43,4,0))>0,IF(MOD(INT(Cron_Uso!E8/Frota!$L8)*Frota!$L8,N(VLOOKUP(Frota!$B8,Premissas!$A$39:$E$43,4,0)))=0,"A","S"),"S")),"")) | F8: =IF(Cron_Uso!F8="","",IF(INT(Cron_Uso!F8/Frota!$L8)>INT(Cron_Uso!E8/Frota!$L8),IF(N(VLOOKUP(Frota!$B8,Premissas!$A$39:$E$43,5,0))>0,IF(MOD(INT(Cron_Uso!F8/Frota!$L8)*Frota!$L8,N(VLOOKUP(Frota!$B8,Premissas!$A$39:$E$43,5,0)))=0,"B",IF(N(VLOOKUP(Frota!$B8,Premissas!$A$39:$E$43,4,0))>0,IF(MOD(INT(Cron_Uso!F8/Frota!$L8)*Frota!$L8,N(VLOOKUP(Frota!$B8,Premissas!$A$39:$E$43,4,0)))=0,"A","S"),"S")),IF(N(VLOOKUP(Frota!$B8,Premissas!$A$39:$E$43,4,0))>0,IF(MOD(INT(Cron_Uso!F8/Frota!$L8)*Frota!$L8,N(VLOOKUP(Frota!$B8,Premissas!$A$39:$E$43,4,0)))=0,"A","S"),"S")),"")) | G8: =IF(Cron_Uso!G8="","",IF(INT(Cron_Uso!G8/Frota!$L8)>INT(Cron_Uso!F8/Frota!$L8),IF(N(VLOOKUP(Frota!$B8,Premissas!$A$39:$E$43,5,0))>0,IF(MOD(INT(Cron_Uso!G8/Frota!$L8)*Frota!$L8,N(VLOOKUP(Frota!$B8,Premissas!$A$39:$E$43,5,0)))=0,"B",IF(N(VLOOKUP(Frota!$B8,Premissas!$A$39:$E$43,4,0))>0,IF(MOD(INT(Cron_Uso!G8/Frota!$L8)*Frota!$L8,N(VLOOKUP(Frota!$B8,Premissas!$A$39:$E$43,4,0)))=0,"A","S"),"S")),IF(N(VLOOKUP(Frota!$B8,Premissas!$A$39:$E$43,4,0))>0,IF(MOD(INT(Cron_Uso!G8/Frota!$L8)*Frota!$L8,N(VLOOKUP(Frota!$B8,Premissas!$A$39:$E$43,4,0)))=0,"A","S"),"S")),"")) | H8: =IF(Cron_Uso!H8="","",IF(INT(Cron_Uso!H8/Frota!$L8)>INT(Cron_Uso!G8/Frota!$L8),IF(N(VLOOKUP(Frota!$B8,Premissas!$A$39:$E$43,5,0))>0,IF(MOD(INT(Cron_Uso!H8/Frota!$L8)*Frota!$L8,N(VLOOKUP(Frota!$B8,Premissas!$A$39:$E$43,5,0)))=0,"B",IF(N(VLOOKUP(Frota!$B8,Premissas!$A$39:$E$43,4,0))>0,IF(MOD(INT(Cron_Uso!H8/Frota!$L8)*Frota!$L8,N(VLOOKUP(Frota!$B8,Premissas!$A$39:$E$43,4,0)))=0,"A","S"),"S")),IF(N(VLOOKUP(Frota!$B8,Premissas!$A$39:$E$43,4,0))>0,IF(MOD(INT(Cron_Uso!H8/Frota!$L8)*Frota!$L8,N(VLOOKUP(Frota!$B8,Premissas!$A$39:$E$43,4,0)))=0,"A","S"),"S")),"")) -> A | I8: =IF(Cron_Uso!I8="","",IF(INT(Cron_Uso!I8/Frota!$L8)>INT(Cron_Uso!H8/Frota!$L8),IF(N(VLOOKUP(Frota!$B8,Premissas!$A$39:$E$43,5,0))>0,IF(MOD(INT(Cron_Uso!I8/Frota!$L8)*Frota!$L8,N(VLOOKUP(Frota!$B8,Premissas!$A$39:$E$43,5,0)))=0,"B",IF(N(VLOOKUP(Frota!$B8,Premissas!$A$39:$E$43,4,0))>0,IF(MOD(INT(Cron_Uso!I8/Frota!$L8)*Frota!$L8,N(VLOOKUP(Frota!$B8,Premissas!$A$39:$E$43,4,0)))=0,"A","S"),"S")),IF(N(VLOOKUP(Frota!$B8,Premissas!$A$39:$E$43,4,0))>0,IF(MOD(INT(Cron_Uso!I8/Frota!$L8)*Frota!$L8,N(VLOOKUP(Frota!$B8,Premissas!$A$39:$E$43,4,0)))=0,"A","S"),"S")),"")) | J8: =IF(Cron_Uso!J8="","",IF(INT(Cron_Uso!J8/Frota!$L8)>INT(Cron_Uso!I8/Frota!$L8),IF(N(VLOOKUP(Frota!$B8,Premissas!$A$39:$E$43,5,0))>0,IF(MOD(INT(Cron_Uso!J8/Frota!$L8)*Frota!$L8,N(VLOOKUP(Frota!$B8,Premissas!$A$39:$E$43,5,0)))=0,"B",IF(N(VLOOKUP(Frota!$B8,Premissas!$A$39:$E$43,4,0))>0,IF(MOD(INT(Cron_Uso!J8/Frota!$L8)*Frota!$L8,N(VLOOKUP(Frota!$B8,Premissas!$A$39:$E$43,4,0)))=0,"A","S"),"S")),IF(N(VLOOKUP(Frota!$B8,Premissas!$A$39:$E$43,4,0))>0,IF(MOD(INT(Cron_Uso!J8/Frota!$L8)*Frota!$L8,N(VLOOKUP(Frota!$B8,Premissas!$A$39:$E$43,4,0)))=0,"A","S"),"S")),"")) | ... BA8: =IF(Cron_Uso!BA8="","",IF(INT(Cron_Uso!BA8/Frota!$L8)>INT(Cron_Uso!AZ8/Frota!$L8),IF(N(VLOOKUP(Frota!$B8,Premissas!$A$39:$E$43,5,0))>0,IF(MOD(INT(Cron_Uso!BA8/Frota!$L8)*Frota!$L8,N(VLOOKUP(Frota!$B8,Premissas!$A$39:$E$43,5,0)))=0,"B",IF(N(VLOOKUP(Frota!$B8,Premissas!$A$39:$E$43,4,0))>0,IF(MOD(INT(Cron_Uso!BA8/Frota!$L8)*Frota!$L8,N(VLOOKUP(Frota!$B8,Premissas!$A$39:$E$43,4,0)))=0,"A","S"),"S")),IF(N(VLOOKUP(Frota!$B8,Premissas!$A$39:$E$43,4,0))>0,IF(MOD(INT(Cron_Uso!BA8/Frota!$L8)*Frota!$L8,N(VLOOKUP(Frota!$B8,Premissas!$A$39:$E$43,4,0)))=0,"A","S"),"S")),""))
A9: =IF(Frota!$A9="","",Frota!$A9) -> Trator NH T7.315 — 401 | B9: =IF(Cron_Uso!B9="","",IF(INT(Cron_Uso!B9/Frota!$L9)>INT(Frota!$I9/Frota!$L9),IF(N(VLOOKUP(Frota!$B9,Premissas!$A$39:$E$43,5,0))>0,IF(MOD(INT(Cron_Uso!B9/Frota!$L9)*Frota!$L9,N(VLOOKUP(Frota!$B9,Premissas!$A$39:$E$43,5,0)))=0,"B",IF(N(VLOOKUP(Frota!$B9,Premissas!$A$39:$E$43,4,0))>0,IF(MOD(INT(Cron_Uso!B9/Frota!$L9)*Frota!$L9,N(VLOOKUP(Frota!$B9,Premissas!$A$39:$E$43,4,0)))=0,"A","S"),"S")),IF(N(VLOOKUP(Frota!$B9,Premissas!$A$39:$E$43,4,0))>0,IF(MOD(INT(Cron_Uso!B9/Frota!$L9)*Frota!$L9,N(VLOOKUP(Frota!$B9,Premissas!$A$39:$E$43,4,0)))=0,"A","S"),"S")),"")) -> S | C9: =IF(Cron_Uso!C9="","",IF(INT(Cron_Uso!C9/Frota!$L9)>INT(Cron_Uso!B9/Frota!$L9),IF(N(VLOOKUP(Frota!$B9,Premissas!$A$39:$E$43,5,0))>0,IF(MOD(INT(Cron_Uso!C9/Frota!$L9)*Frota!$L9,N(VLOOKUP(Frota!$B9,Premissas!$A$39:$E$43,5,0)))=0,"B",IF(N(VLOOKUP(Frota!$B9,Premissas!$A$39:$E$43,4,0))>0,IF(MOD(INT(Cron_Uso!C9/Frota!$L9)*Frota!$L9,N(VLOOKUP(Frota!$B9,Premissas!$A$39:$E$43,4,0)))=0,"A","S"),"S")),IF(N(VLOOKUP(Frota!$B9,Premissas!$A$39:$E$43,4,0))>0,IF(MOD(INT(Cron_Uso!C9/Frota!$L9)*Frota!$L9,N(VLOOKUP(Frota!$B9,Premissas!$A$39:$E$43,4,0)))=0,"A","S"),"S")),"")) | D9: =IF(Cron_Uso!D9="","",IF(INT(Cron_Uso!D9/Frota!$L9)>INT(Cron_Uso!C9/Frota!$L9),IF(N(VLOOKUP(Frota!$B9,Premissas!$A$39:$E$43,5,0))>0,IF(MOD(INT(Cron_Uso!D9/Frota!$L9)*Frota!$L9,N(VLOOKUP(Frota!$B9,Premissas!$A$39:$E$43,5,0)))=0,"B",IF(N(VLOOKUP(Frota!$B9,Premissas!$A$39:$E$43,4,0))>0,IF(MOD(INT(Cron_Uso!D9/Frota!$L9)*Frota!$L9,N(VLOOKUP(Frota!$B9,Premissas!$A$39:$E$43,4,0)))=0,"A","S"),"S")),IF(N(VLOOKUP(Frota!$B9,Premissas!$A$39:$E$43,4,0))>0,IF(MOD(INT(Cron_Uso!D9/Frota!$L9)*Frota!$L9,N(VLOOKUP(Frota!$B9,Premissas!$A$39:$E$43,4,0)))=0,"A","S"),"S")),"")) | E9: =IF(Cron_Uso!E9="","",IF(INT(Cron_Uso!E9/Frota!$L9)>INT(Cron_Uso!D9/Frota!$L9),IF(N(VLOOKUP(Frota!$B9,Premissas!$A$39:$E$43,5,0))>0,IF(MOD(INT(Cron_Uso!E9/Frota!$L9)*Frota!$L9,N(VLOOKUP(Frota!$B9,Premissas!$A$39:$E$43,5,0)))=0,"B",IF(N(VLOOKUP(Frota!$B9,Premissas!$A$39:$E$43,4,0))>0,IF(MOD(INT(Cron_Uso!E9/Frota!$L9)*Frota!$L9,N(VLOOKUP(Frota!$B9,Premissas!$A$39:$E$43,4,0)))=0,"A","S"),"S")),IF(N(VLOOKUP(Frota!$B9,Premissas!$A$39:$E$43,4,0))>0,IF(MOD(INT(Cron_Uso!E9/Frota!$L9)*Frota!$L9,N(VLOOKUP(Frota!$B9,Premissas!$A$39:$E$43,4,0)))=0,"A","S"),"S")),"")) | F9: =IF(Cron_Uso!F9="","",IF(INT(Cron_Uso!F9/Frota!$L9)>INT(Cron_Uso!E9/Frota!$L9),IF(N(VLOOKUP(Frota!$B9,Premissas!$A$39:$E$43,5,0))>0,IF(MOD(INT(Cron_Uso!F9/Frota!$L9)*Frota!$L9,N(VLOOKUP(Frota!$B9,Premissas!$A$39:$E$43,5,0)))=0,"B",IF(N(VLOOKUP(Frota!$B9,Premissas!$A$39:$E$43,4,0))>0,IF(MOD(INT(Cron_Uso!F9/Frota!$L9)*Frota!$L9,N(VLOOKUP(Frota!$B9,Premissas!$A$39:$E$43,4,0)))=0,"A","S"),"S")),IF(N(VLOOKUP(Frota!$B9,Premissas!$A$39:$E$43,4,0))>0,IF(MOD(INT(Cron_Uso!F9/Frota!$L9)*Frota!$L9,N(VLOOKUP(Frota!$B9,Premissas!$A$39:$E$43,4,0)))=0,"A","S"),"S")),"")) | G9: =IF(Cron_Uso!G9="","",IF(INT(Cron_Uso!G9/Frota!$L9)>INT(Cron_Uso!F9/Frota!$L9),IF(N(VLOOKUP(Frota!$B9,Premissas!$A$39:$E$43,5,0))>0,IF(MOD(INT(Cron_Uso!G9/Frota!$L9)*Frota!$L9,N(VLOOKUP(Frota!$B9,Premissas!$A$39:$E$43,5,0)))=0,"B",IF(N(VLOOKUP(Frota!$B9,Premissas!$A$39:$E$43,4,0))>0,IF(MOD(INT(Cron_Uso!G9/Frota!$L9)*Frota!$L9,N(VLOOKUP(Frota!$B9,Premissas!$A$39:$E$43,4,0)))=0,"A","S"),"S")),IF(N(VLOOKUP(Frota!$B9,Premissas!$A$39:$E$43,4,0))>0,IF(MOD(INT(Cron_Uso!G9/Frota!$L9)*Frota!$L9,N(VLOOKUP(Frota!$B9,Premissas!$A$39:$E$43,4,0)))=0,"A","S"),"S")),"")) -> A | H9: =IF(Cron_Uso!H9="","",IF(INT(Cron_Uso!H9/Frota!$L9)>INT(Cron_Uso!G9/Frota!$L9),IF(N(VLOOKUP(Frota!$B9,Premissas!$A$39:$E$43,5,0))>0,IF(MOD(INT(Cron_Uso!H9/Frota!$L9)*Frota!$L9,N(VLOOKUP(Frota!$B9,Premissas!$A$39:$E$43,5,0)))=0,"B",IF(N(VLOOKUP(Frota!$B9,Premissas!$A$39:$E$43,4,0))>0,IF(MOD(INT(Cron_Uso!H9/Frota!$L9)*Frota!$L9,N(VLOOKUP(Frota!$B9,Premissas!$A$39:$E$43,4,0)))=0,"A","S"),"S")),IF(N(VLOOKUP(Frota!$B9,Premissas!$A$39:$E$43,4,0))>0,IF(MOD(INT(Cron_Uso!H9/Frota!$L9)*Frota!$L9,N(VLOOKUP(Frota!$B9,Premissas!$A$39:$E$43,4,0)))=0,"A","S"),"S")),"")) | I9: =IF(Cron_Uso!I9="","",IF(INT(Cron_Uso!I9/Frota!$L9)>INT(Cron_Uso!H9/Frota!$L9),IF(N(VLOOKUP(Frota!$B9,Premissas!$A$39:$E$43,5,0))>0,IF(MOD(INT(Cron_Uso!I9/Frota!$L9)*Frota!$L9,N(VLOOKUP(Frota!$B9,Premissas!$A$39:$E$43,5,0)))=0,"B",IF(N(VLOOKUP(Frota!$B9,Premissas!$A$39:$E$43,4,0))>0,IF(MOD(INT(Cron_Uso!I9/Frota!$L9)*Frota!$L9,N(VLOOKUP(Frota!$B9,Premissas!$A$39:$E$43,4,0)))=0,"A","S"),"S")),IF(N(VLOOKUP(Frota!$B9,Premissas!$A$39:$E$43,4,0))>0,IF(MOD(INT(Cron_Uso!I9/Frota!$L9)*Frota!$L9,N(VLOOKUP(Frota!$B9,Premissas!$A$39:$E$43,4,0)))=0,"A","S"),"S")),"")) | J9: =IF(Cron_Uso!J9="","",IF(INT(Cron_Uso!J9/Frota!$L9)>INT(Cron_Uso!I9/Frota!$L9),IF(N(VLOOKUP(Frota!$B9,Premissas!$A$39:$E$43,5,0))>0,IF(MOD(INT(Cron_Uso!J9/Frota!$L9)*Frota!$L9,N(VLOOKUP(Frota!$B9,Premissas!$A$39:$E$43,5,0)))=0,"B",IF(N(VLOOKUP(Frota!$B9,Premissas!$A$39:$E$43,4,0))>0,IF(MOD(INT(Cron_Uso!J9/Frota!$L9)*Frota!$L9,N(VLOOKUP(Frota!$B9,Premissas!$A$39:$E$43,4,0)))=0,"A","S"),"S")),IF(N(VLOOKUP(Frota!$B9,Premissas!$A$39:$E$43,4,0))>0,IF(MOD(INT(Cron_Uso!J9/Frota!$L9)*Frota!$L9,N(VLOOKUP(Frota!$B9,Premissas!$A$39:$E$43,4,0)))=0,"A","S"),"S")),"")) | ... BA9: =IF(Cron_Uso!BA9="","",IF(INT(Cron_Uso!BA9/Frota!$L9)>INT(Cron_Uso!AZ9/Frota!$L9),IF(N(VLOOKUP(Frota!$B9,Premissas!$A$39:$E$43,5,0))>0,IF(MOD(INT(Cron_Uso!BA9/Frota!$L9)*Frota!$L9,N(VLOOKUP(Frota!$B9,Premissas!$A$39:$E$43,5,0)))=0,"B",IF(N(VLOOKUP(Frota!$B9,Premissas!$A$39:$E$43,4,0))>0,IF(MOD(INT(Cron_Uso!BA9/Frota!$L9)*Frota!$L9,N(VLOOKUP(Frota!$B9,Premissas!$A$39:$E$43,4,0)))=0,"A","S"),"S")),IF(N(VLOOKUP(Frota!$B9,Premissas!$A$39:$E$43,4,0))>0,IF(MOD(INT(Cron_Uso!BA9/Frota!$L9)*Frota!$L9,N(VLOOKUP(Frota!$B9,Premissas!$A$39:$E$43,4,0)))=0,"A","S"),"S")),""))
A10: =IF(Frota!$A10="","",Frota!$A10) -> Trator NH T7.315 — 402 | B10: =IF(Cron_Uso!B10="","",IF(INT(Cron_Uso!B10/Frota!$L10)>INT(Frota!$I10/Frota!$L10),IF(N(VLOOKUP(Frota!$B10,Premissas!$A$39:$E$43,5,0))>0,IF(MOD(INT(Cron_Uso!B10/Frota!$L10)*Frota!$L10,N(VLOOKUP(Frota!$B10,Premissas!$A$39:$E$43,5,0)))=0,"B",IF(N(VLOOKUP(Frota!$B10,Premissas!$A$39:$E$43,4,0))>0,IF(MOD(INT(Cron_Uso!B10/Frota!$L10)*Frota!$L10,N(VLOOKUP(Frota!$B10,Premissas!$A$39:$E$43,4,0)))=0,"A","S"),"S")),IF(N(VLOOKUP(Frota!$B10,Premissas!$A$39:$E$43,4,0))>0,IF(MOD(INT(Cron_Uso!B10/Frota!$L10)*Frota!$L10,N(VLOOKUP(Frota!$B10,Premissas!$A$39:$E$43,4,0)))=0,"A","S"),"S")),"")) | C10: =IF(Cron_Uso!C10="","",IF(INT(Cron_Uso!C10/Frota!$L10)>INT(Cron_Uso!B10/Frota!$L10),IF(N(VLOOKUP(Frota!$B10,Premissas!$A$39:$E$43,5,0))>0,IF(MOD(INT(Cron_Uso!C10/Frota!$L10)*Frota!$L10,N(VLOOKUP(Frota!$B10,Premissas!$A$39:$E$43,5,0)))=0,"B",IF(N(VLOOKUP(Frota!$B10,Premissas!$A$39:$E$43,4,0))>0,IF(MOD(INT(Cron_Uso!C10/Frota!$L10)*Frota!$L10,N(VLOOKUP(Frota!$B10,Premissas!$A$39:$E$43,4,0)))=0,"A","S"),"S")),IF(N(VLOOKUP(Frota!$B10,Premissas!$A$39:$E$43,4,0))>0,IF(MOD(INT(Cron_Uso!C10/Frota!$L10)*Frota!$L10,N(VLOOKUP(Frota!$B10,Premissas!$A$39:$E$43,4,0)))=0,"A","S"),"S")),"")) | D10: =IF(Cron_Uso!D10="","",IF(INT(Cron_Uso!D10/Frota!$L10)>INT(Cron_Uso!C10/Frota!$L10),IF(N(VLOOKUP(Frota!$B10,Premissas!$A$39:$E$43,5,0))>0,IF(MOD(INT(Cron_Uso!D10/Frota!$L10)*Frota!$L10,N(VLOOKUP(Frota!$B10,Premissas!$A$39:$E$43,5,0)))=0,"B",IF(N(VLOOKUP(Frota!$B10,Premissas!$A$39:$E$43,4,0))>0,IF(MOD(INT(Cron_Uso!D10/Frota!$L10)*Frota!$L10,N(VLOOKUP(Frota!$B10,Premissas!$A$39:$E$43,4,0)))=0,"A","S"),"S")),IF(N(VLOOKUP(Frota!$B10,Premissas!$A$39:$E$43,4,0))>0,IF(MOD(INT(Cron_Uso!D10/Frota!$L10)*Frota!$L10,N(VLOOKUP(Frota!$B10,Premissas!$A$39:$E$43,4,0)))=0,"A","S"),"S")),"")) | E10: =IF(Cron_Uso!E10="","",IF(INT(Cron_Uso!E10/Frota!$L10)>INT(Cron_Uso!D10/Frota!$L10),IF(N(VLOOKUP(Frota!$B10,Premissas!$A$39:$E$43,5,0))>0,IF(MOD(INT(Cron_Uso!E10/Frota!$L10)*Frota!$L10,N(VLOOKUP(Frota!$B10,Premissas!$A$39:$E$43,5,0)))=0,"B",IF(N(VLOOKUP(Frota!$B10,Premissas!$A$39:$E$43,4,0))>0,IF(MOD(INT(Cron_Uso!E10/Frota!$L10)*Frota!$L10,N(VLOOKUP(Frota!$B10,Premissas!$A$39:$E$43,4,0)))=0,"A","S"),"S")),IF(N(VLOOKUP(Frota!$B10,Premissas!$A$39:$E$43,4,0))>0,IF(MOD(INT(Cron_Uso!E10/Frota!$L10)*Frota!$L10,N(VLOOKUP(Frota!$B10,Premissas!$A$39:$E$43,4,0)))=0,"A","S"),"S")),"")) -> S | F10: =IF(Cron_Uso!F10="","",IF(INT(Cron_Uso!F10/Frota!$L10)>INT(Cron_Uso!E10/Frota!$L10),IF(N(VLOOKUP(Frota!$B10,Premissas!$A$39:$E$43,5,0))>0,IF(MOD(INT(Cron_Uso!F10/Frota!$L10)*Frota!$L10,N(VLOOKUP(Frota!$B10,Premissas!$A$39:$E$43,5,0)))=0,"B",IF(N(VLOOKUP(Frota!$B10,Premissas!$A$39:$E$43,4,0))>0,IF(MOD(INT(Cron_Uso!F10/Frota!$L10)*Frota!$L10,N(VLOOKUP(Frota!$B10,Premissas!$A$39:$E$43,4,0)))=0,"A","S"),"S")),IF(N(VLOOKUP(Frota!$B10,Premissas!$A$39:$E$43,4,0))>0,IF(MOD(INT(Cron_Uso!F10/Frota!$L10)*Frota!$L10,N(VLOOKUP(Frota!$B10,Premissas!$A$39:$E$43,4,0)))=0,"A","S"),"S")),"")) | G10: =IF(Cron_Uso!G10="","",IF(INT(Cron_Uso!G10/Frota!$L10)>INT(Cron_Uso!F10/Frota!$L10),IF(N(VLOOKUP(Frota!$B10,Premissas!$A$39:$E$43,5,0))>0,IF(MOD(INT(Cron_Uso!G10/Frota!$L10)*Frota!$L10,N(VLOOKUP(Frota!$B10,Premissas!$A$39:$E$43,5,0)))=0,"B",IF(N(VLOOKUP(Frota!$B10,Premissas!$A$39:$E$43,4,0))>0,IF(MOD(INT(Cron_Uso!G10/Frota!$L10)*Frota!$L10,N(VLOOKUP(Frota!$B10,Premissas!$A$39:$E$43,4,0)))=0,"A","S"),"S")),IF(N(VLOOKUP(Frota!$B10,Premissas!$A$39:$E$43,4,0))>0,IF(MOD(INT(Cron_Uso!G10/Frota!$L10)*Frota!$L10,N(VLOOKUP(Frota!$B10,Premissas!$A$39:$E$43,4,0)))=0,"A","S"),"S")),"")) | H10: =IF(Cron_Uso!H10="","",IF(INT(Cron_Uso!H10/Frota!$L10)>INT(Cron_Uso!G10/Frota!$L10),IF(N(VLOOKUP(Frota!$B10,Premissas!$A$39:$E$43,5,0))>0,IF(MOD(INT(Cron_Uso!H10/Frota!$L10)*Frota!$L10,N(VLOOKUP(Frota!$B10,Premissas!$A$39:$E$43,5,0)))=0,"B",IF(N(VLOOKUP(Frota!$B10,Premissas!$A$39:$E$43,4,0))>0,IF(MOD(INT(Cron_Uso!H10/Frota!$L10)*Frota!$L10,N(VLOOKUP(Frota!$B10,Premissas!$A$39:$E$43,4,0)))=0,"A","S"),"S")),IF(N(VLOOKUP(Frota!$B10,Premissas!$A$39:$E$43,4,0))>0,IF(MOD(INT(Cron_Uso!H10/Frota!$L10)*Frota!$L10,N(VLOOKUP(Frota!$B10,Premissas!$A$39:$E$43,4,0)))=0,"A","S"),"S")),"")) | I10: =IF(Cron_Uso!I10="","",IF(INT(Cron_Uso!I10/Frota!$L10)>INT(Cron_Uso!H10/Frota!$L10),IF(N(VLOOKUP(Frota!$B10,Premissas!$A$39:$E$43,5,0))>0,IF(MOD(INT(Cron_Uso!I10/Frota!$L10)*Frota!$L10,N(VLOOKUP(Frota!$B10,Premissas!$A$39:$E$43,5,0)))=0,"B",IF(N(VLOOKUP(Frota!$B10,Premissas!$A$39:$E$43,4,0))>0,IF(MOD(INT(Cron_Uso!I10/Frota!$L10)*Frota!$L10,N(VLOOKUP(Frota!$B10,Premissas!$A$39:$E$43,4,0)))=0,"A","S"),"S")),IF(N(VLOOKUP(Frota!$B10,Premissas!$A$39:$E$43,4,0))>0,IF(MOD(INT(Cron_Uso!I10/Frota!$L10)*Frota!$L10,N(VLOOKUP(Frota!$B10,Premissas!$A$39:$E$43,4,0)))=0,"A","S"),"S")),"")) | J10: =IF(Cron_Uso!J10="","",IF(INT(Cron_Uso!J10/Frota!$L10)>INT(Cron_Uso!I10/Frota!$L10),IF(N(VLOOKUP(Frota!$B10,Premissas!$A$39:$E$43,5,0))>0,IF(MOD(INT(Cron_Uso!J10/Frota!$L10)*Frota!$L10,N(VLOOKUP(Frota!$B10,Premissas!$A$39:$E$43,5,0)))=0,"B",IF(N(VLOOKUP(Frota!$B10,Premissas!$A$39:$E$43,4,0))>0,IF(MOD(INT(Cron_Uso!J10/Frota!$L10)*Frota!$L10,N(VLOOKUP(Frota!$B10,Premissas!$A$39:$E$43,4,0)))=0,"A","S"),"S")),IF(N(VLOOKUP(Frota!$B10,Premissas!$A$39:$E$43,4,0))>0,IF(MOD(INT(Cron_Uso!J10/Frota!$L10)*Frota!$L10,N(VLOOKUP(Frota!$B10,Premissas!$A$39:$E$43,4,0)))=0,"A","S"),"S")),"")) -> A | ... BA10: =IF(Cron_Uso!BA10="","",IF(INT(Cron_Uso!BA10/Frota!$L10)>INT(Cron_Uso!AZ10/Frota!$L10),IF(N(VLOOKUP(Frota!$B10,Premissas!$A$39:$E$43,5,0))>0,IF(MOD(INT(Cron_Uso!BA10/Frota!$L10)*Frota!$L10,N(VLOOKUP(Frota!$B10,Premissas!$A$39:$E$43,5,0)))=0,"B",IF(N(VLOOKUP(Frota!$B10,Premissas!$A$39:$E$43,4,0))>0,IF(MOD(INT(Cron_Uso!BA10/Frota!$L10)*Frota!$L10,N(VLOOKUP(Frota!$B10,Premissas!$A$39:$E$43,4,0)))=0,"A","S"),"S")),IF(N(VLOOKUP(Frota!$B10,Premissas!$A$39:$E$43,4,0))>0,IF(MOD(INT(Cron_Uso!BA10/Frota!$L10)*Frota!$L10,N(VLOOKUP(Frota!$B10,Premissas!$A$39:$E$43,4,0)))=0,"A","S"),"S")),""))
A11: =IF(Frota!$A11="","",Frota!$A11) -> Trator Case Puma 175 — 403 | B11: =IF(Cron_Uso!B11="","",IF(INT(Cron_Uso!B11/Frota!$L11)>INT(Frota!$I11/Frota!$L11),IF(N(VLOOKUP(Frota!$B11,Premissas!$A$39:$E$43,5,0))>0,IF(MOD(INT(Cron_Uso!B11/Frota!$L11)*Frota!$L11,N(VLOOKUP(Frota!$B11,Premissas!$A$39:$E$43,5,0)))=0,"B",IF(N(VLOOKUP(Frota!$B11,Premissas!$A$39:$E$43,4,0))>0,IF(MOD(INT(Cron_Uso!B11/Frota!$L11)*Frota!$L11,N(VLOOKUP(Frota!$B11,Premissas!$A$39:$E$43,4,0)))=0,"A","S"),"S")),IF(N(VLOOKUP(Frota!$B11,Premissas!$A$39:$E$43,4,0))>0,IF(MOD(INT(Cron_Uso!B11/Frota!$L11)*Frota!$L11,N(VLOOKUP(Frota!$B11,Premissas!$A$39:$E$43,4,0)))=0,"A","S"),"S")),"")) | C11: =IF(Cron_Uso!C11="","",IF(INT(Cron_Uso!C11/Frota!$L11)>INT(Cron_Uso!B11/Frota!$L11),IF(N(VLOOKUP(Frota!$B11,Premissas!$A$39:$E$43,5,0))>0,IF(MOD(INT(Cron_Uso!C11/Frota!$L11)*Frota!$L11,N(VLOOKUP(Frota!$B11,Premissas!$A$39:$E$43,5,0)))=0,"B",IF(N(VLOOKUP(Frota!$B11,Premissas!$A$39:$E$43,4,0))>0,IF(MOD(INT(Cron_Uso!C11/Frota!$L11)*Frota!$L11,N(VLOOKUP(Frota!$B11,Premissas!$A$39:$E$43,4,0)))=0,"A","S"),"S")),IF(N(VLOOKUP(Frota!$B11,Premissas!$A$39:$E$43,4,0))>0,IF(MOD(INT(Cron_Uso!C11/Frota!$L11)*Frota!$L11,N(VLOOKUP(Frota!$B11,Premissas!$A$39:$E$43,4,0)))=0,"A","S"),"S")),"")) | D11: =IF(Cron_Uso!D11="","",IF(INT(Cron_Uso!D11/Frota!$L11)>INT(Cron_Uso!C11/Frota!$L11),IF(N(VLOOKUP(Frota!$B11,Premissas!$A$39:$E$43,5,0))>0,IF(MOD(INT(Cron_Uso!D11/Frota!$L11)*Frota!$L11,N(VLOOKUP(Frota!$B11,Premissas!$A$39:$E$43,5,0)))=0,"B",IF(N(VLOOKUP(Frota!$B11,Premissas!$A$39:$E$43,4,0))>0,IF(MOD(INT(Cron_Uso!D11/Frota!$L11)*Frota!$L11,N(VLOOKUP(Frota!$B11,Premissas!$A$39:$E$43,4,0)))=0,"A","S"),"S")),IF(N(VLOOKUP(Frota!$B11,Premissas!$A$39:$E$43,4,0))>0,IF(MOD(INT(Cron_Uso!D11/Frota!$L11)*Frota!$L11,N(VLOOKUP(Frota!$B11,Premissas!$A$39:$E$43,4,0)))=0,"A","S"),"S")),"")) | E11: =IF(Cron_Uso!E11="","",IF(INT(Cron_Uso!E11/Frota!$L11)>INT(Cron_Uso!D11/Frota!$L11),IF(N(VLOOKUP(Frota!$B11,Premissas!$A$39:$E$43,5,0))>0,IF(MOD(INT(Cron_Uso!E11/Frota!$L11)*Frota!$L11,N(VLOOKUP(Frota!$B11,Premissas!$A$39:$E$43,5,0)))=0,"B",IF(N(VLOOKUP(Frota!$B11,Premissas!$A$39:$E$43,4,0))>0,IF(MOD(INT(Cron_Uso!E11/Frota!$L11)*Frota!$L11,N(VLOOKUP(Frota!$B11,Premissas!$A$39:$E$43,4,0)))=0,"A","S"),"S")),IF(N(VLOOKUP(Frota!$B11,Premissas!$A$39:$E$43,4,0))>0,IF(MOD(INT(Cron_Uso!E11/Frota!$L11)*Frota!$L11,N(VLOOKUP(Frota!$B11,Premissas!$A$39:$E$43,4,0)))=0,"A","S"),"S")),"")) -> S | F11: =IF(Cron_Uso!F11="","",IF(INT(Cron_Uso!F11/Frota!$L11)>INT(Cron_Uso!E11/Frota!$L11),IF(N(VLOOKUP(Frota!$B11,Premissas!$A$39:$E$43,5,0))>0,IF(MOD(INT(Cron_Uso!F11/Frota!$L11)*Frota!$L11,N(VLOOKUP(Frota!$B11,Premissas!$A$39:$E$43,5,0)))=0,"B",IF(N(VLOOKUP(Frota!$B11,Premissas!$A$39:$E$43,4,0))>0,IF(MOD(INT(Cron_Uso!F11/Frota!$L11)*Frota!$L11,N(VLOOKUP(Frota!$B11,Premissas!$A$39:$E$43,4,0)))=0,"A","S"),"S")),IF(N(VLOOKUP(Frota!$B11,Premissas!$A$39:$E$43,4,0))>0,IF(MOD(INT(Cron_Uso!F11/Frota!$L11)*Frota!$L11,N(VLOOKUP(Frota!$B11,Premissas!$A$39:$E$43,4,0)))=0,"A","S"),"S")),"")) | G11: =IF(Cron_Uso!G11="","",IF(INT(Cron_Uso!G11/Frota!$L11)>INT(Cron_Uso!F11/Frota!$L11),IF(N(VLOOKUP(Frota!$B11,Premissas!$A$39:$E$43,5,0))>0,IF(MOD(INT(Cron_Uso!G11/Frota!$L11)*Frota!$L11,N(VLOOKUP(Frota!$B11,Premissas!$A$39:$E$43,5,0)))=0,"B",IF(N(VLOOKUP(Frota!$B11,Premissas!$A$39:$E$43,4,0))>0,IF(MOD(INT(Cron_Uso!G11/Frota!$L11)*Frota!$L11,N(VLOOKUP(Frota!$B11,Premissas!$A$39:$E$43,4,0)))=0,"A","S"),"S")),IF(N(VLOOKUP(Frota!$B11,Premissas!$A$39:$E$43,4,0))>0,IF(MOD(INT(Cron_Uso!G11/Frota!$L11)*Frota!$L11,N(VLOOKUP(Frota!$B11,Premissas!$A$39:$E$43,4,0)))=0,"A","S"),"S")),"")) | H11: =IF(Cron_Uso!H11="","",IF(INT(Cron_Uso!H11/Frota!$L11)>INT(Cron_Uso!G11/Frota!$L11),IF(N(VLOOKUP(Frota!$B11,Premissas!$A$39:$E$43,5,0))>0,IF(MOD(INT(Cron_Uso!H11/Frota!$L11)*Frota!$L11,N(VLOOKUP(Frota!$B11,Premissas!$A$39:$E$43,5,0)))=0,"B",IF(N(VLOOKUP(Frota!$B11,Premissas!$A$39:$E$43,4,0))>0,IF(MOD(INT(Cron_Uso!H11/Frota!$L11)*Frota!$L11,N(VLOOKUP(Frota!$B11,Premissas!$A$39:$E$43,4,0)))=0,"A","S"),"S")),IF(N(VLOOKUP(Frota!$B11,Premissas!$A$39:$E$43,4,0))>0,IF(MOD(INT(Cron_Uso!H11/Frota!$L11)*Frota!$L11,N(VLOOKUP(Frota!$B11,Premissas!$A$39:$E$43,4,0)))=0,"A","S"),"S")),"")) | I11: =IF(Cron_Uso!I11="","",IF(INT(Cron_Uso!I11/Frota!$L11)>INT(Cron_Uso!H11/Frota!$L11),IF(N(VLOOKUP(Frota!$B11,Premissas!$A$39:$E$43,5,0))>0,IF(MOD(INT(Cron_Uso!I11/Frota!$L11)*Frota!$L11,N(VLOOKUP(Frota!$B11,Premissas!$A$39:$E$43,5,0)))=0,"B",IF(N(VLOOKUP(Frota!$B11,Premissas!$A$39:$E$43,4,0))>0,IF(MOD(INT(Cron_Uso!I11/Frota!$L11)*Frota!$L11,N(VLOOKUP(Frota!$B11,Premissas!$A$39:$E$43,4,0)))=0,"A","S"),"S")),IF(N(VLOOKUP(Frota!$B11,Premissas!$A$39:$E$43,4,0))>0,IF(MOD(INT(Cron_Uso!I11/Frota!$L11)*Frota!$L11,N(VLOOKUP(Frota!$B11,Premissas!$A$39:$E$43,4,0)))=0,"A","S"),"S")),"")) | J11: =IF(Cron_Uso!J11="","",IF(INT(Cron_Uso!J11/Frota!$L11)>INT(Cron_Uso!I11/Frota!$L11),IF(N(VLOOKUP(Frota!$B11,Premissas!$A$39:$E$43,5,0))>0,IF(MOD(INT(Cron_Uso!J11/Frota!$L11)*Frota!$L11,N(VLOOKUP(Frota!$B11,Premissas!$A$39:$E$43,5,0)))=0,"B",IF(N(VLOOKUP(Frota!$B11,Premissas!$A$39:$E$43,4,0))>0,IF(MOD(INT(Cron_Uso!J11/Frota!$L11)*Frota!$L11,N(VLOOKUP(Frota!$B11,Premissas!$A$39:$E$43,4,0)))=0,"A","S"),"S")),IF(N(VLOOKUP(Frota!$B11,Premissas!$A$39:$E$43,4,0))>0,IF(MOD(INT(Cron_Uso!J11/Frota!$L11)*Frota!$L11,N(VLOOKUP(Frota!$B11,Premissas!$A$39:$E$43,4,0)))=0,"A","S"),"S")),"")) -> A | ... BA11: =IF(Cron_Uso!BA11="","",IF(INT(Cron_Uso!BA11/Frota!$L11)>INT(Cron_Uso!AZ11/Frota!$L11),IF(N(VLOOKUP(Frota!$B11,Premissas!$A$39:$E$43,5,0))>0,IF(MOD(INT(Cron_Uso!BA11/Frota!$L11)*Frota!$L11,N(VLOOKUP(Frota!$B11,Premissas!$A$39:$E$43,5,0)))=0,"B",IF(N(VLOOKUP(Frota!$B11,Premissas!$A$39:$E$43,4,0))>0,IF(MOD(INT(Cron_Uso!BA11/Frota!$L11)*Frota!$L11,N(VLOOKUP(Frota!$B11,Premissas!$A$39:$E$43,4,0)))=0,"A","S"),"S")),IF(N(VLOOKUP(Frota!$B11,Premissas!$A$39:$E$43,4,0))>0,IF(MOD(INT(Cron_Uso!BA11/Frota!$L11)*Frota!$L11,N(VLOOKUP(Frota!$B11,Premissas!$A$39:$E$43,4,0)))=0,"A","S"),"S")),""))
A12: =IF(Frota!$A12="","",Frota!$A12) -> Caminhão Scania G480 — 2748 | B12: =IF(Cron_Uso!B12="","",IF(INT(Cron_Uso!B12/Frota!$L12)>INT(Frota!$I12/Frota!$L12),IF(N(VLOOKUP(Frota!$B12,Premissas!$A$39:$E$43,5,0))>0,IF(MOD(INT(Cron_Uso!B12/Frota!$L12)*Frota!$L12,N(VLOOKUP(Frota!$B12,Premissas!$A$39:$E$43,5,0)))=0,"B",IF(N(VLOOKUP(Frota!$B12,Premissas!$A$39:$E$43,4,0))>0,IF(MOD(INT(Cron_Uso!B12/Frota!$L12)*Frota!$L12,N(VLOOKUP(Frota!$B12,Premissas!$A$39:$E$43,4,0)))=0,"A","S"),"S")),IF(N(VLOOKUP(Frota!$B12,Premissas!$A$39:$E$43,4,0))>0,IF(MOD(INT(Cron_Uso!B12/Frota!$L12)*Frota!$L12,N(VLOOKUP(Frota!$B12,Premissas!$A$39:$E$43,4,0)))=0,"A","S"),"S")),"")) | C12: =IF(Cron_Uso!C12="","",IF(INT(Cron_Uso!C12/Frota!$L12)>INT(Cron_Uso!B12/Frota!$L12),IF(N(VLOOKUP(Frota!$B12,Premissas!$A$39:$E$43,5,0))>0,IF(MOD(INT(Cron_Uso!C12/Frota!$L12)*Frota!$L12,N(VLOOKUP(Frota!$B12,Premissas!$A$39:$E$43,5,0)))=0,"B",IF(N(VLOOKUP(Frota!$B12,Premissas!$A$39:$E$43,4,0))>0,IF(MOD(INT(Cron_Uso!C12/Frota!$L12)*Frota!$L12,N(VLOOKUP(Frota!$B12,Premissas!$A$39:$E$43,4,0)))=0,"A","S"),"S")),IF(N(VLOOKUP(Frota!$B12,Premissas!$A$39:$E$43,4,0))>0,IF(MOD(INT(Cron_Uso!C12/Frota!$L12)*Frota!$L12,N(VLOOKUP(Frota!$B12,Premissas!$A$39:$E$43,4,0)))=0,"A","S"),"S")),"")) | D12: =IF(Cron_Uso!D12="","",IF(INT(Cron_Uso!D12/Frota!$L12)>INT(Cron_Uso!C12/Frota!$L12),IF(N(VLOOKUP(Frota!$B12,Premissas!$A$39:$E$43,5,0))>0,IF(MOD(INT(Cron_Uso!D12/Frota!$L12)*Frota!$L12,N(VLOOKUP(Frota!$B12,Premissas!$A$39:$E$43,5,0)))=0,"B",IF(N(VLOOKUP(Frota!$B12,Premissas!$A$39:$E$43,4,0))>0,IF(MOD(INT(Cron_Uso!D12/Frota!$L12)*Frota!$L12,N(VLOOKUP(Frota!$B12,Premissas!$A$39:$E$43,4,0)))=0,"A","S"),"S")),IF(N(VLOOKUP(Frota!$B12,Premissas!$A$39:$E$43,4,0))>0,IF(MOD(INT(Cron_Uso!D12/Frota!$L12)*Frota!$L12,N(VLOOKUP(Frota!$B12,Premissas!$A$39:$E$43,4,0)))=0,"A","S"),"S")),"")) | E12: =IF(Cron_Uso!E12="","",IF(INT(Cron_Uso!E12/Frota!$L12)>INT(Cron_Uso!D12/Frota!$L12),IF(N(VLOOKUP(Frota!$B12,Premissas!$A$39:$E$43,5,0))>0,IF(MOD(INT(Cron_Uso!E12/Frota!$L12)*Frota!$L12,N(VLOOKUP(Frota!$B12,Premissas!$A$39:$E$43,5,0)))=0,"B",IF(N(VLOOKUP(Frota!$B12,Premissas!$A$39:$E$43,4,0))>0,IF(MOD(INT(Cron_Uso!E12/Frota!$L12)*Frota!$L12,N(VLOOKUP(Frota!$B12,Premissas!$A$39:$E$43,4,0)))=0,"A","S"),"S")),IF(N(VLOOKUP(Frota!$B12,Premissas!$A$39:$E$43,4,0))>0,IF(MOD(INT(Cron_Uso!E12/Frota!$L12)*Frota!$L12,N(VLOOKUP(Frota!$B12,Premissas!$A$39:$E$43,4,0)))=0,"A","S"),"S")),"")) | F12: =IF(Cron_Uso!F12="","",IF(INT(Cron_Uso!F12/Frota!$L12)>INT(Cron_Uso!E12/Frota!$L12),IF(N(VLOOKUP(Frota!$B12,Premissas!$A$39:$E$43,5,0))>0,IF(MOD(INT(Cron_Uso!F12/Frota!$L12)*Frota!$L12,N(VLOOKUP(Frota!$B12,Premissas!$A$39:$E$43,5,0)))=0,"B",IF(N(VLOOKUP(Frota!$B12,Premissas!$A$39:$E$43,4,0))>0,IF(MOD(INT(Cron_Uso!F12/Frota!$L12)*Frota!$L12,N(VLOOKUP(Frota!$B12,Premissas!$A$39:$E$43,4,0)))=0,"A","S"),"S")),IF(N(VLOOKUP(Frota!$B12,Premissas!$A$39:$E$43,4,0))>0,IF(MOD(INT(Cron_Uso!F12/Frota!$L12)*Frota!$L12,N(VLOOKUP(Frota!$B12,Premissas!$A$39:$E$43,4,0)))=0,"A","S"),"S")),"")) -> S | G12: =IF(Cron_Uso!G12="","",IF(INT(Cron_Uso!G12/Frota!$L12)>INT(Cron_Uso!F12/Frota!$L12),IF(N(VLOOKUP(Frota!$B12,Premissas!$A$39:$E$43,5,0))>0,IF(MOD(INT(Cron_Uso!G12/Frota!$L12)*Frota!$L12,N(VLOOKUP(Frota!$B12,Premissas!$A$39:$E$43,5,0)))=0,"B",IF(N(VLOOKUP(Frota!$B12,Premissas!$A$39:$E$43,4,0))>0,IF(MOD(INT(Cron_Uso!G12/Frota!$L12)*Frota!$L12,N(VLOOKUP(Frota!$B12,Premissas!$A$39:$E$43,4,0)))=0,"A","S"),"S")),IF(N(VLOOKUP(Frota!$B12,Premissas!$A$39:$E$43,4,0))>0,IF(MOD(INT(Cron_Uso!G12/Frota!$L12)*Frota!$L12,N(VLOOKUP(Frota!$B12,Premissas!$A$39:$E$43,4,0)))=0,"A","S"),"S")),"")) | H12: =IF(Cron_Uso!H12="","",IF(INT(Cron_Uso!H12/Frota!$L12)>INT(Cron_Uso!G12/Frota!$L12),IF(N(VLOOKUP(Frota!$B12,Premissas!$A$39:$E$43,5,0))>0,IF(MOD(INT(Cron_Uso!H12/Frota!$L12)*Frota!$L12,N(VLOOKUP(Frota!$B12,Premissas!$A$39:$E$43,5,0)))=0,"B",IF(N(VLOOKUP(Frota!$B12,Premissas!$A$39:$E$43,4,0))>0,IF(MOD(INT(Cron_Uso!H12/Frota!$L12)*Frota!$L12,N(VLOOKUP(Frota!$B12,Premissas!$A$39:$E$43,4,0)))=0,"A","S"),"S")),IF(N(VLOOKUP(Frota!$B12,Premissas!$A$39:$E$43,4,0))>0,IF(MOD(INT(Cron_Uso!H12/Frota!$L12)*Frota!$L12,N(VLOOKUP(Frota!$B12,Premissas!$A$39:$E$43,4,0)))=0,"A","S"),"S")),"")) | I12: =IF(Cron_Uso!I12="","",IF(INT(Cron_Uso!I12/Frota!$L12)>INT(Cron_Uso!H12/Frota!$L12),IF(N(VLOOKUP(Frota!$B12,Premissas!$A$39:$E$43,5,0))>0,IF(MOD(INT(Cron_Uso!I12/Frota!$L12)*Frota!$L12,N(VLOOKUP(Frota!$B12,Premissas!$A$39:$E$43,5,0)))=0,"B",IF(N(VLOOKUP(Frota!$B12,Premissas!$A$39:$E$43,4,0))>0,IF(MOD(INT(Cron_Uso!I12/Frota!$L12)*Frota!$L12,N(VLOOKUP(Frota!$B12,Premissas!$A$39:$E$43,4,0)))=0,"A","S"),"S")),IF(N(VLOOKUP(Frota!$B12,Premissas!$A$39:$E$43,4,0))>0,IF(MOD(INT(Cron_Uso!I12/Frota!$L12)*Frota!$L12,N(VLOOKUP(Frota!$B12,Premissas!$A$39:$E$43,4,0)))=0,"A","S"),"S")),"")) | J12: =IF(Cron_Uso!J12="","",IF(INT(Cron_Uso!J12/Frota!$L12)>INT(Cron_Uso!I12/Frota!$L12),IF(N(VLOOKUP(Frota!$B12,Premissas!$A$39:$E$43,5,0))>0,IF(MOD(INT(Cron_Uso!J12/Frota!$L12)*Frota!$L12,N(VLOOKUP(Frota!$B12,Premissas!$A$39:$E$43,5,0)))=0,"B",IF(N(VLOOKUP(Frota!$B12,Premissas!$A$39:$E$43,4,0))>0,IF(MOD(INT(Cron_Uso!J12/Frota!$L12)*Frota!$L12,N(VLOOKUP(Frota!$B12,Premissas!$A$39:$E$43,4,0)))=0,"A","S"),"S")),IF(N(VLOOKUP(Frota!$B12,Premissas!$A$39:$E$43,4,0))>0,IF(MOD(INT(Cron_Uso!J12/Frota!$L12)*Frota!$L12,N(VLOOKUP(Frota!$B12,Premissas!$A$39:$E$43,4,0)))=0,"A","S"),"S")),"")) | ... BA12: =IF(Cron_Uso!BA12="","",IF(INT(Cron_Uso!BA12/Frota!$L12)>INT(Cron_Uso!AZ12/Frota!$L12),IF(N(VLOOKUP(Frota!$B12,Premissas!$A$39:$E$43,5,0))>0,IF(MOD(INT(Cron_Uso!BA12/Frota!$L12)*Frota!$L12,N(VLOOKUP(Frota!$B12,Premissas!$A$39:$E$43,5,0)))=0,"B",IF(N(VLOOKUP(Frota!$B12,Premissas!$A$39:$E$43,4,0))>0,IF(MOD(INT(Cron_Uso!BA12/Frota!$L12)*Frota!$L12,N(VLOOKUP(Frota!$B12,Premissas!$A$39:$E$43,4,0)))=0,"A","S"),"S")),IF(N(VLOOKUP(Frota!$B12,Premissas!$A$39:$E$43,4,0))>0,IF(MOD(INT(Cron_Uso!BA12/Frota!$L12)*Frota!$L12,N(VLOOKUP(Frota!$B12,Premissas!$A$39:$E$43,4,0)))=0,"A","S"),"S")),""))
A13: =IF(Frota!$A13="","",Frota!$A13) -> Caminhão Scania G540 — 2763 | B13: =IF(Cron_Uso!B13="","",IF(INT(Cron_Uso!B13/Frota!$L13)>INT(Frota!$I13/Frota!$L13),IF(N(VLOOKUP(Frota!$B13,Premissas!$A$39:$E$43,5,0))>0,IF(MOD(INT(Cron_Uso!B13/Frota!$L13)*Frota!$L13,N(VLOOKUP(Frota!$B13,Premissas!$A$39:$E$43,5,0)))=0,"B",IF(N(VLOOKUP(Frota!$B13,Premissas!$A$39:$E$43,4,0))>0,IF(MOD(INT(Cron_Uso!B13/Frota!$L13)*Frota!$L13,N(VLOOKUP(Frota!$B13,Premissas!$A$39:$E$43,4,0)))=0,"A","S"),"S")),IF(N(VLOOKUP(Frota!$B13,Premissas!$A$39:$E$43,4,0))>0,IF(MOD(INT(Cron_Uso!B13/Frota!$L13)*Frota!$L13,N(VLOOKUP(Frota!$B13,Premissas!$A$39:$E$43,4,0)))=0,"A","S"),"S")),"")) | C13: =IF(Cron_Uso!C13="","",IF(INT(Cron_Uso!C13/Frota!$L13)>INT(Cron_Uso!B13/Frota!$L13),IF(N(VLOOKUP(Frota!$B13,Premissas!$A$39:$E$43,5,0))>0,IF(MOD(INT(Cron_Uso!C13/Frota!$L13)*Frota!$L13,N(VLOOKUP(Frota!$B13,Premissas!$A$39:$E$43,5,0)))=0,"B",IF(N(VLOOKUP(Frota!$B13,Premissas!$A$39:$E$43,4,0))>0,IF(MOD(INT(Cron_Uso!C13/Frota!$L13)*Frota!$L13,N(VLOOKUP(Frota!$B13,Premissas!$A$39:$E$43,4,0)))=0,"A","S"),"S")),IF(N(VLOOKUP(Frota!$B13,Premissas!$A$39:$E$43,4,0))>0,IF(MOD(INT(Cron_Uso!C13/Frota!$L13)*Frota!$L13,N(VLOOKUP(Frota!$B13,Premissas!$A$39:$E$43,4,0)))=0,"A","S"),"S")),"")) | D13: =IF(Cron_Uso!D13="","",IF(INT(Cron_Uso!D13/Frota!$L13)>INT(Cron_Uso!C13/Frota!$L13),IF(N(VLOOKUP(Frota!$B13,Premissas!$A$39:$E$43,5,0))>0,IF(MOD(INT(Cron_Uso!D13/Frota!$L13)*Frota!$L13,N(VLOOKUP(Frota!$B13,Premissas!$A$39:$E$43,5,0)))=0,"B",IF(N(VLOOKUP(Frota!$B13,Premissas!$A$39:$E$43,4,0))>0,IF(MOD(INT(Cron_Uso!D13/Frota!$L13)*Frota!$L13,N(VLOOKUP(Frota!$B13,Premissas!$A$39:$E$43,4,0)))=0,"A","S"),"S")),IF(N(VLOOKUP(Frota!$B13,Premissas!$A$39:$E$43,4,0))>0,IF(MOD(INT(Cron_Uso!D13/Frota!$L13)*Frota!$L13,N(VLOOKUP(Frota!$B13,Premissas!$A$39:$E$43,4,0)))=0,"A","S"),"S")),"")) | E13: =IF(Cron_Uso!E13="","",IF(INT(Cron_Uso!E13/Frota!$L13)>INT(Cron_Uso!D13/Frota!$L13),IF(N(VLOOKUP(Frota!$B13,Premissas!$A$39:$E$43,5,0))>0,IF(MOD(INT(Cron_Uso!E13/Frota!$L13)*Frota!$L13,N(VLOOKUP(Frota!$B13,Premissas!$A$39:$E$43,5,0)))=0,"B",IF(N(VLOOKUP(Frota!$B13,Premissas!$A$39:$E$43,4,0))>0,IF(MOD(INT(Cron_Uso!E13/Frota!$L13)*Frota!$L13,N(VLOOKUP(Frota!$B13,Premissas!$A$39:$E$43,4,0)))=0,"A","S"),"S")),IF(N(VLOOKUP(Frota!$B13,Premissas!$A$39:$E$43,4,0))>0,IF(MOD(INT(Cron_Uso!E13/Frota!$L13)*Frota!$L13,N(VLOOKUP(Frota!$B13,Premissas!$A$39:$E$43,4,0)))=0,"A","S"),"S")),"")) -> S | F13: =IF(Cron_Uso!F13="","",IF(INT(Cron_Uso!F13/Frota!$L13)>INT(Cron_Uso!E13/Frota!$L13),IF(N(VLOOKUP(Frota!$B13,Premissas!$A$39:$E$43,5,0))>0,IF(MOD(INT(Cron_Uso!F13/Frota!$L13)*Frota!$L13,N(VLOOKUP(Frota!$B13,Premissas!$A$39:$E$43,5,0)))=0,"B",IF(N(VLOOKUP(Frota!$B13,Premissas!$A$39:$E$43,4,0))>0,IF(MOD(INT(Cron_Uso!F13/Frota!$L13)*Frota!$L13,N(VLOOKUP(Frota!$B13,Premissas!$A$39:$E$43,4,0)))=0,"A","S"),"S")),IF(N(VLOOKUP(Frota!$B13,Premissas!$A$39:$E$43,4,0))>0,IF(MOD(INT(Cron_Uso!F13/Frota!$L13)*Frota!$L13,N(VLOOKUP(Frota!$B13,Premissas!$A$39:$E$43,4,0)))=0,"A","S"),"S")),"")) | G13: =IF(Cron_Uso!G13="","",IF(INT(Cron_Uso!G13/Frota!$L13)>INT(Cron_Uso!F13/Frota!$L13),IF(N(VLOOKUP(Frota!$B13,Premissas!$A$39:$E$43,5,0))>0,IF(MOD(INT(Cron_Uso!G13/Frota!$L13)*Frota!$L13,N(VLOOKUP(Frota!$B13,Premissas!$A$39:$E$43,5,0)))=0,"B",IF(N(VLOOKUP(Frota!$B13,Premissas!$A$39:$E$43,4,0))>0,IF(MOD(INT(Cron_Uso!G13/Frota!$L13)*Frota!$L13,N(VLOOKUP(Frota!$B13,Premissas!$A$39:$E$43,4,0)))=0,"A","S"),"S")),IF(N(VLOOKUP(Frota!$B13,Premissas!$A$39:$E$43,4,0))>0,IF(MOD(INT(Cron_Uso!G13/Frota!$L13)*Frota!$L13,N(VLOOKUP(Frota!$B13,Premissas!$A$39:$E$43,4,0)))=0,"A","S"),"S")),"")) | H13: =IF(Cron_Uso!H13="","",IF(INT(Cron_Uso!H13/Frota!$L13)>INT(Cron_Uso!G13/Frota!$L13),IF(N(VLOOKUP(Frota!$B13,Premissas!$A$39:$E$43,5,0))>0,IF(MOD(INT(Cron_Uso!H13/Frota!$L13)*Frota!$L13,N(VLOOKUP(Frota!$B13,Premissas!$A$39:$E$43,5,0)))=0,"B",IF(N(VLOOKUP(Frota!$B13,Premissas!$A$39:$E$43,4,0))>0,IF(MOD(INT(Cron_Uso!H13/Frota!$L13)*Frota!$L13,N(VLOOKUP(Frota!$B13,Premissas!$A$39:$E$43,4,0)))=0,"A","S"),"S")),IF(N(VLOOKUP(Frota!$B13,Premissas!$A$39:$E$43,4,0))>0,IF(MOD(INT(Cron_Uso!H13/Frota!$L13)*Frota!$L13,N(VLOOKUP(Frota!$B13,Premissas!$A$39:$E$43,4,0)))=0,"A","S"),"S")),"")) | I13: =IF(Cron_Uso!I13="","",IF(INT(Cron_Uso!I13/Frota!$L13)>INT(Cron_Uso!H13/Frota!$L13),IF(N(VLOOKUP(Frota!$B13,Premissas!$A$39:$E$43,5,0))>0,IF(MOD(INT(Cron_Uso!I13/Frota!$L13)*Frota!$L13,N(VLOOKUP(Frota!$B13,Premissas!$A$39:$E$43,5,0)))=0,"B",IF(N(VLOOKUP(Frota!$B13,Premissas!$A$39:$E$43,4,0))>0,IF(MOD(INT(Cron_Uso!I13/Frota!$L13)*Frota!$L13,N(VLOOKUP(Frota!$B13,Premissas!$A$39:$E$43,4,0)))=0,"A","S"),"S")),IF(N(VLOOKUP(Frota!$B13,Premissas!$A$39:$E$43,4,0))>0,IF(MOD(INT(Cron_Uso!I13/Frota!$L13)*Frota!$L13,N(VLOOKUP(Frota!$B13,Premissas!$A$39:$E$43,4,0)))=0,"A","S"),"S")),"")) | J13: =IF(Cron_Uso!J13="","",IF(INT(Cron_Uso!J13/Frota!$L13)>INT(Cron_Uso!I13/Frota!$L13),IF(N(VLOOKUP(Frota!$B13,Premissas!$A$39:$E$43,5,0))>0,IF(MOD(INT(Cron_Uso!J13/Frota!$L13)*Frota!$L13,N(VLOOKUP(Frota!$B13,Premissas!$A$39:$E$43,5,0)))=0,"B",IF(N(VLOOKUP(Frota!$B13,Premissas!$A$39:$E$43,4,0))>0,IF(MOD(INT(Cron_Uso!J13/Frota!$L13)*Frota!$L13,N(VLOOKUP(Frota!$B13,Premissas!$A$39:$E$43,4,0)))=0,"A","S"),"S")),IF(N(VLOOKUP(Frota!$B13,Premissas!$A$39:$E$43,4,0))>0,IF(MOD(INT(Cron_Uso!J13/Frota!$L13)*Frota!$L13,N(VLOOKUP(Frota!$B13,Premissas!$A$39:$E$43,4,0)))=0,"A","S"),"S")),"")) | ... BA13: =IF(Cron_Uso!BA13="","",IF(INT(Cron_Uso!BA13/Frota!$L13)>INT(Cron_Uso!AZ13/Frota!$L13),IF(N(VLOOKUP(Frota!$B13,Premissas!$A$39:$E$43,5,0))>0,IF(MOD(INT(Cron_Uso!BA13/Frota!$L13)*Frota!$L13,N(VLOOKUP(Frota!$B13,Premissas!$A$39:$E$43,5,0)))=0,"B",IF(N(VLOOKUP(Frota!$B13,Premissas!$A$39:$E$43,4,0))>0,IF(MOD(INT(Cron_Uso!BA13/Frota!$L13)*Frota!$L13,N(VLOOKUP(Frota!$B13,Premissas!$A$39:$E$43,4,0)))=0,"A","S"),"S")),IF(N(VLOOKUP(Frota!$B13,Premissas!$A$39:$E$43,4,0))>0,IF(MOD(INT(Cron_Uso!BA13/Frota!$L13)*Frota!$L13,N(VLOOKUP(Frota!$B13,Premissas!$A$39:$E$43,4,0)))=0,"A","S"),"S")),"")) -> A
A14: =IF(Frota!$A14="","",Frota!$A14) -> Transbordo Mambra 20t — 801 | B14: =IF(Cron_Uso!B14="","",IF(INT(Cron_Uso!B14/Frota!$L14)>INT(Frota!$I14/Frota!$L14),IF(N(VLOOKUP(Frota!$B14,Premissas!$A$39:$E$43,5,0))>0,IF(MOD(INT(Cron_Uso!B14/Frota!$L14)*Frota!$L14,N(VLOOKUP(Frota!$B14,Premissas!$A$39:$E$43,5,0)))=0,"B",IF(N(VLOOKUP(Frota!$B14,Premissas!$A$39:$E$43,4,0))>0,IF(MOD(INT(Cron_Uso!B14/Frota!$L14)*Frota!$L14,N(VLOOKUP(Frota!$B14,Premissas!$A$39:$E$43,4,0)))=0,"A","S"),"S")),IF(N(VLOOKUP(Frota!$B14,Premissas!$A$39:$E$43,4,0))>0,IF(MOD(INT(Cron_Uso!B14/Frota!$L14)*Frota!$L14,N(VLOOKUP(Frota!$B14,Premissas!$A$39:$E$43,4,0)))=0,"A","S"),"S")),"")) | C14: =IF(Cron_Uso!C14="","",IF(INT(Cron_Uso!C14/Frota!$L14)>INT(Cron_Uso!B14/Frota!$L14),IF(N(VLOOKUP(Frota!$B14,Premissas!$A$39:$E$43,5,0))>0,IF(MOD(INT(Cron_Uso!C14/Frota!$L14)*Frota!$L14,N(VLOOKUP(Frota!$B14,Premissas!$A$39:$E$43,5,0)))=0,"B",IF(N(VLOOKUP(Frota!$B14,Premissas!$A$39:$E$43,4,0))>0,IF(MOD(INT(Cron_Uso!C14/Frota!$L14)*Frota!$L14,N(VLOOKUP(Frota!$B14,Premissas!$A$39:$E$43,4,0)))=0,"A","S"),"S")),IF(N(VLOOKUP(Frota!$B14,Premissas!$A$39:$E$43,4,0))>0,IF(MOD(INT(Cron_Uso!C14/Frota!$L14)*Frota!$L14,N(VLOOKUP(Frota!$B14,Premissas!$A$39:$E$43,4,0)))=0,"A","S"),"S")),"")) | D14: =IF(Cron_Uso!D14="","",IF(INT(Cron_Uso!D14/Frota!$L14)>INT(Cron_Uso!C14/Frota!$L14),IF(N(VLOOKUP(Frota!$B14,Premissas!$A$39:$E$43,5,0))>0,IF(MOD(INT(Cron_Uso!D14/Frota!$L14)*Frota!$L14,N(VLOOKUP(Frota!$B14,Premissas!$A$39:$E$43,5,0)))=0,"B",IF(N(VLOOKUP(Frota!$B14,Premissas!$A$39:$E$43,4,0))>0,IF(MOD(INT(Cron_Uso!D14/Frota!$L14)*Frota!$L14,N(VLOOKUP(Frota!$B14,Premissas!$A$39:$E$43,4,0)))=0,"A","S"),"S")),IF(N(VLOOKUP(Frota!$B14,Premissas!$A$39:$E$43,4,0))>0,IF(MOD(INT(Cron_Uso!D14/Frota!$L14)*Frota!$L14,N(VLOOKUP(Frota!$B14,Premissas!$A$39:$E$43,4,0)))=0,"A","S"),"S")),"")) | E14: =IF(Cron_Uso!E14="","",IF(INT(Cron_Uso!E14/Frota!$L14)>INT(Cron_Uso!D14/Frota!$L14),IF(N(VLOOKUP(Frota!$B14,Premissas!$A$39:$E$43,5,0))>0,IF(MOD(INT(Cron_Uso!E14/Frota!$L14)*Frota!$L14,N(VLOOKUP(Frota!$B14,Premissas!$A$39:$E$43,5,0)))=0,"B",IF(N(VLOOKUP(Frota!$B14,Premissas!$A$39:$E$43,4,0))>0,IF(MOD(INT(Cron_Uso!E14/Frota!$L14)*Frota!$L14,N(VLOOKUP(Frota!$B14,Premissas!$A$39:$E$43,4,0)))=0,"A","S"),"S")),IF(N(VLOOKUP(Frota!$B14,Premissas!$A$39:$E$43,4,0))>0,IF(MOD(INT(Cron_Uso!E14/Frota!$L14)*Frota!$L14,N(VLOOKUP(Frota!$B14,Premissas!$A$39:$E$43,4,0)))=0,"A","S"),"S")),"")) | F14: =IF(Cron_Uso!F14="","",IF(INT(Cron_Uso!F14/Frota!$L14)>INT(Cron_Uso!E14/Frota!$L14),IF(N(VLOOKUP(Frota!$B14,Premissas!$A$39:$E$43,5,0))>0,IF(MOD(INT(Cron_Uso!F14/Frota!$L14)*Frota!$L14,N(VLOOKUP(Frota!$B14,Premissas!$A$39:$E$43,5,0)))=0,"B",IF(N(VLOOKUP(Frota!$B14,Premissas!$A$39:$E$43,4,0))>0,IF(MOD(INT(Cron_Uso!F14/Frota!$L14)*Frota!$L14,N(VLOOKUP(Frota!$B14,Premissas!$A$39:$E$43,4,0)))=0,"A","S"),"S")),IF(N(VLOOKUP(Frota!$B14,Premissas!$A$39:$E$43,4,0))>0,IF(MOD(INT(Cron_Uso!F14/Frota!$L14)*Frota!$L14,N(VLOOKUP(Frota!$B14,Premissas!$A$39:$E$43,4,0)))=0,"A","S"),"S")),"")) | G14: =IF(Cron_Uso!G14="","",IF(INT(Cron_Uso!G14/Frota!$L14)>INT(Cron_Uso!F14/Frota!$L14),IF(N(VLOOKUP(Frota!$B14,Premissas!$A$39:$E$43,5,0))>0,IF(MOD(INT(Cron_Uso!G14/Frota!$L14)*Frota!$L14,N(VLOOKUP(Frota!$B14,Premissas!$A$39:$E$43,5,0)))=0,"B",IF(N(VLOOKUP(Frota!$B14,Premissas!$A$39:$E$43,4,0))>0,IF(MOD(INT(Cron_Uso!G14/Frota!$L14)*Frota!$L14,N(VLOOKUP(Frota!$B14,Premissas!$A$39:$E$43,4,0)))=0,"A","S"),"S")),IF(N(VLOOKUP(Frota!$B14,Premissas!$A$39:$E$43,4,0))>0,IF(MOD(INT(Cron_Uso!G14/Frota!$L14)*Frota!$L14,N(VLOOKUP(Frota!$B14,Premissas!$A$39:$E$43,4,0)))=0,"A","S"),"S")),"")) | H14: =IF(Cron_Uso!H14="","",IF(INT(Cron_Uso!H14/Frota!$L14)>INT(Cron_Uso!G14/Frota!$L14),IF(N(VLOOKUP(Frota!$B14,Premissas!$A$39:$E$43,5,0))>0,IF(MOD(INT(Cron_Uso!H14/Frota!$L14)*Frota!$L14,N(VLOOKUP(Frota!$B14,Premissas!$A$39:$E$43,5,0)))=0,"B",IF(N(VLOOKUP(Frota!$B14,Premissas!$A$39:$E$43,4,0))>0,IF(MOD(INT(Cron_Uso!H14/Frota!$L14)*Frota!$L14,N(VLOOKUP(Frota!$B14,Premissas!$A$39:$E$43,4,0)))=0,"A","S"),"S")),IF(N(VLOOKUP(Frota!$B14,Premissas!$A$39:$E$43,4,0))>0,IF(MOD(INT(Cron_Uso!H14/Frota!$L14)*Frota!$L14,N(VLOOKUP(Frota!$B14,Premissas!$A$39:$E$43,4,0)))=0,"A","S"),"S")),"")) | I14: =IF(Cron_Uso!I14="","",IF(INT(Cron_Uso!I14/Frota!$L14)>INT(Cron_Uso!H14/Frota!$L14),IF(N(VLOOKUP(Frota!$B14,Premissas!$A$39:$E$43,5,0))>0,IF(MOD(INT(Cron_Uso!I14/Frota!$L14)*Frota!$L14,N(VLOOKUP(Frota!$B14,Premissas!$A$39:$E$43,5,0)))=0,"B",IF(N(VLOOKUP(Frota!$B14,Premissas!$A$39:$E$43,4,0))>0,IF(MOD(INT(Cron_Uso!I14/Frota!$L14)*Frota!$L14,N(VLOOKUP(Frota!$B14,Premissas!$A$39:$E$43,4,0)))=0,"A","S"),"S")),IF(N(VLOOKUP(Frota!$B14,Premissas!$A$39:$E$43,4,0))>0,IF(MOD(INT(Cron_Uso!I14/Frota!$L14)*Frota!$L14,N(VLOOKUP(Frota!$B14,Premissas!$A$39:$E$43,4,0)))=0,"A","S"),"S")),"")) -> S | J14: =IF(Cron_Uso!J14="","",IF(INT(Cron_Uso!J14/Frota!$L14)>INT(Cron_Uso!I14/Frota!$L14),IF(N(VLOOKUP(Frota!$B14,Premissas!$A$39:$E$43,5,0))>0,IF(MOD(INT(Cron_Uso!J14/Frota!$L14)*Frota!$L14,N(VLOOKUP(Frota!$B14,Premissas!$A$39:$E$43,5,0)))=0,"B",IF(N(VLOOKUP(Frota!$B14,Premissas!$A$39:$E$43,4,0))>0,IF(MOD(INT(Cron_Uso!J14/Frota!$L14)*Frota!$L14,N(VLOOKUP(Frota!$B14,Premissas!$A$39:$E$43,4,0)))=0,"A","S"),"S")),IF(N(VLOOKUP(Frota!$B14,Premissas!$A$39:$E$43,4,0))>0,IF(MOD(INT(Cron_Uso!J14/Frota!$L14)*Frota!$L14,N(VLOOKUP(Frota!$B14,Premissas!$A$39:$E$43,4,0)))=0,"A","S"),"S")),"")) | ... BA14: =IF(Cron_Uso!BA14="","",IF(INT(Cron_Uso!BA14/Frota!$L14)>INT(Cron_Uso!AZ14/Frota!$L14),IF(N(VLOOKUP(Frota!$B14,Premissas!$A$39:$E$43,5,0))>0,IF(MOD(INT(Cron_Uso!BA14/Frota!$L14)*Frota!$L14,N(VLOOKUP(Frota!$B14,Premissas!$A$39:$E$43,5,0)))=0,"B",IF(N(VLOOKUP(Frota!$B14,Premissas!$A$39:$E$43,4,0))>0,IF(MOD(INT(Cron_Uso!BA14/Frota!$L14)*Frota!$L14,N(VLOOKUP(Frota!$B14,Premissas!$A$39:$E$43,4,0)))=0,"A","S"),"S")),IF(N(VLOOKUP(Frota!$B14,Premissas!$A$39:$E$43,4,0))>0,IF(MOD(INT(Cron_Uso!BA14/Frota!$L14)*Frota!$L14,N(VLOOKUP(Frota!$B14,Premissas!$A$39:$E$43,4,0)))=0,"A","S"),"S")),""))
A15: =IF(Frota!$A15="","",Frota!$A15) -> Implemento Distribuidor — 802 | B15: =IF(Cron_Uso!B15="","",IF(INT(Cron_Uso!B15/Frota!$L15)>INT(Frota!$I15/Frota!$L15),IF(N(VLOOKUP(Frota!$B15,Premissas!$A$39:$E$43,5,0))>0,IF(MOD(INT(Cron_Uso!B15/Frota!$L15)*Frota!$L15,N(VLOOKUP(Frota!$B15,Premissas!$A$39:$E$43,5,0)))=0,"B",IF(N(VLOOKUP(Frota!$B15,Premissas!$A$39:$E$43,4,0))>0,IF(MOD(INT(Cron_Uso!B15/Frota!$L15)*Frota!$L15,N(VLOOKUP(Frota!$B15,Premissas!$A$39:$E$43,4,0)))=0,"A","S"),"S")),IF(N(VLOOKUP(Frota!$B15,Premissas!$A$39:$E$43,4,0))>0,IF(MOD(INT(Cron_Uso!B15/Frota!$L15)*Frota!$L15,N(VLOOKUP(Frota!$B15,Premissas!$A$39:$E$43,4,0)))=0,"A","S"),"S")),"")) | C15: =IF(Cron_Uso!C15="","",IF(INT(Cron_Uso!C15/Frota!$L15)>INT(Cron_Uso!B15/Frota!$L15),IF(N(VLOOKUP(Frota!$B15,Premissas!$A$39:$E$43,5,0))>0,IF(MOD(INT(Cron_Uso!C15/Frota!$L15)*Frota!$L15,N(VLOOKUP(Frota!$B15,Premissas!$A$39:$E$43,5,0)))=0,"B",IF(N(VLOOKUP(Frota!$B15,Premissas!$A$39:$E$43,4,0))>0,IF(MOD(INT(Cron_Uso!C15/Frota!$L15)*Frota!$L15,N(VLOOKUP(Frota!$B15,Premissas!$A$39:$E$43,4,0)))=0,"A","S"),"S")),IF(N(VLOOKUP(Frota!$B15,Premissas!$A$39:$E$43,4,0))>0,IF(MOD(INT(Cron_Uso!C15/Frota!$L15)*Frota!$L15,N(VLOOKUP(Frota!$B15,Premissas!$A$39:$E$43,4,0)))=0,"A","S"),"S")),"")) | D15: =IF(Cron_Uso!D15="","",IF(INT(Cron_Uso!D15/Frota!$L15)>INT(Cron_Uso!C15/Frota!$L15),IF(N(VLOOKUP(Frota!$B15,Premissas!$A$39:$E$43,5,0))>0,IF(MOD(INT(Cron_Uso!D15/Frota!$L15)*Frota!$L15,N(VLOOKUP(Frota!$B15,Premissas!$A$39:$E$43,5,0)))=0,"B",IF(N(VLOOKUP(Frota!$B15,Premissas!$A$39:$E$43,4,0))>0,IF(MOD(INT(Cron_Uso!D15/Frota!$L15)*Frota!$L15,N(VLOOKUP(Frota!$B15,Premissas!$A$39:$E$43,4,0)))=0,"A","S"),"S")),IF(N(VLOOKUP(Frota!$B15,Premissas!$A$39:$E$43,4,0))>0,IF(MOD(INT(Cron_Uso!D15/Frota!$L15)*Frota!$L15,N(VLOOKUP(Frota!$B15,Premissas!$A$39:$E$43,4,0)))=0,"A","S"),"S")),"")) | E15: =IF(Cron_Uso!E15="","",IF(INT(Cron_Uso!E15/Frota!$L15)>INT(Cron_Uso!D15/Frota!$L15),IF(N(VLOOKUP(Frota!$B15,Premissas!$A$39:$E$43,5,0))>0,IF(MOD(INT(Cron_Uso!E15/Frota!$L15)*Frota!$L15,N(VLOOKUP(Frota!$B15,Premissas!$A$39:$E$43,5,0)))=0,"B",IF(N(VLOOKUP(Frota!$B15,Premissas!$A$39:$E$43,4,0))>0,IF(MOD(INT(Cron_Uso!E15/Frota!$L15)*Frota!$L15,N(VLOOKUP(Frota!$B15,Premissas!$A$39:$E$43,4,0)))=0,"A","S"),"S")),IF(N(VLOOKUP(Frota!$B15,Premissas!$A$39:$E$43,4,0))>0,IF(MOD(INT(Cron_Uso!E15/Frota!$L15)*Frota!$L15,N(VLOOKUP(Frota!$B15,Premissas!$A$39:$E$43,4,0)))=0,"A","S"),"S")),"")) | F15: =IF(Cron_Uso!F15="","",IF(INT(Cron_Uso!F15/Frota!$L15)>INT(Cron_Uso!E15/Frota!$L15),IF(N(VLOOKUP(Frota!$B15,Premissas!$A$39:$E$43,5,0))>0,IF(MOD(INT(Cron_Uso!F15/Frota!$L15)*Frota!$L15,N(VLOOKUP(Frota!$B15,Premissas!$A$39:$E$43,5,0)))=0,"B",IF(N(VLOOKUP(Frota!$B15,Premissas!$A$39:$E$43,4,0))>0,IF(MOD(INT(Cron_Uso!F15/Frota!$L15)*Frota!$L15,N(VLOOKUP(Frota!$B15,Premissas!$A$39:$E$43,4,0)))=0,"A","S"),"S")),IF(N(VLOOKUP(Frota!$B15,Premissas!$A$39:$E$43,4,0))>0,IF(MOD(INT(Cron_Uso!F15/Frota!$L15)*Frota!$L15,N(VLOOKUP(Frota!$B15,Premissas!$A$39:$E$43,4,0)))=0,"A","S"),"S")),"")) | G15: =IF(Cron_Uso!G15="","",IF(INT(Cron_Uso!G15/Frota!$L15)>INT(Cron_Uso!F15/Frota!$L15),IF(N(VLOOKUP(Frota!$B15,Premissas!$A$39:$E$43,5,0))>0,IF(MOD(INT(Cron_Uso!G15/Frota!$L15)*Frota!$L15,N(VLOOKUP(Frota!$B15,Premissas!$A$39:$E$43,5,0)))=0,"B",IF(N(VLOOKUP(Frota!$B15,Premissas!$A$39:$E$43,4,0))>0,IF(MOD(INT(Cron_Uso!G15/Frota!$L15)*Frota!$L15,N(VLOOKUP(Frota!$B15,Premissas!$A$39:$E$43,4,0)))=0,"A","S"),"S")),IF(N(VLOOKUP(Frota!$B15,Premissas!$A$39:$E$43,4,0))>0,IF(MOD(INT(Cron_Uso!G15/Frota!$L15)*Frota!$L15,N(VLOOKUP(Frota!$B15,Premissas!$A$39:$E$43,4,0)))=0,"A","S"),"S")),"")) | H15: =IF(Cron_Uso!H15="","",IF(INT(Cron_Uso!H15/Frota!$L15)>INT(Cron_Uso!G15/Frota!$L15),IF(N(VLOOKUP(Frota!$B15,Premissas!$A$39:$E$43,5,0))>0,IF(MOD(INT(Cron_Uso!H15/Frota!$L15)*Frota!$L15,N(VLOOKUP(Frota!$B15,Premissas!$A$39:$E$43,5,0)))=0,"B",IF(N(VLOOKUP(Frota!$B15,Premissas!$A$39:$E$43,4,0))>0,IF(MOD(INT(Cron_Uso!H15/Frota!$L15)*Frota!$L15,N(VLOOKUP(Frota!$B15,Premissas!$A$39:$E$43,4,0)))=0,"A","S"),"S")),IF(N(VLOOKUP(Frota!$B15,Premissas!$A$39:$E$43,4,0))>0,IF(MOD(INT(Cron_Uso!H15/Frota!$L15)*Frota!$L15,N(VLOOKUP(Frota!$B15,Premissas!$A$39:$E$43,4,0)))=0,"A","S"),"S")),"")) -> A | I15: =IF(Cron_Uso!I15="","",IF(INT(Cron_Uso!I15/Frota!$L15)>INT(Cron_Uso!H15/Frota!$L15),IF(N(VLOOKUP(Frota!$B15,Premissas!$A$39:$E$43,5,0))>0,IF(MOD(INT(Cron_Uso!I15/Frota!$L15)*Frota!$L15,N(VLOOKUP(Frota!$B15,Premissas!$A$39:$E$43,5,0)))=0,"B",IF(N(VLOOKUP(Frota!$B15,Premissas!$A$39:$E$43,4,0))>0,IF(MOD(INT(Cron_Uso!I15/Frota!$L15)*Frota!$L15,N(VLOOKUP(Frota!$B15,Premissas!$A$39:$E$43,4,0)))=0,"A","S"),"S")),IF(N(VLOOKUP(Frota!$B15,Premissas!$A$39:$E$43,4,0))>0,IF(MOD(INT(Cron_Uso!I15/Frota!$L15)*Frota!$L15,N(VLOOKUP(Frota!$B15,Premissas!$A$39:$E$43,4,0)))=0,"A","S"),"S")),"")) | J15: =IF(Cron_Uso!J15="","",IF(INT(Cron_Uso!J15/Frota!$L15)>INT(Cron_Uso!I15/Frota!$L15),IF(N(VLOOKUP(Frota!$B15,Premissas!$A$39:$E$43,5,0))>0,IF(MOD(INT(Cron_Uso!J15/Frota!$L15)*Frota!$L15,N(VLOOKUP(Frota!$B15,Premissas!$A$39:$E$43,5,0)))=0,"B",IF(N(VLOOKUP(Frota!$B15,Premissas!$A$39:$E$43,4,0))>0,IF(MOD(INT(Cron_Uso!J15/Frota!$L15)*Frota!$L15,N(VLOOKUP(Frota!$B15,Premissas!$A$39:$E$43,4,0)))=0,"A","S"),"S")),IF(N(VLOOKUP(Frota!$B15,Premissas!$A$39:$E$43,4,0))>0,IF(MOD(INT(Cron_Uso!J15/Frota!$L15)*Frota!$L15,N(VLOOKUP(Frota!$B15,Premissas!$A$39:$E$43,4,0)))=0,"A","S"),"S")),"")) | ... BA15: =IF(Cron_Uso!BA15="","",IF(INT(Cron_Uso!BA15/Frota!$L15)>INT(Cron_Uso!AZ15/Frota!$L15),IF(N(VLOOKUP(Frota!$B15,Premissas!$A$39:$E$43,5,0))>0,IF(MOD(INT(Cron_Uso!BA15/Frota!$L15)*Frota!$L15,N(VLOOKUP(Frota!$B15,Premissas!$A$39:$E$43,5,0)))=0,"B",IF(N(VLOOKUP(Frota!$B15,Premissas!$A$39:$E$43,4,0))>0,IF(MOD(INT(Cron_Uso!BA15/Frota!$L15)*Frota!$L15,N(VLOOKUP(Frota!$B15,Premissas!$A$39:$E$43,4,0)))=0,"A","S"),"S")),IF(N(VLOOKUP(Frota!$B15,Premissas!$A$39:$E$43,4,0))>0,IF(MOD(INT(Cron_Uso!BA15/Frota!$L15)*Frota!$L15,N(VLOOKUP(Frota!$B15,Premissas!$A$39:$E$43,4,0)))=0,"A","S"),"S")),""))
A16: =IF(Frota!$A16="","",Frota!$A16) -> Fiat Toro — 5001 | B16: =IF(Cron_Uso!B16="","",IF(INT(Cron_Uso!B16/Frota!$L16)>INT(Frota!$I16/Frota!$L16),IF(N(VLOOKUP(Frota!$B16,Premissas!$A$39:$E$43,5,0))>0,IF(MOD(INT(Cron_Uso!B16/Frota!$L16)*Frota!$L16,N(VLOOKUP(Frota!$B16,Premissas!$A$39:$E$43,5,0)))=0,"B",IF(N(VLOOKUP(Frota!$B16,Premissas!$A$39:$E$43,4,0))>0,IF(MOD(INT(Cron_Uso!B16/Frota!$L16)*Frota!$L16,N(VLOOKUP(Frota!$B16,Premissas!$A$39:$E$43,4,0)))=0,"A","S"),"S")),IF(N(VLOOKUP(Frota!$B16,Premissas!$A$39:$E$43,4,0))>0,IF(MOD(INT(Cron_Uso!B16/Frota!$L16)*Frota!$L16,N(VLOOKUP(Frota!$B16,Premissas!$A$39:$E$43,4,0)))=0,"A","S"),"S")),"")) | C16: =IF(Cron_Uso!C16="","",IF(INT(Cron_Uso!C16/Frota!$L16)>INT(Cron_Uso!B16/Frota!$L16),IF(N(VLOOKUP(Frota!$B16,Premissas!$A$39:$E$43,5,0))>0,IF(MOD(INT(Cron_Uso!C16/Frota!$L16)*Frota!$L16,N(VLOOKUP(Frota!$B16,Premissas!$A$39:$E$43,5,0)))=0,"B",IF(N(VLOOKUP(Frota!$B16,Premissas!$A$39:$E$43,4,0))>0,IF(MOD(INT(Cron_Uso!C16/Frota!$L16)*Frota!$L16,N(VLOOKUP(Frota!$B16,Premissas!$A$39:$E$43,4,0)))=0,"A","S"),"S")),IF(N(VLOOKUP(Frota!$B16,Premissas!$A$39:$E$43,4,0))>0,IF(MOD(INT(Cron_Uso!C16/Frota!$L16)*Frota!$L16,N(VLOOKUP(Frota!$B16,Premissas!$A$39:$E$43,4,0)))=0,"A","S"),"S")),"")) | D16: =IF(Cron_Uso!D16="","",IF(INT(Cron_Uso!D16/Frota!$L16)>INT(Cron_Uso!C16/Frota!$L16),IF(N(VLOOKUP(Frota!$B16,Premissas!$A$39:$E$43,5,0))>0,IF(MOD(INT(Cron_Uso!D16/Frota!$L16)*Frota!$L16,N(VLOOKUP(Frota!$B16,Premissas!$A$39:$E$43,5,0)))=0,"B",IF(N(VLOOKUP(Frota!$B16,Premissas!$A$39:$E$43,4,0))>0,IF(MOD(INT(Cron_Uso!D16/Frota!$L16)*Frota!$L16,N(VLOOKUP(Frota!$B16,Premissas!$A$39:$E$43,4,0)))=0,"A","S"),"S")),IF(N(VLOOKUP(Frota!$B16,Premissas!$A$39:$E$43,4,0))>0,IF(MOD(INT(Cron_Uso!D16/Frota!$L16)*Frota!$L16,N(VLOOKUP(Frota!$B16,Premissas!$A$39:$E$43,4,0)))=0,"A","S"),"S")),"")) | E16: =IF(Cron_Uso!E16="","",IF(INT(Cron_Uso!E16/Frota!$L16)>INT(Cron_Uso!D16/Frota!$L16),IF(N(VLOOKUP(Frota!$B16,Premissas!$A$39:$E$43,5,0))>0,IF(MOD(INT(Cron_Uso!E16/Frota!$L16)*Frota!$L16,N(VLOOKUP(Frota!$B16,Premissas!$A$39:$E$43,5,0)))=0,"B",IF(N(VLOOKUP(Frota!$B16,Premissas!$A$39:$E$43,4,0))>0,IF(MOD(INT(Cron_Uso!E16/Frota!$L16)*Frota!$L16,N(VLOOKUP(Frota!$B16,Premissas!$A$39:$E$43,4,0)))=0,"A","S"),"S")),IF(N(VLOOKUP(Frota!$B16,Premissas!$A$39:$E$43,4,0))>0,IF(MOD(INT(Cron_Uso!E16/Frota!$L16)*Frota!$L16,N(VLOOKUP(Frota!$B16,Premissas!$A$39:$E$43,4,0)))=0,"A","S"),"S")),"")) | F16: =IF(Cron_Uso!F16="","",IF(INT(Cron_Uso!F16/Frota!$L16)>INT(Cron_Uso!E16/Frota!$L16),IF(N(VLOOKUP(Frota!$B16,Premissas!$A$39:$E$43,5,0))>0,IF(MOD(INT(Cron_Uso!F16/Frota!$L16)*Frota!$L16,N(VLOOKUP(Frota!$B16,Premissas!$A$39:$E$43,5,0)))=0,"B",IF(N(VLOOKUP(Frota!$B16,Premissas!$A$39:$E$43,4,0))>0,IF(MOD(INT(Cron_Uso!F16/Frota!$L16)*Frota!$L16,N(VLOOKUP(Frota!$B16,Premissas!$A$39:$E$43,4,0)))=0,"A","S"),"S")),IF(N(VLOOKUP(Frota!$B16,Premissas!$A$39:$E$43,4,0))>0,IF(MOD(INT(Cron_Uso!F16/Frota!$L16)*Frota!$L16,N(VLOOKUP(Frota!$B16,Premissas!$A$39:$E$43,4,0)))=0,"A","S"),"S")),"")) | G16: =IF(Cron_Uso!G16="","",IF(INT(Cron_Uso!G16/Frota!$L16)>INT(Cron_Uso!F16/Frota!$L16),IF(N(VLOOKUP(Frota!$B16,Premissas!$A$39:$E$43,5,0))>0,IF(MOD(INT(Cron_Uso!G16/Frota!$L16)*Frota!$L16,N(VLOOKUP(Frota!$B16,Premissas!$A$39:$E$43,5,0)))=0,"B",IF(N(VLOOKUP(Frota!$B16,Premissas!$A$39:$E$43,4,0))>0,IF(MOD(INT(Cron_Uso!G16/Frota!$L16)*Frota!$L16,N(VLOOKUP(Frota!$B16,Premissas!$A$39:$E$43,4,0)))=0,"A","S"),"S")),IF(N(VLOOKUP(Frota!$B16,Premissas!$A$39:$E$43,4,0))>0,IF(MOD(INT(Cron_Uso!G16/Frota!$L16)*Frota!$L16,N(VLOOKUP(Frota!$B16,Premissas!$A$39:$E$43,4,0)))=0,"A","S"),"S")),"")) | H16: =IF(Cron_Uso!H16="","",IF(INT(Cron_Uso!H16/Frota!$L16)>INT(Cron_Uso!G16/Frota!$L16),IF(N(VLOOKUP(Frota!$B16,Premissas!$A$39:$E$43,5,0))>0,IF(MOD(INT(Cron_Uso!H16/Frota!$L16)*Frota!$L16,N(VLOOKUP(Frota!$B16,Premissas!$A$39:$E$43,5,0)))=0,"B",IF(N(VLOOKUP(Frota!$B16,Premissas!$A$39:$E$43,4,0))>0,IF(MOD(INT(Cron_Uso!H16/Frota!$L16)*Frota!$L16,N(VLOOKUP(Frota!$B16,Premissas!$A$39:$E$43,4,0)))=0,"A","S"),"S")),IF(N(VLOOKUP(Frota!$B16,Premissas!$A$39:$E$43,4,0))>0,IF(MOD(INT(Cron_Uso!H16/Frota!$L16)*Frota!$L16,N(VLOOKUP(Frota!$B16,Premissas!$A$39:$E$43,4,0)))=0,"A","S"),"S")),"")) | I16: =IF(Cron_Uso!I16="","",IF(INT(Cron_Uso!I16/Frota!$L16)>INT(Cron_Uso!H16/Frota!$L16),IF(N(VLOOKUP(Frota!$B16,Premissas!$A$39:$E$43,5,0))>0,IF(MOD(INT(Cron_Uso!I16/Frota!$L16)*Frota!$L16,N(VLOOKUP(Frota!$B16,Premissas!$A$39:$E$43,5,0)))=0,"B",IF(N(VLOOKUP(Frota!$B16,Premissas!$A$39:$E$43,4,0))>0,IF(MOD(INT(Cron_Uso!I16/Frota!$L16)*Frota!$L16,N(VLOOKUP(Frota!$B16,Premissas!$A$39:$E$43,4,0)))=0,"A","S"),"S")),IF(N(VLOOKUP(Frota!$B16,Premissas!$A$39:$E$43,4,0))>0,IF(MOD(INT(Cron_Uso!I16/Frota!$L16)*Frota!$L16,N(VLOOKUP(Frota!$B16,Premissas!$A$39:$E$43,4,0)))=0,"A","S"),"S")),"")) | J16: =IF(Cron_Uso!J16="","",IF(INT(Cron_Uso!J16/Frota!$L16)>INT(Cron_Uso!I16/Frota!$L16),IF(N(VLOOKUP(Frota!$B16,Premissas!$A$39:$E$43,5,0))>0,IF(MOD(INT(Cron_Uso!J16/Frota!$L16)*Frota!$L16,N(VLOOKUP(Frota!$B16,Premissas!$A$39:$E$43,5,0)))=0,"B",IF(N(VLOOKUP(Frota!$B16,Premissas!$A$39:$E$43,4,0))>0,IF(MOD(INT(Cron_Uso!J16/Frota!$L16)*Frota!$L16,N(VLOOKUP(Frota!$B16,Premissas!$A$39:$E$43,4,0)))=0,"A","S"),"S")),IF(N(VLOOKUP(Frota!$B16,Premissas!$A$39:$E$43,4,0))>0,IF(MOD(INT(Cron_Uso!J16/Frota!$L16)*Frota!$L16,N(VLOOKUP(Frota!$B16,Premissas!$A$39:$E$43,4,0)))=0,"A","S"),"S")),"")) | ... BA16: =IF(Cron_Uso!BA16="","",IF(INT(Cron_Uso!BA16/Frota!$L16)>INT(Cron_Uso!AZ16/Frota!$L16),IF(N(VLOOKUP(Frota!$B16,Premissas!$A$39:$E$43,5,0))>0,IF(MOD(INT(Cron_Uso!BA16/Frota!$L16)*Frota!$L16,N(VLOOKUP(Frota!$B16,Premissas!$A$39:$E$43,5,0)))=0,"B",IF(N(VLOOKUP(Frota!$B16,Premissas!$A$39:$E$43,4,0))>0,IF(MOD(INT(Cron_Uso!BA16/Frota!$L16)*Frota!$L16,N(VLOOKUP(Frota!$B16,Premissas!$A$39:$E$43,4,0)))=0,"A","S"),"S")),IF(N(VLOOKUP(Frota!$B16,Premissas!$A$39:$E$43,4,0))>0,IF(MOD(INT(Cron_Uso!BA16/Frota!$L16)*Frota!$L16,N(VLOOKUP(Frota!$B16,Premissas!$A$39:$E$43,4,0)))=0,"A","S"),"S")),""))
... A34: =IF(Frota!$A34="","",Frota!$A34) | B34: =IF(Cron_Uso!B34="","",IF(INT(Cron_Uso!B34/Frota!$L34)>INT(Frota!$I34/Frota!$L34),IF(N(VLOOKUP(Frota!$B34,Premissas!$A$39:$E$43,5,0))>0,IF(MOD(INT(Cron_Uso!B34/Frota!$L34)*Frota!$L34,N(VLOOKUP(Frota!$B34,Premissas!$A$39:$E$43,5,0)))=0,"B",IF(N(VLOOKUP(Frota!$B34,Premissas!$A$39:$E$43,4,0))>0,IF(MOD(INT(Cron_Uso!B34/Frota!$L34)*Frota!$L34,N(VLOOKUP(Frota!$B34,Premissas!$A$39:$E$43,4,0)))=0,"A","S"),"S")),IF(N(VLOOKUP(Frota!$B34,Premissas!$A$39:$E$43,4,0))>0,IF(MOD(INT(Cron_Uso!B34/Frota!$L34)*Frota!$L34,N(VLOOKUP(Frota!$B34,Premissas!$A$39:$E$43,4,0)))=0,"A","S"),"S")),"")) | C34: =IF(Cron_Uso!C34="","",IF(INT(Cron_Uso!C34/Frota!$L34)>INT(Cron_Uso!B34/Frota!$L34),IF(N(VLOOKUP(Frota!$B34,Premissas!$A$39:$E$43,5,0))>0,IF(MOD(INT(Cron_Uso!C34/Frota!$L34)*Frota!$L34,N(VLOOKUP(Frota!$B34,Premissas!$A$39:$E$43,5,0)))=0,"B",IF(N(VLOOKUP(Frota!$B34,Premissas!$A$39:$E$43,4,0))>0,IF(MOD(INT(Cron_Uso!C34/Frota!$L34)*Frota!$L34,N(VLOOKUP(Frota!$B34,Premissas!$A$39:$E$43,4,0)))=0,"A","S"),"S")),IF(N(VLOOKUP(Frota!$B34,Premissas!$A$39:$E$43,4,0))>0,IF(MOD(INT(Cron_Uso!C34/Frota!$L34)*Frota!$L34,N(VLOOKUP(Frota!$B34,Premissas!$A$39:$E$43,4,0)))=0,"A","S"),"S")),"")) | D34: =IF(Cron_Uso!D34="","",IF(INT(Cron_Uso!D34/Frota!$L34)>INT(Cron_Uso!C34/Frota!$L34),IF(N(VLOOKUP(Frota!$B34,Premissas!$A$39:$E$43,5,0))>0,IF(MOD(INT(Cron_Uso!D34/Frota!$L34)*Frota!$L34,N(VLOOKUP(Frota!$B34,Premissas!$A$39:$E$43,5,0)))=0,"B",IF(N(VLOOKUP(Frota!$B34,Premissas!$A$39:$E$43,4,0))>0,IF(MOD(INT(Cron_Uso!D34/Frota!$L34)*Frota!$L34,N(VLOOKUP(Frota!$B34,Premissas!$A$39:$E$43,4,0)))=0,"A","S"),"S")),IF(N(VLOOKUP(Frota!$B34,Premissas!$A$39:$E$43,4,0))>0,IF(MOD(INT(Cron_Uso!D34/Frota!$L34)*Frota!$L34,N(VLOOKUP(Frota!$B34,Premissas!$A$39:$E$43,4,0)))=0,"A","S"),"S")),"")) | E34: =IF(Cron_Uso!E34="","",IF(INT(Cron_Uso!E34/Frota!$L34)>INT(Cron_Uso!D34/Frota!$L34),IF(N(VLOOKUP(Frota!$B34,Premissas!$A$39:$E$43,5,0))>0,IF(MOD(INT(Cron_Uso!E34/Frota!$L34)*Frota!$L34,N(VLOOKUP(Frota!$B34,Premissas!$A$39:$E$43,5,0)))=0,"B",IF(N(VLOOKUP(Frota!$B34,Premissas!$A$39:$E$43,4,0))>0,IF(MOD(INT(Cron_Uso!E34/Frota!$L34)*Frota!$L34,N(VLOOKUP(Frota!$B34,Premissas!$A$39:$E$43,4,0)))=0,"A","S"),"S")),IF(N(VLOOKUP(Frota!$B34,Premissas!$A$39:$E$43,4,0))>0,IF(MOD(INT(Cron_Uso!E34/Frota!$L34)*Frota!$L34,N(VLOOKUP(Frota!$B34,Premissas!$A$39:$E$43,4,0)))=0,"A","S"),"S")),"")) | F34: =IF(Cron_Uso!F34="","",IF(INT(Cron_Uso!F34/Frota!$L34)>INT(Cron_Uso!E34/Frota!$L34),IF(N(VLOOKUP(Frota!$B34,Premissas!$A$39:$E$43,5,0))>0,IF(MOD(INT(Cron_Uso!F34/Frota!$L34)*Frota!$L34,N(VLOOKUP(Frota!$B34,Premissas!$A$39:$E$43,5,0)))=0,"B",IF(N(VLOOKUP(Frota!$B34,Premissas!$A$39:$E$43,4,0))>0,IF(MOD(INT(Cron_Uso!F34/Frota!$L34)*Frota!$L34,N(VLOOKUP(Frota!$B34,Premissas!$A$39:$E$43,4,0)))=0,"A","S"),"S")),IF(N(VLOOKUP(Frota!$B34,Premissas!$A$39:$E$43,4,0))>0,IF(MOD(INT(Cron_Uso!F34/Frota!$L34)*Frota!$L34,N(VLOOKUP(Frota!$B34,Premissas!$A$39:$E$43,4,0)))=0,"A","S"),"S")),"")) | G34: =IF(Cron_Uso!G34="","",IF(INT(Cron_Uso!G34/Frota!$L34)>INT(Cron_Uso!F34/Frota!$L34),IF(N(VLOOKUP(Frota!$B34,Premissas!$A$39:$E$43,5,0))>0,IF(MOD(INT(Cron_Uso!G34/Frota!$L34)*Frota!$L34,N(VLOOKUP(Frota!$B34,Premissas!$A$39:$E$43,5,0)))=0,"B",IF(N(VLOOKUP(Frota!$B34,Premissas!$A$39:$E$43,4,0))>0,IF(MOD(INT(Cron_Uso!G34/Frota!$L34)*Frota!$L34,N(VLOOKUP(Frota!$B34,Premissas!$A$39:$E$43,4,0)))=0,"A","S"),"S")),IF(N(VLOOKUP(Frota!$B34,Premissas!$A$39:$E$43,4,0))>0,IF(MOD(INT(Cron_Uso!G34/Frota!$L34)*Frota!$L34,N(VLOOKUP(Frota!$B34,Premissas!$A$39:$E$43,4,0)))=0,"A","S"),"S")),"")) | H34: =IF(Cron_Uso!H34="","",IF(INT(Cron_Uso!H34/Frota!$L34)>INT(Cron_Uso!G34/Frota!$L34),IF(N(VLOOKUP(Frota!$B34,Premissas!$A$39:$E$43,5,0))>0,IF(MOD(INT(Cron_Uso!H34/Frota!$L34)*Frota!$L34,N(VLOOKUP(Frota!$B34,Premissas!$A$39:$E$43,5,0)))=0,"B",IF(N(VLOOKUP(Frota!$B34,Premissas!$A$39:$E$43,4,0))>0,IF(MOD(INT(Cron_Uso!H34/Frota!$L34)*Frota!$L34,N(VLOOKUP(Frota!$B34,Premissas!$A$39:$E$43,4,0)))=0,"A","S"),"S")),IF(N(VLOOKUP(Frota!$B34,Premissas!$A$39:$E$43,4,0))>0,IF(MOD(INT(Cron_Uso!H34/Frota!$L34)*Frota!$L34,N(VLOOKUP(Frota!$B34,Premissas!$A$39:$E$43,4,0)))=0,"A","S"),"S")),"")) | I34: =IF(Cron_Uso!I34="","",IF(INT(Cron_Uso!I34/Frota!$L34)>INT(Cron_Uso!H34/Frota!$L34),IF(N(VLOOKUP(Frota!$B34,Premissas!$A$39:$E$43,5,0))>0,IF(MOD(INT(Cron_Uso!I34/Frota!$L34)*Frota!$L34,N(VLOOKUP(Frota!$B34,Premissas!$A$39:$E$43,5,0)))=0,"B",IF(N(VLOOKUP(Frota!$B34,Premissas!$A$39:$E$43,4,0))>0,IF(MOD(INT(Cron_Uso!I34/Frota!$L34)*Frota!$L34,N(VLOOKUP(Frota!$B34,Premissas!$A$39:$E$43,4,0)))=0,"A","S"),"S")),IF(N(VLOOKUP(Frota!$B34,Premissas!$A$39:$E$43,4,0))>0,IF(MOD(INT(Cron_Uso!I34/Frota!$L34)*Frota!$L34,N(VLOOKUP(Frota!$B34,Premissas!$A$39:$E$43,4,0)))=0,"A","S"),"S")),"")) | J34: =IF(Cron_Uso!J34="","",IF(INT(Cron_Uso!J34/Frota!$L34)>INT(Cron_Uso!I34/Frota!$L34),IF(N(VLOOKUP(Frota!$B34,Premissas!$A$39:$E$43,5,0))>0,IF(MOD(INT(Cron_Uso!J34/Frota!$L34)*Frota!$L34,N(VLOOKUP(Frota!$B34,Premissas!$A$39:$E$43,5,0)))=0,"B",IF(N(VLOOKUP(Frota!$B34,Premissas!$A$39:$E$43,4,0))>0,IF(MOD(INT(Cron_Uso!J34/Frota!$L34)*Frota!$L34,N(VLOOKUP(Frota!$B34,Premissas!$A$39:$E$43,4,0)))=0,"A","S"),"S")),IF(N(VLOOKUP(Frota!$B34,Premissas!$A$39:$E$43,4,0))>0,IF(MOD(INT(Cron_Uso!J34/Frota!$L34)*Frota!$L34,N(VLOOKUP(Frota!$B34,Premissas!$A$39:$E$43,4,0)))=0,"A","S"),"S")),"")) | ... BA34: =IF(Cron_Uso!BA34="","",IF(INT(Cron_Uso!BA34/Frota!$L34)>INT(Cron_Uso!AZ34/Frota!$L34),IF(N(VLOOKUP(Frota!$B34,Premissas!$A$39:$E$43,5,0))>0,IF(MOD(INT(Cron_Uso!BA34/Frota!$L34)*Frota!$L34,N(VLOOKUP(Frota!$B34,Premissas!$A$39:$E$43,5,0)))=0,"B",IF(N(VLOOKUP(Frota!$B34,Premissas!$A$39:$E$43,4,0))>0,IF(MOD(INT(Cron_Uso!BA34/Frota!$L34)*Frota!$L34,N(VLOOKUP(Frota!$B34,Premissas!$A$39:$E$43,4,0)))=0,"A","S"),"S")),IF(N(VLOOKUP(Frota!$B34,Premissas!$A$39:$E$43,4,0))>0,IF(MOD(INT(Cron_Uso!BA34/Frota!$L34)*Frota!$L34,N(VLOOKUP(Frota!$B34,Premissas!$A$39:$E$43,4,0)))=0,"A","S"),"S")),""))

Sheet Aux_HH
A1: AUXILIAR — HH cumulativa por classe × tipo × oficina (herança S⊂A⊂B) e contagem de eventos/ano
A3: Chave | B3: Classe | C3: Tipo | D3: Mec. Oficina | E3: Mec. Campo | F3: Elétrica | G3: Lubrificação | H3: Borracharia | I3: Caldeiraria | J3: HH Total | K3: Eventos/ano
A4: =B4&"|"&C4 -> Colhedora|S | B4: Colhedora | C4: S | D4: =ROUND(SUMIFS(Checklist!$H$5:$H$104,Checklist!$C$5:$C$104,$B4,Checklist!$D$5:$D$104,D$3,Checklist!$B$5:$B$104,"S"),2) -> 3.75 | E4: =ROUND(SUMIFS(Checklist!$H$5:$H$104,Checklist!$C$5:$C$104,$B4,Checklist!$D$5:$D$104,E$3,Checklist!$B$5:$B$104,"S"),2) -> 0 | F4: =ROUND(SUMIFS(Checklist!$H$5:$H$104,Checklist!$C$5:$C$104,$B4,Checklist!$D$5:$D$104,F$3,Checklist!$B$5:$B$104,"S"),2) -> 1 | G4: =ROUND(SUMIFS(Checklist!$H$5:$H$104,Checklist!$C$5:$C$104,$B4,Checklist!$D$5:$D$104,G$3,Checklist!$B$5:$B$104,"S"),2) -> 0.75 | H4: =ROUND(SUMIFS(Checklist!$H$5:$H$104,Checklist!$C$5:$C$104,$B4,Checklist!$D$5:$D$104,H$3,Checklist!$B$5:$B$104,"S"),2) -> 0 | I4: =ROUND(SUMIFS(Checklist!$H$5:$H$104,Checklist!$C$5:$C$104,$B4,Checklist!$D$5:$D$104,I$3,Checklist!$B$5:$B$104,"S"),2) -> 0 | J4: =ROUND(SUM(D4:I4),2) -> 5.5 | K4: =COUNTIFS(Eventos!$B$4:$B$1563,$B4,Eventos!$E$4:$E$1563,$C4) -> 13
A5: =B5&"|"&C5 -> Colhedora|A | B5: Colhedora | C5: A | D5: =ROUND(SUMIFS(Checklist!$H$5:$H$104,Checklist!$C$5:$C$104,$B5,Checklist!$D$5:$D$104,D$3,Checklist!$B$5:$B$104,"S")+SUMIFS(Checklist!$H$5:$H$104,Checklist!$C$5:$C$104,$B5,Checklist!$D$5:$D$104,D$3,Checklist!$B$5:$B$104,"A"),2) -> 10.25 | E5: =ROUND(SUMIFS(Checklist!$H$5:$H$104,Checklist!$C$5:$C$104,$B5,Checklist!$D$5:$D$104,E$3,Checklist!$B$5:$B$104,"S")+SUMIFS(Checklist!$H$5:$H$104,Checklist!$C$5:$C$104,$B5,Checklist!$D$5:$D$104,E$3,Checklist!$B$5:$B$104,"A"),2) -> 0 | F5: =ROUND(SUMIFS(Checklist!$H$5:$H$104,Checklist!$C$5:$C$104,$B5,Checklist!$D$5:$D$104,F$3,Checklist!$B$5:$B$104,"S")+SUMIFS(Checklist!$H$5:$H$104,Checklist!$C$5:$C$104,$B5,Checklist!$D$5:$D$104,F$3,Checklist!$B$5:$B$104,"A"),2) -> 3 | G5: =ROUND(SUMIFS(Checklist!$H$5:$H$104,Checklist!$C$5:$C$104,$B5,Checklist!$D$5:$D$104,G$3,Checklist!$B$5:$B$104,"S")+SUMIFS(Checklist!$H$5:$H$104,Checklist!$C$5:$C$104,$B5,Checklist!$D$5:$D$104,G$3,Checklist!$B$5:$B$104,"A"),2) -> 1.75 | H5: =ROUND(SUMIFS(Checklist!$H$5:$H$104,Checklist!$C$5:$C$104,$B5,Checklist!$D$5:$D$104,H$3,Checklist!$B$5:$B$104,"S")+SUMIFS(Checklist!$H$5:$H$104,Checklist!$C$5:$C$104,$B5,Checklist!$D$5:$D$104,H$3,Checklist!$B$5:$B$104,"A"),2) -> 0 | I5: =ROUND(SUMIFS(Checklist!$H$5:$H$104,Checklist!$C$5:$C$104,$B5,Checklist!$D$5:$D$104,I$3,Checklist!$B$5:$B$104,"S")+SUMIFS(Checklist!$H$5:$H$104,Checklist!$C$5:$C$104,$B5,Checklist!$D$5:$D$104,I$3,Checklist!$B$5:$B$104,"A"),2) -> 0 | J5: =ROUND(SUM(D5:I5),2) -> 15 | K5: =COUNTIFS(Eventos!$B$4:$B$1563,$B5,Eventos!$E$4:$E$1563,$C5) -> 6
A6: =B6&"|"&C6 -> Colhedora|B | B6: Colhedora | C6: B | D6: =ROUND(SUMIFS(Checklist!$H$5:$H$104,Checklist!$C$5:$C$104,$B6,Checklist!$D$5:$D$104,D$3,Checklist!$B$5:$B$104,"S")+SUMIFS(Checklist!$H$5:$H$104,Checklist!$C$5:$C$104,$B6,Checklist!$D$5:$D$104,D$3,Checklist!$B$5:$B$104,"A")+SUMIFS(Checklist!$H$5:$H$104,Checklist!$C$5:$C$104,$B6,Checklist!$D$5:$D$104,D$3,Checklist!$B$5:$B$104,"B"),2) -> 10.25 | E6: =ROUND(SUMIFS(Checklist!$H$5:$H$104,Checklist!$C$5:$C$104,$B6,Checklist!$D$5:$D$104,E$3,Checklist!$B$5:$B$104,"S")+SUMIFS(Checklist!$H$5:$H$104,Checklist!$C$5:$C$104,$B6,Checklist!$D$5:$D$104,E$3,Checklist!$B$5:$B$104,"A")+SUMIFS(Checklist!$H$5:$H$104,Checklist!$C$5:$C$104,$B6,Checklist!$D$5:$D$104,E$3,Checklist!$B$5:$B$104,"B"),2) -> 0 | F6: =ROUND(SUMIFS(Checklist!$H$5:$H$104,Checklist!$C$5:$C$104,$B6,Checklist!$D$5:$D$104,F$3,Checklist!$B$5:$B$104,"S")+SUMIFS(Checklist!$H$5:$H$104,Checklist!$C$5:$C$104,$B6,Checklist!$D$5:$D$104,F$3,Checklist!$B$5:$B$104,"A")+SUMIFS(Checklist!$H$5:$H$104,Checklist!$C$5:$C$104,$B6,Checklist!$D$5:$D$104,F$3,Checklist!$B$5:$B$104,"B"),2) -> 3 | G6: =ROUND(SUMIFS(Checklist!$H$5:$H$104,Checklist!$C$5:$C$104,$B6,Checklist!$D$5:$D$104,G$3,Checklist!$B$5:$B$104,"S")+SUMIFS(Checklist!$H$5:$H$104,Checklist!$C$5:$C$104,$B6,Checklist!$D$5:$D$104,G$3,Checklist!$B$5:$B$104,"A")+SUMIFS(Checklist!$H$5:$H$104,Checklist!$C$5:$C$104,$B6,Checklist!$D$5:$D$104,G$3,Checklist!$B$5:$B$104,"B"),2) -> 1.75 | H6: =ROUND(SUMIFS(Checklist!$H$5:$H$104,Checklist!$C$5:$C$104,$B6,Checklist!$D$5:$D$104,H$3,Checklist!$B$5:$B$104,"S")+SUMIFS(Checklist!$H$5:$H$104,Checklist!$C$5:$C$104,$B6,Checklist!$D$5:$D$104,H$3,Checklist!$B$5:$B$104,"A")+SUMIFS(Checklist!$H$5:$H$104,Checklist!$C$5:$C$104,$B6,Checklist!$D$5:$D$104,H$3,Checklist!$B$5:$B$104,"B"),2) -> 0 | I6: =ROUND(SUMIFS(Checklist!$H$5:$H$104,Checklist!$C$5:$C$104,$B6,Checklist!$D$5:$D$104,I$3,Checklist!$B$5:$B$104,"S")+SUMIFS(Checklist!$H$5:$H$104,Checklist!$C$5:$C$104,$B6,Checklist!$D$5:$D$104,I$3,Checklist!$B$5:$B$104,"A")+SUMIFS(Checklist!$H$5:$H$104,Checklist!$C$5:$C$104,$B6,Checklist!$D$5:$D$104,I$3,Checklist!$B$5:$B$104,"B"),2) -> 0 | J6: =ROUND(SUM(D6:I6),2) -> 15 | K6: =COUNTIFS(Eventos!$B$4:$B$1563,$B6,Eventos!$E$4:$E$1563,$C6) -> 8
A7: =B7&"|"&C7 -> Trator|S | B7: Trator | C7: S | D7: =ROUND(SUMIFS(Checklist!$H$5:$H$104,Checklist!$C$5:$C$104,$B7,Checklist!$D$5:$D$104,D$3,Checklist!$B$5:$B$104,"S"),2) -> 1.5 | E7: =ROUND(SUMIFS(Checklist!$H$5:$H$104,Checklist!$C$5:$C$104,$B7,Checklist!$D$5:$D$104,E$3,Checklist!$B$5:$B$104,"S"),2) -> 0 | F7: =ROUND(SUMIFS(Checklist!$H$5:$H$104,Checklist!$C$5:$C$104,$B7,Checklist!$D$5:$D$104,F$3,Checklist!$B$5:$B$104,"S"),2) -> 0 | G7: =ROUND(SUMIFS(Checklist!$H$5:$H$104,Checklist!$C$5:$C$104,$B7,Checklist!$D$5:$D$104,G$3,Checklist!$B$5:$B$104,"S"),2) -> 0.5 | H7: =ROUND(SUMIFS(Checklist!$H$5:$H$104,Checklist!$C$5:$C$104,$B7,Checklist!$D$5:$D$104,H$3,Checklist!$B$5:$B$104,"S"),2) -> 0 | I7: =ROUND(SUMIFS(Checklist!$H$5:$H$104,Checklist!$C$5:$C$104,$B7,Checklist!$D$5:$D$104,I$3,Checklist!$B$5:$B$104,"S"),2) -> 0 | J7: =ROUND(SUM(D7:I7),2) -> 2 | K7: =COUNTIFS(Eventos!$B$4:$B$1563,$B7,Eventos!$E$4:$E$1563,$C7) -> 12
A8: =B8&"|"&C8 -> Trator|A | B8: Trator | C8: A | D8: =ROUND(SUMIFS(Checklist!$H$5:$H$104,Checklist!$C$5:$C$104,$B8,Checklist!$D$5:$D$104,D$3,Checklist!$B$5:$B$104,"S")+SUMIFS(Checklist!$H$5:$H$104,Checklist!$C$5:$C$104,$B8,Checklist!$D$5:$D$104,D$3,Checklist!$B$5:$B$104,"A"),2) -> 1.5 | E8: =ROUND(SUMIFS(Checklist!$H$5:$H$104,Checklist!$C$5:$C$104,$B8,Checklist!$D$5:$D$104,E$3,Checklist!$B$5:$B$104,"S")+SUMIFS(Checklist!$H$5:$H$104,Checklist!$C$5:$C$104,$B8,Checklist!$D$5:$D$104,E$3,Checklist!$B$5:$B$104,"A"),2) -> 0 | F8: =ROUND(SUMIFS(Checklist!$H$5:$H$104,Checklist!$C$5:$C$104,$B8,Checklist!$D$5:$D$104,F$3,Checklist!$B$5:$B$104,"S")+SUMIFS(Checklist!$H$5:$H$104,Checklist!$C$5:$C$104,$B8,Checklist!$D$5:$D$104,F$3,Checklist!$B$5:$B$104,"A"),2) -> 0 | G8: =ROUND(SUMIFS(Checklist!$H$5:$H$104,Checklist!$C$5:$C$104,$B8,Checklist!$D$5:$D$104,G$3,Checklist!$B$5:$B$104,"S")+SUMIFS(Checklist!$H$5:$H$104,Checklist!$C$5:$C$104,$B8,Checklist!$D$5:$D$104,G$3,Checklist!$B$5:$B$104,"A"),2) -> 0.5 | H8: =ROUND(SUMIFS(Checklist!$H$5:$H$104,Checklist!$C$5:$C$104,$B8,Checklist!$D$5:$D$104,H$3,Checklist!$B$5:$B$104,"S")+SUMIFS(Checklist!$H$5:$H$104,Checklist!$C$5:$C$104,$B8,Checklist!$D$5:$D$104,H$3,Checklist!$B$5:$B$104,"A"),2) -> 0 | I8: =ROUND(SUMIFS(Checklist!$H$5:$H$104,Checklist!$C$5:$C$104,$B8,Checklist!$D$5:$D$104,I$3,Checklist!$B$5:$B$104,"S")+SUMIFS(Checklist!$H$5:$H$104,Checklist!$C$5:$C$104,$B8,Checklist!$D$5:$D$104,I$3,Checklist!$B$5:$B$104,"A"),2) -> 0 | J8: =ROUND(SUM(D8:I8),2) -> 2 | K8: =COUNTIFS(Eventos!$B$4:$B$1563,$B8,Eventos!$E$4:$E$1563,$C8) -> 6
A9: =B9&"|"&C9 -> Trator|B | B9: Trator | C9: B | D9: =ROUND(SUMIFS(Checklist!$H$5:$H$104,Checklist!$C$5:$C$104,$B9,Checklist!$D$5:$D$104,D$3,Checklist!$B$5:$B$104,"S")+SUMIFS(Checklist!$H$5:$H$104,Checklist!$C$5:$C$104,$B9,Checklist!$D$5:$D$104,D$3,Checklist!$B$5:$B$104,"A")+SUMIFS(Checklist!$H$5:$H$104,Checklist!$C$5:$C$104,$B9,Checklist!$D$5:$D$104,D$3,Checklist!$B$5:$B$104,"B"),2) -> 1.5 | E9: =ROUND(SUMIFS(Checklist!$H$5:$H$104,Checklist!$C$5:$C$104,$B9,Checklist!$D$5:$D$104,E$3,Checklist!$B$5:$B$104,"S")+SUMIFS(Checklist!$H$5:$H$104,Checklist!$C$5:$C$104,$B9,Checklist!$D$5:$D$104,E$3,Checklist!$B$5:$B$104,"A")+SUMIFS(Checklist!$H$5:$H$104,Checklist!$C$5:$C$104,$B9,Checklist!$D$5:$D$104,E$3,Checklist!$B$5:$B$104,"B"),2) -> 0 | F9: =ROUND(SUMIFS(Checklist!$H$5:$H$104,Checklist!$C$5:$C$104,$B9,Checklist!$D$5:$D$104,F$3,Checklist!$B$5:$B$104,"S")+SUMIFS(Checklist!$H$5:$H$104,Checklist!$C$5:$C$104,$B9,Checklist!$D$5:$D$104,F$3,Checklist!$B$5:$B$104,"A")+SUMIFS(Checklist!$H$5:$H$104,Checklist!$C$5:$C$104,$B9,Checklist!$D$5:$D$104,F$3,Checklist!$B$5:$B$104,"B"),2) -> 0 | G9: =ROUND(SUMIFS(Checklist!$H$5:$H$104,Checklist!$C$5:$C$104,$B9,Checklist!$D$5:$D$104,G$3,Checklist!$B$5:$B$104,"S")+SUMIFS(Checklist!$H$5:$H$104,Checklist!$C$5:$C$104,$B9,Checklist!$D$5:$D$104,G$3,Checklist!$B$5:$B$104,"A")+SUMIFS(Checklist!$H$5:$H$104,Checklist!$C$5:$C$104,$B9,Checklist!$D$5:$D$104,G$3,Checklist!$B$5:$B$104,"B"),2) -> 0.5 | H9: =ROUND(SUMIFS(Checklist!$H$5:$H$104,Checklist!$C$5:$C$104,$B9,Checklist!$D$5:$D$104,H$3,Checklist!$B$5:$B$104,"S")+SUMIFS(Checklist!$H$5:$H$104,Checklist!$C$5:$C$104,$B9,Checklist!$D$5:$D$104,H$3,Checklist!$B$5:$B$104,"A")+SUMIFS(Checklist!$H$5:$H$104,Checklist!$C$5:$C$104,$B9,Checklist!$D$5:$D$104,H$3,Checklist!$B$5:$B$104,"B"),2) -> 0 | I9: =ROUND(SUMIFS(Checklist!$H$5:$H$104,Checklist!$C$5:$C$104,$B9,Checklist!$D$5:$D$104,I$3,Checklist!$B$5:$B$104,"S")+SUMIFS(Checklist!$H$5:$H$104,Checklist!$C$5:$C$104,$B9,Checklist!$D$5:$D$104,I$3,Checklist!$B$5:$B$104,"A")+SUMIFS(Checklist!$H$5:$H$104,Checklist!$C$5:$C$104,$B9,Checklist!$D$5:$D$104,I$3,Checklist!$B$5:$B$104,"B"),2) -> 0 | J9: =ROUND(SUM(D9:I9),2) -> 2 | K9: =COUNTIFS(Eventos!$B$4:$B$1563,$B9,Eventos!$E$4:$E$1563,$C9) -> 5
A10: =B10&"|"&C10 -> Caminhão|S | B10: Caminhão | C10: S | D10: =ROUND(SUMIFS(Checklist!$H$5:$H$104,Checklist!$C$5:$C$104,$B10,Checklist!$D$5:$D$104,D$3,Checklist!$B$5:$B$104,"S"),2) -> 2.25 | E10: =ROUND(SUMIFS(Checklist!$H$5:$H$104,Checklist!$C$5:$C$104,$B10,Checklist!$D$5:$D$104,E$3,Checklist!$B$5:$B$104,"S"),2) -> 0 | F10: =ROUND(SUMIFS(Checklist!$H$5:$H$104,Checklist!$C$5:$C$104,$B10,Checklist!$D$5:$D$104,F$3,Checklist!$B$5:$B$104,"S"),2) -> 0 | G10: =ROUND(SUMIFS(Checklist!$H$5:$H$104,Checklist!$C$5:$C$104,$B10,Checklist!$D$5:$D$104,G$3,Checklist!$B$5:$B$104,"S"),2) -> 0.5 | H10: =ROUND(SUMIFS(Checklist!$H$5:$H$104,Checklist!$C$5:$C$104,$B10,Checklist!$D$5:$D$104,H$3,Checklist!$B$5:$B$104,"S"),2) -> 0.5 | I10: =ROUND(SUMIFS(Checklist!$H$5:$H$104,Checklist!$C$5:$C$104,$B10,Checklist!$D$5:$D$104,I$3,Checklist!$B$5:$B$104,"S"),2) -> 0 | J10: =ROUND(SUM(D10:I10),2) -> 3.25 | K10: =COUNTIFS(Eventos!$B$4:$B$1563,$B10,Eventos!$E$4:$E$1563,$C10) -> 6
A11: =B11&"|"&C11 -> Caminhão|A | B11: Caminhão | C11: A | D11: =ROUND(SUMIFS(Checklist!$H$5:$H$104,Checklist!$C$5:$C$104,$B11,Checklist!$D$5:$D$104,D$3,Checklist!$B$5:$B$104,"S")+SUMIFS(Checklist!$H$5:$H$104,Checklist!$C$5:$C$104,$B11,Checklist!$D$5:$D$104,D$3,Checklist!$B$5:$B$104,"A"),2) -> 6.25 | E11: =ROUND(SUMIFS(Checklist!$H$5:$H$104,Checklist!$C$5:$C$104,$B11,Checklist!$D$5:$D$104,E$3,Checklist!$B$5:$B$104,"S")+SUMIFS(Checklist!$H$5:$H$104,Checklist!$C$5:$C$104,$B11,Checklist!$D$5:$D$104,E$3,Checklist!$B$5:$B$104,"A"),2) -> 0 | F11: =ROUND(SUMIFS(Checklist!$H$5:$H$104,Checklist!$C$5:$C$104,$B11,Checklist!$D$5:$D$104,F$3,Checklist!$B$5:$B$104,"S")+SUMIFS(Checklist!$H$5:$H$104,Checklist!$C$5:$C$104,$B11,Checklist!$D$5:$D$104,F$3,Checklist!$B$5:$B$104,"A"),2) -> 1 | G11: =ROUND(SUMIFS(Checklist!$H$5:$H$104,Checklist!$C$5:$C$104,$B11,Checklist!$D$5:$D$104,G$3,Checklist!$B$5:$B$104,"S")+SUMIFS(Checklist!$H$5:$H$104,Checklist!$C$5:$C$104,$B11,Checklist!$D$5:$D$104,G$3,Checklist!$B$5:$B$104,"A"),2) -> 0.5 | H11: =ROUND(SUMIFS(Checklist!$H$5:$H$104,Checklist!$C$5:$C$104,$B11,Checklist!$D$5:$D$104,H$3,Checklist!$B$5:$B$104,"S")+SUMIFS(Checklist!$H$5:$H$104,Checklist!$C$5:$C$104,$B11,Checklist!$D$5:$D$104,H$3,Checklist!$B$5:$B$104,"A"),2) -> 0.5 | I11: =ROUND(SUMIFS(Checklist!$H$5:$H$104,Checklist!$C$5:$C$104,$B11,Checklist!$D$5:$D$104,I$3,Checklist!$B$5:$B$104,"S")+SUMIFS(Checklist!$H$5:$H$104,Checklist!$C$5:$C$104,$B11,Checklist!$D$5:$D$104,I$3,Checklist!$B$5:$B$104,"A"),2) -> 0 | J11: =ROUND(SUM(D11:I11),2) -> 8.25 | K11: =COUNTIFS(Eventos!$B$4:$B$1563,$B11,Eventos!$E$4:$E$1563,$C11) -> 3
A12: =B12&"|"&C12 -> Caminhão|B | B12: Caminhão | C12: B | D12: =ROUND(SUMIFS(Checklist!$H$5:$H$104,Checklist!$C$5:$C$104,$B12,Checklist!$D$5:$D$104,D$3,Checklist!$B$5:$B$104,"S")+SUMIFS(Checklist!$H$5:$H$104,Checklist!$C$5:$C$104,$B12,Checklist!$D$5:$D$104,D$3,Checklist!$B$5:$B$104,"A")+SUMIFS(Checklist!$H$5:$H$104,Checklist!$C$5:$C$104,$B12,Checklist!$D$5:$D$104,D$3,Checklist!$B$5:$B$104,"B"),2) -> 6.25 | E12: =ROUND(SUMIFS(Checklist!$H$5:$H$104,Checklist!$C$5:$C$104,$B12,Checklist!$D$5:$D$104,E$3,Checklist!$B$5:$B$104,"S")+SUMIFS(Checklist!$H$5:$H$104,Checklist!$C$5:$C$104,$B12,Checklist!$D$5:$D$104,E$3,Checklist!$B$5:$B$104,"A")+SUMIFS(Checklist!$H$5:$H$104,Checklist!$C$5:$C$104,$B12,Checklist!$D$5:$D$104,E$3,Checklist!$B$5:$B$104,"B"),2) -> 0 | F12: =ROUND(SUMIFS(Checklist!$H$5:$H$104,Checklist!$C$5:$C$104,$B12,Checklist!$D$5:$D$104,F$3,Checklist!$B$5:$B$104,"S")+SUMIFS(Checklist!$H$5:$H$104,Checklist!$C$5:$C$104,$B12,Checklist!$D$5:$D$104,F$3,Checklist!$B$5:$B$104,"A")+SUMIFS(Checklist!$H$5:$H$104,Checklist!$C$5:$C$104,$B12,Checklist!$D$5:$D$104,F$3,Checklist!$B$5:$B$104,"B"),2) -> 1 | G12: =ROUND(SUMIFS(Checklist!$H$5:$H$104,Checklist!$C$5:$C$104,$B12,Checklist!$D$5:$D$104,G$3,Checklist!$B$5:$B$104,"S")+SUMIFS(Checklist!$H$5:$H$104,Checklist!$C$5:$C$104,$B12,Checklist!$D$5:$D$104,G$3,Checklist!$B$5:$B$104,"A")+SUMIFS(Checklist!$H$5:$H$104,Checklist!$C$5:$C$104,$B12,Checklist!$D$5:$D$104,G$3,Checklist!$B$5:$B$104,"B"),2) -> 0.5 | H12: =ROUND(SUMIFS(Checklist!$H$5:$H$104,Checklist!$C$5:$C$104,$B12,Checklist!$D$5:$D$104,H$3,Checklist!$B$5:$B$104,"S")+SUMIFS(Checklist!$H$5:$H$104,Checklist!$C$5:$C$104,$B12,Checklist!$D$5:$D$104,H$3,Checklist!$B$5:$B$104,"A")+SUMIFS(Checklist!$H$5:$H$104,Checklist!$C$5:$C$104,$B12,Checklist!$D$5:$D$104,H$3,Checklist!$B$5:$B$104,"B"),2) -> 0.5 | I12: =ROUND(SUMIFS(Checklist!$H$5:$H$104,Checklist!$C$5:$C$104,$B12,Checklist!$D$5:$D$104,I$3,Checklist!$B$5:$B$104,"S")+SUMIFS(Checklist!$H$5:$H$104,Checklist!$C$5:$C$104,$B12,Checklist!$D$5:$D$104,I$3,Checklist!$B$5:$B$104,"A")+SUMIFS(Checklist!$H$5:$H$104,Checklist!$C$5:$C$104,$B12,Checklist!$D$5:$D$104,I$3,Checklist!$B$5:$B$104,"B"),2) -> 0 | J12: =ROUND(SUM(D12:I12),2) -> 8.25 | K12: =COUNTIFS(Eventos!$B$4:$B$1563,$B12,Eventos!$E$4:$E$1563,$C12) -> 3
A13: =B13&"|"&C13 -> Implemento|S | B13: Implemento | C13: S | D13: =ROUND(SUMIFS(Checklist!$H$5:$H$104,Checklist!$C$5:$C$104,$B13,Checklist!$D$5:$D$104,D$3,Checklist!$B$5:$B$104,"S"),2) -> 0.75 | E13: =ROUND(SUMIFS(Checklist!$H$5:$H$104,Checklist!$C$5:$C$104,$B13,Checklist!$D$5:$D$104,E$3,Checklist!$B$5:$B$104,"S"),2) -> 0 | F13: =ROUND(SUMIFS(Checklist!$H$5:$H$104,Checklist!$C$5:$C$104,$B13,Checklist!$D$5:$D$104,F$3,Checklist!$B$5:$B$104,"S"),2) -> 0 | G13: =ROUND(SUMIFS(Checklist!$H$5:$H$104,Checklist!$C$5:$C$104,$B13,Checklist!$D$5:$D$104,G$3,Checklist!$B$5:$B$104,"S"),2) -> 0.5 | H13: =ROUND(SUMIFS(Checklist!$H$5:$H$104,Checklist!$C$5:$C$104,$B13,Checklist!$D$5:$D$104,H$3,Checklist!$B$5:$B$104,"S"),2) -> 0 | I13: =ROUND(SUMIFS(Checklist!$H$5:$H$104,Checklist!$C$5:$C$104,$B13,Checklist!$D$5:$D$104,I$3,Checklist!$B$5:$B$104,"S"),2) -> 1.5 | J13: =ROUND(SUM(D13:I13),2) -> 2.75 | K13: =COUNTIFS(Eventos!$B$4:$B$1563,$B13,Eventos!$E$4:$E$1563,$C13) -> 5
A14: =B14&"|"&C14 -> Implemento|A | B14: Implemento | C14: A | D14: =ROUND(SUMIFS(Checklist!$H$5:$H$104,Checklist!$C$5:$C$104,$B14,Checklist!$D$5:$D$104,D$3,Checklist!$B$5:$B$104,"S")+SUMIFS(Checklist!$H$5:$H$104,Checklist!$C$5:$C$104,$B14,Checklist!$D$5:$D$104,D$3,Checklist!$B$5:$B$104,"A"),2) -> 0.75 | E14: =ROUND(SUMIFS(Checklist!$H$5:$H$104,Checklist!$C$5:$C$104,$B14,Checklist!$D$5:$D$104,E$3,Checklist!$B$5:$B$104,"S")+SUMIFS(Checklist!$H$5:$H$104,Checklist!$C$5:$C$104,$B14,Checklist!$D$5:$D$104,E$3,Checklist!$B$5:$B$104,"A"),2) -> 0 | F14: =ROUND(SUMIFS(Checklist!$H$5:$H$104,Checklist!$C$5:$C$104,$B14,Checklist!$D$5:$D$104,F$3,Checklist!$B$5:$B$104,"S")+SUMIFS(Checklist!$H$5:$H$104,Checklist!$C$5:$C$104,$B14,Checklist!$D$5:$D$104,F$3,Checklist!$B$5:$B$104,"A"),2) -> 0 | G14: =ROUND(SUMIFS(Checklist!$H$5:$H$104,Checklist!$C$5:$C$104,$B14,Checklist!$D$5:$D$104,G$3,Checklist!$B$5:$B$104,"S")+SUMIFS(Checklist!$H$5:$H$104,Checklist!$C$5:$C$104,$B14,Checklist!$D$5:$D$104,G$3,Checklist!$B$5:$B$104,"A"),2) -> 0.5 | H14: =ROUND(SUMIFS(Checklist!$H$5:$H$104,Checklist!$C$5:$C$104,$B14,Checklist!$D$5:$D$104,H$3,Checklist!$B$5:$B$104,"S")+SUMIFS(Checklist!$H$5:$H$104,Checklist!$C$5:$C$104,$B14,Checklist!$D$5:$D$104,H$3,Checklist!$B$5:$B$104,"A"),2) -> 0 | I14: =ROUND(SUMIFS(Checklist!$H$5:$H$104,Checklist!$C$5:$C$104,$B14,Checklist!$D$5:$D$104,I$3,Checklist!$B$5:$B$104,"S")+SUMIFS(Checklist!$H$5:$H$104,Checklist!$C$5:$C$104,$B14,Checklist!$D$5:$D$104,I$3,Checklist!$B$5:$B$104,"A"),2) -> 1.5 | J14: =ROUND(SUM(D14:I14),2) -> 2.75 | K14: =COUNTIFS(Eventos!$B$4:$B$1563,$B14,Eventos!$E$4:$E$1563,$C14) -> 4
A15: =B15&"|"&C15 -> Implemento|B | B15: Implemento | C15: B | D15: =ROUND(SUMIFS(Checklist!$H$5:$H$104,Checklist!$C$5:$C$104,$B15,Checklist!$D$5:$D$104,D$3,Checklist!$B$5:$B$104,"S")+SUMIFS(Checklist!$H$5:$H$104,Checklist!$C$5:$C$104,$B15,Checklist!$D$5:$D$104,D$3,Checklist!$B$5:$B$104,"A")+SUMIFS(Checklist!$H$5:$H$104,Checklist!$C$5:$C$104,$B15,Checklist!$D$5:$D$104,D$3,Checklist!$B$5:$B$104,"B"),2) -> 0.75 | E15: =ROUND(SUMIFS(Checklist!$H$5:$H$104,Checklist!$C$5:$C$104,$B15,Checklist!$D$5:$D$104,E$3,Checklist!$B$5:$B$104,"S")+SUMIFS(Checklist!$H$5:$H$104,Checklist!$C$5:$C$104,$B15,Checklist!$D$5:$D$104,E$3,Checklist!$B$5:$B$104,"A")+SUMIFS(Checklist!$H$5:$H$104,Checklist!$C$5:$C$104,$B15,Checklist!$D$5:$D$104,E$3,Checklist!$B$5:$B$104,"B"),2) -> 0 | F15: =ROUND(SUMIFS(Checklist!$H$5:$H$104,Checklist!$C$5:$C$104,$B15,Checklist!$D$5:$D$104,F$3,Checklist!$B$5:$B$104,"S")+SUMIFS(Checklist!$H$5:$H$104,Checklist!$C$5:$C$104,$B15,Checklist!$D$5:$D$104,F$3,Checklist!$B$5:$B$104,"A")+SUMIFS(Checklist!$H$5:$H$104,Checklist!$C$5:$C$104,$B15,Checklist!$D$5:$D$104,F$3,Checklist!$B$5:$B$104,"B"),2) -> 0 | G15: =ROUND(SUMIFS(Checklist!$H$5:$H$104,Checklist!$C$5:$C$104,$B15,Checklist!$D$5:$D$104,G$3,Checklist!$B$5:$B$104,"S")+SUMIFS(Checklist!$H$5:$H$104,Checklist!$C$5:$C$104,$B15,Checklist!$D$5:$D$104,G$3,Checklist!$B$5:$B$104,"A")+SUMIFS(Checklist!$H$5:$H$104,Checklist!$C$5:$C$104,$B15,Checklist!$D$5:$D$104,G$3,Checklist!$B$5:$B$104,"B"),2) -> 0.5 | H15: =ROUND(SUMIFS(Checklist!$H$5:$H$104,Checklist!$C$5:$C$104,$B15,Checklist!$D$5:$D$104,H$3,Checklist!$B$5:$B$104,"S")+SUMIFS(Checklist!$H$5:$H$104,Checklist!$C$5:$C$104,$B15,Checklist!$D$5:$D$104,H$3,Checklist!$B$5:$B$104,"A")+SUMIFS(Checklist!$H$5:$H$104,Checklist!$C$5:$C$104,$B15,Checklist!$D$5:$D$104,H$3,Checklist!$B$5:$B$104,"B"),2) -> 0 | I15: =ROUND(SUMIFS(Checklist!$H$5:$H$104,Checklist!$C$5:$C$104,$B15,Checklist!$D$5:$D$104,I$3,Checklist!$B$5:$B$104,"S")+SUMIFS(Checklist!$H$5:$H$104,Checklist!$C$5:$C$104,$B15,Checklist!$D$5:$D$104,I$3,Checklist!$B$5:$B$104,"A")+SUMIFS(Checklist!$H$5:$H$104,Checklist!$C$5:$C$104,$B15,Checklist!$D$5:$D$104,I$3,Checklist!$B$5:$B$104,"B"),2) -> 1.5 | J15: =ROUND(SUM(D15:I15),2) -> 2.75 | K15: =COUNTIFS(Eventos!$B$4:$B$1563,$B15,Eventos!$E$4:$E$1563,$C15) -> 0
A16: =B16&"|"&C16 -> Veículo Leve|S | B16: Veículo Leve | C16: S | D16: =ROUND(SUMIFS(Checklist!$H$5:$H$104,Checklist!$C$5:$C$104,$B16,Checklist!$D$5:$D$104,D$3,Checklist!$B$5:$B$104,"S"),2) -> 0 | E16: =ROUND(SUMIFS(Checklist!$H$5:$H$104,Checklist!$C$5:$C$104,$B16,Checklist!$D$5:$D$104,E$3,Checklist!$B$5:$B$104,"S"),2) -> 0 | F16: =ROUND(SUMIFS(Checklist!$H$5:$H$104,Checklist!$C$5:$C$104,$B16,Checklist!$D$5:$D$104,F$3,Checklist!$B$5:$B$104,"S"),2) -> 0 | G16: =ROUND(SUMIFS(Checklist!$H$5:$H$104,Checklist!$C$5:$C$104,$B16,Checklist!$D$5:$D$104,G$3,Checklist!$B$5:$B$104,"S"),2) -> 0 | H16: =ROUND(SUMIFS(Checklist!$H$5:$H$104,Checklist!$C$5:$C$104,$B16,Checklist!$D$5:$D$104,H$3,Checklist!$B$5:$B$104,"S"),2) -> 0 | I16: =ROUND(SUMIFS(Checklist!$H$5:$H$104,Checklist!$C$5:$C$104,$B16,Checklist!$D$5:$D$104,I$3,Checklist!$B$5:$B$104,"S"),2) -> 0 | J16: =ROUND(SUM(D16:I16),2) -> 0 | K16: =COUNTIFS(Eventos!$B$4:$B$1563,$B16,Eventos!$E$4:$E$1563,$C16) -> 3
A17: =B17&"|"&C17 -> Veículo Leve|A | B17: Veículo Leve | C17: A | D17: =ROUND(SUMIFS(Checklist!$H$5:$H$104,Checklist!$C$5:$C$104,$B17,Checklist!$D$5:$D$104,D$3,Checklist!$B$5:$B$104,"S")+SUMIFS(Checklist!$H$5:$H$104,Checklist!$C$5:$C$104,$B17,Checklist!$D$5:$D$104,D$3,Checklist!$B$5:$B$104,"A"),2) -> 0 | E17: =ROUND(SUMIFS(Checklist!$H$5:$H$104,Checklist!$C$5:$C$104,$B17,Checklist!$D$5:$D$104,E$3,Checklist!$B$5:$B$104,"S")+SUMIFS(Checklist!$H$5:$H$104,Checklist!$C$5:$C$104,$B17,Checklist!$D$5:$D$104,E$3,Checklist!$B$5:$B$104,"A"),2) -> 0 | F17: =ROUND(SUMIFS(Checklist!$H$5:$H$104,Checklist!$C$5:$C$104,$B17,Checklist!$D$5:$D$104,F$3,Checklist!$B$5:$B$104,"S")+SUMIFS(Checklist!$H$5:$H$104,Checklist!$C$5:$C$104,$B17,Checklist!$D$5:$D$104,F$3,Checklist!$B$5:$B$104,"A"),2) -> 0 | G17: =ROUND(SUMIFS(Checklist!$H$5:$H$104,Checklist!$C$5:$C$104,$B17,Checklist!$D$5:$D$104,G$3,Checklist!$B$5:$B$104,"S")+SUMIFS(Checklist!$H$5:$H$104,Checklist!$C$5:$C$104,$B17,Checklist!$D$5:$D$104,G$3,Checklist!$B$5:$B$104,"A"),2) -> 0 | H17: =ROUND(SUMIFS(Checklist!$H$5:$H$104,Checklist!$C$5:$C$104,$B17,Checklist!$D$5:$D$104,H$3,Checklist!$B$5:$B$104,"S")+SUMIFS(Checklist!$H$5:$H$104,Checklist!$C$5:$C$104,$B17,Checklist!$D$5:$D$104,H$3,Checklist!$B$5:$B$104,"A"),2) -> 0 | I17: =ROUND(SUMIFS(Checklist!$H$5:$H$104,Checklist!$C$5:$C$104,$B17,Checklist!$D$5:$D$104,I$3,Checklist!$B$5:$B$104,"S")+SUMIFS(Checklist!$H$5:$H$104,Checklist!$C$5:$C$104,$B17,Checklist!$D$5:$D$104,I$3,Checklist!$B$5:$B$104,"A"),2) -> 0 | J17: =ROUND(SUM(D17:I17),2) -> 0 | K17: =COUNTIFS(Eventos!$B$4:$B$1563,$B17,Eventos!$E$4:$E$1563,$C17) -> 4
A18: =B18&"|"&C18 -> Veículo Leve|B | B18: Veículo Leve | C18: B | D18: =ROUND(SUMIFS(Checklist!$H$5:$H$104,Checklist!$C$5:$C$104,$B18,Checklist!$D$5:$D$104,D$3,Checklist!$B$5:$B$104,"S")+SUMIFS(Checklist!$H$5:$H$104,Checklist!$C$5:$C$104,$B18,Checklist!$D$5:$D$104,D$3,Checklist!$B$5:$B$104,"A")+SUMIFS(Checklist!$H$5:$H$104,Checklist!$C$5:$C$104,$B18,Checklist!$D$5:$D$104,D$3,Checklist!$B$5:$B$104,"B"),2) -> 0 | E18: =ROUND(SUMIFS(Checklist!$H$5:$H$104,Checklist!$C$5:$C$104,$B18,Checklist!$D$5:$D$104,E$3,Checklist!$B$5:$B$104,"S")+SUMIFS(Checklist!$H$5:$H$104,Checklist!$C$5:$C$104,$B18,Checklist!$D$5:$D$104,E$3,Checklist!$B$5:$B$104,"A")+SUMIFS(Checklist!$H$5:$H$104,Checklist!$C$5:$C$104,$B18,Checklist!$D$5:$D$104,E$3,Checklist!$B$5:$B$104,"B"),2) -> 0 | F18: =ROUND(SUMIFS(Checklist!$H$5:$H$104,Checklist!$C$5:$C$104,$B18,Checklist!$D$5:$D$104,F$3,Checklist!$B$5:$B$104,"S")+SUMIFS(Checklist!$H$5:$H$104,Checklist!$C$5:$C$104,$B18,Checklist!$D$5:$D$104,F$3,Checklist!$B$5:$B$104,"A")+SUMIFS(Checklist!$H$5:$H$104,Checklist!$C$5:$C$104,$B18,Checklist!$D$5:$D$104,F$3,Checklist!$B$5:$B$104,"B"),2) -> 0 | G18: =ROUND(SUMIFS(Checklist!$H$5:$H$104,Checklist!$C$5:$C$104,$B18,Checklist!$D$5:$D$104,G$3,Checklist!$B$5:$B$104,"S")+SUMIFS(Checklist!$H$5:$H$104,Checklist!$C$5:$C$104,$B18,Checklist!$D$5:$D$104,G$3,Checklist!$B$5:$B$104,"A")+SUMIFS(Checklist!$H$5:$H$104,Checklist!$C$5:$C$104,$B18,Checklist!$D$5:$D$104,G$3,Checklist!$B$5:$B$104,"B"),2) -> 0 | H18: =ROUND(SUMIFS(Checklist!$H$5:$H$104,Checklist!$C$5:$C$104,$B18,Checklist!$D$5:$D$104,H$3,Checklist!$B$5:$B$104,"S")+SUMIFS(Checklist!$H$5:$H$104,Checklist!$C$5:$C$104,$B18,Checklist!$D$5:$D$104,H$3,Checklist!$B$5:$B$104,"A")+SUMIFS(Checklist!$H$5:$H$104,Checklist!$C$5:$C$104,$B18,Checklist!$D$5:$D$104,H$3,Checklist!$B$5:$B$104,"B"),2) -> 0 | I18: =ROUND(SUMIFS(Checklist!$H$5:$H$104,Checklist!$C$5:$C$104,$B18,Checklist!$D$5:$D$104,I$3,Checklist!$B$5:$B$104,"S")+SUMIFS(Checklist!$H$5:$H$104,Checklist!$C$5:$C$104,$B18,Checklist!$D$5:$D$104,I$3,Checklist!$B$5:$B$104,"A")+SUMIFS(Checklist!$H$5:$H$104,Checklist!$C$5:$C$104,$B18,Checklist!$D$5:$D$104,I$3,Checklist!$B$5:$B$104,"B"),2) -> 0 | J18: =ROUND(SUM(D18:I18),2) -> 0 | K18: =COUNTIFS(Eventos!$B$4:$B$1563,$B18,Eventos!$E$4:$E$1563,$C18) -> 0

Sheet Eventos
A1: AUXILIAR — 1 linha por ativo × semana (base dos planos mensais)
A3: Ativo | B3: Classe | C3: Semana | D3: Mês | E3: Tipo | F3: Prev (1/0) | G3: HH Mec. Oficina | H3: HH Mec. Campo | I3: HH Elétrica | J3: HH Lubrificação | K3: HH Borracharia | L3: HH Caldeiraria
A4: =IF(Frota!$A5="","",Frota!$A5) -> Colhedora CASE A8810 — 1035 | B4: =IF(Frota!$A5="","",Frota!$B5) -> Colhedora | C4: 1 | D4: =INDEX(Semanas!$E$3:$E$54,1) -> 4 | E4: =IF(Frota!$A5="","",Cronograma!B5) | F4: =IF(OR($E4="",$E4=0),0,1) -> 0 | G4: =IF($F4=0,0,INDEX(Aux_HH!$D$4:$D$18,MATCH($B4&"|"&$E4,Aux_HH!$A$4:$A$18,0))) -> 0 | H4: =IF($F4=0,0,INDEX(Aux_HH!$E$4:$E$18,MATCH($B4&"|"&$E4,Aux_HH!$A$4:$A$18,0))) -> 0 | I4: =IF($F4=0,0,INDEX(Aux_HH!$F$4:$F$18,MATCH($B4&"|"&$E4,Aux_HH!$A$4:$A$18,0))) -> 0 | J4: =IF($F4=0,0,INDEX(Aux_HH!$G$4:$G$18,MATCH($B4&"|"&$E4,Aux_HH!$A$4:$A$18,0))) -> 0 | K4: =IF($F4=0,0,INDEX(Aux_HH!$H$4:$H$18,MATCH($B4&"|"&$E4,Aux_HH!$A$4:$A$18,0))) -> 0 | L4: =IF($F4=0,0,INDEX(Aux_HH!$I$4:$I$18,MATCH($B4&"|"&$E4,Aux_HH!$A$4:$A$18,0))) -> 0
A5: =IF(Frota!$A5="","",Frota!$A5) -> Colhedora CASE A8810 — 1035 | B5: =IF(Frota!$A5="","",Frota!$B5) -> Colhedora | C5: 2 | D5: =INDEX(Semanas!$E$3:$E$54,2) -> 4 | E5: =IF(Frota!$A5="","",Cronograma!C5) | F5: =IF(OR($E5="",$E5=0),0,1) -> 0 | G5: =IF($F5=0,0,INDEX(Aux_HH!$D$4:$D$18,MATCH($B5&"|"&$E5,Aux_HH!$A$4:$A$18,0))) -> 0 | H5: =IF($F5=0,0,INDEX(Aux_HH!$E$4:$E$18,MATCH($B5&"|"&$E5,Aux_HH!$A$4:$A$18,0))) -> 0 | I5: =IF($F5=0,0,INDEX(Aux_HH!$F$4:$F$18,MATCH($B5&"|"&$E5,Aux_HH!$A$4:$A$18,0))) -> 0 | J5: =IF($F5=0,0,INDEX(Aux_HH!$G$4:$G$18,MATCH($B5&"|"&$E5,Aux_HH!$A$4:$A$18,0))) -> 0 | K5: =IF($F5=0,0,INDEX(Aux_HH!$H$4:$H$18,MATCH($B5&"|"&$E5,Aux_HH!$A$4:$A$18,0))) -> 0 | L5: =IF($F5=0,0,INDEX(Aux_HH!$I$4:$I$18,MATCH($B5&"|"&$E5,Aux_HH!$A$4:$A$18,0))) -> 0
A6: =IF(Frota!$A5="","",Frota!$A5) -> Colhedora CASE A8810 — 1035 | B6: =IF(Frota!$A5="","",Frota!$B5) -> Colhedora | C6: 3 | D6: =INDEX(Semanas!$E$3:$E$54,3) -> 4 | E6: =IF(Frota!$A5="","",Cronograma!D5) | F6: =IF(OR($E6="",$E6=0),0,1) -> 0 | G6: =IF($F6=0,0,INDEX(Aux_HH!$D$4:$D$18,MATCH($B6&"|"&$E6,Aux_HH!$A$4:$A$18,0))) -> 0 | H6: =IF($F6=0,0,INDEX(Aux_HH!$E$4:$E$18,MATCH($B6&"|"&$E6,Aux_HH!$A$4:$A$18,0))) -> 0 | I6: =IF($F6=0,0,INDEX(Aux_HH!$F$4:$F$18,MATCH($B6&"|"&$E6,Aux_HH!$A$4:$A$18,0))) -> 0 | J6: =IF($F6=0,0,INDEX(Aux_HH!$G$4:$G$18,MATCH($B6&"|"&$E6,Aux_HH!$A$4:$A$18,0))) -> 0 | K6: =IF($F6=0,0,INDEX(Aux_HH!$H$4:$H$18,MATCH($B6&"|"&$E6,Aux_HH!$A$4:$A$18,0))) -> 0 | L6: =IF($F6=0,0,INDEX(Aux_HH!$I$4:$I$18,MATCH($B6&"|"&$E6,Aux_HH!$A$4:$A$18,0))) -> 0
A7: =IF(Frota!$A5="","",Frota!$A5) -> Colhedora CASE A8810 — 1035 | B7: =IF(Frota!$A5="","",Frota!$B5) -> Colhedora | C7: 4 | D7: =INDEX(Semanas!$E$3:$E$54,4) -> 4 | E7: =IF(Frota!$A5="","",Cronograma!E5) | F7: =IF(OR($E7="",$E7=0),0,1) -> 0 | G7: =IF($F7=0,0,INDEX(Aux_HH!$D$4:$D$18,MATCH($B7&"|"&$E7,Aux_HH!$A$4:$A$18,0))) -> 0 | H7: =IF($F7=0,0,INDEX(Aux_HH!$E$4:$E$18,MATCH($B7&"|"&$E7,Aux_HH!$A$4:$A$18,0))) -> 0 | I7: =IF($F7=0,0,INDEX(Aux_HH!$F$4:$F$18,MATCH($B7&"|"&$E7,Aux_HH!$A$4:$A$18,0))) -> 0 | J7: =IF($F7=0,0,INDEX(Aux_HH!$G$4:$G$18,MATCH($B7&"|"&$E7,Aux_HH!$A$4:$A$18,0))) -> 0 | K7: =IF($F7=0,0,INDEX(Aux_HH!$H$4:$H$18,MATCH($B7&"|"&$E7,Aux_HH!$A$4:$A$18,0))) -> 0 | L7: =IF($F7=0,0,INDEX(Aux_HH!$I$4:$I$18,MATCH($B7&"|"&$E7,Aux_HH!$A$4:$A$18,0))) -> 0
A8: =IF(Frota!$A5="","",Frota!$A5) -> Colhedora CASE A8810 — 1035 | B8: =IF(Frota!$A5="","",Frota!$B5) -> Colhedora | C8: 5 | D8: =INDEX(Semanas!$E$3:$E$54,5) -> 4 | E8: =IF(Frota!$A5="","",Cronograma!F5) -> B | F8: =IF(OR($E8="",$E8=0),0,1) -> 1 | G8: =IF($F8=0,0,INDEX(Aux_HH!$D$4:$D$18,MATCH($B8&"|"&$E8,Aux_HH!$A$4:$A$18,0))) -> 10.25 | H8: =IF($F8=0,0,INDEX(Aux_HH!$E$4:$E$18,MATCH($B8&"|"&$E8,Aux_HH!$A$4:$A$18,0))) -> 0 | I8: =IF($F8=0,0,INDEX(Aux_HH!$F$4:$F$18,MATCH($B8&"|"&$E8,Aux_HH!$A$4:$A$18,0))) -> 3 | J8: =IF($F8=0,0,INDEX(Aux_HH!$G$4:$G$18,MATCH($B8&"|"&$E8,Aux_HH!$A$4:$A$18,0))) -> 1.75 | K8: =IF($F8=0,0,INDEX(Aux_HH!$H$4:$H$18,MATCH($B8&"|"&$E8,Aux_HH!$A$4:$A$18,0))) -> 0 | L8: =IF($F8=0,0,INDEX(Aux_HH!$I$4:$I$18,MATCH($B8&"|"&$E8,Aux_HH!$A$4:$A$18,0))) -> 0
A9: =IF(Frota!$A5="","",Frota!$A5) -> Colhedora CASE A8810 — 1035 | B9: =IF(Frota!$A5="","",Frota!$B5) -> Colhedora | C9: 6 | D9: =INDEX(Semanas!$E$3:$E$54,6) -> 5 | E9: =IF(Frota!$A5="","",Cronograma!G5) | F9: =IF(OR($E9="",$E9=0),0,1) -> 0 | G9: =IF($F9=0,0,INDEX(Aux_HH!$D$4:$D$18,MATCH($B9&"|"&$E9,Aux_HH!$A$4:$A$18,0))) -> 0 | H9: =IF($F9=0,0,INDEX(Aux_HH!$E$4:$E$18,MATCH($B9&"|"&$E9,Aux_HH!$A$4:$A$18,0))) -> 0 | I9: =IF($F9=0,0,INDEX(Aux_HH!$F$4:$F$18,MATCH($B9&"|"&$E9,Aux_HH!$A$4:$A$18,0))) -> 0 | J9: =IF($F9=0,0,INDEX(Aux_HH!$G$4:$G$18,MATCH($B9&"|"&$E9,Aux_HH!$A$4:$A$18,0))) -> 0 | K9: =IF($F9=0,0,INDEX(Aux_HH!$H$4:$H$18,MATCH($B9&"|"&$E9,Aux_HH!$A$4:$A$18,0))) -> 0 | L9: =IF($F9=0,0,INDEX(Aux_HH!$I$4:$I$18,MATCH($B9&"|"&$E9,Aux_HH!$A$4:$A$18,0))) -> 0
A10: =IF(Frota!$A5="","",Frota!$A5) -> Colhedora CASE A8810 — 1035 | B10: =IF(Frota!$A5="","",Frota!$B5) -> Colhedora | C10: 7 | D10: =INDEX(Semanas!$E$3:$E$54,7) -> 5 | E10: =IF(Frota!$A5="","",Cronograma!H5) | F10: =IF(OR($E10="",$E10=0),0,1) -> 0 | G10: =IF($F10=0,0,INDEX(Aux_HH!$D$4:$D$18,MATCH($B10&"|"&$E10,Aux_HH!$A$4:$A$18,0))) -> 0 | H10: =IF($F10=0,0,INDEX(Aux_HH!$E$4:$E$18,MATCH($B10&"|"&$E10,Aux_HH!$A$4:$A$18,0))) -> 0 | I10: =IF($F10=0,0,INDEX(Aux_HH!$F$4:$F$18,MATCH($B10&"|"&$E10,Aux_HH!$A$4:$A$18,0))) -> 0 | J10: =IF($F10=0,0,INDEX(Aux_HH!$G$4:$G$18,MATCH($B10&"|"&$E10,Aux_HH!$A$4:$A$18,0))) -> 0 | K10: =IF($F10=0,0,INDEX(Aux_HH!$H$4:$H$18,MATCH($B10&"|"&$E10,Aux_HH!$A$4:$A$18,0))) -> 0 | L10: =IF($F10=0,0,INDEX(Aux_HH!$I$4:$I$18,MATCH($B10&"|"&$E10,Aux_HH!$A$4:$A$18,0))) -> 0
A11: =IF(Frota!$A5="","",Frota!$A5) -> Colhedora CASE A8810 — 1035 | B11: =IF(Frota!$A5="","",Frota!$B5) -> Colhedora | C11: 8 | D11: =INDEX(Semanas!$E$3:$E$54,8) -> 5 | E11: =IF(Frota!$A5="","",Cronograma!I5) | F11: =IF(OR($E11="",$E11=0),0,1) -> 0 | G11: =IF($F11=0,0,INDEX(Aux_HH!$D$4:$D$18,MATCH($B11&"|"&$E11,Aux_HH!$A$4:$A$18,0))) -> 0 | H11: =IF($F11=0,0,INDEX(Aux_HH!$E$4:$E$18,MATCH($B11&"|"&$E11,Aux_HH!$A$4:$A$18,0))) -> 0 | I11: =IF($F11=0,0,INDEX(Aux_HH!$F$4:$F$18,MATCH($B11&"|"&$E11,Aux_HH!$A$4:$A$18,0))) -> 0 | J11: =IF($F11=0,0,INDEX(Aux_HH!$G$4:$G$18,MATCH($B11&"|"&$E11,Aux_HH!$A$4:$A$18,0))) -> 0 | K11: =IF($F11=0,0,INDEX(Aux_HH!$H$4:$H$18,MATCH($B11&"|"&$E11,Aux_HH!$A$4:$A$18,0))) -> 0 | L11: =IF($F11=0,0,INDEX(Aux_HH!$I$4:$I$18,MATCH($B11&"|"&$E11,Aux_HH!$A$4:$A$18,0))) -> 0
A12: =IF(Frota!$A5="","",Frota!$A5) -> Colhedora CASE A8810 — 1035 | B12: =IF(Frota!$A5="","",Frota!$B5) -> Colhedora | C12: 9 | D12: =INDEX(Semanas!$E$3:$E$54,9) -> 5 | E12: =IF(Frota!$A5="","",Cronograma!J5) | F12: =IF(OR($E12="",$E12=0),0,1) -> 0 | G12: =IF($F12=0,0,INDEX(Aux_HH!$D$4:$D$18,MATCH($B12&"|"&$E12,Aux_HH!$A$4:$A$18,0))) -> 0 | H12: =IF($F12=0,0,INDEX(Aux_HH!$E$4:$E$18,MATCH($B12&"|"&$E12,Aux_HH!$A$4:$A$18,0))) -> 0 | I12: =IF($F12=0,0,INDEX(Aux_HH!$F$4:$F$18,MATCH($B12&"|"&$E12,Aux_HH!$A$4:$A$18,0))) -> 0 | J12: =IF($F12=0,0,INDEX(Aux_HH!$G$4:$G$18,MATCH($B12&"|"&$E12,Aux_HH!$A$4:$A$18,0))) -> 0 | K12: =IF($F12=0,0,INDEX(Aux_HH!$H$4:$H$18,MATCH($B12&"|"&$E12,Aux_HH!$A$4:$A$18,0))) -> 0 | L12: =IF($F12=0,0,INDEX(Aux_HH!$I$4:$I$18,MATCH($B12&"|"&$E12,Aux_HH!$A$4:$A$18,0))) -> 0
A13: =IF(Frota!$A5="","",Frota!$A5) -> Colhedora CASE A8810 — 1035 | B13: =IF(Frota!$A5="","",Frota!$B5) -> Colhedora | C13: 10 | D13: =INDEX(Semanas!$E$3:$E$54,10) -> 6 | E13: =IF(Frota!$A5="","",Cronograma!K5) | F13: =IF(OR($E13="",$E13=0),0,1) -> 0 | G13: =IF($F13=0,0,INDEX(Aux_HH!$D$4:$D$18,MATCH($B13&"|"&$E13,Aux_HH!$A$4:$A$18,0))) -> 0 | H13: =IF($F13=0,0,INDEX(Aux_HH!$E$4:$E$18,MATCH($B13&"|"&$E13,Aux_HH!$A$4:$A$18,0))) -> 0 | I13: =IF($F13=0,0,INDEX(Aux_HH!$F$4:$F$18,MATCH($B13&"|"&$E13,Aux_HH!$A$4:$A$18,0))) -> 0 | J13: =IF($F13=0,0,INDEX(Aux_HH!$G$4:$G$18,MATCH($B13&"|"&$E13,Aux_HH!$A$4:$A$18,0))) -> 0 | K13: =IF($F13=0,0,INDEX(Aux_HH!$H$4:$H$18,MATCH($B13&"|"&$E13,Aux_HH!$A$4:$A$18,0))) -> 0 | L13: =IF($F13=0,0,INDEX(Aux_HH!$I$4:$I$18,MATCH($B13&"|"&$E13,Aux_HH!$A$4:$A$18,0))) -> 0
A14: =IF(Frota!$A5="","",Frota!$A5) -> Colhedora CASE A8810 — 1035 | B14: =IF(Frota!$A5="","",Frota!$B5) -> Colhedora | C14: 11 | D14: =INDEX(Semanas!$E$3:$E$54,11) -> 6 | E14: =IF(Frota!$A5="","",Cronograma!L5) -> S | F14: =IF(OR($E14="",$E14=0),0,1) -> 1 | G14: =IF($F14=0,0,INDEX(Aux_HH!$D$4:$D$18,MATCH($B14&"|"&$E14,Aux_HH!$A$4:$A$18,0))) -> 3.75 | H14: =IF($F14=0,0,INDEX(Aux_HH!$E$4:$E$18,MATCH($B14&"|"&$E14,Aux_HH!$A$4:$A$18,0))) -> 0 | I14: =IF($F14=0,0,INDEX(Aux_HH!$F$4:$F$18,MATCH($B14&"|"&$E14,Aux_HH!$A$4:$A$18,0))) -> 1 | J14: =IF($F14=0,0,INDEX(Aux_HH!$G$4:$G$18,MATCH($B14&"|"&$E14,Aux_HH!$A$4:$A$18,0))) -> 0.75 | K14: =IF($F14=0,0,INDEX(Aux_HH!$H$4:$H$18,MATCH($B14&"|"&$E14,Aux_HH!$A$4:$A$18,0))) -> 0 | L14: =IF($F14=0,0,INDEX(Aux_HH!$I$4:$I$18,MATCH($B14&"|"&$E14,Aux_HH!$A$4:$A$18,0))) -> 0
A15: =IF(Frota!$A5="","",Frota!$A5) -> Colhedora CASE A8810 — 1035 | B15: =IF(Frota!$A5="","",Frota!$B5) -> Colhedora | C15: 12 | D15: =INDEX(Semanas!$E$3:$E$54,12) -> 6 | E15: =IF(Frota!$A5="","",Cronograma!M5) | F15: =IF(OR($E15="",$E15=0),0,1) -> 0 | G15: =IF($F15=0,0,INDEX(Aux_HH!$D$4:$D$18,MATCH($B15&"|"&$E15,Aux_HH!$A$4:$A$18,0))) -> 0 | H15: =IF($F15=0,0,INDEX(Aux_HH!$E$4:$E$18,MATCH($B15&"|"&$E15,Aux_HH!$A$4:$A$18,0))) -> 0 | I15: =IF($F15=0,0,INDEX(Aux_HH!$F$4:$F$18,MATCH($B15&"|"&$E15,Aux_HH!$A$4:$A$18,0))) -> 0 | J15: =IF($F15=0,0,INDEX(Aux_HH!$G$4:$G$18,MATCH($B15&"|"&$E15,Aux_HH!$A$4:$A$18,0))) -> 0 | K15: =IF($F15=0,0,INDEX(Aux_HH!$H$4:$H$18,MATCH($B15&"|"&$E15,Aux_HH!$A$4:$A$18,0))) -> 0 | L15: =IF($F15=0,0,INDEX(Aux_HH!$I$4:$I$18,MATCH($B15&"|"&$E15,Aux_HH!$A$4:$A$18,0))) -> 0
A16: =IF(Frota!$A5="","",Frota!$A5) -> Colhedora CASE A8810 — 1035 | B16: =IF(Frota!$A5="","",Frota!$B5) -> Colhedora | C16: 13 | D16: =INDEX(Semanas!$E$3:$E$54,13) -> 6 | E16: =IF(Frota!$A5="","",Cronograma!N5) | F16: =IF(OR($E16="",$E16=0),0,1) -> 0 | G16: =IF($F16=0,0,INDEX(Aux_HH!$D$4:$D$18,MATCH($B16&"|"&$E16,Aux_HH!$A$4:$A$18,0))) -> 0 | H16: =IF($F16=0,0,INDEX(Aux_HH!$E$4:$E$18,MATCH($B16&"|"&$E16,Aux_HH!$A$4:$A$18,0))) -> 0 | I16: =IF($F16=0,0,INDEX(Aux_HH!$F$4:$F$18,MATCH($B16&"|"&$E16,Aux_HH!$A$4:$A$18,0))) -> 0 | J16: =IF($F16=0,0,INDEX(Aux_HH!$G$4:$G$18,MATCH($B16&"|"&$E16,Aux_HH!$A$4:$A$18,0))) -> 0 | K16: =IF($F16=0,0,INDEX(Aux_HH!$H$4:$H$18,MATCH($B16&"|"&$E16,Aux_HH!$A$4:$A$18,0))) -> 0 | L16: =IF($F16=0,0,INDEX(Aux_HH!$I$4:$I$18,MATCH($B16&"|"&$E16,Aux_HH!$A$4:$A$18,0))) -> 0
A17: =IF(Frota!$A5="","",Frota!$A5) -> Colhedora CASE A8810 — 1035 | B17: =IF(Frota!$A5="","",Frota!$B5) -> Colhedora | C17: 14 | D17: =INDEX(Semanas!$E$3:$E$54,14) -> 7 | E17: =IF(Frota!$A5="","",Cronograma!O5) | F17: =IF(OR($E17="",$E17=0),0,1) -> 0 | G17: =IF($F17=0,0,INDEX(Aux_HH!$D$4:$D$18,MATCH($B17&"|"&$E17,Aux_HH!$A$4:$A$18,0))) -> 0 | H17: =IF($F17=0,0,INDEX(Aux_HH!$E$4:$E$18,MATCH($B17&"|"&$E17,Aux_HH!$A$4:$A$18,0))) -> 0 | I17: =IF($F17=0,0,INDEX(Aux_HH!$F$4:$F$18,MATCH($B17&"|"&$E17,Aux_HH!$A$4:$A$18,0))) -> 0 | J17: =IF($F17=0,0,INDEX(Aux_HH!$G$4:$G$18,MATCH($B17&"|"&$E17,Aux_HH!$A$4:$A$18,0))) -> 0 | K17: =IF($F17=0,0,INDEX(Aux_HH!$H$4:$H$18,MATCH($B17&"|"&$E17,Aux_HH!$A$4:$A$18,0))) -> 0 | L17: =IF($F17=0,0,INDEX(Aux_HH!$I$4:$I$18,MATCH($B17&"|"&$E17,Aux_HH!$A$4:$A$18,0))) -> 0
A18: =IF(Frota!$A5="","",Frota!$A5) -> Colhedora CASE A8810 — 1035 | B18: =IF(Frota!$A5="","",Frota!$B5) -> Colhedora | C18: 15 | D18: =INDEX(Semanas!$E$3:$E$54,15) -> 7 | E18: =IF(Frota!$A5="","",Cronograma!P5) | F18: =IF(OR($E18="",$E18=0),0,1) -> 0 | G18: =IF($F18=0,0,INDEX(Aux_HH!$D$4:$D$18,MATCH($B18&"|"&$E18,Aux_HH!$A$4:$A$18,0))) -> 0 | H18: =IF($F18=0,0,INDEX(Aux_HH!$E$4:$E$18,MATCH($B18&"|"&$E18,Aux_HH!$A$4:$A$18,0))) -> 0 | I18: =IF($F18=0,0,INDEX(Aux_HH!$F$4:$F$18,MATCH($B18&"|"&$E18,Aux_HH!$A$4:$A$18,0))) -> 0 | J18: =IF($F18=0,0,INDEX(Aux_HH!$G$4:$G$18,MATCH($B18&"|"&$E18,Aux_HH!$A$4:$A$18,0))) -> 0 | K18: =IF($F18=0,0,INDEX(Aux_HH!$H$4:$H$18,MATCH($B18&"|"&$E18,Aux_HH!$A$4:$A$18,0))) -> 0 | L18: =IF($F18=0,0,INDEX(Aux_HH!$I$4:$I$18,MATCH($B18&"|"&$E18,Aux_HH!$A$4:$A$18,0))) -> 0
A19: =IF(Frota!$A5="","",Frota!$A5) -> Colhedora CASE A8810 — 1035 | B19: =IF(Frota!$A5="","",Frota!$B5) -> Colhedora | C19: 16 | D19: =INDEX(Semanas!$E$3:$E$54,16) -> 7 | E19: =IF(Frota!$A5="","",Cronograma!Q5) -> A | F19: =IF(OR($E19="",$E19=0),0,1) -> 1 | G19: =IF($F19=0,0,INDEX(Aux_HH!$D$4:$D$18,MATCH($B19&"|"&$E19,Aux_HH!$A$4:$A$18,0))) -> 10.25 | H19: =IF($F19=0,0,INDEX(Aux_HH!$E$4:$E$18,MATCH($B19&"|"&$E19,Aux_HH!$A$4:$A$18,0))) -> 0 | I19: =IF($F19=0,0,INDEX(Aux_HH!$F$4:$F$18,MATCH($B19&"|"&$E19,Aux_HH!$A$4:$A$18,0))) -> 3 | J19: =IF($F19=0,0,INDEX(Aux_HH!$G$4:$G$18,MATCH($B19&"|"&$E19,Aux_HH!$A$4:$A$18,0))) -> 1.75 | K19: =IF($F19=0,0,INDEX(Aux_HH!$H$4:$H$18,MATCH($B19&"|"&$E19,Aux_HH!$A$4:$A$18,0))) -> 0 | L19: =IF($F19=0,0,INDEX(Aux_HH!$I$4:$I$18,MATCH($B19&"|"&$E19,Aux_HH!$A$4:$A$18,0))) -> 0
A20: =IF(Frota!$A5="","",Frota!$A5) -> Colhedora CASE A8810 — 1035 | B20: =IF(Frota!$A5="","",Frota!$B5) -> Colhedora | C20: 17 | D20: =INDEX(Semanas!$E$3:$E$54,17) -> 7 | E20: =IF(Frota!$A5="","",Cronograma!R5) | F20: =IF(OR($E20="",$E20=0),0,1) -> 0 | G20: =IF($F20=0,0,INDEX(Aux_HH!$D$4:$D$18,MATCH($B20&"|"&$E20,Aux_HH!$A$4:$A$18,0))) -> 0 | H20: =IF($F20=0,0,INDEX(Aux_HH!$E$4:$E$18,MATCH($B20&"|"&$E20,Aux_HH!$A$4:$A$18,0))) -> 0 | I20: =IF($F20=0,0,INDEX(Aux_HH!$F$4:$F$18,MATCH($B20&"|"&$E20,Aux_HH!$A$4:$A$18,0))) -> 0 | J20: =IF($F20=0,0,INDEX(Aux_HH!$G$4:$G$18,MATCH($B20&"|"&$E20,Aux_HH!$A$4:$A$18,0))) -> 0 | K20: =IF($F20=0,0,INDEX(Aux_HH!$H$4:$H$18,MATCH($B20&"|"&$E20,Aux_HH!$A$4:$A$18,0))) -> 0 | L20: =IF($F20=0,0,INDEX(Aux_HH!$I$4:$I$18,MATCH($B20&"|"&$E20,Aux_HH!$A$4:$A$18,0))) -> 0
A21: =IF(Frota!$A5="","",Frota!$A5) -> Colhedora CASE A8810 — 1035 | B21: =IF(Frota!$A5="","",Frota!$B5) -> Colhedora | C21: 18 | D21: =INDEX(Semanas!$E$3:$E$54,18) -> 7 | E21: =IF(Frota!$A5="","",Cronograma!S5) | F21: =IF(OR($E21="",$E21=0),0,1) -> 0 | G21: =IF($F21=0,0,INDEX(Aux_HH!$D$4:$D$18,MATCH($B21&"|"&$E21,Aux_HH!$A$4:$A$18,0))) -> 0 | H21: =IF($F21=0,0,INDEX(Aux_HH!$E$4:$E$18,MATCH($B21&"|"&$E21,Aux_HH!$A$4:$A$18,0))) -> 0 | I21: =IF($F21=0,0,INDEX(Aux_HH!$F$4:$F$18,MATCH($B21&"|"&$E21,Aux_HH!$A$4:$A$18,0))) -> 0 | J21: =IF($F21=0,0,INDEX(Aux_HH!$G$4:$G$18,MATCH($B21&"|"&$E21,Aux_HH!$A$4:$A$18,0))) -> 0 | K21: =IF($F21=0,0,INDEX(Aux_HH!$H$4:$H$18,MATCH($B21&"|"&$E21,Aux_HH!$A$4:$A$18,0))) -> 0 | L21: =IF($F21=0,0,INDEX(Aux_HH!$I$4:$I$18,MATCH($B21&"|"&$E21,Aux_HH!$A$4:$A$18,0))) -> 0
A22: =IF(Frota!$A5="","",Frota!$A5) -> Colhedora CASE A8810 — 1035 | B22: =IF(Frota!$A5="","",Frota!$B5) -> Colhedora | C22: 19 | D22: =INDEX(Semanas!$E$3:$E$54,19) -> 8 | E22: =IF(Frota!$A5="","",Cronograma!T5) | F22: =IF(OR($E22="",$E22=0),0,1) -> 0 | G22: =IF($F22=0,0,INDEX(Aux_HH!$D$4:$D$18,MATCH($B22&"|"&$E22,Aux_HH!$A$4:$A$18,0))) -> 0 | H22: =IF($F22=0,0,INDEX(Aux_HH!$E$4:$E$18,MATCH($B22&"|"&$E22,Aux_HH!$A$4:$A$18,0))) -> 0 | I22: =IF($F22=0,0,INDEX(Aux_HH!$F$4:$F$18,MATCH($B22&"|"&$E22,Aux_HH!$A$4:$A$18,0))) -> 0 | J22: =IF($F22=0,0,INDEX(Aux_HH!$G$4:$G$18,MATCH($B22&"|"&$E22,Aux_HH!$A$4:$A$18,0))) -> 0 | K22: =IF($F22=0,0,INDEX(Aux_HH!$H$4:$H$18,MATCH($B22&"|"&$E22,Aux_HH!$A$4:$A$18,0))) -> 0 | L22: =IF($F22=0,0,INDEX(Aux_HH!$I$4:$I$18,MATCH($B22&"|"&$E22,Aux_HH!$A$4:$A$18,0))) -> 0
A23: =IF(Frota!$A5="","",Frota!$A5) -> Colhedora CASE A8810 — 1035 | B23: =IF(Frota!$A5="","",Frota!$B5) -> Colhedora | C23: 20 | D23: =INDEX(Semanas!$E$3:$E$54,20) -> 8 | E23: =IF(Frota!$A5="","",Cronograma!U5) | F23: =IF(OR($E23="",$E23=0),0,1) -> 0 | G23: =IF($F23=0,0,INDEX(Aux_HH!$D$4:$D$18,MATCH($B23&"|"&$E23,Aux_HH!$A$4:$A$18,0))) -> 0 | H23: =IF($F23=0,0,INDEX(Aux_HH!$E$4:$E$18,MATCH($B23&"|"&$E23,Aux_HH!$A$4:$A$18,0))) -> 0 | I23: =IF($F23=0,0,INDEX(Aux_HH!$F$4:$F$18,MATCH($B23&"|"&$E23,Aux_HH!$A$4:$A$18,0))) -> 0 | J23: =IF($F23=0,0,INDEX(Aux_HH!$G$4:$G$18,MATCH($B23&"|"&$E23,Aux_HH!$A$4:$A$18,0))) -> 0 | K23: =IF($F23=0,0,INDEX(Aux_HH!$H$4:$H$18,MATCH($B23&"|"&$E23,Aux_HH!$A$4:$A$18,0))) -> 0 | L23: =IF($F23=0,0,INDEX(Aux_HH!$I$4:$I$18,MATCH($B23&"|"&$E23,Aux_HH!$A$4:$A$18,0))) -> 0
A24: =IF(Frota!$A5="","",Frota!$A5) -> Colhedora CASE A8810 — 1035 | B24: =IF(Frota!$A5="","",Frota!$B5) -> Colhedora | C24: 21 | D24: =INDEX(Semanas!$E$3:$E$54,21) -> 8 | E24: =IF(Frota!$A5="","",Cronograma!V5) | F24: =IF(OR($E24="",$E24=0),0,1) -> 0 | G24: =IF($F24=0,0,INDEX(Aux_HH!$D$4:$D$18,MATCH($B24&"|"&$E24,Aux_HH!$A$4:$A$18,0))) -> 0 | H24: =IF($F24=0,0,INDEX(Aux_HH!$E$4:$E$18,MATCH($B24&"|"&$E24,Aux_HH!$A$4:$A$18,0))) -> 0 | I24: =IF($F24=0,0,INDEX(Aux_HH!$F$4:$F$18,MATCH($B24&"|"&$E24,Aux_HH!$A$4:$A$18,0))) -> 0 | J24: =IF($F24=0,0,INDEX(Aux_HH!$G$4:$G$18,MATCH($B24&"|"&$E24,Aux_HH!$A$4:$A$18,0))) -> 0 | K24: =IF($F24=0,0,INDEX(Aux_HH!$H$4:$H$18,MATCH($B24&"|"&$E24,Aux_HH!$A$4:$A$18,0))) -> 0 | L24: =IF($F24=0,0,INDEX(Aux_HH!$I$4:$I$18,MATCH($B24&"|"&$E24,Aux_HH!$A$4:$A$18,0))) -> 0
A25: =IF(Frota!$A5="","",Frota!$A5) -> Colhedora CASE A8810 — 1035 | B25: =IF(Frota!$A5="","",Frota!$B5) -> Colhedora | C25: 22 | D25: =INDEX(Semanas!$E$3:$E$54,22) -> 8 | E25: =IF(Frota!$A5="","",Cronograma!W5) -> S | F25: =IF(OR($E25="",$E25=0),0,1) -> 1 | G25: =IF($F25=0,0,INDEX(Aux_HH!$D$4:$D$18,MATCH($B25&"|"&$E25,Aux_HH!$A$4:$A$18,0))) -> 3.75 | H25: =IF($F25=0,0,INDEX(Aux_HH!$E$4:$E$18,MATCH($B25&"|"&$E25,Aux_HH!$A$4:$A$18,0))) -> 0 | I25: =IF($F25=0,0,INDEX(Aux_HH!$F$4:$F$18,MATCH($B25&"|"&$E25,Aux_HH!$A$4:$A$18,0))) -> 1 | J25: =IF($F25=0,0,INDEX(Aux_HH!$G$4:$G$18,MATCH($B25&"|"&$E25,Aux_HH!$A$4:$A$18,0))) -> 0.75 | K25: =IF($F25=0,0,INDEX(Aux_HH!$H$4:$H$18,MATCH($B25&"|"&$E25,Aux_HH!$A$4:$A$18,0))) -> 0 | L25: =IF($F25=0,0,INDEX(Aux_HH!$I$4:$I$18,MATCH($B25&"|"&$E25,Aux_HH!$A$4:$A$18,0))) -> 0
A26: =IF(Frota!$A5="","",Frota!$A5) -> Colhedora CASE A8810 — 1035 | B26: =IF(Frota!$A5="","",Frota!$B5) -> Colhedora | C26: 23 | D26: =INDEX(Semanas!$E$3:$E$54,23) -> 9 | E26: =IF(Frota!$A5="","",Cronograma!X5) | F26: =IF(OR($E26="",$E26=0),0,1) -> 0 | G26: =IF($F26=0,0,INDEX(Aux_HH!$D$4:$D$18,MATCH($B26&"|"&$E26,Aux_HH!$A$4:$A$18,0))) -> 0 | H26: =IF($F26=0,0,INDEX(Aux_HH!$E$4:$E$18,MATCH($B26&"|"&$E26,Aux_HH!$A$4:$A$18,0))) -> 0 | I26: =IF($F26=0,0,INDEX(Aux_HH!$F$4:$F$18,MATCH($B26&"|"&$E26,Aux_HH!$A$4:$A$18,0))) -> 0 | J26: =IF($F26=0,0,INDEX(Aux_HH!$G$4:$G$18,MATCH($B26&"|"&$E26,Aux_HH!$A$4:$A$18,0))) -> 0 | K26: =IF($F26=0,0,INDEX(Aux_HH!$H$4:$H$18,MATCH($B26&"|"&$E26,Aux_HH!$A$4:$A$18,0))) -> 0 | L26: =IF($F26=0,0,INDEX(Aux_HH!$I$4:$I$18,MATCH($B26&"|"&$E26,Aux_HH!$A$4:$A$18,0))) -> 0
A27: =IF(Frota!$A5="","",Frota!$A5) -> Colhedora CASE A8810 — 1035 | B27: =IF(Frota!$A5="","",Frota!$B5) -> Colhedora | C27: 24 | D27: =INDEX(Semanas!$E$3:$E$54,24) -> 9 | E27: =IF(Frota!$A5="","",Cronograma!Y5) | F27: =IF(OR($E27="",$E27=0),0,1) -> 0 | G27: =IF($F27=0,0,INDEX(Aux_HH!$D$4:$D$18,MATCH($B27&"|"&$E27,Aux_HH!$A$4:$A$18,0))) -> 0 | H27: =IF($F27=0,0,INDEX(Aux_HH!$E$4:$E$18,MATCH($B27&"|"&$E27,Aux_HH!$A$4:$A$18,0))) -> 0 | I27: =IF($F27=0,0,INDEX(Aux_HH!$F$4:$F$18,MATCH($B27&"|"&$E27,Aux_HH!$A$4:$A$18,0))) -> 0 | J27: =IF($F27=0,0,INDEX(Aux_HH!$G$4:$G$18,MATCH($B27&"|"&$E27,Aux_HH!$A$4:$A$18,0))) -> 0 | K27: =IF($F27=0,0,INDEX(Aux_HH!$H$4:$H$18,MATCH($B27&"|"&$E27,Aux_HH!$A$4:$A$18,0))) -> 0 | L27: =IF($F27=0,0,INDEX(Aux_HH!$I$4:$I$18,MATCH($B27&"|"&$E27,Aux_HH!$A$4:$A$18,0))) -> 0
A28: =IF(Frota!$A5="","",Frota!$A5) -> Colhedora CASE A8810 — 1035 | B28: =IF(Frota!$A5="","",Frota!$B5) -> Colhedora | C28: 25 | D28: =INDEX(Semanas!$E$3:$E$54,25) -> 9 | E28: =IF(Frota!$A5="","",Cronograma!Z5) | F28: =IF(OR($E28="",$E28=0),0,1) -> 0 | G28: =IF($F28=0,0,INDEX(Aux_HH!$D$4:$D$18,MATCH($B28&"|"&$E28,Aux_HH!$A$4:$A$18,0))) -> 0 | H28: =IF($F28=0,0,INDEX(Aux_HH!$E$4:$E$18,MATCH($B28&"|"&$E28,Aux_HH!$A$4:$A$18,0))) -> 0 | I28: =IF($F28=0,0,INDEX(Aux_HH!$F$4:$F$18,MATCH($B28&"|"&$E28,Aux_HH!$A$4:$A$18,0))) -> 0 | J28: =IF($F28=0,0,INDEX(Aux_HH!$G$4:$G$18,MATCH($B28&"|"&$E28,Aux_HH!$A$4:$A$18,0))) -> 0 | K28: =IF($F28=0,0,INDEX(Aux_HH!$H$4:$H$18,MATCH($B28&"|"&$E28,Aux_HH!$A$4:$A$18,0))) -> 0 | L28: =IF($F28=0,0,INDEX(Aux_HH!$I$4:$I$18,MATCH($B28&"|"&$E28,Aux_HH!$A$4:$A$18,0))) -> 0
A29: =IF(Frota!$A5="","",Frota!$A5) -> Colhedora CASE A8810 — 1035 | B29: =IF(Frota!$A5="","",Frota!$B5) -> Colhedora | C29: 26 | D29: =INDEX(Semanas!$E$3:$E$54,26) -> 9 | E29: =IF(Frota!$A5="","",Cronograma!AA5) | F29: =IF(OR($E29="",$E29=0),0,1) -> 0 | G29: =IF($F29=0,0,INDEX(Aux_HH!$D$4:$D$18,MATCH($B29&"|"&$E29,Aux_HH!$A$4:$A$18,0))) -> 0 | H29: =IF($F29=0,0,INDEX(Aux_HH!$E$4:$E$18,MATCH($B29&"|"&$E29,Aux_HH!$A$4:$A$18,0))) -> 0 | I29: =IF($F29=0,0,INDEX(Aux_HH!$F$4:$F$18,MATCH($B29&"|"&$E29,Aux_HH!$A$4:$A$18,0))) -> 0 | J29: =IF($F29=0,0,INDEX(Aux_HH!$G$4:$G$18,MATCH($B29&"|"&$E29,Aux_HH!$A$4:$A$18,0))) -> 0 | K29: =IF($F29=0,0,INDEX(Aux_HH!$H$4:$H$18,MATCH($B29&"|"&$E29,Aux_HH!$A$4:$A$18,0))) -> 0 | L29: =IF($F29=0,0,INDEX(Aux_HH!$I$4:$I$18,MATCH($B29&"|"&$E29,Aux_HH!$A$4:$A$18,0))) -> 0
A30: =IF(Frota!$A5="","",Frota!$A5) -> Colhedora CASE A8810 — 1035 | B30: =IF(Frota!$A5="","",Frota!$B5) -> Colhedora | C30: 27 | D30: =INDEX(Semanas!$E$3:$E$54,27) -> 9 | E30: =IF(Frota!$A5="","",Cronograma!AB5) | F30: =IF(OR($E30="",$E30=0),0,1) -> 0 | G30: =IF($F30=0,0,INDEX(Aux_HH!$D$4:$D$18,MATCH($B30&"|"&$E30,Aux_HH!$A$4:$A$18,0))) -> 0 | H30: =IF($F30=0,0,INDEX(Aux_HH!$E$4:$E$18,MATCH($B30&"|"&$E30,Aux_HH!$A$4:$A$18,0))) -> 0 | I30: =IF($F30=0,0,INDEX(Aux_HH!$F$4:$F$18,MATCH($B30&"|"&$E30,Aux_HH!$A$4:$A$18,0))) -> 0 | J30: =IF($F30=0,0,INDEX(Aux_HH!$G$4:$G$18,MATCH($B30&"|"&$E30,Aux_HH!$A$4:$A$18,0))) -> 0 | K30: =IF($F30=0,0,INDEX(Aux_HH!$H$4:$H$18,MATCH($B30&"|"&$E30,Aux_HH!$A$4:$A$18,0))) -> 0 | L30: =IF($F30=0,0,INDEX(Aux_HH!$I$4:$I$18,MATCH($B30&"|"&$E30,Aux_HH!$A$4:$A$18,0))) -> 0
A31: =IF(Frota!$A5="","",Frota!$A5) -> Colhedora CASE A8810 — 1035 | B31: =IF(Frota!$A5="","",Frota!$B5) -> Colhedora | C31: 28 | D31: =INDEX(Semanas!$E$3:$E$54,28) -> 10 | E31: =IF(Frota!$A5="","",Cronograma!AC5) -> B | F31: =IF(OR($E31="",$E31=0),0,1) -> 1 | G31: =IF($F31=0,0,INDEX(Aux_HH!$D$4:$D$18,MATCH($B31&"|"&$E31,Aux_HH!$A$4:$A$18,0))) -> 10.25 | H31: =IF($F31=0,0,INDEX(Aux_HH!$E$4:$E$18,MATCH($B31&"|"&$E31,Aux_HH!$A$4:$A$18,0))) -> 0 | I31: =IF($F31=0,0,INDEX(Aux_HH!$F$4:$F$18,MATCH($B31&"|"&$E31,Aux_HH!$A$4:$A$18,0))) -> 3 | J31: =IF($F31=0,0,INDEX(Aux_HH!$G$4:$G$18,MATCH($B31&"|"&$E31,Aux_HH!$A$4:$A$18,0))) -> 1.75 | K31: =IF($F31=0,0,INDEX(Aux_HH!$H$4:$H$18,MATCH($B31&"|"&$E31,Aux_HH!$A$4:$A$18,0))) -> 0 | L31: =IF($F31=0,0,INDEX(Aux_HH!$I$4:$I$18,MATCH($B31&"|"&$E31,Aux_HH!$A$4:$A$18,0))) -> 0
A32: =IF(Frota!$A5="","",Frota!$A5) -> Colhedora CASE A8810 — 1035 | B32: =IF(Frota!$A5="","",Frota!$B5) -> Colhedora | C32: 29 | D32: =INDEX(Semanas!$E$3:$E$54,29) -> 10 | E32: =IF(Frota!$A5="","",Cronograma!AD5) | F32: =IF(OR($E32="",$E32=0),0,1) -> 0 | G32: =IF($F32=0,0,INDEX(Aux_HH!$D$4:$D$18,MATCH($B32&"|"&$E32,Aux_HH!$A$4:$A$18,0))) -> 0 | H32: =IF($F32=0,0,INDEX(Aux_HH!$E$4:$E$18,MATCH($B32&"|"&$E32,Aux_HH!$A$4:$A$18,0))) -> 0 | I32: =IF($F32=0,0,INDEX(Aux_HH!$F$4:$F$18,MATCH($B32&"|"&$E32,Aux_HH!$A$4:$A$18,0))) -> 0 | J32: =IF($F32=0,0,INDEX(Aux_HH!$G$4:$G$18,MATCH($B32&"|"&$E32,Aux_HH!$A$4:$A$18,0))) -> 0 | K32: =IF($F32=0,0,INDEX(Aux_HH!$H$4:$H$18,MATCH($B32&"|"&$E32,Aux_HH!$A$4:$A$18,0))) -> 0 | L32: =IF($F32=0,0,INDEX(Aux_HH!$I$4:$I$18,MATCH($B32&"|"&$E32,Aux_HH!$A$4:$A$18,0))) -> 0
A33: =IF(Frota!$A5="","",Frota!$A5) -> Colhedora CASE A8810 — 1035 | B33: =IF(Frota!$A5="","",Frota!$B5) -> Colhedora | C33: 30 | D33: =INDEX(Semanas!$E$3:$E$54,30) -> 10 | E33: =IF(Frota!$A5="","",Cronograma!AE5) | F33: =IF(OR($E33="",$E33=0),0,1) -> 0 | G33: =IF($F33=0,0,INDEX(Aux_HH!$D$4:$D$18,MATCH($B33&"|"&$E33,Aux_HH!$A$4:$A$18,0))) -> 0 | H33: =IF($F33=0,0,INDEX(Aux_HH!$E$4:$E$18,MATCH($B33&"|"&$E33,Aux_HH!$A$4:$A$18,0))) -> 0 | I33: =IF($F33=0,0,INDEX(Aux_HH!$F$4:$F$18,MATCH($B33&"|"&$E33,Aux_HH!$A$4:$A$18,0))) -> 0 | J33: =IF($F33=0,0,INDEX(Aux_HH!$G$4:$G$18,MATCH($B33&"|"&$E33,Aux_HH!$A$4:$A$18,0))) -> 0 | K33: =IF($F33=0,0,INDEX(Aux_HH!$H$4:$H$18,MATCH($B33&"|"&$E33,Aux_HH!$A$4:$A$18,0))) -> 0 | L33: =IF($F33=0,0,INDEX(Aux_HH!$I$4:$I$18,MATCH($B33&"|"&$E33,Aux_HH!$A$4:$A$18,0))) -> 0
A34: =IF(Frota!$A5="","",Frota!$A5) -> Colhedora CASE A8810 — 1035 | B34: =IF(Frota!$A5="","",Frota!$B5) -> Colhedora | C34: 31 | D34: =INDEX(Semanas!$E$3:$E$54,31) -> 10 | E34: =IF(Frota!$A5="","",Cronograma!AF5) | F34: =IF(OR($E34="",$E34=0),0,1) -> 0 | G34: =IF($F34=0,0,INDEX(Aux_HH!$D$4:$D$18,MATCH($B34&"|"&$E34,Aux_HH!$A$4:$A$18,0))) -> 0 | H34: =IF($F34=0,0,INDEX(Aux_HH!$E$4:$E$18,MATCH($B34&"|"&$E34,Aux_HH!$A$4:$A$18,0))) -> 0 | I34: =IF($F34=0,0,INDEX(Aux_HH!$F$4:$F$18,MATCH($B34&"|"&$E34,Aux_HH!$A$4:$A$18,0))) -> 0 | J34: =IF($F34=0,0,INDEX(Aux_HH!$G$4:$G$18,MATCH($B34&"|"&$E34,Aux_HH!$A$4:$A$18,0))) -> 0 | K34: =IF($F34=0,0,INDEX(Aux_HH!$H$4:$H$18,MATCH($B34&"|"&$E34,Aux_HH!$A$4:$A$18,0))) -> 0 | L34: =IF($F34=0,0,INDEX(Aux_HH!$I$4:$I$18,MATCH($B34&"|"&$E34,Aux_HH!$A$4:$A$18,0))) -> 0
A35: =IF(Frota!$A5="","",Frota!$A5) -> Colhedora CASE A8810 — 1035 | B35: =IF(Frota!$A5="","",Frota!$B5) -> Colhedora | C35: 32 | D35: =INDEX(Semanas!$E$3:$E$54,32) -> 11 | E35: =IF(Frota!$A5="","",Cronograma!AG5) | F35: =IF(OR($E35="",$E35=0),0,1) -> 0 | G35: =IF($F35=0,0,INDEX(Aux_HH!$D$4:$D$18,MATCH($B35&"|"&$E35,Aux_HH!$A$4:$A$18,0))) -> 0 | H35: =IF($F35=0,0,INDEX(Aux_HH!$E$4:$E$18,MATCH($B35&"|"&$E35,Aux_HH!$A$4:$A$18,0))) -> 0 | I35: =IF($F35=0,0,INDEX(Aux_HH!$F$4:$F$18,MATCH($B35&"|"&$E35,Aux_HH!$A$4:$A$18,0))) -> 0 | J35: =IF($F35=0,0,INDEX(Aux_HH!$G$4:$G$18,MATCH($B35&"|"&$E35,Aux_HH!$A$4:$A$18,0))) -> 0 | K35: =IF($F35=0,0,INDEX(Aux_HH!$H$4:$H$18,MATCH($B35&"|"&$E35,Aux_HH!$A$4:$A$18,0))) -> 0 | L35: =IF($F35=0,0,INDEX(Aux_HH!$I$4:$I$18,MATCH($B35&"|"&$E35,Aux_HH!$A$4:$A$18,0))) -> 0
A36: =IF(Frota!$A5="","",Frota!$A5) -> Colhedora CASE A8810 — 1035 | B36: =IF(Frota!$A5="","",Frota!$B5) -> Colhedora | C36: 33 | D36: =INDEX(Semanas!$E$3:$E$54,33) -> 11 | E36: =IF(Frota!$A5="","",Cronograma!AH5) -> S | F36: =IF(OR($E36="",$E36=0),0,1) -> 1 | G36: =IF($F36=0,0,INDEX(Aux_HH!$D$4:$D$18,MATCH($B36&"|"&$E36,Aux_HH!$A$4:$A$18,0))) -> 3.75 | H36: =IF($F36=0,0,INDEX(Aux_HH!$E$4:$E$18,MATCH($B36&"|"&$E36,Aux_HH!$A$4:$A$18,0))) -> 0 | I36: =IF($F36=0,0,INDEX(Aux_HH!$F$4:$F$18,MATCH($B36&"|"&$E36,Aux_HH!$A$4:$A$18,0))) -> 1 | J36: =IF($F36=0,0,INDEX(Aux_HH!$G$4:$G$18,MATCH($B36&"|"&$E36,Aux_HH!$A$4:$A$18,0))) -> 0.75 | K36: =IF($F36=0,0,INDEX(Aux_HH!$H$4:$H$18,MATCH($B36&"|"&$E36,Aux_HH!$A$4:$A$18,0))) -> 0 | L36: =IF($F36=0,0,INDEX(Aux_HH!$I$4:$I$18,MATCH($B36&"|"&$E36,Aux_HH!$A$4:$A$18,0))) -> 0
A37: =IF(Frota!$A5="","",Frota!$A5) -> Colhedora CASE A8810 — 1035 | B37: =IF(Frota!$A5="","",Frota!$B5) -> Colhedora | C37: 34 | D37: =INDEX(Semanas!$E$3:$E$54,34) -> 11 | E37: =IF(Frota!$A5="","",Cronograma!AI5) | F37: =IF(OR($E37="",$E37=0),0,1) -> 0 | G37: =IF($F37=0,0,INDEX(Aux_HH!$D$4:$D$18,MATCH($B37&"|"&$E37,Aux_HH!$A$4:$A$18,0))) -> 0 | H37: =IF($F37=0,0,INDEX(Aux_HH!$E$4:$E$18,MATCH($B37&"|"&$E37,Aux_HH!$A$4:$A$18,0))) -> 0 | I37: =IF($F37=0,0,INDEX(Aux_HH!$F$4:$F$18,MATCH($B37&"|"&$E37,Aux_HH!$A$4:$A$18,0))) -> 0 | J37: =IF($F37=0,0,INDEX(Aux_HH!$G$4:$G$18,MATCH($B37&"|"&$E37,Aux_HH!$A$4:$A$18,0))) -> 0 | K37: =IF($F37=0,0,INDEX(Aux_HH!$H$4:$H$18,MATCH($B37&"|"&$E37,Aux_HH!$A$4:$A$18,0))) -> 0 | L37: =IF($F37=0,0,INDEX(Aux_HH!$I$4:$I$18,MATCH($B37&"|"&$E37,Aux_HH!$A$4:$A$18,0))) -> 0
A38: =IF(Frota!$A5="","",Frota!$A5) -> Colhedora CASE A8810 — 1035 | B38: =IF(Frota!$A5="","",Frota!$B5) -> Colhedora | C38: 35 | D38: =INDEX(Semanas!$E$3:$E$54,35) -> 11 | E38: =IF(Frota!$A5="","",Cronograma!AJ5) | F38: =IF(OR($E38="",$E38=0),0,1) -> 0 | G38: =IF($F38=0,0,INDEX(Aux_HH!$D$4:$D$18,MATCH($B38&"|"&$E38,Aux_HH!$A$4:$A$18,0))) -> 0 | H38: =IF($F38=0,0,INDEX(Aux_HH!$E$4:$E$18,MATCH($B38&"|"&$E38,Aux_HH!$A$4:$A$18,0))) -> 0 | I38: =IF($F38=0,0,INDEX(Aux_HH!$F$4:$F$18,MATCH($B38&"|"&$E38,Aux_HH!$A$4:$A$18,0))) -> 0 | J38: =IF($F38=0,0,INDEX(Aux_HH!$G$4:$G$18,MATCH($B38&"|"&$E38,Aux_HH!$A$4:$A$18,0))) -> 0 | K38: =IF($F38=0,0,INDEX(Aux_HH!$H$4:$H$18,MATCH($B38&"|"&$E38,Aux_HH!$A$4:$A$18,0))) -> 0 | L38: =IF($F38=0,0,INDEX(Aux_HH!$I$4:$I$18,MATCH($B38&"|"&$E38,Aux_HH!$A$4:$A$18,0))) -> 0
A39: =IF(Frota!$A5="","",Frota!$A5) -> Colhedora CASE A8810 — 1035 | B39: =IF(Frota!$A5="","",Frota!$B5) -> Colhedora | C39: 36 | D39: =INDEX(Semanas!$E$3:$E$54,36) -> 12 | E39: =IF(Frota!$A5="","",Cronograma!AK5) | F39: =IF(OR($E39="",$E39=0),0,1) -> 0 | G39: =IF($F39=0,0,INDEX(Aux_HH!$D$4:$D$18,MATCH($B39&"|"&$E39,Aux_HH!$A$4:$A$18,0))) -> 0 | H39: =IF($F39=0,0,INDEX(Aux_HH!$E$4:$E$18,MATCH($B39&"|"&$E39,Aux_HH!$A$4:$A$18,0))) -> 0 | I39: =IF($F39=0,0,INDEX(Aux_HH!$F$4:$F$18,MATCH($B39&"|"&$E39,Aux_HH!$A$4:$A$18,0))) -> 0 | J39: =IF($F39=0,0,INDEX(Aux_HH!$G$4:$G$18,MATCH($B39&"|"&$E39,Aux_HH!$A$4:$A$18,0))) -> 0 | K39: =IF($F39=0,0,INDEX(Aux_HH!$H$4:$H$18,MATCH($B39&"|"&$E39,Aux_HH!$A$4:$A$18,0))) -> 0 | L39: =IF($F39=0,0,INDEX(Aux_HH!$I$4:$I$18,MATCH($B39&"|"&$E39,Aux_HH!$A$4:$A$18,0))) -> 0
A40: =IF(Frota!$A5="","",Frota!$A5) -> Colhedora CASE A8810 — 1035 | B40: =IF(Frota!$A5="","",Frota!$B5) -> Colhedora | C40: 37 | D40: =INDEX(Semanas!$E$3:$E$54,37) -> 12 | E40: =IF(Frota!$A5="","",Cronograma!AL5) | F40: =IF(OR($E40="",$E40=0),0,1) -> 0 | G40: =IF($F40=0,0,INDEX(Aux_HH!$D$4:$D$18,MATCH($B40&"|"&$E40,Aux_HH!$A$4:$A$18,0))) -> 0 | H40: =IF($F40=0,0,INDEX(Aux_HH!$E$4:$E$18,MATCH($B40&"|"&$E40,Aux_HH!$A$4:$A$18,0))) -> 0 | I40: =IF($F40=0,0,INDEX(Aux_HH!$F$4:$F$18,MATCH($B40&"|"&$E40,Aux_HH!$A$4:$A$18,0))) -> 0 | J40: =IF($F40=0,0,INDEX(Aux_HH!$G$4:$G$18,MATCH($B40&"|"&$E40,Aux_HH!$A$4:$A$18,0))) -> 0 | K40: =IF($F40=0,0,INDEX(Aux_HH!$H$4:$H$18,MATCH($B40&"|"&$E40,Aux_HH!$A$4:$A$18,0))) -> 0 | L40: =IF($F40=0,0,INDEX(Aux_HH!$I$4:$I$18,MATCH($B40&"|"&$E40,Aux_HH!$A$4:$A$18,0))) -> 0
A41: =IF(Frota!$A5="","",Frota!$A5) -> Colhedora CASE A8810 — 1035 | B41: =IF(Frota!$A5="","",Frota!$B5) -> Colhedora | C41: 38 | D41: =INDEX(Semanas!$E$3:$E$54,38) -> 12 | E41: =IF(Frota!$A5="","",Cronograma!AM5) | F41: =IF(OR($E41="",$E41=0),0,1) -> 0 | G41: =IF($F41=0,0,INDEX(Aux_HH!$D$4:$D$18,MATCH($B41&"|"&$E41,Aux_HH!$A$4:$A$18,0))) -> 0 | H41: =IF($F41=0,0,INDEX(Aux_HH!$E$4:$E$18,MATCH($B41&"|"&$E41,Aux_HH!$A$4:$A$18,0))) -> 0 | I41: =IF($F41=0,0,INDEX(Aux_HH!$F$4:$F$18,MATCH($B41&"|"&$E41,Aux_HH!$A$4:$A$18,0))) -> 0 | J41: =IF($F41=0,0,INDEX(Aux_HH!$G$4:$G$18,MATCH($B41&"|"&$E41,Aux_HH!$A$4:$A$18,0))) -> 0 | K41: =IF($F41=0,0,INDEX(Aux_HH!$H$4:$H$18,MATCH($B41&"|"&$E41,Aux_HH!$A$4:$A$18,0))) -> 0 | L41: =IF($F41=0,0,INDEX(Aux_HH!$I$4:$I$18,MATCH($B41&"|"&$E41,Aux_HH!$A$4:$A$18,0))) -> 0
A42: =IF(Frota!$A5="","",Frota!$A5) -> Colhedora CASE A8810 — 1035 | B42: =IF(Frota!$A5="","",Frota!$B5) -> Colhedora | C42: 39 | D42: =INDEX(Semanas!$E$3:$E$54,39) -> 12 | E42: =IF(Frota!$A5="","",Cronograma!AN5) | F42: =IF(OR($E42="",$E42=0),0,1) -> 0 | G42: =IF($F42=0,0,INDEX(Aux_HH!$D$4:$D$18,MATCH($B42&"|"&$E42,Aux_HH!$A$4:$A$18,0))) -> 0 | H42: =IF($F42=0,0,INDEX(Aux_HH!$E$4:$E$18,MATCH($B42&"|"&$E42,Aux_HH!$A$4:$A$18,0))) -> 0 | I42: =IF($F42=0,0,INDEX(Aux_HH!$F$4:$F$18,MATCH($B42&"|"&$E42,Aux_HH!$A$4:$A$18,0))) -> 0 | J42: =IF($F42=0,0,INDEX(Aux_HH!$G$4:$G$18,MATCH($B42&"|"&$E42,Aux_HH!$A$4:$A$18,0))) -> 0 | K42: =IF($F42=0,0,INDEX(Aux_HH!$H$4:$H$18,MATCH($B42&"|"&$E42,Aux_HH!$A$4:$A$18,0))) -> 0 | L42: =IF($F42=0,0,INDEX(Aux_HH!$I$4:$I$18,MATCH($B42&"|"&$E42,Aux_HH!$A$4:$A$18,0))) -> 0
A43: =IF(Frota!$A5="","",Frota!$A5) -> Colhedora CASE A8810 — 1035 | B43: =IF(Frota!$A5="","",Frota!$B5) -> Colhedora | C43: 40 | D43: =INDEX(Semanas!$E$3:$E$54,40) -> 12 | E43: =IF(Frota!$A5="","",Cronograma!AO5) | F43: =IF(OR($E43="",$E43=0),0,1) -> 0 | G43: =IF($F43=0,0,INDEX(Aux_HH!$D$4:$D$18,MATCH($B43&"|"&$E43,Aux_HH!$A$4:$A$18,0))) -> 0 | H43: =IF($F43=0,0,INDEX(Aux_HH!$E$4:$E$18,MATCH($B43&"|"&$E43,Aux_HH!$A$4:$A$18,0))) -> 0 | I43: =IF($F43=0,0,INDEX(Aux_HH!$F$4:$F$18,MATCH($B43&"|"&$E43,Aux_HH!$A$4:$A$18,0))) -> 0 | J43: =IF($F43=0,0,INDEX(Aux_HH!$G$4:$G$18,MATCH($B43&"|"&$E43,Aux_HH!$A$4:$A$18,0))) -> 0 | K43: =IF($F43=0,0,INDEX(Aux_HH!$H$4:$H$18,MATCH($B43&"|"&$E43,Aux_HH!$A$4:$A$18,0))) -> 0 | L43: =IF($F43=0,0,INDEX(Aux_HH!$I$4:$I$18,MATCH($B43&"|"&$E43,Aux_HH!$A$4:$A$18,0))) -> 0
A44: =IF(Frota!$A5="","",Frota!$A5) -> Colhedora CASE A8810 — 1035 | B44: =IF(Frota!$A5="","",Frota!$B5) -> Colhedora | C44: 41 | D44: =INDEX(Semanas!$E$3:$E$54,41) -> 1 | E44: =IF(Frota!$A5="","",Cronograma!AP5) | F44: =IF(OR($E44="",$E44=0),0,1) -> 0 | G44: =IF($F44=0,0,INDEX(Aux_HH!$D$4:$D$18,MATCH($B44&"|"&$E44,Aux_HH!$A$4:$A$18,0))) -> 0 | H44: =IF($F44=0,0,INDEX(Aux_HH!$E$4:$E$18,MATCH($B44&"|"&$E44,Aux_HH!$A$4:$A$18,0))) -> 0 | I44: =IF($F44=0,0,INDEX(Aux_HH!$F$4:$F$18,MATCH($B44&"|"&$E44,Aux_HH!$A$4:$A$18,0))) -> 0 | J44: =IF($F44=0,0,INDEX(Aux_HH!$G$4:$G$18,MATCH($B44&"|"&$E44,Aux_HH!$A$4:$A$18,0))) -> 0 | K44: =IF($F44=0,0,INDEX(Aux_HH!$H$4:$H$18,MATCH($B44&"|"&$E44,Aux_HH!$A$4:$A$18,0))) -> 0 | L44: =IF($F44=0,0,INDEX(Aux_HH!$I$4:$I$18,MATCH($B44&"|"&$E44,Aux_HH!$A$4:$A$18,0))) -> 0
A45: =IF(Frota!$A5="","",Frota!$A5) -> Colhedora CASE A8810 — 1035 | B45: =IF(Frota!$A5="","",Frota!$B5) -> Colhedora | C45: 42 | D45: =INDEX(Semanas!$E$3:$E$54,42) -> 1 | E45: =IF(Frota!$A5="","",Cronograma!AQ5) | F45: =IF(OR($E45="",$E45=0),0,1) -> 0 | G45: =IF($F45=0,0,INDEX(Aux_HH!$D$4:$D$18,MATCH($B45&"|"&$E45,Aux_HH!$A$4:$A$18,0))) -> 0 | H45: =IF($F45=0,0,INDEX(Aux_HH!$E$4:$E$18,MATCH($B45&"|"&$E45,Aux_HH!$A$4:$A$18,0))) -> 0 | I45: =IF($F45=0,0,INDEX(Aux_HH!$F$4:$F$18,MATCH($B45&"|"&$E45,Aux_HH!$A$4:$A$18,0))) -> 0 | J45: =IF($F45=0,0,INDEX(Aux_HH!$G$4:$G$18,MATCH($B45&"|"&$E45,Aux_HH!$A$4:$A$18,0))) -> 0 | K45: =IF($F45=0,0,INDEX(Aux_HH!$H$4:$H$18,MATCH($B45&"|"&$E45,Aux_HH!$A$4:$A$18,0))) -> 0 | L45: =IF($F45=0,0,INDEX(Aux_HH!$I$4:$I$18,MATCH($B45&"|"&$E45,Aux_HH!$A$4:$A$18,0))) -> 0
A46: =IF(Frota!$A5="","",Frota!$A5) -> Colhedora CASE A8810 — 1035 | B46: =IF(Frota!$A5="","",Frota!$B5) -> Colhedora | C46: 43 | D46: =INDEX(Semanas!$E$3:$E$54,43) -> 1 | E46: =IF(Frota!$A5="","",Cronograma!AR5) | F46: =IF(OR($E46="",$E46=0),0,1) -> 0 | G46: =IF($F46=0,0,INDEX(Aux_HH!$D$4:$D$18,MATCH($B46&"|"&$E46,Aux_HH!$A$4:$A$18,0))) -> 0 | H46: =IF($F46=0,0,INDEX(Aux_HH!$E$4:$E$18,MATCH($B46&"|"&$E46,Aux_HH!$A$4:$A$18,0))) -> 0 | I46: =IF($F46=0,0,INDEX(Aux_HH!$F$4:$F$18,MATCH($B46&"|"&$E46,Aux_HH!$A$4:$A$18,0))) -> 0 | J46: =IF($F46=0,0,INDEX(Aux_HH!$G$4:$G$18,MATCH($B46&"|"&$E46,Aux_HH!$A$4:$A$18,0))) -> 0 | K46: =IF($F46=0,0,INDEX(Aux_HH!$H$4:$H$18,MATCH($B46&"|"&$E46,Aux_HH!$A$4:$A$18,0))) -> 0 | L46: =IF($F46=0,0,INDEX(Aux_HH!$I$4:$I$18,MATCH($B46&"|"&$E46,Aux_HH!$A$4:$A$18,0))) -> 0
A47: =IF(Frota!$A5="","",Frota!$A5) -> Colhedora CASE A8810 — 1035 | B47: =IF(Frota!$A5="","",Frota!$B5) -> Colhedora | C47: 44 | D47: =INDEX(Semanas!$E$3:$E$54,44) -> 1 | E47: =IF(Frota!$A5="","",Cronograma!AS5) | F47: =IF(OR($E47="",$E47=0),0,1) -> 0 | G47: =IF($F47=0,0,INDEX(Aux_HH!$D$4:$D$18,MATCH($B47&"|"&$E47,Aux_HH!$A$4:$A$18,0))) -> 0 | H47: =IF($F47=0,0,INDEX(Aux_HH!$E$4:$E$18,MATCH($B47&"|"&$E47,Aux_HH!$A$4:$A$18,0))) -> 0 | I47: =IF($F47=0,0,INDEX(Aux_HH!$F$4:$F$18,MATCH($B47&"|"&$E47,Aux_HH!$A$4:$A$18,0))) -> 0 | J47: =IF($F47=0,0,INDEX(Aux_HH!$G$4:$G$18,MATCH($B47&"|"&$E47,Aux_HH!$A$4:$A$18,0))) -> 0 | K47: =IF($F47=0,0,INDEX(Aux_HH!$H$4:$H$18,MATCH($B47&"|"&$E47,Aux_HH!$A$4:$A$18,0))) -> 0 | L47: =IF($F47=0,0,INDEX(Aux_HH!$I$4:$I$18,MATCH($B47&"|"&$E47,Aux_HH!$A$4:$A$18,0))) -> 0
A48: =IF(Frota!$A5="","",Frota!$A5) -> Colhedora CASE A8810 — 1035 | B48: =IF(Frota!$A5="","",Frota!$B5) -> Colhedora | C48: 45 | D48: =INDEX(Semanas!$E$3:$E$54,45) -> 2 | E48: =IF(Frota!$A5="","",Cronograma!AT5) | F48: =IF(OR($E48="",$E48=0),0,1) -> 0 | G48: =IF($F48=0,0,INDEX(Aux_HH!$D$4:$D$18,MATCH($B48&"|"&$E48,Aux_HH!$A$4:$A$18,0))) -> 0 | H48: =IF($F48=0,0,INDEX(Aux_HH!$E$4:$E$18,MATCH($B48&"|"&$E48,Aux_HH!$A$4:$A$18,0))) -> 0 | I48: =IF($F48=0,0,INDEX(Aux_HH!$F$4:$F$18,MATCH($B48&"|"&$E48,Aux_HH!$A$4:$A$18,0))) -> 0 | J48: =IF($F48=0,0,INDEX(Aux_HH!$G$4:$G$18,MATCH($B48&"|"&$E48,Aux_HH!$A$4:$A$18,0))) -> 0 | K48: =IF($F48=0,0,INDEX(Aux_HH!$H$4:$H$18,MATCH($B48&"|"&$E48,Aux_HH!$A$4:$A$18,0))) -> 0 | L48: =IF($F48=0,0,INDEX(Aux_HH!$I$4:$I$18,MATCH($B48&"|"&$E48,Aux_HH!$A$4:$A$18,0))) -> 0
A49: =IF(Frota!$A5="","",Frota!$A5) -> Colhedora CASE A8810 — 1035 | B49: =IF(Frota!$A5="","",Frota!$B5) -> Colhedora | C49: 46 | D49: =INDEX(Semanas!$E$3:$E$54,46) -> 2 | E49: =IF(Frota!$A5="","",Cronograma!AU5) | F49: =IF(OR($E49="",$E49=0),0,1) -> 0 | G49: =IF($F49=0,0,INDEX(Aux_HH!$D$4:$D$18,MATCH($B49&"|"&$E49,Aux_HH!$A$4:$A$18,0))) -> 0 | H49: =IF($F49=0,0,INDEX(Aux_HH!$E$4:$E$18,MATCH($B49&"|"&$E49,Aux_HH!$A$4:$A$18,0))) -> 0 | I49: =IF($F49=0,0,INDEX(Aux_HH!$F$4:$F$18,MATCH($B49&"|"&$E49,Aux_HH!$A$4:$A$18,0))) -> 0 | J49: =IF($F49=0,0,INDEX(Aux_HH!$G$4:$G$18,MATCH($B49&"|"&$E49,Aux_HH!$A$4:$A$18,0))) -> 0 | K49: =IF($F49=0,0,INDEX(Aux_HH!$H$4:$H$18,MATCH($B49&"|"&$E49,Aux_HH!$A$4:$A$18,0))) -> 0 | L49: =IF($F49=0,0,INDEX(Aux_HH!$I$4:$I$18,MATCH($B49&"|"&$E49,Aux_HH!$A$4:$A$18,0))) -> 0
A50: =IF(Frota!$A5="","",Frota!$A5) -> Colhedora CASE A8810 — 1035 | B50: =IF(Frota!$A5="","",Frota!$B5) -> Colhedora | C50: 47 | D50: =INDEX(Semanas!$E$3:$E$54,47) -> 2 | E50: =IF(Frota!$A5="","",Cronograma!AV5) | F50: =IF(OR($E50="",$E50=0),0,1) -> 0 | G50: =IF($F50=0,0,INDEX(Aux_HH!$D$4:$D$18,MATCH($B50&"|"&$E50,Aux_HH!$A$4:$A$18,0))) -> 0 | H50: =IF($F50=0,0,INDEX(Aux_HH!$E$4:$E$18,MATCH($B50&"|"&$E50,Aux_HH!$A$4:$A$18,0))) -> 0 | I50: =IF($F50=0,0,INDEX(Aux_HH!$F$4:$F$18,MATCH($B50&"|"&$E50,Aux_HH!$A$4:$A$18,0))) -> 0 | J50: =IF($F50=0,0,INDEX(Aux_HH!$G$4:$G$18,MATCH($B50&"|"&$E50,Aux_HH!$A$4:$A$18,0))) -> 0 | K50: =IF($F50=0,0,INDEX(Aux_HH!$H$4:$H$18,MATCH($B50&"|"&$E50,Aux_HH!$A$4:$A$18,0))) -> 0 | L50: =IF($F50=0,0,INDEX(Aux_HH!$I$4:$I$18,MATCH($B50&"|"&$E50,Aux_HH!$A$4:$A$18,0))) -> 0
A51: =IF(Frota!$A5="","",Frota!$A5) -> Colhedora CASE A8810 — 1035 | B51: =IF(Frota!$A5="","",Frota!$B5) -> Colhedora | C51: 48 | D51: =INDEX(Semanas!$E$3:$E$54,48) -> 2 | E51: =IF(Frota!$A5="","",Cronograma!AW5) | F51: =IF(OR($E51="",$E51=0),0,1) -> 0 | G51: =IF($F51=0,0,INDEX(Aux_HH!$D$4:$D$18,MATCH($B51&"|"&$E51,Aux_HH!$A$4:$A$18,0))) -> 0 | H51: =IF($F51=0,0,INDEX(Aux_HH!$E$4:$E$18,MATCH($B51&"|"&$E51,Aux_HH!$A$4:$A$18,0))) -> 0 | I51: =IF($F51=0,0,INDEX(Aux_HH!$F$4:$F$18,MATCH($B51&"|"&$E51,Aux_HH!$A$4:$A$18,0))) -> 0 | J51: =IF($F51=0,0,INDEX(Aux_HH!$G$4:$G$18,MATCH($B51&"|"&$E51,Aux_HH!$A$4:$A$18,0))) -> 0 | K51: =IF($F51=0,0,INDEX(Aux_HH!$H$4:$H$18,MATCH($B51&"|"&$E51,Aux_HH!$A$4:$A$18,0))) -> 0 | L51: =IF($F51=0,0,INDEX(Aux_HH!$I$4:$I$18,MATCH($B51&"|"&$E51,Aux_HH!$A$4:$A$18,0))) -> 0
A52: =IF(Frota!$A5="","",Frota!$A5) -> Colhedora CASE A8810 — 1035 | B52: =IF(Frota!$A5="","",Frota!$B5) -> Colhedora | C52: 49 | D52: =INDEX(Semanas!$E$3:$E$54,49) -> 3 | E52: =IF(Frota!$A5="","",Cronograma!AX5) | F52: =IF(OR($E52="",$E52=0),0,1) -> 0 | G52: =IF($F52=0,0,INDEX(Aux_HH!$D$4:$D$18,MATCH($B52&"|"&$E52,Aux_HH!$A$4:$A$18,0))) -> 0 | H52: =IF($F52=0,0,INDEX(Aux_HH!$E$4:$E$18,MATCH($B52&"|"&$E52,Aux_HH!$A$4:$A$18,0))) -> 0 | I52: =IF($F52=0,0,INDEX(Aux_HH!$F$4:$F$18,MATCH($B52&"|"&$E52,Aux_HH!$A$4:$A$18,0))) -> 0 | J52: =IF($F52=0,0,INDEX(Aux_HH!$G$4:$G$18,MATCH($B52&"|"&$E52,Aux_HH!$A$4:$A$18,0))) -> 0 | K52: =IF($F52=0,0,INDEX(Aux_HH!$H$4:$H$18,MATCH($B52&"|"&$E52,Aux_HH!$A$4:$A$18,0))) -> 0 | L52: =IF($F52=0,0,INDEX(Aux_HH!$I$4:$I$18,MATCH($B52&"|"&$E52,Aux_HH!$A$4:$A$18,0))) -> 0
A53: =IF(Frota!$A5="","",Frota!$A5) -> Colhedora CASE A8810 — 1035 | B53: =IF(Frota!$A5="","",Frota!$B5) -> Colhedora | C53: 50 | D53: =INDEX(Semanas!$E$3:$E$54,50) -> 3 | E53: =IF(Frota!$A5="","",Cronograma!AY5) | F53: =IF(OR($E53="",$E53=0),0,1) -> 0 | G53: =IF($F53=0,0,INDEX(Aux_HH!$D$4:$D$18,MATCH($B53&"|"&$E53,Aux_HH!$A$4:$A$18,0))) -> 0 | H53: =IF($F53=0,0,INDEX(Aux_HH!$E$4:$E$18,MATCH($B53&"|"&$E53,Aux_HH!$A$4:$A$18,0))) -> 0 | I53: =IF($F53=0,0,INDEX(Aux_HH!$F$4:$F$18,MATCH($B53&"|"&$E53,Aux_HH!$A$4:$A$18,0))) -> 0 | J53: =IF($F53=0,0,INDEX(Aux_HH!$G$4:$G$18,MATCH($B53&"|"&$E53,Aux_HH!$A$4:$A$18,0))) -> 0 | K53: =IF($F53=0,0,INDEX(Aux_HH!$H$4:$H$18,MATCH($B53&"|"&$E53,Aux_HH!$A$4:$A$18,0))) -> 0 | L53: =IF($F53=0,0,INDEX(Aux_HH!$I$4:$I$18,MATCH($B53&"|"&$E53,Aux_HH!$A$4:$A$18,0))) -> 0
A54: =IF(Frota!$A5="","",Frota!$A5) -> Colhedora CASE A8810 — 1035 | B54: =IF(Frota!$A5="","",Frota!$B5) -> Colhedora | C54: 51 | D54: =INDEX(Semanas!$E$3:$E$54,51) -> 3 | E54: =IF(Frota!$A5="","",Cronograma!AZ5) | F54: =IF(OR($E54="",$E54=0),0,1) -> 0 | G54: =IF($F54=0,0,INDEX(Aux_HH!$D$4:$D$18,MATCH($B54&"|"&$E54,Aux_HH!$A$4:$A$18,0))) -> 0 | H54: =IF($F54=0,0,INDEX(Aux_HH!$E$4:$E$18,MATCH($B54&"|"&$E54,Aux_HH!$A$4:$A$18,0))) -> 0 | I54: =IF($F54=0,0,INDEX(Aux_HH!$F$4:$F$18,MATCH($B54&"|"&$E54,Aux_HH!$A$4:$A$18,0))) -> 0 | J54: =IF($F54=0,0,INDEX(Aux_HH!$G$4:$G$18,MATCH($B54&"|"&$E54,Aux_HH!$A$4:$A$18,0))) -> 0 | K54: =IF($F54=0,0,INDEX(Aux_HH!$H$4:$H$18,MATCH($B54&"|"&$E54,Aux_HH!$A$4:$A$18,0))) -> 0 | L54: =IF($F54=0,0,INDEX(Aux_HH!$I$4:$I$18,MATCH($B54&"|"&$E54,Aux_HH!$A$4:$A$18,0))) -> 0
A55: =IF(Frota!$A5="","",Frota!$A5) -> Colhedora CASE A8810 — 1035 | B55: =IF(Frota!$A5="","",Frota!$B5) -> Colhedora | C55: 52 | D55: =INDEX(Semanas!$E$3:$E$54,52) -> 3 | E55: =IF(Frota!$A5="","",Cronograma!BA5) | F55: =IF(OR($E55="",$E55=0),0,1) -> 0 | G55: =IF($F55=0,0,INDEX(Aux_HH!$D$4:$D$18,MATCH($B55&"|"&$E55,Aux_HH!$A$4:$A$18,0))) -> 0 | H55: =IF($F55=0,0,INDEX(Aux_HH!$E$4:$E$18,MATCH($B55&"|"&$E55,Aux_HH!$A$4:$A$18,0))) -> 0 | I55: =IF($F55=0,0,INDEX(Aux_HH!$F$4:$F$18,MATCH($B55&"|"&$E55,Aux_HH!$A$4:$A$18,0))) -> 0 | J55: =IF($F55=0,0,INDEX(Aux_HH!$G$4:$G$18,MATCH($B55&"|"&$E55,Aux_HH!$A$4:$A$18,0))) -> 0 | K55: =IF($F55=0,0,INDEX(Aux_HH!$H$4:$H$18,MATCH($B55&"|"&$E55,Aux_HH!$A$4:$A$18,0))) -> 0 | L55: =IF($F55=0,0,INDEX(Aux_HH!$I$4:$I$18,MATCH($B55&"|"&$E55,Aux_HH!$A$4:$A$18,0))) -> 0
A56: =IF(Frota!$A6="","",Frota!$A6) -> Colhedora CASE A8810 — 1036 | B56: =IF(Frota!$A6="","",Frota!$B6) -> Colhedora | C56: 1 | D56: =INDEX(Semanas!$E$3:$E$54,1) -> 4 | E56: =IF(Frota!$A6="","",Cronograma!B6) -> A | F56: =IF(OR($E56="",$E56=0),0,1) -> 1 | G56: =IF($F56=0,0,INDEX(Aux_HH!$D$4:$D$18,MATCH($B56&"|"&$E56,Aux_HH!$A$4:$A$18,0))) -> 10.25 | H56: =IF($F56=0,0,INDEX(Aux_HH!$E$4:$E$18,MATCH($B56&"|"&$E56,Aux_HH!$A$4:$A$18,0))) -> 0 | I56: =IF($F56=0,0,INDEX(Aux_HH!$F$4:$F$18,MATCH($B56&"|"&$E56,Aux_HH!$A$4:$A$18,0))) -> 3 | J56: =IF($F56=0,0,INDEX(Aux_HH!$G$4:$G$18,MATCH($B56&"|"&$E56,Aux_HH!$A$4:$A$18,0))) -> 1.75 | K56: =IF($F56=0,0,INDEX(Aux_HH!$H$4:$H$18,MATCH($B56&"|"&$E56,Aux_HH!$A$4:$A$18,0))) -> 0 | L56: =IF($F56=0,0,INDEX(Aux_HH!$I$4:$I$18,MATCH($B56&"|"&$E56,Aux_HH!$A$4:$A$18,0))) -> 0
A57: =IF(Frota!$A6="","",Frota!$A6) -> Colhedora CASE A8810 — 1036 | B57: =IF(Frota!$A6="","",Frota!$B6) -> Colhedora | C57: 2 | D57: =INDEX(Semanas!$E$3:$E$54,2) -> 4 | E57: =IF(Frota!$A6="","",Cronograma!C6) | F57: =IF(OR($E57="",$E57=0),0,1) -> 0 | G57: =IF($F57=0,0,INDEX(Aux_HH!$D$4:$D$18,MATCH($B57&"|"&$E57,Aux_HH!$A$4:$A$18,0))) -> 0 | H57: =IF($F57=0,0,INDEX(Aux_HH!$E$4:$E$18,MATCH($B57&"|"&$E57,Aux_HH!$A$4:$A$18,0))) -> 0 | I57: =IF($F57=0,0,INDEX(Aux_HH!$F$4:$F$18,MATCH($B57&"|"&$E57,Aux_HH!$A$4:$A$18,0))) -> 0 | J57: =IF($F57=0,0,INDEX(Aux_HH!$G$4:$G$18,MATCH($B57&"|"&$E57,Aux_HH!$A$4:$A$18,0))) -> 0 | K57: =IF($F57=0,0,INDEX(Aux_HH!$H$4:$H$18,MATCH($B57&"|"&$E57,Aux_HH!$A$4:$A$18,0))) -> 0 | L57: =IF($F57=0,0,INDEX(Aux_HH!$I$4:$I$18,MATCH($B57&"|"&$E57,Aux_HH!$A$4:$A$18,0))) -> 0
A58: =IF(Frota!$A6="","",Frota!$A6) -> Colhedora CASE A8810 — 1036 | B58: =IF(Frota!$A6="","",Frota!$B6) -> Colhedora | C58: 3 | D58: =INDEX(Semanas!$E$3:$E$54,3) -> 4 | E58: =IF(Frota!$A6="","",Cronograma!D6) | F58: =IF(OR($E58="",$E58=0),0,1) -> 0 | G58: =IF($F58=0,0,INDEX(Aux_HH!$D$4:$D$18,MATCH($B58&"|"&$E58,Aux_HH!$A$4:$A$18,0))) -> 0 | H58: =IF($F58=0,0,INDEX(Aux_HH!$E$4:$E$18,MATCH($B58&"|"&$E58,Aux_HH!$A$4:$A$18,0))) -> 0 | I58: =IF($F58=0,0,INDEX(Aux_HH!$F$4:$F$18,MATCH($B58&"|"&$E58,Aux_HH!$A$4:$A$18,0))) -> 0 | J58: =IF($F58=0,0,INDEX(Aux_HH!$G$4:$G$18,MATCH($B58&"|"&$E58,Aux_HH!$A$4:$A$18,0))) -> 0 | K58: =IF($F58=0,0,INDEX(Aux_HH!$H$4:$H$18,MATCH($B58&"|"&$E58,Aux_HH!$A$4:$A$18,0))) -> 0 | L58: =IF($F58=0,0,INDEX(Aux_HH!$I$4:$I$18,MATCH($B58&"|"&$E58,Aux_HH!$A$4:$A$18,0))) -> 0
A59: =IF(Frota!$A6="","",Frota!$A6) -> Colhedora CASE A8810 — 1036 | B59: =IF(Frota!$A6="","",Frota!$B6) -> Colhedora | C59: 4 | D59: =INDEX(Semanas!$E$3:$E$54,4) -> 4 | E59: =IF(Frota!$A6="","",Cronograma!E6) | F59: =IF(OR($E59="",$E59=0),0,1) -> 0 | G59: =IF($F59=0,0,INDEX(Aux_HH!$D$4:$D$18,MATCH($B59&"|"&$E59,Aux_HH!$A$4:$A$18,0))) -> 0 | H59: =IF($F59=0,0,INDEX(Aux_HH!$E$4:$E$18,MATCH($B59&"|"&$E59,Aux_HH!$A$4:$A$18,0))) -> 0 | I59: =IF($F59=0,0,INDEX(Aux_HH!$F$4:$F$18,MATCH($B59&"|"&$E59,Aux_HH!$A$4:$A$18,0))) -> 0 | J59: =IF($F59=0,0,INDEX(Aux_HH!$G$4:$G$18,MATCH($B59&"|"&$E59,Aux_HH!$A$4:$A$18,0))) -> 0 | K59: =IF($F59=0,0,INDEX(Aux_HH!$H$4:$H$18,MATCH($B59&"|"&$E59,Aux_HH!$A$4:$A$18,0))) -> 0 | L59: =IF($F59=0,0,INDEX(Aux_HH!$I$4:$I$18,MATCH($B59&"|"&$E59,Aux_HH!$A$4:$A$18,0))) -> 0
A60: =IF(Frota!$A6="","",Frota!$A6) -> Colhedora CASE A8810 — 1036 | B60: =IF(Frota!$A6="","",Frota!$B6) -> Colhedora | C60: 5 | D60: =INDEX(Semanas!$E$3:$E$54,5) -> 4 | E60: =IF(Frota!$A6="","",Cronograma!F6) | F60: =IF(OR($E60="",$E60=0),0,1) -> 0 | G60: =IF($F60=0,0,INDEX(Aux_HH!$D$4:$D$18,MATCH($B60&"|"&$E60,Aux_HH!$A$4:$A$18,0))) -> 0 | H60: =IF($F60=0,0,INDEX(Aux_HH!$E$4:$E$18,MATCH($B60&"|"&$E60,Aux_HH!$A$4:$A$18,0))) -> 0 | I60: =IF($F60=0,0,INDEX(Aux_HH!$F$4:$F$18,MATCH($B60&"|"&$E60,Aux_HH!$A$4:$A$18,0))) -> 0 | J60: =IF($F60=0,0,INDEX(Aux_HH!$G$4:$G$18,MATCH($B60&"|"&$E60,Aux_HH!$A$4:$A$18,0))) -> 0 | K60: =IF($F60=0,0,INDEX(Aux_HH!$H$4:$H$18,MATCH($B60&"|"&$E60,Aux_HH!$A$4:$A$18,0))) -> 0 | L60: =IF($F60=0,0,INDEX(Aux_HH!$I$4:$I$18,MATCH($B60&"|"&$E60,Aux_HH!$A$4:$A$18,0))) -> 0
A61: =IF(Frota!$A6="","",Frota!$A6) -> Colhedora CASE A8810 — 1036 | B61: =IF(Frota!$A6="","",Frota!$B6) -> Colhedora | C61: 6 | D61: =INDEX(Semanas!$E$3:$E$54,6) -> 5 | E61: =IF(Frota!$A6="","",Cronograma!G6) -> S | F61: =IF(OR($E61="",$E61=0),0,1) -> 1 | G61: =IF($F61=0,0,INDEX(Aux_HH!$D$4:$D$18,MATCH($B61&"|"&$E61,Aux_HH!$A$4:$A$18,0))) -> 3.75 | H61: =IF($F61=0,0,INDEX(Aux_HH!$E$4:$E$18,MATCH($B61&"|"&$E61,Aux_HH!$A$4:$A$18,0))) -> 0 | I61: =IF($F61=0,0,INDEX(Aux_HH!$F$4:$F$18,MATCH($B61&"|"&$E61,Aux_HH!$A$4:$A$18,0))) -> 1 | J61: =IF($F61=0,0,INDEX(Aux_HH!$G$4:$G$18,MATCH($B61&"|"&$E61,Aux_HH!$A$4:$A$18,0))) -> 0.75 | K61: =IF($F61=0,0,INDEX(Aux_HH!$H$4:$H$18,MATCH($B61&"|"&$E61,Aux_HH!$A$4:$A$18,0))) -> 0 | L61: =IF($F61=0,0,INDEX(Aux_HH!$I$4:$I$18,MATCH($B61&"|"&$E61,Aux_HH!$A$4:$A$18,0))) -> 0
A62: =IF(Frota!$A6="","",Frota!$A6) -> Colhedora CASE A8810 — 1036 | B62: =IF(Frota!$A6="","",Frota!$B6) -> Colhedora | C62: 7 | D62: =INDEX(Semanas!$E$3:$E$54,7) -> 5 | E62: =IF(Frota!$A6="","",Cronograma!H6) | F62: =IF(OR($E62="",$E62=0),0,1) -> 0 | G62: =IF($F62=0,0,INDEX(Aux_HH!$D$4:$D$18,MATCH($B62&"|"&$E62,Aux_HH!$A$4:$A$18,0))) -> 0 | H62: =IF($F62=0,0,INDEX(Aux_HH!$E$4:$E$18,MATCH($B62&"|"&$E62,Aux_HH!$A$4:$A$18,0))) -> 0 | I62: =IF($F62=0,0,INDEX(Aux_HH!$F$4:$F$18,MATCH($B62&"|"&$E62,Aux_HH!$A$4:$A$18,0))) -> 0 | J62: =IF($F62=0,0,INDEX(Aux_HH!$G$4:$G$18,MATCH($B62&"|"&$E62,Aux_HH!$A$4:$A$18,0))) -> 0 | K62: =IF($F62=0,0,INDEX(Aux_HH!$H$4:$H$18,MATCH($B62&"|"&$E62,Aux_HH!$A$4:$A$18,0))) -> 0 | L62: =IF($F62=0,0,INDEX(Aux_HH!$I$4:$I$18,MATCH($B62&"|"&$E62,Aux_HH!$A$4:$A$18,0))) -> 0
A63: =IF(Frota!$A6="","",Frota!$A6) -> Colhedora CASE A8810 — 1036 | B63: =IF(Frota!$A6="","",Frota!$B6) -> Colhedora | C63: 8 | D63: =INDEX(Semanas!$E$3:$E$54,8) -> 5 | E63: =IF(Frota!$A6="","",Cronograma!I6) | F63: =IF(OR($E63="",$E63=0),0,1) -> 0 | G63: =IF($F63=0,0,INDEX(Aux_HH!$D$4:$D$18,MATCH($B63&"|"&$E63,Aux_HH!$A$4:$A$18,0))) -> 0 | H63: =IF($F63=0,0,INDEX(Aux_HH!$E$4:$E$18,MATCH($B63&"|"&$E63,Aux_HH!$A$4:$A$18,0))) -> 0 | I63: =IF($F63=0,0,INDEX(Aux_HH!$F$4:$F$18,MATCH($B63&"|"&$E63,Aux_HH!$A$4:$A$18,0))) -> 0 | J63: =IF($F63=0,0,INDEX(Aux_HH!$G$4:$G$18,MATCH($B63&"|"&$E63,Aux_HH!$A$4:$A$18,0))) -> 0 | K63: =IF($F63=0,0,INDEX(Aux_HH!$H$4:$H$18,MATCH($B63&"|"&$E63,Aux_HH!$A$4:$A$18,0))) -> 0 | L63: =IF($F63=0,0,INDEX(Aux_HH!$I$4:$I$18,MATCH($B63&"|"&$E63,Aux_HH!$A$4:$A$18,0))) -> 0
A64: =IF(Frota!$A6="","",Frota!$A6) -> Colhedora CASE A8810 — 1036 | B64: =IF(Frota!$A6="","",Frota!$B6) -> Colhedora | C64: 9 | D64: =INDEX(Semanas!$E$3:$E$54,9) -> 5 | E64: =IF(Frota!$A6="","",Cronograma!J6) | F64: =IF(OR($E64="",$E64=0),0,1) -> 0 | G64: =IF($F64=0,0,INDEX(Aux_HH!$D$4:$D$18,MATCH($B64&"|"&$E64,Aux_HH!$A$4:$A$18,0))) -> 0 | H64: =IF($F64=0,0,INDEX(Aux_HH!$E$4:$E$18,MATCH($B64&"|"&$E64,Aux_HH!$A$4:$A$18,0))) -> 0 | I64: =IF($F64=0,0,INDEX(Aux_HH!$F$4:$F$18,MATCH($B64&"|"&$E64,Aux_HH!$A$4:$A$18,0))) -> 0 | J64: =IF($F64=0,0,INDEX(Aux_HH!$G$4:$G$18,MATCH($B64&"|"&$E64,Aux_HH!$A$4:$A$18,0))) -> 0 | K64: =IF($F64=0,0,INDEX(Aux_HH!$H$4:$H$18,MATCH($B64&"|"&$E64,Aux_HH!$A$4:$A$18,0))) -> 0 | L64: =IF($F64=0,0,INDEX(Aux_HH!$I$4:$I$18,MATCH($B64&"|"&$E64,Aux_HH!$A$4:$A$18,0))) -> 0
A65: =IF(Frota!$A6="","",Frota!$A6) -> Colhedora CASE A8810 — 1036 | B65: =IF(Frota!$A6="","",Frota!$B6) -> Colhedora | C65: 10 | D65: =INDEX(Semanas!$E$3:$E$54,10) -> 6 | E65: =IF(Frota!$A6="","",Cronograma!K6) | F65: =IF(OR($E65="",$E65=0),0,1) -> 0 | G65: =IF($F65=0,0,INDEX(Aux_HH!$D$4:$D$18,MATCH($B65&"|"&$E65,Aux_HH!$A$4:$A$18,0))) -> 0 | H65: =IF($F65=0,0,INDEX(Aux_HH!$E$4:$E$18,MATCH($B65&"|"&$E65,Aux_HH!$A$4:$A$18,0))) -> 0 | I65: =IF($F65=0,0,INDEX(Aux_HH!$F$4:$F$18,MATCH($B65&"|"&$E65,Aux_HH!$A$4:$A$18,0))) -> 0 | J65: =IF($F65=0,0,INDEX(Aux_HH!$G$4:$G$18,MATCH($B65&"|"&$E65,Aux_HH!$A$4:$A$18,0))) -> 0 | K65: =IF($F65=0,0,INDEX(Aux_HH!$H$4:$H$18,MATCH($B65&"|"&$E65,Aux_HH!$A$4:$A$18,0))) -> 0 | L65: =IF($F65=0,0,INDEX(Aux_HH!$I$4:$I$18,MATCH($B65&"|"&$E65,Aux_HH!$A$4:$A$18,0))) -> 0
A66: =IF(Frota!$A6="","",Frota!$A6) -> Colhedora CASE A8810 — 1036 | B66: =IF(Frota!$A6="","",Frota!$B6) -> Colhedora | C66: 11 | D66: =INDEX(Semanas!$E$3:$E$54,11) -> 6 | E66: =IF(Frota!$A6="","",Cronograma!L6) | F66: =IF(OR($E66="",$E66=0),0,1) -> 0 | G66: =IF($F66=0,0,INDEX(Aux_HH!$D$4:$D$18,MATCH($B66&"|"&$E66,Aux_HH!$A$4:$A$18,0))) -> 0 | H66: =IF($F66=0,0,INDEX(Aux_HH!$E$4:$E$18,MATCH($B66&"|"&$E66,Aux_HH!$A$4:$A$18,0))) -> 0 | I66: =IF($F66=0,0,INDEX(Aux_HH!$F$4:$F$18,MATCH($B66&"|"&$E66,Aux_HH!$A$4:$A$18,0))) -> 0 | J66: =IF($F66=0,0,INDEX(Aux_HH!$G$4:$G$18,MATCH($B66&"|"&$E66,Aux_HH!$A$4:$A$18,0))) -> 0 | K66: =IF($F66=0,0,INDEX(Aux_HH!$H$4:$H$18,MATCH($B66&"|"&$E66,Aux_HH!$A$4:$A$18,0))) -> 0 | L66: =IF($F66=0,0,INDEX(Aux_HH!$I$4:$I$18,MATCH($B66&"|"&$E66,Aux_HH!$A$4:$A$18,0))) -> 0
A67: =IF(Frota!$A6="","",Frota!$A6) -> Colhedora CASE A8810 — 1036 | B67: =IF(Frota!$A6="","",Frota!$B6) -> Colhedora | C67: 12 | D67: =INDEX(Semanas!$E$3:$E$54,12) -> 6 | E67: =IF(Frota!$A6="","",Cronograma!M6) -> B | F67: =IF(OR($E67="",$E67=0),0,1) -> 1 | G67: =IF($F67=0,0,INDEX(Aux_HH!$D$4:$D$18,MATCH($B67&"|"&$E67,Aux_HH!$A$4:$A$18,0))) -> 10.25 | H67: =IF($F67=0,0,INDEX(Aux_HH!$E$4:$E$18,MATCH($B67&"|"&$E67,Aux_HH!$A$4:$A$18,0))) -> 0 | I67: =IF($F67=0,0,INDEX(Aux_HH!$F$4:$F$18,MATCH($B67&"|"&$E67,Aux_HH!$A$4:$A$18,0))) -> 3 | J67: =IF($F67=0,0,INDEX(Aux_HH!$G$4:$G$18,MATCH($B67&"|"&$E67,Aux_HH!$A$4:$A$18,0))) -> 1.75 | K67: =IF($F67=0,0,INDEX(Aux_HH!$H$4:$H$18,MATCH($B67&"|"&$E67,Aux_HH!$A$4:$A$18,0))) -> 0 | L67: =IF($F67=0,0,INDEX(Aux_HH!$I$4:$I$18,MATCH($B67&"|"&$E67,Aux_HH!$A$4:$A$18,0))) -> 0
A68: =IF(Frota!$A6="","",Frota!$A6) -> Colhedora CASE A8810 — 1036 | B68: =IF(Frota!$A6="","",Frota!$B6) -> Colhedora | C68: 13 | D68: =INDEX(Semanas!$E$3:$E$54,13) -> 6 | E68: =IF(Frota!$A6="","",Cronograma!N6) | F68: =IF(OR($E68="",$E68=0),0,1) -> 0 | G68: =IF($F68=0,0,INDEX(Aux_HH!$D$4:$D$18,MATCH($B68&"|"&$E68,Aux_HH!$A$4:$A$18,0))) -> 0 | H68: =IF($F68=0,0,INDEX(Aux_HH!$E$4:$E$18,MATCH($B68&"|"&$E68,Aux_HH!$A$4:$A$18,0))) -> 0 | I68: =IF($F68=0,0,INDEX(Aux_HH!$F$4:$F$18,MATCH($B68&"|"&$E68,Aux_HH!$A$4:$A$18,0))) -> 0 | J68: =IF($F68=0,0,INDEX(Aux_HH!$G$4:$G$18,MATCH($B68&"|"&$E68,Aux_HH!$A$4:$A$18,0))) -> 0 | K68: =IF($F68=0,0,INDEX(Aux_HH!$H$4:$H$18,MATCH($B68&"|"&$E68,Aux_HH!$A$4:$A$18,0))) -> 0 | L68: =IF($F68=0,0,INDEX(Aux_HH!$I$4:$I$18,MATCH($B68&"|"&$E68,Aux_HH!$A$4:$A$18,0))) -> 0
A69: =IF(Frota!$A6="","",Frota!$A6) -> Colhedora CASE A8810 — 1036 | B69: =IF(Frota!$A6="","",Frota!$B6) -> Colhedora | C69: 14 | D69: =INDEX(Semanas!$E$3:$E$54,14) -> 7 | E69: =IF(Frota!$A6="","",Cronograma!O6) | F69: =IF(OR($E69="",$E69=0),0,1) -> 0 | G69: =IF($F69=0,0,INDEX(Aux_HH!$D$4:$D$18,MATCH($B69&"|"&$E69,Aux_HH!$A$4:$A$18,0))) -> 0 | H69: =IF($F69=0,0,INDEX(Aux_HH!$E$4:$E$18,MATCH($B69&"|"&$E69,Aux_HH!$A$4:$A$18,0))) -> 0 | I69: =IF($F69=0,0,INDEX(Aux_HH!$F$4:$F$18,MATCH($B69&"|"&$E69,Aux_HH!$A$4:$A$18,0))) -> 0 | J69: =IF($F69=0,0,INDEX(Aux_HH!$G$4:$G$18,MATCH($B69&"|"&$E69,Aux_HH!$A$4:$A$18,0))) -> 0 | K69: =IF($F69=0,0,INDEX(Aux_HH!$H$4:$H$18,MATCH($B69&"|"&$E69,Aux_HH!$A$4:$A$18,0))) -> 0 | L69: =IF($F69=0,0,INDEX(Aux_HH!$I$4:$I$18,MATCH($B69&"|"&$E69,Aux_HH!$A$4:$A$18,0))) -> 0
A70: =IF(Frota!$A6="","",Frota!$A6) -> Colhedora CASE A8810 — 1036 | B70: =IF(Frota!$A6="","",Frota!$B6) -> Colhedora | C70: 15 | D70: =INDEX(Semanas!$E$3:$E$54,15) -> 7 | E70: =IF(Frota!$A6="","",Cronograma!P6) | F70: =IF(OR($E70="",$E70=0),0,1) -> 0 | G70: =IF($F70=0,0,INDEX(Aux_HH!$D$4:$D$18,MATCH($B70&"|"&$E70,Aux_HH!$A$4:$A$18,0))) -> 0 | H70: =IF($F70=0,0,INDEX(Aux_HH!$E$4:$E$18,MATCH($B70&"|"&$E70,Aux_HH!$A$4:$A$18,0))) -> 0 | I70: =IF($F70=0,0,INDEX(Aux_HH!$F$4:$F$18,MATCH($B70&"|"&$E70,Aux_HH!$A$4:$A$18,0))) -> 0 | J70: =IF($F70=0,0,INDEX(Aux_HH!$G$4:$G$18,MATCH($B70&"|"&$E70,Aux_HH!$A$4:$A$18,0))) -> 0 | K70: =IF($F70=0,0,INDEX(Aux_HH!$H$4:$H$18,MATCH($B70&"|"&$E70,Aux_HH!$A$4:$A$18,0))) -> 0 | L70: =IF($F70=0,0,INDEX(Aux_HH!$I$4:$I$18,MATCH($B70&"|"&$E70,Aux_HH!$A$4:$A$18,0))) -> 0
A71: =IF(Frota!$A6="","",Frota!$A6) -> Colhedora CASE A8810 — 1036 | B71: =IF(Frota!$A6="","",Frota!$B6) -> Colhedora | C71: 16 | D71: =INDEX(Semanas!$E$3:$E$54,16) -> 7 | E71: =IF(Frota!$A6="","",Cronograma!Q6) | F71: =IF(OR($E71="",$E71=0),0,1) -> 0 | G71: =IF($F71=0,0,INDEX(Aux_HH!$D$4:$D$18,MATCH($B71&"|"&$E71,Aux_HH!$A$4:$A$18,0))) -> 0 | H71: =IF($F71=0,0,INDEX(Aux_HH!$E$4:$E$18,MATCH($B71&"|"&$E71,Aux_HH!$A$4:$A$18,0))) -> 0 | I71: =IF($F71=0,0,INDEX(Aux_HH!$F$4:$F$18,MATCH($B71&"|"&$E71,Aux_HH!$A$4:$A$18,0))) -> 0 | J71: =IF($F71=0,0,INDEX(Aux_HH!$G$4:$G$18,MATCH($B71&"|"&$E71,Aux_HH!$A$4:$A$18,0))) -> 0 | K71: =IF($F71=0,0,INDEX(Aux_HH!$H$4:$H$18,MATCH($B71&"|"&$E71,Aux_HH!$A$4:$A$18,0))) -> 0 | L71: =IF($F71=0,0,INDEX(Aux_HH!$I$4:$I$18,MATCH($B71&"|"&$E71,Aux_HH!$A$4:$A$18,0))) -> 0
A72: =IF(Frota!$A6="","",Frota!$A6) -> Colhedora CASE A8810 — 1036 | B72: =IF(Frota!$A6="","",Frota!$B6) -> Colhedora | C72: 17 | D72: =INDEX(Semanas!$E$3:$E$54,17) -> 7 | E72: =IF(Frota!$A6="","",Cronograma!R6) | F72: =IF(OR($E72="",$E72=0),0,1) -> 0 | G72: =IF($F72=0,0,INDEX(Aux_HH!$D$4:$D$18,MATCH($B72&"|"&$E72,Aux_HH!$A$4:$A$18,0))) -> 0 | H72: =IF($F72=0,0,INDEX(Aux_HH!$E$4:$E$18,MATCH($B72&"|"&$E72,Aux_HH!$A$4:$A$18,0))) -> 0 | I72: =IF($F72=0,0,INDEX(Aux_HH!$F$4:$F$18,MATCH($B72&"|"&$E72,Aux_HH!$A$4:$A$18,0))) -> 0 | J72: =IF($F72=0,0,INDEX(Aux_HH!$G$4:$G$18,MATCH($B72&"|"&$E72,Aux_HH!$A$4:$A$18,0))) -> 0 | K72: =IF($F72=0,0,INDEX(Aux_HH!$H$4:$H$18,MATCH($B72&"|"&$E72,Aux_HH!$A$4:$A$18,0))) -> 0 | L72: =IF($F72=0,0,INDEX(Aux_HH!$I$4:$I$18,MATCH($B72&"|"&$E72,Aux_HH!$A$4:$A$18,0))) -> 0
A73: =IF(Frota!$A6="","",Frota!$A6) -> Colhedora CASE A8810 — 1036 | B73: =IF(Frota!$A6="","",Frota!$B6) -> Colhedora | C73: 18 | D73: =INDEX(Semanas!$E$3:$E$54,18) -> 7 | E73: =IF(Frota!$A6="","",Cronograma!S6) -> S | F73: =IF(OR($E73="",$E73=0),0,1) -> 1 | G73: =IF($F73=0,0,INDEX(Aux_HH!$D$4:$D$18,MATCH($B73&"|"&$E73,Aux_HH!$A$4:$A$18,0))) -> 3.75 | H73: =IF($F73=0,0,INDEX(Aux_HH!$E$4:$E$18,MATCH($B73&"|"&$E73,Aux_HH!$A$4:$A$18,0))) -> 0 | I73: =IF($F73=0,0,INDEX(Aux_HH!$F$4:$F$18,MATCH($B73&"|"&$E73,Aux_HH!$A$4:$A$18,0))) -> 1 | J73: =IF($F73=0,0,INDEX(Aux_HH!$G$4:$G$18,MATCH($B73&"|"&$E73,Aux_HH!$A$4:$A$18,0))) -> 0.75 | K73: =IF($F73=0,0,INDEX(Aux_HH!$H$4:$H$18,MATCH($B73&"|"&$E73,Aux_HH!$A$4:$A$18,0))) -> 0 | L73: =IF($F73=0,0,INDEX(Aux_HH!$I$4:$I$18,MATCH($B73&"|"&$E73,Aux_HH!$A$4:$A$18,0))) -> 0
A74: =IF(Frota!$A6="","",Frota!$A6) -> Colhedora CASE A8810 — 1036 | B74: =IF(Frota!$A6="","",Frota!$B6) -> Colhedora | C74: 19 | D74: =INDEX(Semanas!$E$3:$E$54,19) -> 8 | E74: =IF(Frota!$A6="","",Cronograma!T6) | F74: =IF(OR($E74="",$E74=0),0,1) -> 0 | G74: =IF($F74=0,0,INDEX(Aux_HH!$D$4:$D$18,MATCH($B74&"|"&$E74,Aux_HH!$A$4:$A$18,0))) -> 0 | H74: =IF($F74=0,0,INDEX(Aux_HH!$E$4:$E$18,MATCH($B74&"|"&$E74,Aux_HH!$A$4:$A$18,0))) -> 0 | I74: =IF($F74=0,0,INDEX(Aux_HH!$F$4:$F$18,MATCH($B74&"|"&$E74,Aux_HH!$A$4:$A$18,0))) -> 0 | J74: =IF($F74=0,0,INDEX(Aux_HH!$G$4:$G$18,MATCH($B74&"|"&$E74,Aux_HH!$A$4:$A$18,0))) -> 0 | K74: =IF($F74=0,0,INDEX(Aux_HH!$H$4:$H$18,MATCH($B74&"|"&$E74,Aux_HH!$A$4:$A$18,0))) -> 0 | L74: =IF($F74=0,0,INDEX(Aux_HH!$I$4:$I$18,MATCH($B74&"|"&$E74,Aux_HH!$A$4:$A$18,0))) -> 0
A75: =IF(Frota!$A6="","",Frota!$A6) -> Colhedora CASE A8810 — 1036 | B75: =IF(Frota!$A6="","",Frota!$B6) -> Colhedora | C75: 20 | D75: =INDEX(Semanas!$E$3:$E$54,20) -> 8 | E75: =IF(Frota!$A6="","",Cronograma!U6) | F75: =IF(OR($E75="",$E75=0),0,1) -> 0 | G75: =IF($F75=0,0,INDEX(Aux_HH!$D$4:$D$18,MATCH($B75&"|"&$E75,Aux_HH!$A$4:$A$18,0))) -> 0 | H75: =IF($F75=0,0,INDEX(Aux_HH!$E$4:$E$18,MATCH($B75&"|"&$E75,Aux_HH!$A$4:$A$18,0))) -> 0 | I75: =IF($F75=0,0,INDEX(Aux_HH!$F$4:$F$18,MATCH($B75&"|"&$E75,Aux_HH!$A$4:$A$18,0))) -> 0 | J75: =IF($F75=0,0,INDEX(Aux_HH!$G$4:$G$18,MATCH($B75&"|"&$E75,Aux_HH!$A$4:$A$18,0))) -> 0 | K75: =IF($F75=0,0,INDEX(Aux_HH!$H$4:$H$18,MATCH($B75&"|"&$E75,Aux_HH!$A$4:$A$18,0))) -> 0 | L75: =IF($F75=0,0,INDEX(Aux_HH!$I$4:$I$18,MATCH($B75&"|"&$E75,Aux_HH!$A$4:$A$18,0))) -> 0
